Workbook

Sheet ACCUEIL
B2: =PARAMETRES!$C$5 -> CAFE VICTOR HUGO
B3: =PARAMETRES!$C$6&", "&PARAMETRES!$C$7 -> Mohammedia, Maroc
B4: SYSTÈME DE GESTION — CAISSE, DÉPENSES, CHARGES ET RÉSULTATS
B7: LE MOIS EN COURS | D7: =PARAMETRES!$C$15 -> 46235
B8: Recette | C8: Dépenses | D8: Résultat | E8: Marge | F8: Caisse | G8: Jours saisis
B9: =SUMIFS(JOURNAL!$H$8:$H$1007,JOURNAL!$D$8:$D$1007,"RECETTE",JOURNAL!$C$8:$C$1007,PARAMETRES!$C$14) -> 54937 | C9: =SUMIFS(JOURNAL!$H$8:$H$1007,JOURNAL!$D$8:$D$1007,"DEPENSE",JOURNAL!$C$8:$C$1007,PARAMETRES!$C$14) -> 50714 | D9: =SUMIFS(JOURNAL!$H$8:$H$1007,JOURNAL!$D$8:$D$1007,"RECETTE",JOURNAL!$C$8:$C$1007,PARAMETRES!$C$14)-SUMIFS(JOURNAL!$H$8:$H$1007,JOURNAL!$D$8:$D$1007,"DEPENSE",JOURNAL!$C$8:$C$1007,PARAMETRES!$C$14) -> 4223 | E9: =IFERROR((SUMIFS(JOURNAL!$H$8:$H$1007,JOURNAL!$D$8:$D$1007,"RECETTE",JOURNAL!$C$8:$C$1007,PARAMETRES!$C$14)-SUMIFS(JOURNAL!$H$8:$H$1007,JOURNAL!$D$8:$D$1007,"DEPENSE",JOURNAL!$C$8:$C$1007,PARAMETRES!$C$14))/SUMIFS(JOURNAL!$H$8:$H$1007,JOURNAL!$D$8:$D$1007,"RECETTE",JOURNAL!$C$8:$C$1007,PARAMETRES!$C$14),0) -> 0.076869869 | F9: ='RECAP JOUR'!$O$37 -> 4223 | G9: =COUNTIF('RECAP JOUR'!$F$6:$F$36,">0") -> 27
B11: COMMENT UTILISER CE CLASSEUR — 3 ÉTAPES
B12: 1 | C12: CHAQUE SOIR, APRÈS LA FERMETURE
C13: Ouvrez la feuille JOURNAL. Sur la première ligne vide : la date du jour, le type RECETTE, la catégorie « Vente Caisse », et le montant compté dans la caisse. Puis une ligne DEPENSE par achat ou paiement de la journée (fournisseur, montant).
B15: 2 | C15: VÉRIFIEZ QUE LA LIGNE EST VERTE
C16: La dernière colonne du JOURNAL affiche OK en vert quand la ligne est complète. Si elle affiche « Catégorie ? » ou « Montant ? », corrigez avant de passer à la suite.
B18: 3 | C18: REGARDEZ LE TABLEAU DE BORD
C19: Tout est déjà calculé : recette du mois, dépenses, résultat, marge, caisse, graphiques. Vous n’avez jamais à recopier un chiffre d’une feuille à l’autre.
B21: LES FEUILLES DU CLASSEUR
B22: FEUILLE | C22: À QUOI ELLE SERT | H22: SAISIE ?
B23: ACCUEIL | C23: Cette page : mode d’emploi et chiffres du mois. | H23: Non
B24: PARAMETRES | C24: Nom du commerce, mois analysé, caisse de départ, listes de fournisseurs et de catégories. | H24: Oui
B25: JOURNAL | C25: Le cœur du système : une ligne par opération, recette ou dépense. C’est la seule feuille à remplir tous les jours. | H25: Oui
B26: RECAP JOUR | C26: Le mois jour par jour : recette, dépenses par type, résultat, caisse cumulée. | H26: Non
B27: TABLEAU DE BORD | C27: La photo du mois : indicateurs et graphiques. | H27: Non
B28: SUIVI MENSUEL | C28: Mois par mois, 2025 et 2026, pour voir les tendances. | H28: Non
B29: CHARGES FIXES | C29: Budget mensuel par poste comparé au réalisé, et coût de fonctionnement par jour. | H29: Budget
B30: SALAIRES | C30: Le personnel, le salaire convenu et ce qui a été versé dans le mois. | H30: Salaires
B31: MARGES PRODUITS | C31: Ce que rapporte chaque boisson une fois le coût matière déduit. | H31: Couts
B32: ASSOCIÉS | C32: Apports de Hamid et Mouhssine : achat du fonds et aménagement du café. | H32: Non
B33: ARCHIVE | C33: Données de l’ancien classeur sans rapport avec le café, conservées pour mémoire. | H33: Non
B35: CE QUI A ÉTÉ REPRIS DE L’ANCIEN CLASSEUR
B36: 27 journées d’août 2026 | C36: 145 opérations transférées dans le JOURNAL | E36: 54 937 DH de recettes et 50 714 DH de dépenses — identiques à la feuille SUIVI d’origine.
B37: Historique mensuel 2025 | C37: 10 mois de recettes et d’achats | E37: Repris dans SUIVI MENSUEL depuis la feuille Feuil1.
B38: Charges fixes et salaires | C38: 9 postes de charges, 11 personnes | E38: Repris dans CHARGES FIXES et SALAIRES depuis la feuille CHARGE.
B39: Comptes des associés | C39: 105 lignes d’apports | E39: Reprises dans ASSOCIÉS depuis la feuille DEPENSE_CAFE, sans modification.
B40: Prix de vente | C40: 4 produits | E40: Repris dans MARGES PRODUITS depuis la feuille CHARGE.
B42: Différence avec l’ancien classeur : il fallait auparavant créer une feuille par jour et recopier les totaux à la main dans la feuille SUIVI. Ici, une seule feuille se remplit (JOURNAL) et les 31 jours du mois, le tableau de bord, le suivi mensuel et les charges se calculent seuls. Pour changer de mois, il suffit de modifier le numéro du mois dans PARAMÈTRES — rien d’autre.

Sheet TABLEAU DE BORD
A1: TABLEAU DE BORD
A2: Photo du mois en cours. Tout se met à jour dès que vous saisissez dans le JOURNAL.
A4: =PARAMETRES!$C$15 -> 46235 | K4: =PARAMETRES!$C$5&" — "&PARAMETRES!$C$6 -> CAFE VICTOR HUGO — Mohammedia
A6: RECETTE DU MOIS | E6: DÉPENSES DU MOIS | I6: RÉSULTAT NET | M6: MARGE NETTE
A7: =SUMIFS(JOURNAL!$H$8:$H$1007,JOURNAL!$D$8:$D$1007,"RECETTE",JOURNAL!$C$8:$C$1007,PARAMETRES!$C$14) -> 54937 | E7: =SUMIFS(JOURNAL!$H$8:$H$1007,JOURNAL!$D$8:$D$1007,"DEPENSE",JOURNAL!$C$8:$C$1007,PARAMETRES!$C$14) -> 50714 | I7: =SUMIFS(JOURNAL!$H$8:$H$1007,JOURNAL!$D$8:$D$1007,"RECETTE",JOURNAL!$C$8:$C$1007,PARAMETRES!$C$14)-SUMIFS(JOURNAL!$H$8:$H$1007,JOURNAL!$D$8:$D$1007,"DEPENSE",JOURNAL!$C$8:$C$1007,PARAMETRES!$C$14) -> 4223 | M7: =IFERROR((SUMIFS(JOURNAL!$H$8:$H$1007,JOURNAL!$D$8:$D$1007,"RECETTE",JOURNAL!$C$8:$C$1007,PARAMETRES!$C$14)-SUMIFS(JOURNAL!$H$8:$H$1007,JOURNAL!$D$8:$D$1007,"DEPENSE",JOURNAL!$C$8:$C$1007,PARAMETRES!$C$14))/SUMIFS(JOURNAL!$H$8:$H$1007,JOURNAL!$D$8:$D$1007,"RECETTE",JOURNAL!$C$8:$C$1007,PARAMETRES!$C$14),0) -> 0.076869869
A8: Total encaissé ce mois | E8: Achats, salaires, charges, virements | I8: Recette moins dépenses | M8: Part de la recette qui reste
A10: RECETTE MOYENNE / JOUR | E10: MEILLEURE JOURNÉE | I10: CAISSE EN FIN DE MOIS | M10: JOURS SAISIS
A11: =IFERROR(SUMIFS(JOURNAL!$H$8:$H$1007,JOURNAL!$D$8:$D$1007,"RECETTE",JOURNAL!$C$8:$C$1007,PARAMETRES!$C$14)/COUNTIF('RECAP JOUR'!$F$6:$F$36,">0"),0) -> 2034.7037 | E11: =IFERROR(MAX('RECAP JOUR'!$F$6:$F$36),0) -> 2456 | I11: ='RECAP JOUR'!$O$37 -> 4223 | M11: =COUNTIF('RECAP JOUR'!$F$6:$F$36,">0") -> 27
A12: Sur les jours réellement travaillés | E12: Recette la plus haute du mois | I12: Solde théorique d'espèces | M12: Jours avec une recette enregistrée
A15: ÉVOLUTION DU MOIS
A34: ANALYSE DES DÉPENSES
A58: DÉPENSES PAR CATÉGORIE | F58: PRINCIPAUX FOURNISSEURS
A59: CATÉGORIE | B59: MONTANT | C59: PART | D59: PAR JOUR | F59: FOURNISSEUR | G59: MONTANT | H59: PART | I59: NB ACHATS
A60: Boissons | B60: =SUMIFS(JOURNAL!$H$8:$H$1007,JOURNAL!$E$8:$E$1007,"Boissons",JOURNAL!$C$8:$C$1007,PARAMETRES!$C$14) -> 6566 | C60: =IFERROR($B60/$B$76,0) -> 0.12947115 | D60: =IFERROR($B60/COUNTIF('RECAP JOUR'!$F$6:$F$36,">0"),0) -> 243.18519 | F60: BIM | G60: =SUMIFS(JOURNAL!$H$8:$H$1007,JOURNAL!$F$8:$F$1007,"BIM",JOURNAL!$C$8:$C$1007,PARAMETRES!$C$14) -> 5500 | H60: =IFERROR($G60/$B$76,0) -> 0.10845132 | I60: =COUNTIFS(JOURNAL!$F$8:$F$1007,"BIM",JOURNAL!$C$8:$C$1007,PARAMETRES!$C$14) -> 22
A61: Café & Torréfaction | B61: =SUMIFS(JOURNAL!$H$8:$H$1007,JOURNAL!$E$8:$E$1007,"Café & Torréfaction",JOURNAL!$C$8:$C$1007,PARAMETRES!$C$14) -> 4910 | C61: =IFERROR($B61/$B$76,0) -> 0.096817447 | D61: =IFERROR($B61/COUNTIF('RECAP JOUR'!$F$6:$F$36,">0"),0) -> 181.85185 | F61: TAXE NADAFA 2026 | G61: =SUMIFS(JOURNAL!$H$8:$H$1007,JOURNAL!$F$8:$F$1007,"TAXE NADAFA 2026",JOURNAL!$C$8:$C$1007,PARAMETRES!$C$14) -> 5000 | H61: =IFERROR($G61/$B$76,0) -> 0.098592105 | I61: =COUNTIFS(JOURNAL!$F$8:$F$1007,"TAXE NADAFA 2026",JOURNAL!$C$8:$C$1007,PARAMETRES!$C$14) -> 1
A62: Boulangerie | B62: =SUMIFS(JOURNAL!$H$8:$H$1007,JOURNAL!$E$8:$E$1007,"Boulangerie",JOURNAL!$C$8:$C$1007,PARAMETRES!$C$14) -> 1303 | C62: =IFERROR($B62/$B$76,0) -> 0.025693102 | D62: =IFERROR($B62/COUNTIF('RECAP JOUR'!$F$6:$F$36,">0"),0) -> 48.259259 | F62: AIN SAISS | G62: =SUMIFS(JOURNAL!$H$8:$H$1007,JOURNAL!$F$8:$F$1007,"AIN SAISS",JOURNAL!$C$8:$C$1007,PARAMETRES!$C$14) -> 4956 | H62: =IFERROR($G62/$B$76,0) -> 0.097724494 | I62: =COUNTIFS(JOURNAL!$F$8:$F$1007,"AIN SAISS",JOURNAL!$C$8:$C$1007,PARAMETRES!$C$14) -> 16
A63: Fruits & Légumes | B63: =SUMIFS(JOURNAL!$H$8:$H$1007,JOURNAL!$E$8:$E$1007,"Fruits & Légumes",JOURNAL!$C$8:$C$1007,PARAMETRES!$C$14) -> 2135 | C63: =IFERROR($B63/$B$76,0) -> 0.042098829 | D63: =IFERROR($B63/COUNTIF('RECAP JOUR'!$F$6:$F$36,">0"),0) -> 79.074074 | F63: NADAFA | G63: =SUMIFS(JOURNAL!$H$8:$H$1007,JOURNAL!$F$8:$F$1007,"NADAFA",JOURNAL!$C$8:$C$1007,PARAMETRES!$C$14) -> 4050 | H63: =IFERROR($G63/$B$76,0) -> 0.079859605 | I63: =COUNTIFS(JOURNAL!$F$8:$F$1007,"NADAFA",JOURNAL!$C$8:$C$1007,PARAMETRES!$C$14) -> 27
A64: Épicerie & Divers | B64: =SUMIFS(JOURNAL!$H$8:$H$1007,JOURNAL!$E$8:$E$1007,"Épicerie & Divers",JOURNAL!$C$8:$C$1007,PARAMETRES!$C$14) -> 5565 | C64: =IFERROR($B64/$B$76,0) -> 0.10973301 | D64: =IFERROR($B64/COUNTIF('RECAP JOUR'!$F$6:$F$36,">0"),0) -> 206.11111 | F64: CAFE | G64: =SUMIFS(JOURNAL!$H$8:$H$1007,JOURNAL!$F$8:$F$1007,"CAFE",JOURNAL!$C$8:$C$1007,PARAMETRES!$C$14) -> 4000 | H64: =IFERROR($G64/$B$76,0) -> 0.078873684 | I64: =COUNTIFS(JOURNAL!$F$8:$F$1007,"CAFE",JOURNAL!$C$8:$C$1007,PARAMETRES!$C$14) -> 3
A65: Nettoyage | B65: =SUMIFS(JOURNAL!$H$8:$H$1007,JOURNAL!$E$8:$E$1007,"Nettoyage",JOURNAL!$C$8:$C$1007,PARAMETRES!$C$14) -> 4050 | C65: =IFERROR($B65/$B$76,0) -> 0.079859605 | D65: =IFERROR($B65/COUNTIF('RECAP JOUR'!$F$6:$F$36,">0"),0) -> 150 | F65: EAU + ELECTRICITE | G65: =SUMIFS(JOURNAL!$H$8:$H$1007,JOURNAL!$F$8:$F$1007,"EAU + ELECTRICITE",JOURNAL!$C$8:$C$1007,PARAMETRES!$C$14) -> 3785 | H65: =IFERROR($G65/$B$76,0) -> 0.074634223 | I65: =COUNTIFS(JOURNAL!$F$8:$F$1007,"EAU + ELECTRICITE",JOURNAL!$C$8:$C$1007,PARAMETRES!$C$14) -> 1
A66: Salaires | B66: =SUMIFS(JOURNAL!$H$8:$H$1007,JOURNAL!$E$8:$E$1007,"Salaires",JOURNAL!$C$8:$C$1007,PARAMETRES!$C$14) -> 12400 | C66: =IFERROR($B66/$B$76,0) -> 0.24450842 | D66: =IFERROR($B66/COUNTIF('RECAP JOUR'!$F$6:$F$36,">0"),0) -> 459.25926 | F66: ORANGE | G66: =SUMIFS(JOURNAL!$H$8:$H$1007,JOURNAL!$F$8:$F$1007,"ORANGE",JOURNAL!$C$8:$C$1007,PARAMETRES!$C$14) -> 1980 | H66: =IFERROR($G66/$B$76,0) -> 0.039042473 | I66: =COUNTIFS(JOURNAL!$F$8:$F$1007,"ORANGE",JOURNAL!$C$8:$C$1007,PARAMETRES!$C$14) -> 12
A67: Loyer | B67: =SUMIFS(JOURNAL!$H$8:$H$1007,JOURNAL!$E$8:$E$1007,"Loyer",JOURNAL!$C$8:$C$1007,PARAMETRES!$C$14) -> 5000 | C67: =IFERROR($B67/$B$76,0) -> 0.098592105 | D67: =IFERROR($B67/COUNTIF('RECAP JOUR'!$F$6:$F$36,">0"),0) -> 185.18519 | F67: BOULANGERIE | G67: =SUMIFS(JOURNAL!$H$8:$H$1007,JOURNAL!$F$8:$F$1007,"BOULANGERIE",JOURNAL!$C$8:$C$1007,PARAMETRES!$C$14) -> 1303 | H67: =IFERROR($G67/$B$76,0) -> 0.025693102 | I67: =COUNTIFS(JOURNAL!$F$8:$F$1007,"BOULANGERIE",JOURNAL!$C$8:$C$1007,PARAMETRES!$C$14) -> 4
A68: Eau & Électricité | B68: =SUMIFS(JOURNAL!$H$8:$H$1007,JOURNAL!$E$8:$E$1007,"Eau & Électricité",JOURNAL!$C$8:$C$1007,PARAMETRES!$C$14) -> 3785 | C68: =IFERROR($B68/$B$76,0) -> 0.074634223 | D68: =IFERROR($B68/COUNTIF('RECAP JOUR'!$F$6:$F$36,">0"),0) -> 140.18519 | F68: COCA | G68: =SUMIFS(JOURNAL!$H$8:$H$1007,JOURNAL!$F$8:$F$1007,"COCA",JOURNAL!$C$8:$C$1007,PARAMETRES!$C$14) -> 1116 | H68: =IFERROR($G68/$B$76,0) -> 0.022005758 | I68: =COUNTIFS(JOURNAL!$F$8:$F$1007,"COCA",JOURNAL!$C$8:$C$1007,PARAMETRES!$C$14) -> 2
A69: Internet & Télécom | B69: =SUMIFS(JOURNAL!$H$8:$H$1007,JOURNAL!$E$8:$E$1007,"Internet & Télécom",JOURNAL!$C$8:$C$1007,PARAMETRES!$C$14) -> 0 | C69: =IFERROR($B69/$B$76,0) -> 0 | D69: =IFERROR($B69/COUNTIF('RECAP JOUR'!$F$6:$F$36,">0"),0) -> 0 | F69: MECAFE | G69: =SUMIFS(JOURNAL!$H$8:$H$1007,JOURNAL!$F$8:$F$1007,"MECAFE",JOURNAL!$C$8:$C$1007,PARAMETRES!$C$14) -> 910 | H69: =IFERROR($G69/$B$76,0) -> 0.017943763 | I69: =COUNTIFS(JOURNAL!$F$8:$F$1007,"MECAFE",JOURNAL!$C$8:$C$1007,PARAMETRES!$C$14) -> 1
A70: Taxes & Impôts | B70: =SUMIFS(JOURNAL!$H$8:$H$1007,JOURNAL!$E$8:$E$1007,"Taxes & Impôts",JOURNAL!$C$8:$C$1007,PARAMETRES!$C$14) -> 5000 | C70: =IFERROR($B70/$B$76,0) -> 0.098592105 | D70: =IFERROR($B70/COUNTIF('RECAP JOUR'!$F$6:$F$36,">0"),0) -> 185.18519 | F70: OULMES | G70: =SUMIFS(JOURNAL!$H$8:$H$1007,JOURNAL!$F$8:$F$1007,"OULMES",JOURNAL!$C$8:$C$1007,PARAMETRES!$C$14) -> 468 | H70: =IFERROR($G70/$B$76,0) -> 0.009228221 | I70: =COUNTIFS(JOURNAL!$F$8:$F$1007,"OULMES",JOURNAL!$C$8:$C$1007,PARAMETRES!$C$14) -> 3
A71: Abonnements | B71: =SUMIFS(JOURNAL!$H$8:$H$1007,JOURNAL!$E$8:$E$1007,"Abonnements",JOURNAL!$C$8:$C$1007,PARAMETRES!$C$14) -> 0 | C71: =IFERROR($B71/$B$76,0) -> 0 | D71: =IFERROR($B71/COUNTIF('RECAP JOUR'!$F$6:$F$36,">0"),0) -> 0 | F71: FRUITS | G71: =SUMIFS(JOURNAL!$H$8:$H$1007,JOURNAL!$F$8:$F$1007,"FRUITS",JOURNAL!$C$8:$C$1007,PARAMETRES!$C$14) -> 155 | H71: =IFERROR($G71/$B$76,0) -> 0.0030563552 | I71: =COUNTIFS(JOURNAL!$F$8:$F$1007,"FRUITS",JOURNAL!$C$8:$C$1007,PARAMETRES!$C$14) -> 2
A72: Entretien & Réparation | B72: =SUMIFS(JOURNAL!$H$8:$H$1007,JOURNAL!$E$8:$E$1007,"Entretien & Réparation",JOURNAL!$C$8:$C$1007,PARAMETRES!$C$14) -> 0 | C72: =IFERROR($B72/$B$76,0) -> 0 | D72: =IFERROR($B72/COUNTIF('RECAP JOUR'!$F$6:$F$36,">0"),0) -> 0
A73: Virement Banque | B73: =SUMIFS(JOURNAL!$H$8:$H$1007,JOURNAL!$E$8:$E$1007,"Virement Banque",JOURNAL!$C$8:$C$1007,PARAMETRES!$C$14) -> 0 | C73: =IFERROR($B73/$B$76,0) -> 0 | D73: =IFERROR($B73/COUNTIF('RECAP JOUR'!$F$6:$F$36,">0"),0) -> 0
A74: Virement Associés | B74: =SUMIFS(JOURNAL!$H$8:$H$1007,JOURNAL!$E$8:$E$1007,"Virement Associés",JOURNAL!$C$8:$C$1007,PARAMETRES!$C$14) -> 0 | C74: =IFERROR($B74/$B$76,0) -> 0 | D74: =IFERROR($B74/COUNTIF('RECAP JOUR'!$F$6:$F$36,">0"),0) -> 0
A75: Divers | B75: =SUMIFS(JOURNAL!$H$8:$H$1007,JOURNAL!$E$8:$E$1007,"Divers",JOURNAL!$C$8:$C$1007,PARAMETRES!$C$14) -> 0 | C75: =IFERROR($B75/$B$76,0) -> 0 | D75: =IFERROR($B75/COUNTIF('RECAP JOUR'!$F$6:$F$36,">0"),0) -> 0
A76: TOTAL DÉPENSES | B76: =SUM($B$60:$B$75) -> 50714 | C76: =IFERROR($B76/$B76,0) -> 1 | D76: =IFERROR($B76/COUNTIF('RECAP JOUR'!$F$6:$F$36,">0"),0) -> 1878.2963
A79: Les deux tableaux ci-dessus alimentent les graphiques et se recalculent sur le mois choisi dans PARAMÈTRES. L’ordre des fournisseurs a été figé sur le poids constaté en août 2026 (données reprises de l’ancien classeur) ; les montants, eux, suivent toujours le mois en cours.

Sheet JOURNAL
A1: JOURNAL DES OPÉRATIONS
A2: Toute la vie du café se saisit ici, une ligne par opération. Le reste du classeur se met à jour tout seul.
A3: COMMENT SAISIR ▸ 1. Tapez la DATE ▸ 2. Choisissez RECETTE ou DEPENSE ▸ 3. Choisissez la CATÉGORIE et le FOURNISSEUR dans la liste ▸ 4. Tapez le MONTANT en DH. La colonne CONTRÔLE passe au vert quand la ligne est complète.
A5: Lignes saisies | C5: Total recettes | E5: Total dépenses | G5: Résultat
A6: =COUNT($B$8:$B$1007) -> 145 | C6: =SUMIF($D$8:$D$1007,"RECETTE",$H$8:$H$1007) -> 54937 | E6: =SUMIF($D$8:$D$1007,"DEPENSE",$H$8:$H$1007) -> 50714 | G6: =SUMIF($D$8:$D$1007,"RECETTE",$H$8:$H$1007)-SUMIF($D$8:$D$1007,"DEPENSE",$H$8:$H$1007) -> 4223
A7: N° | B7: DATE | C7: CLE MOIS | D7: TYPE | E7: CATÉGORIE | F7: FOURNISSEUR / BÉNÉFICIAIRE | G7: DESCRIPTION | H7: MONTANT (DH) | I7: MODE | J7: CONTROLE
A8: =IF($B8="","",ROW()-7) -> 1 | B8: 46235 | C8: =IF($B8="","",YEAR($B8)*100+MONTH($B8)) -> 202608 | D8: RECETTE | E8: Vente Caisse | F8: CLIENT | G8: Recette caisse du jour | H8: 2335 | I8: Espèce | J8: =IF($B8="","",IF(N($H8)<=0,"Montant ?",IF($D8="RECETTE",IF(COUNTIF(PARAMETRES!$E$5:$E$9,$E8)=0,"Catégorie ?","OK"),IF($D8="DEPENSE",IF(COUNTIF(PARAMETRES!$G$5:$G$20,$E8)=0,"Catégorie ?","OK"),"Type ?")))) -> OK
A9: =IF($B9="","",ROW()-7) -> 2 | B9: 46235 | C9: =IF($B9="","",YEAR($B9)*100+MONTH($B9)) -> 202608 | D9: DEPENSE | E9: Boissons | F9: AIN SAISS | G9: Achat du jour | H9: 306 | I9: Espèce | J9: =IF($B9="","",IF(N($H9)<=0,"Montant ?",IF($D9="RECETTE",IF(COUNTIF(PARAMETRES!$E$5:$E$9,$E9)=0,"Catégorie ?","OK"),IF($D9="DEPENSE",IF(COUNTIF(PARAMETRES!$G$5:$G$20,$E9)=0,"Catégorie ?","OK"),"Type ?")))) -> OK
A10: =IF($B10="","",ROW()-7) -> 3 | B10: 46235 | C10: =IF($B10="","",YEAR($B10)*100+MONTH($B10)) -> 202608 | D10: DEPENSE | E10: Épicerie & Divers | F10: BIM | G10: Achat du jour | H10: 300 | I10: Espèce | J10: =IF($B10="","",IF(N($H10)<=0,"Montant ?",IF($D10="RECETTE",IF(COUNTIF(PARAMETRES!$E$5:$E$9,$E10)=0,"Catégorie ?","OK"),IF($D10="DEPENSE",IF(COUNTIF(PARAMETRES!$G$5:$G$20,$E10)=0,"Catégorie ?","OK"),"Type ?")))) -> OK
A11: =IF($B11="","",ROW()-7) -> 4 | B11: 46235 | C11: =IF($B11="","",YEAR($B11)*100+MONTH($B11)) -> 202608 | D11: DEPENSE | E11: Fruits & Légumes | F11: ORANGE | G11: Achat du jour | H11: 165 | I11: Espèce | J11: =IF($B11="","",IF(N($H11)<=0,"Montant ?",IF($D11="RECETTE",IF(COUNTIF(PARAMETRES!$E$5:$E$9,$E11)=0,"Catégorie ?","OK"),IF($D11="DEPENSE",IF(COUNTIF(PARAMETRES!$G$5:$G$20,$E11)=0,"Catégorie ?","OK"),"Type ?")))) -> OK
A12: =IF($B12="","",ROW()-7) -> 5 | B12: 46235 | C12: =IF($B12="","",YEAR($B12)*100+MONTH($B12)) -> 202608 | D12: DEPENSE | E12: Nettoyage | F12: NADAFA | G12: Achat du jour | H12: 150 | I12: Espèce | J12: =IF($B12="","",IF(N($H12)<=0,"Montant ?",IF($D12="RECETTE",IF(COUNTIF(PARAMETRES!$E$5:$E$9,$E12)=0,"Catégorie ?","OK"),IF($D12="DEPENSE",IF(COUNTIF(PARAMETRES!$G$5:$G$20,$E12)=0,"Catégorie ?","OK"),"Type ?")))) -> OK
A13: =IF($B13="","",ROW()-7) -> 6 | B13: 46236 | C13: =IF($B13="","",YEAR($B13)*100+MONTH($B13)) -> 202608 | D13: RECETTE | E13: Vente Caisse | F13: CLIENT | G13: Recette caisse du jour | H13: 2456 | I13: Espèce | J13: =IF($B13="","",IF(N($H13)<=0,"Montant ?",IF($D13="RECETTE",IF(COUNTIF(PARAMETRES!$E$5:$E$9,$E13)=0,"Catégorie ?","OK"),IF($D13="DEPENSE",IF(COUNTIF(PARAMETRES!$G$5:$G$20,$E13)=0,"Catégorie ?","OK"),"Type ?")))) -> OK
A14: =IF($B14="","",ROW()-7) -> 7 | B14: 46236 | C14: =IF($B14="","",YEAR($B14)*100+MONTH($B14)) -> 202608 | D14: DEPENSE | E14: Boissons | F14: AIN SAISS | G14: Achat du jour | H14: 306 | I14: Espèce | J14: =IF($B14="","",IF(N($H14)<=0,"Montant ?",IF($D14="RECETTE",IF(COUNTIF(PARAMETRES!$E$5:$E$9,$E14)=0,"Catégorie ?","OK"),IF($D14="DEPENSE",IF(COUNTIF(PARAMETRES!$G$5:$G$20,$E14)=0,"Catégorie ?","OK"),"Type ?")))) -> OK
A15: =IF($B15="","",ROW()-7) -> 8 | B15: 46236 | C15: =IF($B15="","",YEAR($B15)*100+MONTH($B15)) -> 202608 | D15: DEPENSE | E15: Épicerie & Divers | F15: BIM | G15: Achat du jour | H15: 300 | I15: Espèce | J15: =IF($B15="","",IF(N($H15)<=0,"Montant ?",IF($D15="RECETTE",IF(COUNTIF(PARAMETRES!$E$5:$E$9,$E15)=0,"Catégorie ?","OK"),IF($D15="DEPENSE",IF(COUNTIF(PARAMETRES!$G$5:$G$20,$E15)=0,"Catégorie ?","OK"),"Type ?")))) -> OK
A16: =IF($B16="","",ROW()-7) -> 9 | B16: 46236 | C16: =IF($B16="","",YEAR($B16)*100+MONTH($B16)) -> 202608 | D16: DEPENSE | E16: Boissons | F16: OULMES | G16: Achat du jour | H16: 156 | I16: Espèce | J16: =IF($B16="","",IF(N($H16)<=0,"Montant ?",IF($D16="RECETTE",IF(COUNTIF(PARAMETRES!$E$5:$E$9,$E16)=0,"Catégorie ?","OK"),IF($D16="DEPENSE",IF(COUNTIF(PARAMETRES!$G$5:$G$20,$E16)=0,"Catégorie ?","OK"),"Type ?")))) -> OK
A17: =IF($B17="","",ROW()-7) -> 10 | B17: 46236 | C17: =IF($B17="","",YEAR($B17)*100+MONTH($B17)) -> 202608 | D17: DEPENSE | E17: Nettoyage | F17: NADAFA | G17: Achat du jour | H17: 150 | I17: Espèce | J17: =IF($B17="","",IF(N($H17)<=0,"Montant ?",IF($D17="RECETTE",IF(COUNTIF(PARAMETRES!$E$5:$E$9,$E17)=0,"Catégorie ?","OK"),IF($D17="DEPENSE",IF(COUNTIF(PARAMETRES!$G$5:$G$20,$E17)=0,"Catégorie ?","OK"),"Type ?")))) -> OK
A18: =IF($B18="","",ROW()-7) -> 11 | B18: 46236 | C18: =IF($B18="","",YEAR($B18)*100+MONTH($B18)) -> 202608 | D18: DEPENSE | E18: Salaires | F18: BAR MEN | G18: Salaire / avance | H18: 600 | I18: Espèce | J18: =IF($B18="","",IF(N($H18)<=0,"Montant ?",IF($D18="RECETTE",IF(COUNTIF(PARAMETRES!$E$5:$E$9,$E18)=0,"Catégorie ?","OK"),IF($D18="DEPENSE",IF(COUNTIF(PARAMETRES!$G$5:$G$20,$E18)=0,"Catégorie ?","OK"),"Type ?")))) -> OK
A19: =IF($B19="","",ROW()-7) -> 12 | B19: 46236 | C19: =IF($B19="","",YEAR($B19)*100+MONTH($B19)) -> 202608 | D19: DEPENSE | E19: Salaires | F19: BAR MEN ALI | G19: Salaire / avance | H19: 600 | I19: Espèce | J19: =IF($B19="","",IF(N($H19)<=0,"Montant ?",IF($D19="RECETTE",IF(COUNTIF(PARAMETRES!$E$5:$E$9,$E19)=0,"Catégorie ?","OK"),IF($D19="DEPENSE",IF(COUNTIF(PARAMETRES!$G$5:$G$20,$E19)=0,"Catégorie ?","OK"),"Type ?")))) -> OK
... A152: =IF($B152="","",ROW()-7) -> 145 | B152: 46261 | C152: =IF($B152="","",YEAR($B152)*100+MONTH($B152)) -> 202608 | D152: DEPENSE | E152: Épicerie & Divers | F152: BIM | G152: Achat du jour | H152: 200 | I152: Espèce | J152: =IF($B152="","",IF(N($H152)<=0,"Montant ?",IF($D152="RECETTE",IF(COUNTIF(PARAMETRES!$E$5:$E$9,$E152)=0,"Catégorie ?","OK"),IF($D152="DEPENSE",IF(COUNTIF(PARAMETRES!$G$5:$G$20,$E152)=0,"Catégorie ?","OK"),"Type ?")))) -> OK
A153: =IF($B153="","",ROW()-7) | C153: =IF($B153="","",YEAR($B153)*100+MONTH($B153)) | J153: =IF($B153="","",IF(N($H153)<=0,"Montant ?",IF($D153="RECETTE",IF(COUNTIF(PARAMETRES!$E$5:$E$9,$E153)=0,"Catégorie ?","OK"),IF($D153="DEPENSE",IF(COUNTIF(PARAMETRES!$G$5:$G$20,$E153)=0,"Catégorie ?","OK"),"Type ?"))))
A154: =IF($B154="","",ROW()-7) | C154: =IF($B154="","",YEAR($B154)*100+MONTH($B154)) | J154: =IF($B154="","",IF(N($H154)<=0,"Montant ?",IF($D154="RECETTE",IF(COUNTIF(PARAMETRES!$E$5:$E$9,$E154)=0,"Catégorie ?","OK"),IF($D154="DEPENSE",IF(COUNTIF(PARAMETRES!$G$5:$G$20,$E154)=0,"Catégorie ?","OK"),"Type ?"))))
A155: =IF($B155="","",ROW()-7) | C155: =IF($B155="","",YEAR($B155)*100+MONTH($B155)) | J155: =IF($B155="","",IF(N($H155)<=0,"Montant ?",IF($D155="RECETTE",IF(COUNTIF(PARAMETRES!$E$5:$E$9,$E155)=0,"Catégorie ?","OK"),IF($D155="DEPENSE",IF(COUNTIF(PARAMETRES!$G$5:$G$20,$E155)=0,"Catégorie ?","OK"),"Type ?"))))
A156: =IF($B156="","",ROW()-7) | C156: =IF($B156="","",YEAR($B156)*100+MONTH($B156)) | J156: =IF($B156="","",IF(N($H156)<=0,"Montant ?",IF($D156="RECETTE",IF(COUNTIF(PARAMETRES!$E$5:$E$9,$E156)=0,"Catégorie ?","OK"),IF($D156="DEPENSE",IF(COUNTIF(PARAMETRES!$G$5:$G$20,$E156)=0,"Catégorie ?","OK"),"Type ?"))))
A157: =IF($B157="","",ROW()-7) | C157: =IF($B157="","",YEAR($B157)*100+MONTH($B157)) | J157: =IF($B157="","",IF(N($H157)<=0,"Montant ?",IF($D157="RECETTE",IF(COUNTIF(PARAMETRES!$E$5:$E$9,$E157)=0,"Catégorie ?","OK"),IF($D157="DEPENSE",IF(COUNTIF(PARAMETRES!$G$5:$G$20,$E157)=0,"Catégorie ?","OK"),"Type ?"))))
A158: =IF($B158="","",ROW()-7) | C158: =IF($B158="","",YEAR($B158)*100+MONTH($B158)) | J158: =IF($B158="","",IF(N($H158)<=0,"Montant ?",IF($D158="RECETTE",IF(COUNTIF(PARAMETRES!$E$5:$E$9,$E158)=0,"Catégorie ?","OK"),IF($D158="DEPENSE",IF(COUNTIF(PARAMETRES!$G$5:$G$20,$E158)=0,"Catégorie ?","OK"),"Type ?"))))
A159: =IF($B159="","",ROW()-7) | C159: =IF($B159="","",YEAR($B159)*100+MONTH($B159)) | J159: =IF($B159="","",IF(N($H159)<=0,"Montant ?",IF($D159="RECETTE",IF(COUNTIF(PARAMETRES!$E$5:$E$9,$E159)=0,"Catégorie ?","OK"),IF($D159="DEPENSE",IF(COUNTIF(PARAMETRES!$G$5:$G$20,$E159)=0,"Catégorie ?","OK"),"Type ?"))))
A160: =IF($B160="","",ROW()-7) | C160: =IF($B160="","",YEAR($B160)*100+MONTH($B160)) | J160: =IF($B160="","",IF(N($H160)<=0,"Montant ?",IF($D160="RECETTE",IF(COUNTIF(PARAMETRES!$E$5:$E$9,$E160)=0,"Catégorie ?","OK"),IF($D160="DEPENSE",IF(COUNTIF(PARAMETRES!$G$5:$G$20,$E160)=0,"Catégorie ?","OK"),"Type ?"))))
A161: =IF($B161="","",ROW()-7) | C161: =IF($B161="","",YEAR($B161)*100+MONTH($B161)) | J161: =IF($B161="","",IF(N($H161)<=0,"Montant ?",IF($D161="RECETTE",IF(COUNTIF(PARAMETRES!$E$5:$E$9,$E161)=0,"Catégorie ?","OK"),IF($D161="DEPENSE",IF(COUNTIF(PARAMETRES!$G$5:$G$20,$E161)=0,"Catégorie ?","OK"),"Type ?"))))
A162: =IF($B162="","",ROW()-7) | C162: =IF($B162="","",YEAR($B162)*100+MONTH($B162)) | J162: =IF($B162="","",IF(N($H162)<=0,"Montant ?",IF($D162="RECETTE",IF(COUNTIF(PARAMETRES!$E$5:$E$9,$E162)=0,"Catégorie ?","OK"),IF($D162="DEPENSE",IF(COUNTIF(PARAMETRES!$G$5:$G$20,$E162)=0,"Catégorie ?","OK"),"Type ?"))))
A163: =IF($B163="","",ROW()-7) | C163: =IF($B163="","",YEAR($B163)*100+MONTH($B163)) | J163: =IF($B163="","",IF(N($H163)<=0,"Montant ?",IF($D163="RECETTE",IF(COUNTIF(PARAMETRES!$E$5:$E$9,$E163)=0,"Catégorie ?","OK"),IF($D163="DEPENSE",IF(COUNTIF(PARAMETRES!$G$5:$G$20,$E163)=0,"Catégorie ?","OK"),"Type ?"))))
A164: =IF($B164="","",ROW()-7) | C164: =IF($B164="","",YEAR($B164)*100+MONTH($B164)) | J164: =IF($B164="","",IF(N($H164)<=0,"Montant ?",IF($D164="RECETTE",IF(COUNTIF(PARAMETRES!$E$5:$E$9,$E164)=0,"Catégorie ?","OK"),IF($D164="DEPENSE",IF(COUNTIF(PARAMETRES!$G$5:$G$20,$E164)=0,"Catégorie ?","OK"),"Type ?"))))
... A1007: =IF($B1007="","",ROW()-7) | C1007: =IF($B1007="","",YEAR($B1007)*100+MONTH($B1007)) | J1007: =IF($B1007="","",IF(N($H1007)<=0,"Montant ?",IF($D1007="RECETTE",IF(COUNTIF(PARAMETRES!$E$5:$E$9,$E1007)=0,"Catégorie ?","OK"),IF($D1007="DEPENSE",IF(COUNTIF(PARAMETRES!$G$5:$G$20,$E1007)=0,"Catégorie ?","OK"),"Type ?"))))

Sheet RECAP JOUR
A1: RÉCAP JOURNALIER DU MOIS
A2: Calculé automatiquement depuis le JOURNAL. Aucune saisie ici. Changez le mois dans PARAMÈTRES pour changer la période.
A3: =PARAMETRES!$C$15 -> 46235
A5: DATE | B5: JOUR | C5: RECETTE CAISSE | D5: GLOVO ESPECE | E5: GLOVO CARTE | F5: TOTAL RECETTE | G5: ACHATS | H5: NETTOYAGE | I5: SALAIRES | J5: CHARGES FIXES | K5: VIREMENTS | L5: AUTRES | M5: TOTAL DÉPENSES | N5: RÉSULTAT DU JOUR | O5: CAISSE CUMULÉE | P5: vs OBJ.
A6: =IF(1>PARAMETRES!$C$16,"",DATE(PARAMETRES!$C$12,PARAMETRES!$C$13,1)) -> 46235 | B6: =IF($A6="","",CHOOSE(WEEKDAY($A6,2),"Lundi","Mardi","Mercredi","Jeudi","Vendredi","Samedi","Dimanche")) -> Samedi | C6: =IF($A6="","",SUMIFS(JOURNAL!$H$8:$H$1007,JOURNAL!$E$8:$E$1007,"Vente Caisse",JOURNAL!$B$8:$B$1007,$A6)+SUMIFS(JOURNAL!$H$8:$H$1007,JOURNAL!$E$8:$E$1007,"Terrasse",JOURNAL!$B$8:$B$1007,$A6)+SUMIFS(JOURNAL!$H$8:$H$1007,JOURNAL!$E$8:$E$1007,"Autre Recette",JOURNAL!$B$8:$B$1007,$A6)) -> 2335 | D6: =IF($A6="","",SUMIFS(JOURNAL!$H$8:$H$1007,JOURNAL!$E$8:$E$1007,"Glovo Espèce",JOURNAL!$B$8:$B$1007,$A6)) -> 0 | E6: =IF($A6="","",SUMIFS(JOURNAL!$H$8:$H$1007,JOURNAL!$E$8:$E$1007,"Glovo Carte",JOURNAL!$B$8:$B$1007,$A6)) -> 0 | F6: =IF($A6="","",SUM($C6:$E6)) -> 2335 | G6: =IF($A6="","",SUMIFS(JOURNAL!$H$8:$H$1007,JOURNAL!$E$8:$E$1007,"Boissons",JOURNAL!$B$8:$B$1007,$A6)+SUMIFS(JOURNAL!$H$8:$H$1007,JOURNAL!$E$8:$E$1007,"Café & Torréfaction",JOURNAL!$B$8:$B$1007,$A6)+SUMIFS(JOURNAL!$H$8:$H$1007,JOURNAL!$E$8:$E$1007,"Boulangerie",JOURNAL!$B$8:$B$1007,$A6)+SUMIFS(JOURNAL!$H$8:$H$1007,JOURNAL!$E$8:$E$1007,"Fruits & Légumes",JOURNAL!$B$8:$B$1007,$A6)+SUMIFS(JOURNAL!$H$8:$H$1007,JOURNAL!$E$8:$E$1007,"Épicerie & Divers",JOURNAL!$B$8:$B$1007,$A6)) -> 771 | H6: =IF($A6="","",SUMIFS(JOURNAL!$H$8:$H$1007,JOURNAL!$E$8:$E$1007,"Nettoyage",JOURNAL!$B$8:$B$1007,$A6)) -> 150 | I6: =IF($A6="","",SUMIFS(JOURNAL!$H$8:$H$1007,JOURNAL!$E$8:$E$1007,"Salaires",JOURNAL!$B$8:$B$1007,$A6)) -> 0 | J6: =IF($A6="","",SUMIFS(JOURNAL!$H$8:$H$1007,JOURNAL!$E$8:$E$1007,"Loyer",JOURNAL!$B$8:$B$1007,$A6)+SUMIFS(JOURNAL!$H$8:$H$1007,JOURNAL!$E$8:$E$1007,"Eau & Électricité",JOURNAL!$B$8:$B$1007,$A6)+SUMIFS(JOURNAL!$H$8:$H$1007,JOURNAL!$E$8:$E$1007,"Internet & Télécom",JOURNAL!$B$8:$B$1007,$A6)+SUMIFS(JOURNAL!$H$8:$H$1007,JOURNAL!$E$8:$E$1007,"Taxes & Impôts",JOURNAL!$B$8:$B$1007,$A6)+SUMIFS(JOURNAL!$H$8:$H$1007,JOURNAL!$E$8:$E$1007,"Abonnements",JOURNAL!$B$8:$B$1007,$A6)+SUMIFS(JOURNAL!$H$8:$H$1007,JOURNAL!$E$8:$E$1007,"Entretien & Réparation",JOURNAL!$B$8:$B$1007,$A6)) -> 0 | K6: =IF($A6="","",SUMIFS(JOURNAL!$H$8:$H$1007,JOURNAL!$E$8:$E$1007,"Virement Banque",JOURNAL!$B$8:$B$1007,$A6)+SUMIFS(JOURNAL!$H$8:$H$1007,JOURNAL!$E$8:$E$1007,"Virement Associés",JOURNAL!$B$8:$B$1007,$A6)) -> 0 | L6: =IF($A6="","",$M6-SUM($G6:$K6)) -> 0 | M6: =IF($A6="","",SUMIFS(JOURNAL!$H$8:$H$1007,JOURNAL!$D$8:$D$1007,"DEPENSE",JOURNAL!$B$8:$B$1007,$A6)) -> 921 | N6: =IF($A6="","",$F6-$M6) -> 1414 | O6: =IF($A6="","",PARAMETRES!$C$19+$N6) -> 1414 | P6: =IF($A6="","",IF($F6=0,"—",$F6-PARAMETRES!$C$20)) -> 135
A7: =IF(2>PARAMETRES!$C$16,"",DATE(PARAMETRES!$C$12,PARAMETRES!$C$13,2)) -> 46236 | B7: =IF($A7="","",CHOOSE(WEEKDAY($A7,2),"Lundi","Mardi","Mercredi","Jeudi","Vendredi","Samedi","Dimanche")) -> Dimanche | C7: =IF($A7="","",SUMIFS(JOURNAL!$H$8:$H$1007,JOURNAL!$E$8:$E$1007,"Vente Caisse",JOURNAL!$B$8:$B$1007,$A7)+SUMIFS(JOURNAL!$H$8:$H$1007,JOURNAL!$E$8:$E$1007,"Terrasse",JOURNAL!$B$8:$B$1007,$A7)+SUMIFS(JOURNAL!$H$8:$H$1007,JOURNAL!$E$8:$E$1007,"Autre Recette",JOURNAL!$B$8:$B$1007,$A7)) -> 2456 | D7: =IF($A7="","",SUMIFS(JOURNAL!$H$8:$H$1007,JOURNAL!$E$8:$E$1007,"Glovo Espèce",JOURNAL!$B$8:$B$1007,$A7)) -> 0 | E7: =IF($A7="","",SUMIFS(JOURNAL!$H$8:$H$1007,JOURNAL!$E$8:$E$1007,"Glovo Carte",JOURNAL!$B$8:$B$1007,$A7)) -> 0 | F7: =IF($A7="","",SUM($C7:$E7)) -> 2456 | G7: =IF($A7="","",SUMIFS(JOURNAL!$H$8:$H$1007,JOURNAL!$E$8:$E$1007,"Boissons",JOURNAL!$B$8:$B$1007,$A7)+SUMIFS(JOURNAL!$H$8:$H$1007,JOURNAL!$E$8:$E$1007,"Café & Torréfaction",JOURNAL!$B$8:$B$1007,$A7)+SUMIFS(JOURNAL!$H$8:$H$1007,JOURNAL!$E$8:$E$1007,"Boulangerie",JOURNAL!$B$8:$B$1007,$A7)+SUMIFS(JOURNAL!$H$8:$H$1007,JOURNAL!$E$8:$E$1007,"Fruits & Légumes",JOURNAL!$B$8:$B$1007,$A7)+SUMIFS(JOURNAL!$H$8:$H$1007,JOURNAL!$E$8:$E$1007,"Épicerie & Divers",JOURNAL!$B$8:$B$1007,$A7)) -> 762 | H7: =IF($A7="","",SUMIFS(JOURNAL!$H$8:$H$1007,JOURNAL!$E$8:$E$1007,"Nettoyage",JOURNAL!$B$8:$B$1007,$A7)) -> 150 | I7: =IF($A7="","",SUMIFS(JOURNAL!$H$8:$H$1007,JOURNAL!$E$8:$E$1007,"Salaires",JOURNAL!$B$8:$B$1007,$A7)) -> 2700 | J7: =IF($A7="","",SUMIFS(JOURNAL!$H$8:$H$1007,JOURNAL!$E$8:$E$1007,"Loyer",JOURNAL!$B$8:$B$1007,$A7)+SUMIFS(JOURNAL!$H$8:$H$1007,JOURNAL!$E$8:$E$1007,"Eau & Électricité",JOURNAL!$B$8:$B$1007,$A7)+SUMIFS(JOURNAL!$H$8:$H$1007,JOURNAL!$E$8:$E$1007,"Internet & Télécom",JOURNAL!$B$8:$B$1007,$A7)+SUMIFS(JOURNAL!$H$8:$H$1007,JOURNAL!$E$8:$E$1007,"Taxes & Impôts",JOURNAL!$B$8:$B$1007,$A7)+SUMIFS(JOURNAL!$H$8:$H$1007,JOURNAL!$E$8:$E$1007,"Abonnements",JOURNAL!$B$8:$B$1007,$A7)+SUMIFS(JOURNAL!$H$8:$H$1007,JOURNAL!$E$8:$E$1007,"Entretien & Réparation",JOURNAL!$B$8:$B$1007,$A7)) -> 0 | K7: =IF($A7="","",SUMIFS(JOURNAL!$H$8:$H$1007,JOURNAL!$E$8:$E$1007,"Virement Banque",JOURNAL!$B$8:$B$1007,$A7)+SUMIFS(JOURNAL!$H$8:$H$1007,JOURNAL!$E$8:$E$1007,"Virement Associés",JOURNAL!$B$8:$B$1007,$A7)) -> 0 | L7: =IF($A7="","",$M7-SUM($G7:$K7)) -> 0 | M7: =IF($A7="","",SUMIFS(JOURNAL!$H$8:$H$1007,JOURNAL!$D$8:$D$1007,"DEPENSE",JOURNAL!$B$8:$B$1007,$A7)) -> 3612 | N7: =IF($A7="","",$F7-$M7) -> -1156 | O7: =IF($A7="","",$O6+$N7) -> 258 | P7: =IF($A7="","",IF($F7=0,"—",$F7-PARAMETRES!$C$20)) -> 256
A8: =IF(3>PARAMETRES!$C$16,"",DATE(PARAMETRES!$C$12,PARAMETRES!$C$13,3)) -> 46237 | B8: =IF($A8="","",CHOOSE(WEEKDAY($A8,2),"Lundi","Mardi","Mercredi","Jeudi","Vendredi","Samedi","Dimanche")) -> Lundi | C8: =IF($A8="","",SUMIFS(JOURNAL!$H$8:$H$1007,JOURNAL!$E$8:$E$1007,"Vente Caisse",JOURNAL!$B$8:$B$1007,$A8)+SUMIFS(JOURNAL!$H$8:$H$1007,JOURNAL!$E$8:$E$1007,"Terrasse",JOURNAL!$B$8:$B$1007,$A8)+SUMIFS(JOURNAL!$H$8:$H$1007,JOURNAL!$E$8:$E$1007,"Autre Recette",JOURNAL!$B$8:$B$1007,$A8)) -> 2456 | D8: =IF($A8="","",SUMIFS(JOURNAL!$H$8:$H$1007,JOURNAL!$E$8:$E$1007,"Glovo Espèce",JOURNAL!$B$8:$B$1007,$A8)) -> 0 | E8: =IF($A8="","",SUMIFS(JOURNAL!$H$8:$H$1007,JOURNAL!$E$8:$E$1007,"Glovo Carte",JOURNAL!$B$8:$B$1007,$A8)) -> 0 | F8: =IF($A8="","",SUM($C8:$E8)) -> 2456 | G8: =IF($A8="","",SUMIFS(JOURNAL!$H$8:$H$1007,JOURNAL!$E$8:$E$1007,"Boissons",JOURNAL!$B$8:$B$1007,$A8)+SUMIFS(JOURNAL!$H$8:$H$1007,JOURNAL!$E$8:$E$1007,"Café & Torréfaction",JOURNAL!$B$8:$B$1007,$A8)+SUMIFS(JOURNAL!$H$8:$H$1007,JOURNAL!$E$8:$E$1007,"Boulangerie",JOURNAL!$B$8:$B$1007,$A8)+SUMIFS(JOURNAL!$H$8:$H$1007,JOURNAL!$E$8:$E$1007,"Fruits & Légumes",JOURNAL!$B$8:$B$1007,$A8)+SUMIFS(JOURNAL!$H$8:$H$1007,JOURNAL!$E$8:$E$1007,"Épicerie & Divers",JOURNAL!$B$8:$B$1007,$A8)) -> 465 | H8: =IF($A8="","",SUMIFS(JOURNAL!$H$8:$H$1007,JOURNAL!$E$8:$E$1007,"Nettoyage",JOURNAL!$B$8:$B$1007,$A8)) -> 150 | I8: =IF($A8="","",SUMIFS(JOURNAL!$H$8:$H$1007,JOURNAL!$E$8:$E$1007,"Salaires",JOURNAL!$B$8:$B$1007,$A8)) -> 0 | J8: =IF($A8="","",SUMIFS(JOURNAL!$H$8:$H$1007,JOURNAL!$E$8:$E$1007,"Loyer",JOURNAL!$B$8:$B$1007,$A8)+SUMIFS(JOURNAL!$H$8:$H$1007,JOURNAL!$E$8:$E$1007,"Eau & Électricité",JOURNAL!$B$8:$B$1007,$A8)+SUMIFS(JOURNAL!$H$8:$H$1007,JOURNAL!$E$8:$E$1007,"Internet & Télécom",JOURNAL!$B$8:$B$1007,$A8)+SUMIFS(JOURNAL!$H$8:$H$1007,JOURNAL!$E$8:$E$1007,"Taxes & Impôts",JOURNAL!$B$8:$B$1007,$A8)+SUMIFS(JOURNAL!$H$8:$H$1007,JOURNAL!$E$8:$E$1007,"Abonnements",JOURNAL!$B$8:$B$1007,$A8)+SUMIFS(JOURNAL!$H$8:$H$1007,JOURNAL!$E$8:$E$1007,"Entretien & Réparation",JOURNAL!$B$8:$B$1007,$A8)) -> 0 | K8: =IF($A8="","",SUMIFS(JOURNAL!$H$8:$H$1007,JOURNAL!$E$8:$E$1007,"Virement Banque",JOURNAL!$B$8:$B$1007,$A8)+SUMIFS(JOURNAL!$H$8:$H$1007,JOURNAL!$E$8:$E$1007,"Virement Associés",JOURNAL!$B$8:$B$1007,$A8)) -> 0 | L8: =IF($A8="","",$M8-SUM($G8:$K8)) -> 0 | M8: =IF($A8="","",SUMIFS(JOURNAL!$H$8:$H$1007,JOURNAL!$D$8:$D$1007,"DEPENSE",JOURNAL!$B$8:$B$1007,$A8)) -> 615 | N8: =IF($A8="","",$F8-$M8) -> 1841 | O8: =IF($A8="","",$O7+$N8) -> 2099 | P8: =IF($A8="","",IF($F8=0,"—",$F8-PARAMETRES!$C$20)) -> 256
A9: =IF(4>PARAMETRES!$C$16,"",DATE(PARAMETRES!$C$12,PARAMETRES!$C$13,4)) -> 46238 | B9: =IF($A9="","",CHOOSE(WEEKDAY($A9,2),"Lundi","Mardi","Mercredi","Jeudi","Vendredi","Samedi","Dimanche")) -> Mardi | C9: =IF($A9="","",SUMIFS(JOURNAL!$H$8:$H$1007,JOURNAL!$E$8:$E$1007,"Vente Caisse",JOURNAL!$B$8:$B$1007,$A9)+SUMIFS(JOURNAL!$H$8:$H$1007,JOURNAL!$E$8:$E$1007,"Terrasse",JOURNAL!$B$8:$B$1007,$A9)+SUMIFS(JOURNAL!$H$8:$H$1007,JOURNAL!$E$8:$E$1007,"Autre Recette",JOURNAL!$B$8:$B$1007,$A9)) -> 2145 | D9: =IF($A9="","",SUMIFS(JOURNAL!$H$8:$H$1007,JOURNAL!$E$8:$E$1007,"Glovo Espèce",JOURNAL!$B$8:$B$1007,$A9)) -> 0 | E9: =IF($A9="","",SUMIFS(JOURNAL!$H$8:$H$1007,JOURNAL!$E$8:$E$1007,"Glovo Carte",JOURNAL!$B$8:$B$1007,$A9)) -> 0 | F9: =IF($A9="","",SUM($C9:$E9)) -> 2145 | G9: =IF($A9="","",SUMIFS(JOURNAL!$H$8:$H$1007,JOURNAL!$E$8:$E$1007,"Boissons",JOURNAL!$B$8:$B$1007,$A9)+SUMIFS(JOURNAL!$H$8:$H$1007,JOURNAL!$E$8:$E$1007,"Café & Torréfaction",JOURNAL!$B$8:$B$1007,$A9)+SUMIFS(JOURNAL!$H$8:$H$1007,JOURNAL!$E$8:$E$1007,"Boulangerie",JOURNAL!$B$8:$B$1007,$A9)+SUMIFS(JOURNAL!$H$8:$H$1007,JOURNAL!$E$8:$E$1007,"Fruits & Légumes",JOURNAL!$B$8:$B$1007,$A9)+SUMIFS(JOURNAL!$H$8:$H$1007,JOURNAL!$E$8:$E$1007,"Épicerie & Divers",JOURNAL!$B$8:$B$1007,$A9)) -> 1416 | H9: =IF($A9="","",SUMIFS(JOURNAL!$H$8:$H$1007,JOURNAL!$E$8:$E$1007,"Nettoyage",JOURNAL!$B$8:$B$1007,$A9)) -> 150 | I9: =IF($A9="","",SUMIFS(JOURNAL!$H$8:$H$1007,JOURNAL!$E$8:$E$1007,"Salaires",JOURNAL!$B$8:$B$1007,$A9)) -> 0 | J9: =IF($A9="","",SUMIFS(JOURNAL!$H$8:$H$1007,JOURNAL!$E$8:$E$1007,"Loyer",JOURNAL!$B$8:$B$1007,$A9)+SUMIFS(JOURNAL!$H$8:$H$1007,JOURNAL!$E$8:$E$1007,"Eau & Électricité",JOURNAL!$B$8:$B$1007,$A9)+SUMIFS(JOURNAL!$H$8:$H$1007,JOURNAL!$E$8:$E$1007,"Internet & Télécom",JOURNAL!$B$8:$B$1007,$A9)+SUMIFS(JOURNAL!$H$8:$H$1007,JOURNAL!$E$8:$E$1007,"Taxes & Impôts",JOURNAL!$B$8:$B$1007,$A9)+SUMIFS(JOURNAL!$H$8:$H$1007,JOURNAL!$E$8:$E$1007,"Abonnements",JOURNAL!$B$8:$B$1007,$A9)+SUMIFS(JOURNAL!$H$8:$H$1007,JOURNAL!$E$8:$E$1007,"Entretien & Réparation",JOURNAL!$B$8:$B$1007,$A9)) -> 0 | K9: =IF($A9="","",SUMIFS(JOURNAL!$H$8:$H$1007,JOURNAL!$E$8:$E$1007,"Virement Banque",JOURNAL!$B$8:$B$1007,$A9)+SUMIFS(JOURNAL!$H$8:$H$1007,JOURNAL!$E$8:$E$1007,"Virement Associés",JOURNAL!$B$8:$B$1007,$A9)) -> 0 | L9: =IF($A9="","",$M9-SUM($G9:$K9)) -> 0 | M9: =IF($A9="","",SUMIFS(JOURNAL!$H$8:$H$1007,JOURNAL!$D$8:$D$1007,"DEPENSE",JOURNAL!$B$8:$B$1007,$A9)) -> 1566 | N9: =IF($A9="","",$F9-$M9) -> 579 | O9: =IF($A9="","",$O8+$N9) -> 2678 | P9: =IF($A9="","",IF($F9=0,"—",$F9-PARAMETRES!$C$20)) -> -55
A10: =IF(5>PARAMETRES!$C$16,"",DATE(PARAMETRES!$C$12,PARAMETRES!$C$13,5)) -> 46239 | B10: =IF($A10="","",CHOOSE(WEEKDAY($A10,2),"Lundi","Mardi","Mercredi","Jeudi","Vendredi","Samedi","Dimanche")) -> Mercredi | C10: =IF($A10="","",SUMIFS(JOURNAL!$H$8:$H$1007,JOURNAL!$E$8:$E$1007,"Vente Caisse",JOURNAL!$B$8:$B$1007,$A10)+SUMIFS(JOURNAL!$H$8:$H$1007,JOURNAL!$E$8:$E$1007,"Terrasse",JOURNAL!$B$8:$B$1007,$A10)+SUMIFS(JOURNAL!$H$8:$H$1007,JOURNAL!$E$8:$E$1007,"Autre Recette",JOURNAL!$B$8:$B$1007,$A10)) -> 2233 | D10: =IF($A10="","",SUMIFS(JOURNAL!$H$8:$H$1007,JOURNAL!$E$8:$E$1007,"Glovo Espèce",JOURNAL!$B$8:$B$1007,$A10)) -> 0 | E10: =IF($A10="","",SUMIFS(JOURNAL!$H$8:$H$1007,JOURNAL!$E$8:$E$1007,"Glovo Carte",JOURNAL!$B$8:$B$1007,$A10)) -> 0 | F10: =IF($A10="","",SUM($C10:$E10)) -> 2233 | G10: =IF($A10="","",SUMIFS(JOURNAL!$H$8:$H$1007,JOURNAL!$E$8:$E$1007,"Boissons",JOURNAL!$B$8:$B$1007,$A10)+SUMIFS(JOURNAL!$H$8:$H$1007,JOURNAL!$E$8:$E$1007,"Café & Torréfaction",JOURNAL!$B$8:$B$1007,$A10)+SUMIFS(JOURNAL!$H$8:$H$1007,JOURNAL!$E$8:$E$1007,"Boulangerie",JOURNAL!$B$8:$B$1007,$A10)+SUMIFS(JOURNAL!$H$8:$H$1007,JOURNAL!$E$8:$E$1007,"Fruits & Légumes",JOURNAL!$B$8:$B$1007,$A10)+SUMIFS(JOURNAL!$H$8:$H$1007,JOURNAL!$E$8:$E$1007,"Épicerie & Divers",JOURNAL!$B$8:$B$1007,$A10)) -> 571 | H10: =IF($A10="","",SUMIFS(JOURNAL!$H$8:$H$1007,JOURNAL!$E$8:$E$1007,"Nettoyage",JOURNAL!$B$8:$B$1007,$A10)) -> 150 | I10: =IF($A10="","",SUMIFS(JOURNAL!$H$8:$H$1007,JOURNAL!$E$8:$E$1007,"Salaires",JOURNAL!$B$8:$B$1007,$A10)) -> 0 | J10: =IF($A10="","",SUMIFS(JOURNAL!$H$8:$H$1007,JOURNAL!$E$8:$E$1007,"Loyer",JOURNAL!$B$8:$B$1007,$A10)+SUMIFS(JOURNAL!$H$8:$H$1007,JOURNAL!$E$8:$E$1007,"Eau & Électricité",JOURNAL!$B$8:$B$1007,$A10)+SUMIFS(JOURNAL!$H$8:$H$1007,JOURNAL!$E$8:$E$1007,"Internet & Télécom",JOURNAL!$B$8:$B$1007,$A10)+SUMIFS(JOURNAL!$H$8:$H$1007,JOURNAL!$E$8:$E$1007,"Taxes & Impôts",JOURNAL!$B$8:$B$1007,$A10)+SUMIFS(JOURNAL!$H$8:$H$1007,JOURNAL!$E$8:$E$1007,"Abonnements",JOURNAL!$B$8:$B$1007,$A10)+SUMIFS(JOURNAL!$H$8:$H$1007,JOURNAL!$E$8:$E$1007,"Entretien & Réparation",JOURNAL!$B$8:$B$1007,$A10)) -> 0 | K10: =IF($A10="","",SUMIFS(JOURNAL!$H$8:$H$1007,JOURNAL!$E$8:$E$1007,"Virement Banque",JOURNAL!$B$8:$B$1007,$A10)+SUMIFS(JOURNAL!$H$8:$H$1007,JOURNAL!$E$8:$E$1007,"Virement Associés",JOURNAL!$B$8:$B$1007,$A10)) -> 0 | L10: =IF($A10="","",$M10-SUM($G10:$K10)) -> 0 | M10: =IF($A10="","",SUMIFS(JOURNAL!$H$8:$H$1007,JOURNAL!$D$8:$D$1007,"DEPENSE",JOURNAL!$B$8:$B$1007,$A10)) -> 721 | N10: =IF($A10="","",$F10-$M10) -> 1512 | O10: =IF($A10="","",$O9+$N10) -> 4190 | P10: =IF($A10="","",IF($F10=0,"—",$F10-PARAMETRES!$C$20)) -> 33
A11: =IF(6>PARAMETRES!$C$16,"",DATE(PARAMETRES!$C$12,PARAMETRES!$C$13,6)) -> 46240 | B11: =IF($A11="","",CHOOSE(WEEKDAY($A11,2),"Lundi","Mardi","Mercredi","Jeudi","Vendredi","Samedi","Dimanche")) -> Jeudi | C11: =IF($A11="","",SUMIFS(JOURNAL!$H$8:$H$1007,JOURNAL!$E$8:$E$1007,"Vente Caisse",JOURNAL!$B$8:$B$1007,$A11)+SUMIFS(JOURNAL!$H$8:$H$1007,JOURNAL!$E$8:$E$1007,"Terrasse",JOURNAL!$B$8:$B$1007,$A11)+SUMIFS(JOURNAL!$H$8:$H$1007,JOURNAL!$E$8:$E$1007,"Autre Recette",JOURNAL!$B$8:$B$1007,$A11)) -> 2074 | D11: =IF($A11="","",SUMIFS(JOURNAL!$H$8:$H$1007,JOURNAL!$E$8:$E$1007,"Glovo Espèce",JOURNAL!$B$8:$B$1007,$A11)) -> 0 | E11: =IF($A11="","",SUMIFS(JOURNAL!$H$8:$H$1007,JOURNAL!$E$8:$E$1007,"Glovo Carte",JOURNAL!$B$8:$B$1007,$A11)) -> 0 | F11: =IF($A11="","",SUM($C11:$E11)) -> 2074 | G11: =IF($A11="","",SUMIFS(JOURNAL!$H$8:$H$1007,JOURNAL!$E$8:$E$1007,"Boissons",JOURNAL!$B$8:$B$1007,$A11)+SUMIFS(JOURNAL!$H$8:$H$1007,JOURNAL!$E$8:$E$1007,"Café & Torréfaction",JOURNAL!$B$8:$B$1007,$A11)+SUMIFS(JOURNAL!$H$8:$H$1007,JOURNAL!$E$8:$E$1007,"Boulangerie",JOURNAL!$B$8:$B$1007,$A11)+SUMIFS(JOURNAL!$H$8:$H$1007,JOURNAL!$E$8:$E$1007,"Fruits & Légumes",JOURNAL!$B$8:$B$1007,$A11)+SUMIFS(JOURNAL!$H$8:$H$1007,JOURNAL!$E$8:$E$1007,"Épicerie & Divers",JOURNAL!$B$8:$B$1007,$A11)) -> 591 | H11: =IF($A11="","",SUMIFS(JOURNAL!$H$8:$H$1007,JOURNAL!$E$8:$E$1007,"Nettoyage",JOURNAL!$B$8:$B$1007,$A11)) -> 150 | I11: =IF($A11="","",SUMIFS(JOURNAL!$H$8:$H$1007,JOURNAL!$E$8:$E$1007,"Salaires",JOURNAL!$B$8:$B$1007,$A11)) -> 0 | J11: =IF($A11="","",SUMIFS(JOURNAL!$H$8:$H$1007,JOURNAL!$E$8:$E$1007,"Loyer",JOURNAL!$B$8:$B$1007,$A11)+SUMIFS(JOURNAL!$H$8:$H$1007,JOURNAL!$E$8:$E$1007,"Eau & Électricité",JOURNAL!$B$8:$B$1007,$A11)+SUMIFS(JOURNAL!$H$8:$H$1007,JOURNAL!$E$8:$E$1007,"Internet & Télécom",JOURNAL!$B$8:$B$1007,$A11)+SUMIFS(JOURNAL!$H$8:$H$1007,JOURNAL!$E$8:$E$1007,"Taxes & Impôts",JOURNAL!$B$8:$B$1007,$A11)+SUMIFS(JOURNAL!$H$8:$H$1007,JOURNAL!$E$8:$E$1007,"Abonnements",JOURNAL!$B$8:$B$1007,$A11)+SUMIFS(JOURNAL!$H$8:$H$1007,JOURNAL!$E$8:$E$1007,"Entretien & Réparation",JOURNAL!$B$8:$B$1007,$A11)) -> 0 | K11: =IF($A11="","",SUMIFS(JOURNAL!$H$8:$H$1007,JOURNAL!$E$8:$E$1007,"Virement Banque",JOURNAL!$B$8:$B$1007,$A11)+SUMIFS(JOURNAL!$H$8:$H$1007,JOURNAL!$E$8:$E$1007,"Virement Associés",JOURNAL!$B$8:$B$1007,$A11)) -> 0 | L11: =IF($A11="","",$M11-SUM($G11:$K11)) -> 0 | M11: =IF($A11="","",SUMIFS(JOURNAL!$H$8:$H$1007,JOURNAL!$D$8:$D$1007,"DEPENSE",JOURNAL!$B$8:$B$1007,$A11)) -> 741 | N11: =IF($A11="","",$F11-$M11) -> 1333 | O11: =IF($A11="","",$O10+$N11) -> 5523 | P11: =IF($A11="","",IF($F11=0,"—",$F11-PARAMETRES!$C$20)) -> -126
A12: =IF(7>PARAMETRES!$C$16,"",DATE(PARAMETRES!$C$12,PARAMETRES!$C$13,7)) -> 46241 | B12: =IF($A12="","",CHOOSE(WEEKDAY($A12,2),"Lundi","Mardi","Mercredi","Jeudi","Vendredi","Samedi","Dimanche")) -> Vendredi | C12: =IF($A12="","",SUMIFS(JOURNAL!$H$8:$H$1007,JOURNAL!$E$8:$E$1007,"Vente Caisse",JOURNAL!$B$8:$B$1007,$A12)+SUMIFS(JOURNAL!$H$8:$H$1007,JOURNAL!$E$8:$E$1007,"Terrasse",JOURNAL!$B$8:$B$1007,$A12)+SUMIFS(JOURNAL!$H$8:$H$1007,JOURNAL!$E$8:$E$1007,"Autre Recette",JOURNAL!$B$8:$B$1007,$A12)) -> 1892 | D12: =IF($A12="","",SUMIFS(JOURNAL!$H$8:$H$1007,JOURNAL!$E$8:$E$1007,"Glovo Espèce",JOURNAL!$B$8:$B$1007,$A12)) -> 0 | E12: =IF($A12="","",SUMIFS(JOURNAL!$H$8:$H$1007,JOURNAL!$E$8:$E$1007,"Glovo Carte",JOURNAL!$B$8:$B$1007,$A12)) -> 0 | F12: =IF($A12="","",SUM($C12:$E12)) -> 1892 | G12: =IF($A12="","",SUMIFS(JOURNAL!$H$8:$H$1007,JOURNAL!$E$8:$E$1007,"Boissons",JOURNAL!$B$8:$B$1007,$A12)+SUMIFS(JOURNAL!$H$8:$H$1007,JOURNAL!$E$8:$E$1007,"Café & Torréfaction",JOURNAL!$B$8:$B$1007,$A12)+SUMIFS(JOURNAL!$H$8:$H$1007,JOURNAL!$E$8:$E$1007,"Boulangerie",JOURNAL!$B$8:$B$1007,$A12)+SUMIFS(JOURNAL!$H$8:$H$1007,JOURNAL!$E$8:$E$1007,"Fruits & Légumes",JOURNAL!$B$8:$B$1007,$A12)+SUMIFS(JOURNAL!$H$8:$H$1007,JOURNAL!$E$8:$E$1007,"Épicerie & Divers",JOURNAL!$B$8:$B$1007,$A12)) -> 326 | H12: =IF($A12="","",SUMIFS(JOURNAL!$H$8:$H$1007,JOURNAL!$E$8:$E$1007,"Nettoyage",JOURNAL!$B$8:$B$1007,$A12)) -> 150 | I12: =IF($A12="","",SUMIFS(JOURNAL!$H$8:$H$1007,JOURNAL!$E$8:$E$1007,"Salaires",JOURNAL!$B$8:$B$1007,$A12)) -> 0 | J12: =IF($A12="","",SUMIFS(JOURNAL!$H$8:$H$1007,JOURNAL!$E$8:$E$1007,"Loyer",JOURNAL!$B$8:$B$1007,$A12)+SUMIFS(JOURNAL!$H$8:$H$1007,JOURNAL!$E$8:$E$1007,"Eau & Électricité",JOURNAL!$B$8:$B$1007,$A12)+SUMIFS(JOURNAL!$H$8:$H$1007,JOURNAL!$E$8:$E$1007,"Internet & Télécom",JOURNAL!$B$8:$B$1007,$A12)+SUMIFS(JOURNAL!$H$8:$H$1007,JOURNAL!$E$8:$E$1007,"Taxes & Impôts",JOURNAL!$B$8:$B$1007,$A12)+SUMIFS(JOURNAL!$H$8:$H$1007,JOURNAL!$E$8:$E$1007,"Abonnements",JOURNAL!$B$8:$B$1007,$A12)+SUMIFS(JOURNAL!$H$8:$H$1007,JOURNAL!$E$8:$E$1007,"Entretien & Réparation",JOURNAL!$B$8:$B$1007,$A12)) -> 0 | K12: =IF($A12="","",SUMIFS(JOURNAL!$H$8:$H$1007,JOURNAL!$E$8:$E$1007,"Virement Banque",JOURNAL!$B$8:$B$1007,$A12)+SUMIFS(JOURNAL!$H$8:$H$1007,JOURNAL!$E$8:$E$1007,"Virement Associés",JOURNAL!$B$8:$B$1007,$A12)) -> 0 | L12: =IF($A12="","",$M12-SUM($G12:$K12)) -> 0 | M12: =IF($A12="","",SUMIFS(JOURNAL!$H$8:$H$1007,JOURNAL!$D$8:$D$1007,"DEPENSE",JOURNAL!$B$8:$B$1007,$A12)) -> 476 | N12: =IF($A12="","",$F12-$M12) -> 1416 | O12: =IF($A12="","",$O11+$N12) -> 6939 | P12: =IF($A12="","",IF($F12=0,"—",$F12-PARAMETRES!$C$20)) -> -308
A13: =IF(8>PARAMETRES!$C$16,"",DATE(PARAMETRES!$C$12,PARAMETRES!$C$13,8)) -> 46242 | B13: =IF($A13="","",CHOOSE(WEEKDAY($A13,2),"Lundi","Mardi","Mercredi","Jeudi","Vendredi","Samedi","Dimanche")) -> Samedi | C13: =IF($A13="","",SUMIFS(JOURNAL!$H$8:$H$1007,JOURNAL!$E$8:$E$1007,"Vente Caisse",JOURNAL!$B$8:$B$1007,$A13)+SUMIFS(JOURNAL!$H$8:$H$1007,JOURNAL!$E$8:$E$1007,"Terrasse",JOURNAL!$B$8:$B$1007,$A13)+SUMIFS(JOURNAL!$H$8:$H$1007,JOURNAL!$E$8:$E$1007,"Autre Recette",JOURNAL!$B$8:$B$1007,$A13)) -> 2172 | D13: =IF($A13="","",SUMIFS(JOURNAL!$H$8:$H$1007,JOURNAL!$E$8:$E$1007,"Glovo Espèce",JOURNAL!$B$8:$B$1007,$A13)) -> 0 | E13: =IF($A13="","",SUMIFS(JOURNAL!$H$8:$H$1007,JOURNAL!$E$8:$E$1007,"Glovo Carte",JOURNAL!$B$8:$B$1007,$A13)) -> 0 | F13: =IF($A13="","",SUM($C13:$E13)) -> 2172 | G13: =IF($A13="","",SUMIFS(JOURNAL!$H$8:$H$1007,JOURNAL!$E$8:$E$1007,"Boissons",JOURNAL!$B$8:$B$1007,$A13)+SUMIFS(JOURNAL!$H$8:$H$1007,JOURNAL!$E$8:$E$1007,"Café & Torréfaction",JOURNAL!$B$8:$B$1007,$A13)+SUMIFS(JOURNAL!$H$8:$H$1007,JOURNAL!$E$8:$E$1007,"Boulangerie",JOURNAL!$B$8:$B$1007,$A13)+SUMIFS(JOURNAL!$H$8:$H$1007,JOURNAL!$E$8:$E$1007,"Fruits & Légumes",JOURNAL!$B$8:$B$1007,$A13)+SUMIFS(JOURNAL!$H$8:$H$1007,JOURNAL!$E$8:$E$1007,"Épicerie & Divers",JOURNAL!$B$8:$B$1007,$A13)) -> 606 | H13: =IF($A13="","",SUMIFS(JOURNAL!$H$8:$H$1007,JOURNAL!$E$8:$E$1007,"Nettoyage",JOURNAL!$B$8:$B$1007,$A13)) -> 150 | I13: =IF($A13="","",SUMIFS(JOURNAL!$H$8:$H$1007,JOURNAL!$E$8:$E$1007,"Salaires",JOURNAL!$B$8:$B$1007,$A13)) -> 0 | J13: =IF($A13="","",SUMIFS(JOURNAL!$H$8:$H$1007,JOURNAL!$E$8:$E$1007,"Loyer",JOURNAL!$B$8:$B$1007,$A13)+SUMIFS(JOURNAL!$H$8:$H$1007,JOURNAL!$E$8:$E$1007,"Eau & Électricité",JOURNAL!$B$8:$B$1007,$A13)+SUMIFS(JOURNAL!$H$8:$H$1007,JOURNAL!$E$8:$E$1007,"Internet & Télécom",JOURNAL!$B$8:$B$1007,$A13)+SUMIFS(JOURNAL!$H$8:$H$1007,JOURNAL!$E$8:$E$1007,"Taxes & Impôts",JOURNAL!$B$8:$B$1007,$A13)+SUMIFS(JOURNAL!$H$8:$H$1007,JOURNAL!$E$8:$E$1007,"Abonnements",JOURNAL!$B$8:$B$1007,$A13)+SUMIFS(JOURNAL!$H$8:$H$1007,JOURNAL!$E$8:$E$1007,"Entretien & Réparation",JOURNAL!$B$8:$B$1007,$A13)) -> 0 | K13: =IF($A13="","",SUMIFS(JOURNAL!$H$8:$H$1007,JOURNAL!$E$8:$E$1007,"Virement Banque",JOURNAL!$B$8:$B$1007,$A13)+SUMIFS(JOURNAL!$H$8:$H$1007,JOURNAL!$E$8:$E$1007,"Virement Associés",JOURNAL!$B$8:$B$1007,$A13)) -> 0 | L13: =IF($A13="","",$M13-SUM($G13:$K13)) -> 0 | M13: =IF($A13="","",SUMIFS(JOURNAL!$H$8:$H$1007,JOURNAL!$D$8:$D$1007,"DEPENSE",JOURNAL!$B$8:$B$1007,$A13)) -> 756 | N13: =IF($A13="","",$F13-$M13) -> 1416 | O13: =IF($A13="","",$O12+$N13) -> 8355 | P13: =IF($A13="","",IF($F13=0,"—",$F13-PARAMETRES!$C$20)) -> -28
A14: =IF(9>PARAMETRES!$C$16,"",DATE(PARAMETRES!$C$12,PARAMETRES!$C$13,9)) -> 46243 | B14: =IF($A14="","",CHOOSE(WEEKDAY($A14,2),"Lundi","Mardi","Mercredi","Jeudi","Vendredi","Samedi","Dimanche")) -> Dimanche | C14: =IF($A14="","",SUMIFS(JOURNAL!$H$8:$H$1007,JOURNAL!$E$8:$E$1007,"Vente Caisse",JOURNAL!$B$8:$B$1007,$A14)+SUMIFS(JOURNAL!$H$8:$H$1007,JOURNAL!$E$8:$E$1007,"Terrasse",JOURNAL!$B$8:$B$1007,$A14)+SUMIFS(JOURNAL!$H$8:$H$1007,JOURNAL!$E$8:$E$1007,"Autre Recette",JOURNAL!$B$8:$B$1007,$A14)) -> 2218 | D14: =IF($A14="","",SUMIFS(JOURNAL!$H$8:$H$1007,JOURNAL!$E$8:$E$1007,"Glovo Espèce",JOURNAL!$B$8:$B$1007,$A14)) -> 0 | E14: =IF($A14="","",SUMIFS(JOURNAL!$H$8:$H$1007,JOURNAL!$E$8:$E$1007,"Glovo Carte",JOURNAL!$B$8:$B$1007,$A14)) -> 0 | F14: =IF($A14="","",SUM($C14:$E14)) -> 2218 | G14: =IF($A14="","",SUMIFS(JOURNAL!$H$8:$H$1007,JOURNAL!$E$8:$E$1007,"Boissons",JOURNAL!$B$8:$B$1007,$A14)+SUMIFS(JOURNAL!$H$8:$H$1007,JOURNAL!$E$8:$E$1007,"Café & Torréfaction",JOURNAL!$B$8:$B$1007,$A14)+SUMIFS(JOURNAL!$H$8:$H$1007,JOURNAL!$E$8:$E$1007,"Boulangerie",JOURNAL!$B$8:$B$1007,$A14)+SUMIFS(JOURNAL!$H$8:$H$1007,JOURNAL!$E$8:$E$1007,"Fruits & Légumes",JOURNAL!$B$8:$B$1007,$A14)+SUMIFS(JOURNAL!$H$8:$H$1007,JOURNAL!$E$8:$E$1007,"Épicerie & Divers",JOURNAL!$B$8:$B$1007,$A14)) -> 1023 | H14: =IF($A14="","",SUMIFS(JOURNAL!$H$8:$H$1007,JOURNAL!$E$8:$E$1007,"Nettoyage",JOURNAL!$B$8:$B$1007,$A14)) -> 150 | I14: =IF($A14="","",SUMIFS(JOURNAL!$H$8:$H$1007,JOURNAL!$E$8:$E$1007,"Salaires",JOURNAL!$B$8:$B$1007,$A14)) -> 2700 | J14: =IF($A14="","",SUMIFS(JOURNAL!$H$8:$H$1007,JOURNAL!$E$8:$E$1007,"Loyer",JOURNAL!$B$8:$B$1007,$A14)+SUMIFS(JOURNAL!$H$8:$H$1007,JOURNAL!$E$8:$E$1007,"Eau & Électricité",JOURNAL!$B$8:$B$1007,$A14)+SUMIFS(JOURNAL!$H$8:$H$1007,JOURNAL!$E$8:$E$1007,"Internet & Télécom",JOURNAL!$B$8:$B$1007,$A14)+SUMIFS(JOURNAL!$H$8:$H$1007,JOURNAL!$E$8:$E$1007,"Taxes & Impôts",JOURNAL!$B$8:$B$1007,$A14)+SUMIFS(JOURNAL!$H$8:$H$1007,JOURNAL!$E$8:$E$1007,"Abonnements",JOURNAL!$B$8:$B$1007,$A14)+SUMIFS(JOURNAL!$H$8:$H$1007,JOURNAL!$E$8:$E$1007,"Entretien & Réparation",JOURNAL!$B$8:$B$1007,$A14)) -> 0 | K14: =IF($A14="","",SUMIFS(JOURNAL!$H$8:$H$1007,JOURNAL!$E$8:$E$1007,"Virement Banque",JOURNAL!$B$8:$B$1007,$A14)+SUMIFS(JOURNAL!$H$8:$H$1007,JOURNAL!$E$8:$E$1007,"Virement Associés",JOURNAL!$B$8:$B$1007,$A14)) -> 0 | L14: =IF($A14="","",$M14-SUM($G14:$K14)) -> 0 | M14: =IF($A14="","",SUMIFS(JOURNAL!$H$8:$H$1007,JOURNAL!$D$8:$D$1007,"DEPENSE",JOURNAL!$B$8:$B$1007,$A14)) -> 3873 | N14: =IF($A14="","",$F14-$M14) -> -1655 | O14: =IF($A14="","",$O13+$N14) -> 6700 | P14: =IF($A14="","",IF($F14=0,"—",$F14-PARAMETRES!$C$20)) -> 18
A15: =IF(10>PARAMETRES!$C$16,"",DATE(PARAMETRES!$C$12,PARAMETRES!$C$13,10)) -> 46244 | B15: =IF($A15="","",CHOOSE(WEEKDAY($A15,2),"Lundi","Mardi","Mercredi","Jeudi","Vendredi","Samedi","Dimanche")) -> Lundi | C15: =IF($A15="","",SUMIFS(JOURNAL!$H$8:$H$1007,JOURNAL!$E$8:$E$1007,"Vente Caisse",JOURNAL!$B$8:$B$1007,$A15)+SUMIFS(JOURNAL!$H$8:$H$1007,JOURNAL!$E$8:$E$1007,"Terrasse",JOURNAL!$B$8:$B$1007,$A15)+SUMIFS(JOURNAL!$H$8:$H$1007,JOURNAL!$E$8:$E$1007,"Autre Recette",JOURNAL!$B$8:$B$1007,$A15)) -> 1548 | D15: =IF($A15="","",SUMIFS(JOURNAL!$H$8:$H$1007,JOURNAL!$E$8:$E$1007,"Glovo Espèce",JOURNAL!$B$8:$B$1007,$A15)) -> 0 | E15: =IF($A15="","",SUMIFS(JOURNAL!$H$8:$H$1007,JOURNAL!$E$8:$E$1007,"Glovo Carte",JOURNAL!$B$8:$B$1007,$A15)) -> 0 | F15: =IF($A15="","",SUM($C15:$E15)) -> 1548 | G15: =IF($A15="","",SUMIFS(JOURNAL!$H$8:$H$1007,JOURNAL!$E$8:$E$1007,"Boissons",JOURNAL!$B$8:$B$1007,$A15)+SUMIFS(JOURNAL!$H$8:$H$1007,JOURNAL!$E$8:$E$1007,"Café & Torréfaction",JOURNAL!$B$8:$B$1007,$A15)+SUMIFS(JOURNAL!$H$8:$H$1007,JOURNAL!$E$8:$E$1007,"Boulangerie",JOURNAL!$B$8:$B$1007,$A15)+SUMIFS(JOURNAL!$H$8:$H$1007,JOURNAL!$E$8:$E$1007,"Fruits & Légumes",JOURNAL!$B$8:$B$1007,$A15)+SUMIFS(JOURNAL!$H$8:$H$1007,JOURNAL!$E$8:$E$1007,"Épicerie & Divers",JOURNAL!$B$8:$B$1007,$A15)) -> 471 | H15: =IF($A15="","",SUMIFS(JOURNAL!$H$8:$H$1007,JOURNAL!$E$8:$E$1007,"Nettoyage",JOURNAL!$B$8:$B$1007,$A15)) -> 150 | I15: =IF($A15="","",SUMIFS(JOURNAL!$H$8:$H$1007,JOURNAL!$E$8:$E$1007,"Salaires",JOURNAL!$B$8:$B$1007,$A15)) -> 0 | J15: =IF($A15="","",SUMIFS(JOURNAL!$H$8:$H$1007,JOURNAL!$E$8:$E$1007,"Loyer",JOURNAL!$B$8:$B$1007,$A15)+SUMIFS(JOURNAL!$H$8:$H$1007,JOURNAL!$E$8:$E$1007,"Eau & Électricité",JOURNAL!$B$8:$B$1007,$A15)+SUMIFS(JOURNAL!$H$8:$H$1007,JOURNAL!$E$8:$E$1007,"Internet & Télécom",JOURNAL!$B$8:$B$1007,$A15)+SUMIFS(JOURNAL!$H$8:$H$1007,JOURNAL!$E$8:$E$1007,"Taxes & Impôts",JOURNAL!$B$8:$B$1007,$A15)+SUMIFS(JOURNAL!$H$8:$H$1007,JOURNAL!$E$8:$E$1007,"Abonnements",JOURNAL!$B$8:$B$1007,$A15)+SUMIFS(JOURNAL!$H$8:$H$1007,JOURNAL!$E$8:$E$1007,"Entretien & Réparation",JOURNAL!$B$8:$B$1007,$A15)) -> 0 | K15: =IF($A15="","",SUMIFS(JOURNAL!$H$8:$H$1007,JOURNAL!$E$8:$E$1007,"Virement Banque",JOURNAL!$B$8:$B$1007,$A15)+SUMIFS(JOURNAL!$H$8:$H$1007,JOURNAL!$E$8:$E$1007,"Virement Associés",JOURNAL!$B$8:$B$1007,$A15)) -> 0 | L15: =IF($A15="","",$M15-SUM($G15:$K15)) -> 0 | M15: =IF($A15="","",SUMIFS(JOURNAL!$H$8:$H$1007,JOURNAL!$D$8:$D$1007,"DEPENSE",JOURNAL!$B$8:$B$1007,$A15)) -> 621 | N15: =IF($A15="","",$F15-$M15) -> 927 | O15: =IF($A15="","",$O14+$N15) -> 7627 | P15: =IF($A15="","",IF($F15=0,"—",$F15-PARAMETRES!$C$20)) -> -652
A16: =IF(11>PARAMETRES!$C$16,"",DATE(PARAMETRES!$C$12,PARAMETRES!$C$13,11)) -> 46245 | B16: =IF($A16="","",CHOOSE(WEEKDAY($A16,2),"Lundi","Mardi","Mercredi","Jeudi","Vendredi","Samedi","Dimanche")) -> Mardi | C16: =IF($A16="","",SUMIFS(JOURNAL!$H$8:$H$1007,JOURNAL!$E$8:$E$1007,"Vente Caisse",JOURNAL!$B$8:$B$1007,$A16)+SUMIFS(JOURNAL!$H$8:$H$1007,JOURNAL!$E$8:$E$1007,"Terrasse",JOURNAL!$B$8:$B$1007,$A16)+SUMIFS(JOURNAL!$H$8:$H$1007,JOURNAL!$E$8:$E$1007,"Autre Recette",JOURNAL!$B$8:$B$1007,$A16)) -> 1973 | D16: =IF($A16="","",SUMIFS(JOURNAL!$H$8:$H$1007,JOURNAL!$E$8:$E$1007,"Glovo Espèce",JOURNAL!$B$8:$B$1007,$A16)) -> 0 | E16: =IF($A16="","",SUMIFS(JOURNAL!$H$8:$H$1007,JOURNAL!$E$8:$E$1007,"Glovo Carte",JOURNAL!$B$8:$B$1007,$A16)) -> 0 | F16: =IF($A16="","",SUM($C16:$E16)) -> 1973 | G16: =IF($A16="","",SUMIFS(JOURNAL!$H$8:$H$1007,JOURNAL!$E$8:$E$1007,"Boissons",JOURNAL!$B$8:$B$1007,$A16)+SUMIFS(JOURNAL!$H$8:$H$1007,JOURNAL!$E$8:$E$1007,"Café & Torréfaction",JOURNAL!$B$8:$B$1007,$A16)+SUMIFS(JOURNAL!$H$8:$H$1007,JOURNAL!$E$8:$E$1007,"Boulangerie",JOURNAL!$B$8:$B$1007,$A16)+SUMIFS(JOURNAL!$H$8:$H$1007,JOURNAL!$E$8:$E$1007,"Fruits & Légumes",JOURNAL!$B$8:$B$1007,$A16)+SUMIFS(JOURNAL!$H$8:$H$1007,JOURNAL!$E$8:$E$1007,"Épicerie & Divers",JOURNAL!$B$8:$B$1007,$A16)) -> 737 | H16: =IF($A16="","",SUMIFS(JOURNAL!$H$8:$H$1007,JOURNAL!$E$8:$E$1007,"Nettoyage",JOURNAL!$B$8:$B$1007,$A16)) -> 150 | I16: =IF($A16="","",SUMIFS(JOURNAL!$H$8:$H$1007,JOURNAL!$E$8:$E$1007,"Salaires",JOURNAL!$B$8:$B$1007,$A16)) -> 2000 | J16: =IF($A16="","",SUMIFS(JOURNAL!$H$8:$H$1007,JOURNAL!$E$8:$E$1007,"Loyer",JOURNAL!$B$8:$B$1007,$A16)+SUMIFS(JOURNAL!$H$8:$H$1007,JOURNAL!$E$8:$E$1007,"Eau & Électricité",JOURNAL!$B$8:$B$1007,$A16)+SUMIFS(JOURNAL!$H$8:$H$1007,JOURNAL!$E$8:$E$1007,"Internet & Télécom",JOURNAL!$B$8:$B$1007,$A16)+SUMIFS(JOURNAL!$H$8:$H$1007,JOURNAL!$E$8:$E$1007,"Taxes & Impôts",JOURNAL!$B$8:$B$1007,$A16)+SUMIFS(JOURNAL!$H$8:$H$1007,JOURNAL!$E$8:$E$1007,"Abonnements",JOURNAL!$B$8:$B$1007,$A16)+SUMIFS(JOURNAL!$H$8:$H$1007,JOURNAL!$E$8:$E$1007,"Entretien & Réparation",JOURNAL!$B$8:$B$1007,$A16)) -> 5000 | K16: =IF($A16="","",SUMIFS(JOURNAL!$H$8:$H$1007,JOURNAL!$E$8:$E$1007,"Virement Banque",JOURNAL!$B$8:$B$1007,$A16)+SUMIFS(JOURNAL!$H$8:$H$1007,JOURNAL!$E$8:$E$1007,"Virement Associés",JOURNAL!$B$8:$B$1007,$A16)) -> 0 | L16: =IF($A16="","",$M16-SUM($G16:$K16)) -> 0 | M16: =IF($A16="","",SUMIFS(JOURNAL!$H$8:$H$1007,JOURNAL!$D$8:$D$1007,"DEPENSE",JOURNAL!$B$8:$B$1007,$A16)) -> 7887 | N16: =IF($A16="","",$F16-$M16) -> -5914 | O16: =IF($A16="","",$O15+$N16) -> 1713 | P16: =IF($A16="","",IF($F16=0,"—",$F16-PARAMETRES!$C$20)) -> -227
A17: =IF(12>PARAMETRES!$C$16,"",DATE(PARAMETRES!$C$12,PARAMETRES!$C$13,12)) -> 46246 | B17: =IF($A17="","",CHOOSE(WEEKDAY($A17,2),"Lundi","Mardi","Mercredi","Jeudi","Vendredi","Samedi","Dimanche")) -> Mercredi | C17: =IF($A17="","",SUMIFS(JOURNAL!$H$8:$H$1007,JOURNAL!$E$8:$E$1007,"Vente Caisse",JOURNAL!$B$8:$B$1007,$A17)+SUMIFS(JOURNAL!$H$8:$H$1007,JOURNAL!$E$8:$E$1007,"Terrasse",JOURNAL!$B$8:$B$1007,$A17)+SUMIFS(JOURNAL!$H$8:$H$1007,JOURNAL!$E$8:$E$1007,"Autre Recette",JOURNAL!$B$8:$B$1007,$A17)) -> 2045 | D17: =IF($A17="","",SUMIFS(JOURNAL!$H$8:$H$1007,JOURNAL!$E$8:$E$1007,"Glovo Espèce",JOURNAL!$B$8:$B$1007,$A17)) -> 0 | E17: =IF($A17="","",SUMIFS(JOURNAL!$H$8:$H$1007,JOURNAL!$E$8:$E$1007,"Glovo Carte",JOURNAL!$B$8:$B$1007,$A17)) -> 0 | F17: =IF($A17="","",SUM($C17:$E17)) -> 2045 | G17: =IF($A17="","",SUMIFS(JOURNAL!$H$8:$H$1007,JOURNAL!$E$8:$E$1007,"Boissons",JOURNAL!$B$8:$B$1007,$A17)+SUMIFS(JOURNAL!$H$8:$H$1007,JOURNAL!$E$8:$E$1007,"Café & Torréfaction",JOURNAL!$B$8:$B$1007,$A17)+SUMIFS(JOURNAL!$H$8:$H$1007,JOURNAL!$E$8:$E$1007,"Boulangerie",JOURNAL!$B$8:$B$1007,$A17)+SUMIFS(JOURNAL!$H$8:$H$1007,JOURNAL!$E$8:$E$1007,"Fruits & Légumes",JOURNAL!$B$8:$B$1007,$A17)+SUMIFS(JOURNAL!$H$8:$H$1007,JOURNAL!$E$8:$E$1007,"Épicerie & Divers",JOURNAL!$B$8:$B$1007,$A17)) -> 2191 | H17: =IF($A17="","",SUMIFS(JOURNAL!$H$8:$H$1007,JOURNAL!$E$8:$E$1007,"Nettoyage",JOURNAL!$B$8:$B$1007,$A17)) -> 150 | I17: =IF($A17="","",SUMIFS(JOURNAL!$H$8:$H$1007,JOURNAL!$E$8:$E$1007,"Salaires",JOURNAL!$B$8:$B$1007,$A17)) -> 0 | J17: =IF($A17="","",SUMIFS(JOURNAL!$H$8:$H$1007,JOURNAL!$E$8:$E$1007,"Loyer",JOURNAL!$B$8:$B$1007,$A17)+SUMIFS(JOURNAL!$H$8:$H$1007,JOURNAL!$E$8:$E$1007,"Eau & Électricité",JOURNAL!$B$8:$B$1007,$A17)+SUMIFS(JOURNAL!$H$8:$H$1007,JOURNAL!$E$8:$E$1007,"Internet & Télécom",JOURNAL!$B$8:$B$1007,$A17)+SUMIFS(JOURNAL!$H$8:$H$1007,JOURNAL!$E$8:$E$1007,"Taxes & Impôts",JOURNAL!$B$8:$B$1007,$A17)+SUMIFS(JOURNAL!$H$8:$H$1007,JOURNAL!$E$8:$E$1007,"Abonnements",JOURNAL!$B$8:$B$1007,$A17)+SUMIFS(JOURNAL!$H$8:$H$1007,JOURNAL!$E$8:$E$1007,"Entretien & Réparation",JOURNAL!$B$8:$B$1007,$A17)) -> 0 | K17: =IF($A17="","",SUMIFS(JOURNAL!$H$8:$H$1007,JOURNAL!$E$8:$E$1007,"Virement Banque",JOURNAL!$B$8:$B$1007,$A17)+SUMIFS(JOURNAL!$H$8:$H$1007,JOURNAL!$E$8:$E$1007,"Virement Associés",JOURNAL!$B$8:$B$1007,$A17)) -> 0 | L17: =IF($A17="","",$M17-SUM($G17:$K17)) -> 0 | M17: =IF($A17="","",SUMIFS(JOURNAL!$H$8:$H$1007,JOURNAL!$D$8:$D$1007,"DEPENSE",JOURNAL!$B$8:$B$1007,$A17)) -> 2341 | N17: =IF($A17="","",$F17-$M17) -> -296 | O17: =IF($A17="","",$O16+$N17) -> 1417 | P17: =IF($A17="","",IF($F17=0,"—",$F17-PARAMETRES!$C$20)) -> -155
A18: =IF(13>PARAMETRES!$C$16,"",DATE(PARAMETRES!$C$12,PARAMETRES!$C$13,13)) -> 46247 | B18: =IF($A18="","",CHOOSE(WEEKDAY($A18,2),"Lundi","Mardi","Mercredi","Jeudi","Vendredi","Samedi","Dimanche")) -> Jeudi | C18: =IF($A18="","",SUMIFS(JOURNAL!$H$8:$H$1007,JOURNAL!$E$8:$E$1007,"Vente Caisse",JOURNAL!$B$8:$B$1007,$A18)+SUMIFS(JOURNAL!$H$8:$H$1007,JOURNAL!$E$8:$E$1007,"Terrasse",JOURNAL!$B$8:$B$1007,$A18)+SUMIFS(JOURNAL!$H$8:$H$1007,JOURNAL!$E$8:$E$1007,"Autre Recette",JOURNAL!$B$8:$B$1007,$A18)) -> 2014 | D18: =IF($A18="","",SUMIFS(JOURNAL!$H$8:$H$1007,JOURNAL!$E$8:$E$1007,"Glovo Espèce",JOURNAL!$B$8:$B$1007,$A18)) -> 0 | E18: =IF($A18="","",SUMIFS(JOURNAL!$H$8:$H$1007,JOURNAL!$E$8:$E$1007,"Glovo Carte",JOURNAL!$B$8:$B$1007,$A18)) -> 0 | F18: =IF($A18="","",SUM($C18:$E18)) -> 2014 | G18: =IF($A18="","",SUMIFS(JOURNAL!$H$8:$H$1007,JOURNAL!$E$8:$E$1007,"Boissons",JOURNAL!$B$8:$B$1007,$A18)+SUMIFS(JOURNAL!$H$8:$H$1007,JOURNAL!$E$8:$E$1007,"Café & Torréfaction",JOURNAL!$B$8:$B$1007,$A18)+SUMIFS(JOURNAL!$H$8:$H$1007,JOURNAL!$E$8:$E$1007,"Boulangerie",JOURNAL!$B$8:$B$1007,$A18)+SUMIFS(JOURNAL!$H$8:$H$1007,JOURNAL!$E$8:$E$1007,"Fruits & Légumes",JOURNAL!$B$8:$B$1007,$A18)+SUMIFS(JOURNAL!$H$8:$H$1007,JOURNAL!$E$8:$E$1007,"Épicerie & Divers",JOURNAL!$B$8:$B$1007,$A18)) -> 465 | H18: =IF($A18="","",SUMIFS(JOURNAL!$H$8:$H$1007,JOURNAL!$E$8:$E$1007,"Nettoyage",JOURNAL!$B$8:$B$1007,$A18)) -> 150 | I18: =IF($A18="","",SUMIFS(JOURNAL!$H$8:$H$1007,JOURNAL!$E$8:$E$1007,"Salaires",JOURNAL!$B$8:$B$1007,$A18)) -> 0 | J18: =IF($A18="","",SUMIFS(JOURNAL!$H$8:$H$1007,JOURNAL!$E$8:$E$1007,"Loyer",JOURNAL!$B$8:$B$1007,$A18)+SUMIFS(JOURNAL!$H$8:$H$1007,JOURNAL!$E$8:$E$1007,"Eau & Électricité",JOURNAL!$B$8:$B$1007,$A18)+SUMIFS(JOURNAL!$H$8:$H$1007,JOURNAL!$E$8:$E$1007,"Internet & Télécom",JOURNAL!$B$8:$B$1007,$A18)+SUMIFS(JOURNAL!$H$8:$H$1007,JOURNAL!$E$8:$E$1007,"Taxes & Impôts",JOURNAL!$B$8:$B$1007,$A18)+SUMIFS(JOURNAL!$H$8:$H$1007,JOURNAL!$E$8:$E$1007,"Abonnements",JOURNAL!$B$8:$B$1007,$A18)+SUMIFS(JOURNAL!$H$8:$H$1007,JOURNAL!$E$8:$E$1007,"Entretien & Réparation",JOURNAL!$B$8:$B$1007,$A18)) -> 0 | K18: =IF($A18="","",SUMIFS(JOURNAL!$H$8:$H$1007,JOURNAL!$E$8:$E$1007,"Virement Banque",JOURNAL!$B$8:$B$1007,$A18)+SUMIFS(JOURNAL!$H$8:$H$1007,JOURNAL!$E$8:$E$1007,"Virement Associés",JOURNAL!$B$8:$B$1007,$A18)) -> 0 | L18: =IF($A18="","",$M18-SUM($G18:$K18)) -> 0 | M18: =IF($A18="","",SUMIFS(JOURNAL!$H$8:$H$1007,JOURNAL!$D$8:$D$1007,"DEPENSE",JOURNAL!$B$8:$B$1007,$A18)) -> 615 | N18: =IF($A18="","",$F18-$M18) -> 1399 | O18: =IF($A18="","",$O17+$N18) -> 2816 | P18: =IF($A18="","",IF($F18=0,"—",$F18-PARAMETRES!$C$20)) -> -186
A19: =IF(14>PARAMETRES!$C$16,"",DATE(PARAMETRES!$C$12,PARAMETRES!$C$13,14)) -> 46248 | B19: =IF($A19="","",CHOOSE(WEEKDAY($A19,2),"Lundi","Mardi","Mercredi","Jeudi","Vendredi","Samedi","Dimanche")) -> Vendredi | C19: =IF($A19="","",SUMIFS(JOURNAL!$H$8:$H$1007,JOURNAL!$E$8:$E$1007,"Vente Caisse",JOURNAL!$B$8:$B$1007,$A19)+SUMIFS(JOURNAL!$H$8:$H$1007,JOURNAL!$E$8:$E$1007,"Terrasse",JOURNAL!$B$8:$B$1007,$A19)+SUMIFS(JOURNAL!$H$8:$H$1007,JOURNAL!$E$8:$E$1007,"Autre Recette",JOURNAL!$B$8:$B$1007,$A19)) -> 1902 | D19: =IF($A19="","",SUMIFS(JOURNAL!$H$8:$H$1007,JOURNAL!$E$8:$E$1007,"Glovo Espèce",JOURNAL!$B$8:$B$1007,$A19)) -> 0 | E19: =IF($A19="","",SUMIFS(JOURNAL!$H$8:$H$1007,JOURNAL!$E$8:$E$1007,"Glovo Carte",JOURNAL!$B$8:$B$1007,$A19)) -> 0 | F19: =IF($A19="","",SUM($C19:$E19)) -> 1902 | G19: =IF($A19="","",SUMIFS(JOURNAL!$H$8:$H$1007,JOURNAL!$E$8:$E$1007,"Boissons",JOURNAL!$B$8:$B$1007,$A19)+SUMIFS(JOURNAL!$H$8:$H$1007,JOURNAL!$E$8:$E$1007,"Café & Torréfaction",JOURNAL!$B$8:$B$1007,$A19)+SUMIFS(JOURNAL!$H$8:$H$1007,JOURNAL!$E$8:$E$1007,"Boulangerie",JOURNAL!$B$8:$B$1007,$A19)+SUMIFS(JOURNAL!$H$8:$H$1007,JOURNAL!$E$8:$E$1007,"Fruits & Légumes",JOURNAL!$B$8:$B$1007,$A19)+SUMIFS(JOURNAL!$H$8:$H$1007,JOURNAL!$E$8:$E$1007,"Épicerie & Divers",JOURNAL!$B$8:$B$1007,$A19)) -> 606 | H19: =IF($A19="","",SUMIFS(JOURNAL!$H$8:$H$1007,JOURNAL!$E$8:$E$1007,"Nettoyage",JOURNAL!$B$8:$B$1007,$A19)) -> 150 | I19: =IF($A19="","",SUMIFS(JOURNAL!$H$8:$H$1007,JOURNAL!$E$8:$E$1007,"Salaires",JOURNAL!$B$8:$B$1007,$A19)) -> 0 | J19: =IF($A19="","",SUMIFS(JOURNAL!$H$8:$H$1007,JOURNAL!$E$8:$E$1007,"Loyer",JOURNAL!$B$8:$B$1007,$A19)+SUMIFS(JOURNAL!$H$8:$H$1007,JOURNAL!$E$8:$E$1007,"Eau & Électricité",JOURNAL!$B$8:$B$1007,$A19)+SUMIFS(JOURNAL!$H$8:$H$1007,JOURNAL!$E$8:$E$1007,"Internet & Télécom",JOURNAL!$B$8:$B$1007,$A19)+SUMIFS(JOURNAL!$H$8:$H$1007,JOURNAL!$E$8:$E$1007,"Taxes & Impôts",JOURNAL!$B$8:$B$1007,$A19)+SUMIFS(JOURNAL!$H$8:$H$1007,JOURNAL!$E$8:$E$1007,"Abonnements",JOURNAL!$B$8:$B$1007,$A19)+SUMIFS(JOURNAL!$H$8:$H$1007,JOURNAL!$E$8:$E$1007,"Entretien & Réparation",JOURNAL!$B$8:$B$1007,$A19)) -> 0 | K19: =IF($A19="","",SUMIFS(JOURNAL!$H$8:$H$1007,JOURNAL!$E$8:$E$1007,"Virement Banque",JOURNAL!$B$8:$B$1007,$A19)+SUMIFS(JOURNAL!$H$8:$H$1007,JOURNAL!$E$8:$E$1007,"Virement Associés",JOURNAL!$B$8:$B$1007,$A19)) -> 0 | L19: =IF($A19="","",$M19-SUM($G19:$K19)) -> 0 | M19: =IF($A19="","",SUMIFS(JOURNAL!$H$8:$H$1007,JOURNAL!$D$8:$D$1007,"DEPENSE",JOURNAL!$B$8:$B$1007,$A19)) -> 756 | N19: =IF($A19="","",$F19-$M19) -> 1146 | O19: =IF($A19="","",$O18+$N19) -> 3962 | P19: =IF($A19="","",IF($F19=0,"—",$F19-PARAMETRES!$C$20)) -> -298
A20: =IF(15>PARAMETRES!$C$16,"",DATE(PARAMETRES!$C$12,PARAMETRES!$C$13,15)) -> 46249 | B20: =IF($A20="","",CHOOSE(WEEKDAY($A20,2),"Lundi","Mardi","Mercredi","Jeudi","Vendredi","Samedi","Dimanche")) -> Samedi | C20: =IF($A20="","",SUMIFS(JOURNAL!$H$8:$H$1007,JOURNAL!$E$8:$E$1007,"Vente Caisse",JOURNAL!$B$8:$B$1007,$A20)+SUMIFS(JOURNAL!$H$8:$H$1007,JOURNAL!$E$8:$E$1007,"Terrasse",JOURNAL!$B$8:$B$1007,$A20)+SUMIFS(JOURNAL!$H$8:$H$1007,JOURNAL!$E$8:$E$1007,"Autre Recette",JOURNAL!$B$8:$B$1007,$A20)) -> 2053 | D20: =IF($A20="","",SUMIFS(JOURNAL!$H$8:$H$1007,JOURNAL!$E$8:$E$1007,"Glovo Espèce",JOURNAL!$B$8:$B$1007,$A20)) -> 0 | E20: =IF($A20="","",SUMIFS(JOURNAL!$H$8:$H$1007,JOURNAL!$E$8:$E$1007,"Glovo Carte",JOURNAL!$B$8:$B$1007,$A20)) -> 0 | F20: =IF($A20="","",SUM($C20:$E20)) -> 2053 | G20: =IF($A20="","",SUMIFS(JOURNAL!$H$8:$H$1007,JOURNAL!$E$8:$E$1007,"Boissons",JOURNAL!$B$8:$B$1007,$A20)+SUMIFS(JOURNAL!$H$8:$H$1007,JOURNAL!$E$8:$E$1007,"Café & Torréfaction",JOURNAL!$B$8:$B$1007,$A20)+SUMIFS(JOURNAL!$H$8:$H$1007,JOURNAL!$E$8:$E$1007,"Boulangerie",JOURNAL!$B$8:$B$1007,$A20)+SUMIFS(JOURNAL!$H$8:$H$1007,JOURNAL!$E$8:$E$1007,"Fruits & Légumes",JOURNAL!$B$8:$B$1007,$A20)+SUMIFS(JOURNAL!$H$8:$H$1007,JOURNAL!$E$8:$E$1007,"Épicerie & Divers",JOURNAL!$B$8:$B$1007,$A20)) -> 456 | H20: =IF($A20="","",SUMIFS(JOURNAL!$H$8:$H$1007,JOURNAL!$E$8:$E$1007,"Nettoyage",JOURNAL!$B$8:$B$1007,$A20)) -> 150 | I20: =IF($A20="","",SUMIFS(JOURNAL!$H$8:$H$1007,JOURNAL!$E$8:$E$1007,"Salaires",JOURNAL!$B$8:$B$1007,$A20)) -> 0 | J20: =IF($A20="","",SUMIFS(JOURNAL!$H$8:$H$1007,JOURNAL!$E$8:$E$1007,"Loyer",JOURNAL!$B$8:$B$1007,$A20)+SUMIFS(JOURNAL!$H$8:$H$1007,JOURNAL!$E$8:$E$1007,"Eau & Électricité",JOURNAL!$B$8:$B$1007,$A20)+SUMIFS(JOURNAL!$H$8:$H$1007,JOURNAL!$E$8:$E$1007,"Internet & Télécom",JOURNAL!$B$8:$B$1007,$A20)+SUMIFS(JOURNAL!$H$8:$H$1007,JOURNAL!$E$8:$E$1007,"Taxes & Impôts",JOURNAL!$B$8:$B$1007,$A20)+SUMIFS(JOURNAL!$H$8:$H$1007,JOURNAL!$E$8:$E$1007,"Abonnements",JOURNAL!$B$8:$B$1007,$A20)+SUMIFS(JOURNAL!$H$8:$H$1007,JOURNAL!$E$8:$E$1007,"Entretien & Réparation",JOURNAL!$B$8:$B$1007,$A20)) -> 0 | K20: =IF($A20="","",SUMIFS(JOURNAL!$H$8:$H$1007,JOURNAL!$E$8:$E$1007,"Virement Banque",JOURNAL!$B$8:$B$1007,$A20)+SUMIFS(JOURNAL!$H$8:$H$1007,JOURNAL!$E$8:$E$1007,"Virement Associés",JOURNAL!$B$8:$B$1007,$A20)) -> 0 | L20: =IF($A20="","",$M20-SUM($G20:$K20)) -> 0 | M20: =IF($A20="","",SUMIFS(JOURNAL!$H$8:$H$1007,JOURNAL!$D$8:$D$1007,"DEPENSE",JOURNAL!$B$8:$B$1007,$A20)) -> 606 | N20: =IF($A20="","",$F20-$M20) -> 1447 | O20: =IF($A20="","",$O19+$N20) -> 5409 | P20: =IF($A20="","",IF($F20=0,"—",$F20-PARAMETRES!$C$20)) -> -147
A21: =IF(16>PARAMETRES!$C$16,"",DATE(PARAMETRES!$C$12,PARAMETRES!$C$13,16)) -> 46250 | B21: =IF($A21="","",CHOOSE(WEEKDAY($A21,2),"Lundi","Mardi","Mercredi","Jeudi","Vendredi","Samedi","Dimanche")) -> Dimanche | C21: =IF($A21="","",SUMIFS(JOURNAL!$H$8:$H$1007,JOURNAL!$E$8:$E$1007,"Vente Caisse",JOURNAL!$B$8:$B$1007,$A21)+SUMIFS(JOURNAL!$H$8:$H$1007,JOURNAL!$E$8:$E$1007,"Terrasse",JOURNAL!$B$8:$B$1007,$A21)+SUMIFS(JOURNAL!$H$8:$H$1007,JOURNAL!$E$8:$E$1007,"Autre Recette",JOURNAL!$B$8:$B$1007,$A21)) -> 2100 | D21: =IF($A21="","",SUMIFS(JOURNAL!$H$8:$H$1007,JOURNAL!$E$8:$E$1007,"Glovo Espèce",JOURNAL!$B$8:$B$1007,$A21)) -> 0 | E21: =IF($A21="","",SUMIFS(JOURNAL!$H$8:$H$1007,JOURNAL!$E$8:$E$1007,"Glovo Carte",JOURNAL!$B$8:$B$1007,$A21)) -> 0 | F21: =IF($A21="","",SUM($C21:$E21)) -> 2100 | G21: =IF($A21="","",SUMIFS(JOURNAL!$H$8:$H$1007,JOURNAL!$E$8:$E$1007,"Boissons",JOURNAL!$B$8:$B$1007,$A21)+SUMIFS(JOURNAL!$H$8:$H$1007,JOURNAL!$E$8:$E$1007,"Café & Torréfaction",JOURNAL!$B$8:$B$1007,$A21)+SUMIFS(JOURNAL!$H$8:$H$1007,JOURNAL!$E$8:$E$1007,"Boulangerie",JOURNAL!$B$8:$B$1007,$A21)+SUMIFS(JOURNAL!$H$8:$H$1007,JOURNAL!$E$8:$E$1007,"Fruits & Légumes",JOURNAL!$B$8:$B$1007,$A21)+SUMIFS(JOURNAL!$H$8:$H$1007,JOURNAL!$E$8:$E$1007,"Épicerie & Divers",JOURNAL!$B$8:$B$1007,$A21)) -> 536 | H21: =IF($A21="","",SUMIFS(JOURNAL!$H$8:$H$1007,JOURNAL!$E$8:$E$1007,"Nettoyage",JOURNAL!$B$8:$B$1007,$A21)) -> 150 | I21: =IF($A21="","",SUMIFS(JOURNAL!$H$8:$H$1007,JOURNAL!$E$8:$E$1007,"Salaires",JOURNAL!$B$8:$B$1007,$A21)) -> 2500 | J21: =IF($A21="","",SUMIFS(JOURNAL!$H$8:$H$1007,JOURNAL!$E$8:$E$1007,"Loyer",JOURNAL!$B$8:$B$1007,$A21)+SUMIFS(JOURNAL!$H$8:$H$1007,JOURNAL!$E$8:$E$1007,"Eau & Électricité",JOURNAL!$B$8:$B$1007,$A21)+SUMIFS(JOURNAL!$H$8:$H$1007,JOURNAL!$E$8:$E$1007,"Internet & Télécom",JOURNAL!$B$8:$B$1007,$A21)+SUMIFS(JOURNAL!$H$8:$H$1007,JOURNAL!$E$8:$E$1007,"Taxes & Impôts",JOURNAL!$B$8:$B$1007,$A21)+SUMIFS(JOURNAL!$H$8:$H$1007,JOURNAL!$E$8:$E$1007,"Abonnements",JOURNAL!$B$8:$B$1007,$A21)+SUMIFS(JOURNAL!$H$8:$H$1007,JOURNAL!$E$8:$E$1007,"Entretien & Réparation",JOURNAL!$B$8:$B$1007,$A21)) -> 3785 | K21: =IF($A21="","",SUMIFS(JOURNAL!$H$8:$H$1007,JOURNAL!$E$8:$E$1007,"Virement Banque",JOURNAL!$B$8:$B$1007,$A21)+SUMIFS(JOURNAL!$H$8:$H$1007,JOURNAL!$E$8:$E$1007,"Virement Associés",JOURNAL!$B$8:$B$1007,$A21)) -> 0 | L21: =IF($A21="","",$M21-SUM($G21:$K21)) -> 0 | M21: =IF($A21="","",SUMIFS(JOURNAL!$H$8:$H$1007,JOURNAL!$D$8:$D$1007,"DEPENSE",JOURNAL!$B$8:$B$1007,$A21)) -> 6971 | N21: =IF($A21="","",$F21-$M21) -> -4871 | O21: =IF($A21="","",$O20+$N21) -> 538 | P21: =IF($A21="","",IF($F21=0,"—",$F21-PARAMETRES!$C$20)) -> -100
A22: =IF(17>PARAMETRES!$C$16,"",DATE(PARAMETRES!$C$12,PARAMETRES!$C$13,17)) -> 46251 | B22: =IF($A22="","",CHOOSE(WEEKDAY($A22,2),"Lundi","Mardi","Mercredi","Jeudi","Vendredi","Samedi","Dimanche")) -> Lundi | C22: =IF($A22="","",SUMIFS(JOURNAL!$H$8:$H$1007,JOURNAL!$E$8:$E$1007,"Vente Caisse",JOURNAL!$B$8:$B$1007,$A22)+SUMIFS(JOURNAL!$H$8:$H$1007,JOURNAL!$E$8:$E$1007,"Terrasse",JOURNAL!$B$8:$B$1007,$A22)+SUMIFS(JOURNAL!$H$8:$H$1007,JOURNAL!$E$8:$E$1007,"Autre Recette",JOURNAL!$B$8:$B$1007,$A22)) -> 1930 | D22: =IF($A22="","",SUMIFS(JOURNAL!$H$8:$H$1007,JOURNAL!$E$8:$E$1007,"Glovo Espèce",JOURNAL!$B$8:$B$1007,$A22)) -> 0 | E22: =IF($A22="","",SUMIFS(JOURNAL!$H$8:$H$1007,JOURNAL!$E$8:$E$1007,"Glovo Carte",JOURNAL!$B$8:$B$1007,$A22)) -> 0 | F22: =IF($A22="","",SUM($C22:$E22)) -> 1930 | G22: =IF($A22="","",SUMIFS(JOURNAL!$H$8:$H$1007,JOURNAL!$E$8:$E$1007,"Boissons",JOURNAL!$B$8:$B$1007,$A22)+SUMIFS(JOURNAL!$H$8:$H$1007,JOURNAL!$E$8:$E$1007,"Café & Torréfaction",JOURNAL!$B$8:$B$1007,$A22)+SUMIFS(JOURNAL!$H$8:$H$1007,JOURNAL!$E$8:$E$1007,"Boulangerie",JOURNAL!$B$8:$B$1007,$A22)+SUMIFS(JOURNAL!$H$8:$H$1007,JOURNAL!$E$8:$E$1007,"Fruits & Légumes",JOURNAL!$B$8:$B$1007,$A22)+SUMIFS(JOURNAL!$H$8:$H$1007,JOURNAL!$E$8:$E$1007,"Épicerie & Divers",JOURNAL!$B$8:$B$1007,$A22)) -> 606 | H22: =IF($A22="","",SUMIFS(JOURNAL!$H$8:$H$1007,JOURNAL!$E$8:$E$1007,"Nettoyage",JOURNAL!$B$8:$B$1007,$A22)) -> 150 | I22: =IF($A22="","",SUMIFS(JOURNAL!$H$8:$H$1007,JOURNAL!$E$8:$E$1007,"Salaires",JOURNAL!$B$8:$B$1007,$A22)) -> 0 | J22: =IF($A22="","",SUMIFS(JOURNAL!$H$8:$H$1007,JOURNAL!$E$8:$E$1007,"Loyer",JOURNAL!$B$8:$B$1007,$A22)+SUMIFS(JOURNAL!$H$8:$H$1007,JOURNAL!$E$8:$E$1007,"Eau & Électricité",JOURNAL!$B$8:$B$1007,$A22)+SUMIFS(JOURNAL!$H$8:$H$1007,JOURNAL!$E$8:$E$1007,"Internet & Télécom",JOURNAL!$B$8:$B$1007,$A22)+SUMIFS(JOURNAL!$H$8:$H$1007,JOURNAL!$E$8:$E$1007,"Taxes & Impôts",JOURNAL!$B$8:$B$1007,$A22)+SUMIFS(JOURNAL!$H$8:$H$1007,JOURNAL!$E$8:$E$1007,"Abonnements",JOURNAL!$B$8:$B$1007,$A22)+SUMIFS(JOURNAL!$H$8:$H$1007,JOURNAL!$E$8:$E$1007,"Entretien & Réparation",JOURNAL!$B$8:$B$1007,$A22)) -> 0 | K22: =IF($A22="","",SUMIFS(JOURNAL!$H$8:$H$1007,JOURNAL!$E$8:$E$1007,"Virement Banque",JOURNAL!$B$8:$B$1007,$A22)+SUMIFS(JOURNAL!$H$8:$H$1007,JOURNAL!$E$8:$E$1007,"Virement Associés",JOURNAL!$B$8:$B$1007,$A22)) -> 0 | L22: =IF($A22="","",$M22-SUM($G22:$K22)) -> 0 | M22: =IF($A22="","",SUMIFS(JOURNAL!$H$8:$H$1007,JOURNAL!$D$8:$D$1007,"DEPENSE",JOURNAL!$B$8:$B$1007,$A22)) -> 756 | N22: =IF($A22="","",$F22-$M22) -> 1174 | O22: =IF($A22="","",$O21+$N22) -> 1712 | P22: =IF($A22="","",IF($F22=0,"—",$F22-PARAMETRES!$C$20)) -> -270
A23: =IF(18>PARAMETRES!$C$16,"",DATE(PARAMETRES!$C$12,PARAMETRES!$C$13,18)) -> 46252 | B23: =IF($A23="","",CHOOSE(WEEKDAY($A23,2),"Lundi","Mardi","Mercredi","Jeudi","Vendredi","Samedi","Dimanche")) -> Mardi | C23: =IF($A23="","",SUMIFS(JOURNAL!$H$8:$H$1007,JOURNAL!$E$8:$E$1007,"Vente Caisse",JOURNAL!$B$8:$B$1007,$A23)+SUMIFS(JOURNAL!$H$8:$H$1007,JOURNAL!$E$8:$E$1007,"Terrasse",JOURNAL!$B$8:$B$1007,$A23)+SUMIFS(JOURNAL!$H$8:$H$1007,JOURNAL!$E$8:$E$1007,"Autre Recette",JOURNAL!$B$8:$B$1007,$A23)) -> 2081 | D23: =IF($A23="","",SUMIFS(JOURNAL!$H$8:$H$1007,JOURNAL!$E$8:$E$1007,"Glovo Espèce",JOURNAL!$B$8:$B$1007,$A23)) -> 0 | E23: =IF($A23="","",SUMIFS(JOURNAL!$H$8:$H$1007,JOURNAL!$E$8:$E$1007,"Glovo Carte",JOURNAL!$B$8:$B$1007,$A23)) -> 0 | F23: =IF($A23="","",SUM($C23:$E23)) -> 2081 | G23: =IF($A23="","",SUMIFS(JOURNAL!$H$8:$H$1007,JOURNAL!$E$8:$E$1007,"Boissons",JOURNAL!$B$8:$B$1007,$A23)+SUMIFS(JOURNAL!$H$8:$H$1007,JOURNAL!$E$8:$E$1007,"Café & Torréfaction",JOURNAL!$B$8:$B$1007,$A23)+SUMIFS(JOURNAL!$H$8:$H$1007,JOURNAL!$E$8:$E$1007,"Boulangerie",JOURNAL!$B$8:$B$1007,$A23)+SUMIFS(JOURNAL!$H$8:$H$1007,JOURNAL!$E$8:$E$1007,"Fruits & Légumes",JOURNAL!$B$8:$B$1007,$A23)+SUMIFS(JOURNAL!$H$8:$H$1007,JOURNAL!$E$8:$E$1007,"Épicerie & Divers",JOURNAL!$B$8:$B$1007,$A23)) -> 465 | H23: =IF($A23="","",SUMIFS(JOURNAL!$H$8:$H$1007,JOURNAL!$E$8:$E$1007,"Nettoyage",JOURNAL!$B$8:$B$1007,$A23)) -> 150 | I23: =IF($A23="","",SUMIFS(JOURNAL!$H$8:$H$1007,JOURNAL!$E$8:$E$1007,"Salaires",JOURNAL!$B$8:$B$1007,$A23)) -> 0 | J23: =IF($A23="","",SUMIFS(JOURNAL!$H$8:$H$1007,JOURNAL!$E$8:$E$1007,"Loyer",JOURNAL!$B$8:$B$1007,$A23)+SUMIFS(JOURNAL!$H$8:$H$1007,JOURNAL!$E$8:$E$1007,"Eau & Électricité",JOURNAL!$B$8:$B$1007,$A23)+SUMIFS(JOURNAL!$H$8:$H$1007,JOURNAL!$E$8:$E$1007,"Internet & Télécom",JOURNAL!$B$8:$B$1007,$A23)+SUMIFS(JOURNAL!$H$8:$H$1007,JOURNAL!$E$8:$E$1007,"Taxes & Impôts",JOURNAL!$B$8:$B$1007,$A23)+SUMIFS(JOURNAL!$H$8:$H$1007,JOURNAL!$E$8:$E$1007,"Abonnements",JOURNAL!$B$8:$B$1007,$A23)+SUMIFS(JOURNAL!$H$8:$H$1007,JOURNAL!$E$8:$E$1007,"Entretien & Réparation",JOURNAL!$B$8:$B$1007,$A23)) -> 0 | K23: =IF($A23="","",SUMIFS(JOURNAL!$H$8:$H$1007,JOURNAL!$E$8:$E$1007,"Virement Banque",JOURNAL!$B$8:$B$1007,$A23)+SUMIFS(JOURNAL!$H$8:$H$1007,JOURNAL!$E$8:$E$1007,"Virement Associés",JOURNAL!$B$8:$B$1007,$A23)) -> 0 | L23: =IF($A23="","",$M23-SUM($G23:$K23)) -> 0 | M23: =IF($A23="","",SUMIFS(JOURNAL!$H$8:$H$1007,JOURNAL!$D$8:$D$1007,"DEPENSE",JOURNAL!$B$8:$B$1007,$A23)) -> 615 | N23: =IF($A23="","",$F23-$M23) -> 1466 | O23: =IF($A23="","",$O22+$N23) -> 3178 | P23: =IF($A23="","",IF($F23=0,"—",$F23-PARAMETRES!$C$20)) -> -119
A24: =IF(19>PARAMETRES!$C$16,"",DATE(PARAMETRES!$C$12,PARAMETRES!$C$13,19)) -> 46253 | B24: =IF($A24="","",CHOOSE(WEEKDAY($A24,2),"Lundi","Mardi","Mercredi","Jeudi","Vendredi","Samedi","Dimanche")) -> Mercredi | C24: =IF($A24="","",SUMIFS(JOURNAL!$H$8:$H$1007,JOURNAL!$E$8:$E$1007,"Vente Caisse",JOURNAL!$B$8:$B$1007,$A24)+SUMIFS(JOURNAL!$H$8:$H$1007,JOURNAL!$E$8:$E$1007,"Terrasse",JOURNAL!$B$8:$B$1007,$A24)+SUMIFS(JOURNAL!$H$8:$H$1007,JOURNAL!$E$8:$E$1007,"Autre Recette",JOURNAL!$B$8:$B$1007,$A24)) -> 2002 | D24: =IF($A24="","",SUMIFS(JOURNAL!$H$8:$H$1007,JOURNAL!$E$8:$E$1007,"Glovo Espèce",JOURNAL!$B$8:$B$1007,$A24)) -> 0 | E24: =IF($A24="","",SUMIFS(JOURNAL!$H$8:$H$1007,JOURNAL!$E$8:$E$1007,"Glovo Carte",JOURNAL!$B$8:$B$1007,$A24)) -> 0 | F24: =IF($A24="","",SUM($C24:$E24)) -> 2002 | G24: =IF($A24="","",SUMIFS(JOURNAL!$H$8:$H$1007,JOURNAL!$E$8:$E$1007,"Boissons",JOURNAL!$B$8:$B$1007,$A24)+SUMIFS(JOURNAL!$H$8:$H$1007,JOURNAL!$E$8:$E$1007,"Café & Torréfaction",JOURNAL!$B$8:$B$1007,$A24)+SUMIFS(JOURNAL!$H$8:$H$1007,JOURNAL!$E$8:$E$1007,"Boulangerie",JOURNAL!$B$8:$B$1007,$A24)+SUMIFS(JOURNAL!$H$8:$H$1007,JOURNAL!$E$8:$E$1007,"Fruits & Légumes",JOURNAL!$B$8:$B$1007,$A24)+SUMIFS(JOURNAL!$H$8:$H$1007,JOURNAL!$E$8:$E$1007,"Épicerie & Divers",JOURNAL!$B$8:$B$1007,$A24)) -> 2066 | H24: =IF($A24="","",SUMIFS(JOURNAL!$H$8:$H$1007,JOURNAL!$E$8:$E$1007,"Nettoyage",JOURNAL!$B$8:$B$1007,$A24)) -> 150 | I24: =IF($A24="","",SUMIFS(JOURNAL!$H$8:$H$1007,JOURNAL!$E$8:$E$1007,"Salaires",JOURNAL!$B$8:$B$1007,$A24)) -> 0 | J24: =IF($A24="","",SUMIFS(JOURNAL!$H$8:$H$1007,JOURNAL!$E$8:$E$1007,"Loyer",JOURNAL!$B$8:$B$1007,$A24)+SUMIFS(JOURNAL!$H$8:$H$1007,JOURNAL!$E$8:$E$1007,"Eau & Électricité",JOURNAL!$B$8:$B$1007,$A24)+SUMIFS(JOURNAL!$H$8:$H$1007,JOURNAL!$E$8:$E$1007,"Internet & Télécom",JOURNAL!$B$8:$B$1007,$A24)+SUMIFS(JOURNAL!$H$8:$H$1007,JOURNAL!$E$8:$E$1007,"Taxes & Impôts",JOURNAL!$B$8:$B$1007,$A24)+SUMIFS(JOURNAL!$H$8:$H$1007,JOURNAL!$E$8:$E$1007,"Abonnements",JOURNAL!$B$8:$B$1007,$A24)+SUMIFS(JOURNAL!$H$8:$H$1007,JOURNAL!$E$8:$E$1007,"Entretien & Réparation",JOURNAL!$B$8:$B$1007,$A24)) -> 0 | K24: =IF($A24="","",SUMIFS(JOURNAL!$H$8:$H$1007,JOURNAL!$E$8:$E$1007,"Virement Banque",JOURNAL!$B$8:$B$1007,$A24)+SUMIFS(JOURNAL!$H$8:$H$1007,JOURNAL!$E$8:$E$1007,"Virement Associés",JOURNAL!$B$8:$B$1007,$A24)) -> 0 | L24: =IF($A24="","",$M24-SUM($G24:$K24)) -> 0 | M24: =IF($A24="","",SUMIFS(JOURNAL!$H$8:$H$1007,JOURNAL!$D$8:$D$1007,"DEPENSE",JOURNAL!$B$8:$B$1007,$A24)) -> 2216 | N24: =IF($A24="","",$F24-$M24) -> -214 | O24: =IF($A24="","",$O23+$N24) -> 2964 | P24: =IF($A24="","",IF($F24=0,"—",$F24-PARAMETRES!$C$20)) -> -198
A25: =IF(20>PARAMETRES!$C$16,"",DATE(PARAMETRES!$C$12,PARAMETRES!$C$13,20)) -> 46254 | B25: =IF($A25="","",CHOOSE(WEEKDAY($A25,2),"Lundi","Mardi","Mercredi","Jeudi","Vendredi","Samedi","Dimanche")) -> Jeudi | C25: =IF($A25="","",SUMIFS(JOURNAL!$H$8:$H$1007,JOURNAL!$E$8:$E$1007,"Vente Caisse",JOURNAL!$B$8:$B$1007,$A25)+SUMIFS(JOURNAL!$H$8:$H$1007,JOURNAL!$E$8:$E$1007,"Terrasse",JOURNAL!$B$8:$B$1007,$A25)+SUMIFS(JOURNAL!$H$8:$H$1007,JOURNAL!$E$8:$E$1007,"Autre Recette",JOURNAL!$B$8:$B$1007,$A25)) -> 2253 | D25: =IF($A25="","",SUMIFS(JOURNAL!$H$8:$H$1007,JOURNAL!$E$8:$E$1007,"Glovo Espèce",JOURNAL!$B$8:$B$1007,$A25)) -> 0 | E25: =IF($A25="","",SUMIFS(JOURNAL!$H$8:$H$1007,JOURNAL!$E$8:$E$1007,"Glovo Carte",JOURNAL!$B$8:$B$1007,$A25)) -> 0 | F25: =IF($A25="","",SUM($C25:$E25)) -> 2253 | G25: =IF($A25="","",SUMIFS(JOURNAL!$H$8:$H$1007,JOURNAL!$E$8:$E$1007,"Boissons",JOURNAL!$B$8:$B$1007,$A25)+SUMIFS(JOURNAL!$H$8:$H$1007,JOURNAL!$E$8:$E$1007,"Café & Torréfaction",JOURNAL!$B$8:$B$1007,$A25)+SUMIFS(JOURNAL!$H$8:$H$1007,JOURNAL!$E$8:$E$1007,"Boulangerie",JOURNAL!$B$8:$B$1007,$A25)+SUMIFS(JOURNAL!$H$8:$H$1007,JOURNAL!$E$8:$E$1007,"Fruits & Légumes",JOURNAL!$B$8:$B$1007,$A25)+SUMIFS(JOURNAL!$H$8:$H$1007,JOURNAL!$E$8:$E$1007,"Épicerie & Divers",JOURNAL!$B$8:$B$1007,$A25)) -> 520 | H25: =IF($A25="","",SUMIFS(JOURNAL!$H$8:$H$1007,JOURNAL!$E$8:$E$1007,"Nettoyage",JOURNAL!$B$8:$B$1007,$A25)) -> 150 | I25: =IF($A25="","",SUMIFS(JOURNAL!$H$8:$H$1007,JOURNAL!$E$8:$E$1007,"Salaires",JOURNAL!$B$8:$B$1007,$A25)) -> 0 | J25: =IF($A25="","",SUMIFS(JOURNAL!$H$8:$H$1007,JOURNAL!$E$8:$E$1007,"Loyer",JOURNAL!$B$8:$B$1007,$A25)+SUMIFS(JOURNAL!$H$8:$H$1007,JOURNAL!$E$8:$E$1007,"Eau & Électricité",JOURNAL!$B$8:$B$1007,$A25)+SUMIFS(JOURNAL!$H$8:$H$1007,JOURNAL!$E$8:$E$1007,"Internet & Télécom",JOURNAL!$B$8:$B$1007,$A25)+SUMIFS(JOURNAL!$H$8:$H$1007,JOURNAL!$E$8:$E$1007,"Taxes & Impôts",JOURNAL!$B$8:$B$1007,$A25)+SUMIFS(JOURNAL!$H$8:$H$1007,JOURNAL!$E$8:$E$1007,"Abonnements",JOURNAL!$B$8:$B$1007,$A25)+SUMIFS(JOURNAL!$H$8:$H$1007,JOURNAL!$E$8:$E$1007,"Entretien & Réparation",JOURNAL!$B$8:$B$1007,$A25)) -> 0 | K25: =IF($A25="","",SUMIFS(JOURNAL!$H$8:$H$1007,JOURNAL!$E$8:$E$1007,"Virement Banque",JOURNAL!$B$8:$B$1007,$A25)+SUMIFS(JOURNAL!$H$8:$H$1007,JOURNAL!$E$8:$E$1007,"Virement Associés",JOURNAL!$B$8:$B$1007,$A25)) -> 0 | L25: =IF($A25="","",$M25-SUM($G25:$K25)) -> 0 | M25: =IF($A25="","",SUMIFS(JOURNAL!$H$8:$H$1007,JOURNAL!$D$8:$D$1007,"DEPENSE",JOURNAL!$B$8:$B$1007,$A25)) -> 670 | N25: =IF($A25="","",$F25-$M25) -> 1583 | O25: =IF($A25="","",$O24+$N25) -> 4547 | P25: =IF($A25="","",IF($F25=0,"—",$F25-PARAMETRES!$C$20)) -> 53
A26: =IF(21>PARAMETRES!$C$16,"",DATE(PARAMETRES!$C$12,PARAMETRES!$C$13,21)) -> 46255 | B26: =IF($A26="","",CHOOSE(WEEKDAY($A26,2),"Lundi","Mardi","Mercredi","Jeudi","Vendredi","Samedi","Dimanche")) -> Vendredi | C26: =IF($A26="","",SUMIFS(JOURNAL!$H$8:$H$1007,JOURNAL!$E$8:$E$1007,"Vente Caisse",JOURNAL!$B$8:$B$1007,$A26)+SUMIFS(JOURNAL!$H$8:$H$1007,JOURNAL!$E$8:$E$1007,"Terrasse",JOURNAL!$B$8:$B$1007,$A26)+SUMIFS(JOURNAL!$H$8:$H$1007,JOURNAL!$E$8:$E$1007,"Autre Recette",JOURNAL!$B$8:$B$1007,$A26)) -> 1607 | D26: =IF($A26="","",SUMIFS(JOURNAL!$H$8:$H$1007,JOURNAL!$E$8:$E$1007,"Glovo Espèce",JOURNAL!$B$8:$B$1007,$A26)) -> 0 | E26: =IF($A26="","",SUMIFS(JOURNAL!$H$8:$H$1007,JOURNAL!$E$8:$E$1007,"Glovo Carte",JOURNAL!$B$8:$B$1007,$A26)) -> 0 | F26: =IF($A26="","",SUM($C26:$E26)) -> 1607 | G26: =IF($A26="","",SUMIFS(JOURNAL!$H$8:$H$1007,JOURNAL!$E$8:$E$1007,"Boissons",JOURNAL!$B$8:$B$1007,$A26)+SUMIFS(JOURNAL!$H$8:$H$1007,JOURNAL!$E$8:$E$1007,"Café & Torréfaction",JOURNAL!$B$8:$B$1007,$A26)+SUMIFS(JOURNAL!$H$8:$H$1007,JOURNAL!$E$8:$E$1007,"Boulangerie",JOURNAL!$B$8:$B$1007,$A26)+SUMIFS(JOURNAL!$H$8:$H$1007,JOURNAL!$E$8:$E$1007,"Fruits & Légumes",JOURNAL!$B$8:$B$1007,$A26)+SUMIFS(JOURNAL!$H$8:$H$1007,JOURNAL!$E$8:$E$1007,"Épicerie & Divers",JOURNAL!$B$8:$B$1007,$A26)) -> 406 | H26: =IF($A26="","",SUMIFS(JOURNAL!$H$8:$H$1007,JOURNAL!$E$8:$E$1007,"Nettoyage",JOURNAL!$B$8:$B$1007,$A26)) -> 150 | I26: =IF($A26="","",SUMIFS(JOURNAL!$H$8:$H$1007,JOURNAL!$E$8:$E$1007,"Salaires",JOURNAL!$B$8:$B$1007,$A26)) -> 0 | J26: =IF($A26="","",SUMIFS(JOURNAL!$H$8:$H$1007,JOURNAL!$E$8:$E$1007,"Loyer",JOURNAL!$B$8:$B$1007,$A26)+SUMIFS(JOURNAL!$H$8:$H$1007,JOURNAL!$E$8:$E$1007,"Eau & Électricité",JOURNAL!$B$8:$B$1007,$A26)+SUMIFS(JOURNAL!$H$8:$H$1007,JOURNAL!$E$8:$E$1007,"Internet & Télécom",JOURNAL!$B$8:$B$1007,$A26)+SUMIFS(JOURNAL!$H$8:$H$1007,JOURNAL!$E$8:$E$1007,"Taxes & Impôts",JOURNAL!$B$8:$B$1007,$A26)+SUMIFS(JOURNAL!$H$8:$H$1007,JOURNAL!$E$8:$E$1007,"Abonnements",JOURNAL!$B$8:$B$1007,$A26)+SUMIFS(JOURNAL!$H$8:$H$1007,JOURNAL!$E$8:$E$1007,"Entretien & Réparation",JOURNAL!$B$8:$B$1007,$A26)) -> 0 | K26: =IF($A26="","",SUMIFS(JOURNAL!$H$8:$H$1007,JOURNAL!$E$8:$E$1007,"Virement Banque",JOURNAL!$B$8:$B$1007,$A26)+SUMIFS(JOURNAL!$H$8:$H$1007,JOURNAL!$E$8:$E$1007,"Virement Associés",JOURNAL!$B$8:$B$1007,$A26)) -> 0 | L26: =IF($A26="","",$M26-SUM($G26:$K26)) -> 0 | M26: =IF($A26="","",SUMIFS(JOURNAL!$H$8:$H$1007,JOURNAL!$D$8:$D$1007,"DEPENSE",JOURNAL!$B$8:$B$1007,$A26)) -> 556 | N26: =IF($A26="","",$F26-$M26) -> 1051 | O26: =IF($A26="","",$O25+$N26) -> 5598 | P26: =IF($A26="","",IF($F26=0,"—",$F26-PARAMETRES!$C$20)) -> -593
A27: =IF(22>PARAMETRES!$C$16,"",DATE(PARAMETRES!$C$12,PARAMETRES!$C$13,22)) -> 46256 | B27: =IF($A27="","",CHOOSE(WEEKDAY($A27,2),"Lundi","Mardi","Mercredi","Jeudi","Vendredi","Samedi","Dimanche")) -> Samedi | C27: =IF($A27="","",SUMIFS(JOURNAL!$H$8:$H$1007,JOURNAL!$E$8:$E$1007,"Vente Caisse",JOURNAL!$B$8:$B$1007,$A27)+SUMIFS(JOURNAL!$H$8:$H$1007,JOURNAL!$E$8:$E$1007,"Terrasse",JOURNAL!$B$8:$B$1007,$A27)+SUMIFS(JOURNAL!$H$8:$H$1007,JOURNAL!$E$8:$E$1007,"Autre Recette",JOURNAL!$B$8:$B$1007,$A27)) -> 1853 | D27: =IF($A27="","",SUMIFS(JOURNAL!$H$8:$H$1007,JOURNAL!$E$8:$E$1007,"Glovo Espèce",JOURNAL!$B$8:$B$1007,$A27)) -> 0 | E27: =IF($A27="","",SUMIFS(JOURNAL!$H$8:$H$1007,JOURNAL!$E$8:$E$1007,"Glovo Carte",JOURNAL!$B$8:$B$1007,$A27)) -> 0 | F27: =IF($A27="","",SUM($C27:$E27)) -> 1853 | G27: =IF($A27="","",SUMIFS(JOURNAL!$H$8:$H$1007,JOURNAL!$E$8:$E$1007,"Boissons",JOURNAL!$B$8:$B$1007,$A27)+SUMIFS(JOURNAL!$H$8:$H$1007,JOURNAL!$E$8:$E$1007,"Café & Torréfaction",JOURNAL!$B$8:$B$1007,$A27)+SUMIFS(JOURNAL!$H$8:$H$1007,JOURNAL!$E$8:$E$1007,"Boulangerie",JOURNAL!$B$8:$B$1007,$A27)+SUMIFS(JOURNAL!$H$8:$H$1007,JOURNAL!$E$8:$E$1007,"Fruits & Légumes",JOURNAL!$B$8:$B$1007,$A27)+SUMIFS(JOURNAL!$H$8:$H$1007,JOURNAL!$E$8:$E$1007,"Épicerie & Divers",JOURNAL!$B$8:$B$1007,$A27)) -> 1048 | H27: =IF($A27="","",SUMIFS(JOURNAL!$H$8:$H$1007,JOURNAL!$E$8:$E$1007,"Nettoyage",JOURNAL!$B$8:$B$1007,$A27)) -> 150 | I27: =IF($A27="","",SUMIFS(JOURNAL!$H$8:$H$1007,JOURNAL!$E$8:$E$1007,"Salaires",JOURNAL!$B$8:$B$1007,$A27)) -> 0 | J27: =IF($A27="","",SUMIFS(JOURNAL!$H$8:$H$1007,JOURNAL!$E$8:$E$1007,"Loyer",JOURNAL!$B$8:$B$1007,$A27)+SUMIFS(JOURNAL!$H$8:$H$1007,JOURNAL!$E$8:$E$1007,"Eau & Électricité",JOURNAL!$B$8:$B$1007,$A27)+SUMIFS(JOURNAL!$H$8:$H$1007,JOURNAL!$E$8:$E$1007,"Internet & Télécom",JOURNAL!$B$8:$B$1007,$A27)+SUMIFS(JOURNAL!$H$8:$H$1007,JOURNAL!$E$8:$E$1007,"Taxes & Impôts",JOURNAL!$B$8:$B$1007,$A27)+SUMIFS(JOURNAL!$H$8:$H$1007,JOURNAL!$E$8:$E$1007,"Abonnements",JOURNAL!$B$8:$B$1007,$A27)+SUMIFS(JOURNAL!$H$8:$H$1007,JOURNAL!$E$8:$E$1007,"Entretien & Réparation",JOURNAL!$B$8:$B$1007,$A27)) -> 0 | K27: =IF($A27="","",SUMIFS(JOURNAL!$H$8:$H$1007,JOURNAL!$E$8:$E$1007,"Virement Banque",JOURNAL!$B$8:$B$1007,$A27)+SUMIFS(JOURNAL!$H$8:$H$1007,JOURNAL!$E$8:$E$1007,"Virement Associés",JOURNAL!$B$8:$B$1007,$A27)) -> 0 | L27: =IF($A27="","",$M27-SUM($G27:$K27)) -> 0 | M27: =IF($A27="","",SUMIFS(JOURNAL!$H$8:$H$1007,JOURNAL!$D$8:$D$1007,"DEPENSE",JOURNAL!$B$8:$B$1007,$A27)) -> 1198 | N27: =IF($A27="","",$F27-$M27) -> 655 | O27: =IF($A27="","",$O26+$N27) -> 6253 | P27: =IF($A27="","",IF($F27=0,"—",$F27-PARAMETRES!$C$20)) -> -347
A28: =IF(23>PARAMETRES!$C$16,"",DATE(PARAMETRES!$C$12,PARAMETRES!$C$13,23)) -> 46257 | B28: =IF($A28="","",CHOOSE(WEEKDAY($A28,2),"Lundi","Mardi","Mercredi","Jeudi","Vendredi","Samedi","Dimanche")) -> Dimanche | C28: =IF($A28="","",SUMIFS(JOURNAL!$H$8:$H$1007,JOURNAL!$E$8:$E$1007,"Vente Caisse",JOURNAL!$B$8:$B$1007,$A28)+SUMIFS(JOURNAL!$H$8:$H$1007,JOURNAL!$E$8:$E$1007,"Terrasse",JOURNAL!$B$8:$B$1007,$A28)+SUMIFS(JOURNAL!$H$8:$H$1007,JOURNAL!$E$8:$E$1007,"Autre Recette",JOURNAL!$B$8:$B$1007,$A28)) -> 2141 | D28: =IF($A28="","",SUMIFS(JOURNAL!$H$8:$H$1007,JOURNAL!$E$8:$E$1007,"Glovo Espèce",JOURNAL!$B$8:$B$1007,$A28)) -> 0 | E28: =IF($A28="","",SUMIFS(JOURNAL!$H$8:$H$1007,JOURNAL!$E$8:$E$1007,"Glovo Carte",JOURNAL!$B$8:$B$1007,$A28)) -> 0 | F28: =IF($A28="","",SUM($C28:$E28)) -> 2141 | G28: =IF($A28="","",SUMIFS(JOURNAL!$H$8:$H$1007,JOURNAL!$E$8:$E$1007,"Boissons",JOURNAL!$B$8:$B$1007,$A28)+SUMIFS(JOURNAL!$H$8:$H$1007,JOURNAL!$E$8:$E$1007,"Café & Torréfaction",JOURNAL!$B$8:$B$1007,$A28)+SUMIFS(JOURNAL!$H$8:$H$1007,JOURNAL!$E$8:$E$1007,"Boulangerie",JOURNAL!$B$8:$B$1007,$A28)+SUMIFS(JOURNAL!$H$8:$H$1007,JOURNAL!$E$8:$E$1007,"Fruits & Légumes",JOURNAL!$B$8:$B$1007,$A28)+SUMIFS(JOURNAL!$H$8:$H$1007,JOURNAL!$E$8:$E$1007,"Épicerie & Divers",JOURNAL!$B$8:$B$1007,$A28)) -> 621 | H28: =IF($A28="","",SUMIFS(JOURNAL!$H$8:$H$1007,JOURNAL!$E$8:$E$1007,"Nettoyage",JOURNAL!$B$8:$B$1007,$A28)) -> 150 | I28: =IF($A28="","",SUMIFS(JOURNAL!$H$8:$H$1007,JOURNAL!$E$8:$E$1007,"Salaires",JOURNAL!$B$8:$B$1007,$A28)) -> 2500 | J28: =IF($A28="","",SUMIFS(JOURNAL!$H$8:$H$1007,JOURNAL!$E$8:$E$1007,"Loyer",JOURNAL!$B$8:$B$1007,$A28)+SUMIFS(JOURNAL!$H$8:$H$1007,JOURNAL!$E$8:$E$1007,"Eau & Électricité",JOURNAL!$B$8:$B$1007,$A28)+SUMIFS(JOURNAL!$H$8:$H$1007,JOURNAL!$E$8:$E$1007,"Internet & Télécom",JOURNAL!$B$8:$B$1007,$A28)+SUMIFS(JOURNAL!$H$8:$H$1007,JOURNAL!$E$8:$E$1007,"Taxes & Impôts",JOURNAL!$B$8:$B$1007,$A28)+SUMIFS(JOURNAL!$H$8:$H$1007,JOURNAL!$E$8:$E$1007,"Abonnements",JOURNAL!$B$8:$B$1007,$A28)+SUMIFS(JOURNAL!$H$8:$H$1007,JOURNAL!$E$8:$E$1007,"Entretien & Réparation",JOURNAL!$B$8:$B$1007,$A28)) -> 0 | K28: =IF($A28="","",SUMIFS(JOURNAL!$H$8:$H$1007,JOURNAL!$E$8:$E$1007,"Virement Banque",JOURNAL!$B$8:$B$1007,$A28)+SUMIFS(JOURNAL!$H$8:$H$1007,JOURNAL!$E$8:$E$1007,"Virement Associés",JOURNAL!$B$8:$B$1007,$A28)) -> 0 | L28: =IF($A28="","",$M28-SUM($G28:$K28)) -> 0 | M28: =IF($A28="","",SUMIFS(JOURNAL!$H$8:$H$1007,JOURNAL!$D$8:$D$1007,"DEPENSE",JOURNAL!$B$8:$B$1007,$A28)) -> 3271 | N28: =IF($A28="","",$F28-$M28) -> -1130 | O28: =IF($A28="","",$O27+$N28) -> 5123 | P28: =IF($A28="","",IF($F28=0,"—",$F28-PARAMETRES!$C$20)) -> -59
A29: =IF(24>PARAMETRES!$C$16,"",DATE(PARAMETRES!$C$12,PARAMETRES!$C$13,24)) -> 46258 | B29: =IF($A29="","",CHOOSE(WEEKDAY($A29,2),"Lundi","Mardi","Mercredi","Jeudi","Vendredi","Samedi","Dimanche")) -> Lundi | C29: =IF($A29="","",SUMIFS(JOURNAL!$H$8:$H$1007,JOURNAL!$E$8:$E$1007,"Vente Caisse",JOURNAL!$B$8:$B$1007,$A29)+SUMIFS(JOURNAL!$H$8:$H$1007,JOURNAL!$E$8:$E$1007,"Terrasse",JOURNAL!$B$8:$B$1007,$A29)+SUMIFS(JOURNAL!$H$8:$H$1007,JOURNAL!$E$8:$E$1007,"Autre Recette",JOURNAL!$B$8:$B$1007,$A29)) -> 2154 | D29: =IF($A29="","",SUMIFS(JOURNAL!$H$8:$H$1007,JOURNAL!$E$8:$E$1007,"Glovo Espèce",JOURNAL!$B$8:$B$1007,$A29)) -> 0 | E29: =IF($A29="","",SUMIFS(JOURNAL!$H$8:$H$1007,JOURNAL!$E$8:$E$1007,"Glovo Carte",JOURNAL!$B$8:$B$1007,$A29)) -> 0 | F29: =IF($A29="","",SUM($C29:$E29)) -> 2154 | G29: =IF($A29="","",SUMIFS(JOURNAL!$H$8:$H$1007,JOURNAL!$E$8:$E$1007,"Boissons",JOURNAL!$B$8:$B$1007,$A29)+SUMIFS(JOURNAL!$H$8:$H$1007,JOURNAL!$E$8:$E$1007,"Café & Torréfaction",JOURNAL!$B$8:$B$1007,$A29)+SUMIFS(JOURNAL!$H$8:$H$1007,JOURNAL!$E$8:$E$1007,"Boulangerie",JOURNAL!$B$8:$B$1007,$A29)+SUMIFS(JOURNAL!$H$8:$H$1007,JOURNAL!$E$8:$E$1007,"Fruits & Légumes",JOURNAL!$B$8:$B$1007,$A29)+SUMIFS(JOURNAL!$H$8:$H$1007,JOURNAL!$E$8:$E$1007,"Épicerie & Divers",JOURNAL!$B$8:$B$1007,$A29)) -> 456 | H29: =IF($A29="","",SUMIFS(JOURNAL!$H$8:$H$1007,JOURNAL!$E$8:$E$1007,"Nettoyage",JOURNAL!$B$8:$B$1007,$A29)) -> 150 | I29: =IF($A29="","",SUMIFS(JOURNAL!$H$8:$H$1007,JOURNAL!$E$8:$E$1007,"Salaires",JOURNAL!$B$8:$B$1007,$A29)) -> 0 | J29: =IF($A29="","",SUMIFS(JOURNAL!$H$8:$H$1007,JOURNAL!$E$8:$E$1007,"Loyer",JOURNAL!$B$8:$B$1007,$A29)+SUMIFS(JOURNAL!$H$8:$H$1007,JOURNAL!$E$8:$E$1007,"Eau & Électricité",JOURNAL!$B$8:$B$1007,$A29)+SUMIFS(JOURNAL!$H$8:$H$1007,JOURNAL!$E$8:$E$1007,"Internet & Télécom",JOURNAL!$B$8:$B$1007,$A29)+SUMIFS(JOURNAL!$H$8:$H$1007,JOURNAL!$E$8:$E$1007,"Taxes & Impôts",JOURNAL!$B$8:$B$1007,$A29)+SUMIFS(JOURNAL!$H$8:$H$1007,JOURNAL!$E$8:$E$1007,"Abonnements",JOURNAL!$B$8:$B$1007,$A29)+SUMIFS(JOURNAL!$H$8:$H$1007,JOURNAL!$E$8:$E$1007,"Entretien & Réparation",JOURNAL!$B$8:$B$1007,$A29)) -> 5000 | K29: =IF($A29="","",SUMIFS(JOURNAL!$H$8:$H$1007,JOURNAL!$E$8:$E$1007,"Virement Banque",JOURNAL!$B$8:$B$1007,$A29)+SUMIFS(JOURNAL!$H$8:$H$1007,JOURNAL!$E$8:$E$1007,"Virement Associés",JOURNAL!$B$8:$B$1007,$A29)) -> 0 | L29: =IF($A29="","",$M29-SUM($G29:$K29)) -> 0 | M29: =IF($A29="","",SUMIFS(JOURNAL!$H$8:$H$1007,JOURNAL!$D$8:$D$1007,"DEPENSE",JOURNAL!$B$8:$B$1007,$A29)) -> 5606 | N29: =IF($A29="","",$F29-$M29) -> -3452 | O29: =IF($A29="","",$O28+$N29) -> 1671 | P29: =IF($A29="","",IF($F29=0,"—",$F29-PARAMETRES!$C$20)) -> -46
A30: =IF(25>PARAMETRES!$C$16,"",DATE(PARAMETRES!$C$12,PARAMETRES!$C$13,25)) -> 46259 | B30: =IF($A30="","",CHOOSE(WEEKDAY($A30,2),"Lundi","Mardi","Mercredi","Jeudi","Vendredi","Samedi","Dimanche")) -> Mardi | C30: =IF($A30="","",SUMIFS(JOURNAL!$H$8:$H$1007,JOURNAL!$E$8:$E$1007,"Vente Caisse",JOURNAL!$B$8:$B$1007,$A30)+SUMIFS(JOURNAL!$H$8:$H$1007,JOURNAL!$E$8:$E$1007,"Terrasse",JOURNAL!$B$8:$B$1007,$A30)+SUMIFS(JOURNAL!$H$8:$H$1007,JOURNAL!$E$8:$E$1007,"Autre Recette",JOURNAL!$B$8:$B$1007,$A30)) -> 1900 | D30: =IF($A30="","",SUMIFS(JOURNAL!$H$8:$H$1007,JOURNAL!$E$8:$E$1007,"Glovo Espèce",JOURNAL!$B$8:$B$1007,$A30)) -> 0 | E30: =IF($A30="","",SUMIFS(JOURNAL!$H$8:$H$1007,JOURNAL!$E$8:$E$1007,"Glovo Carte",JOURNAL!$B$8:$B$1007,$A30)) -> 0 | F30: =IF($A30="","",SUM($C30:$E30)) -> 1900 | G30: =IF($A30="","",SUMIFS(JOURNAL!$H$8:$H$1007,JOURNAL!$E$8:$E$1007,"Boissons",JOURNAL!$B$8:$B$1007,$A30)+SUMIFS(JOURNAL!$H$8:$H$1007,JOURNAL!$E$8:$E$1007,"Café & Torréfaction",JOURNAL!$B$8:$B$1007,$A30)+SUMIFS(JOURNAL!$H$8:$H$1007,JOURNAL!$E$8:$E$1007,"Boulangerie",JOURNAL!$B$8:$B$1007,$A30)+SUMIFS(JOURNAL!$H$8:$H$1007,JOURNAL!$E$8:$E$1007,"Fruits & Légumes",JOURNAL!$B$8:$B$1007,$A30)+SUMIFS(JOURNAL!$H$8:$H$1007,JOURNAL!$E$8:$E$1007,"Épicerie & Divers",JOURNAL!$B$8:$B$1007,$A30)) -> 571 | H30: =IF($A30="","",SUMIFS(JOURNAL!$H$8:$H$1007,JOURNAL!$E$8:$E$1007,"Nettoyage",JOURNAL!$B$8:$B$1007,$A30)) -> 150 | I30: =IF($A30="","",SUMIFS(JOURNAL!$H$8:$H$1007,JOURNAL!$E$8:$E$1007,"Salaires",JOURNAL!$B$8:$B$1007,$A30)) -> 0 | J30: =IF($A30="","",SUMIFS(JOURNAL!$H$8:$H$1007,JOURNAL!$E$8:$E$1007,"Loyer",JOURNAL!$B$8:$B$1007,$A30)+SUMIFS(JOURNAL!$H$8:$H$1007,JOURNAL!$E$8:$E$1007,"Eau & Électricité",JOURNAL!$B$8:$B$1007,$A30)+SUMIFS(JOURNAL!$H$8:$H$1007,JOURNAL!$E$8:$E$1007,"Internet & Télécom",JOURNAL!$B$8:$B$1007,$A30)+SUMIFS(JOURNAL!$H$8:$H$1007,JOURNAL!$E$8:$E$1007,"Taxes & Impôts",JOURNAL!$B$8:$B$1007,$A30)+SUMIFS(JOURNAL!$H$8:$H$1007,JOURNAL!$E$8:$E$1007,"Abonnements",JOURNAL!$B$8:$B$1007,$A30)+SUMIFS(JOURNAL!$H$8:$H$1007,JOURNAL!$E$8:$E$1007,"Entretien & Réparation",JOURNAL!$B$8:$B$1007,$A30)) -> 0 | K30: =IF($A30="","",SUMIFS(JOURNAL!$H$8:$H$1007,JOURNAL!$E$8:$E$1007,"Virement Banque",JOURNAL!$B$8:$B$1007,$A30)+SUMIFS(JOURNAL!$H$8:$H$1007,JOURNAL!$E$8:$E$1007,"Virement Associés",JOURNAL!$B$8:$B$1007,$A30)) -> 0 | L30: =IF($A30="","",$M30-SUM($G30:$K30)) -> 0 | M30: =IF($A30="","",SUMIFS(JOURNAL!$H$8:$H$1007,JOURNAL!$D$8:$D$1007,"DEPENSE",JOURNAL!$B$8:$B$1007,$A30)) -> 721 | N30: =IF($A30="","",$F30-$M30) -> 1179 | O30: =IF($A30="","",$O29+$N30) -> 2850 | P30: =IF($A30="","",IF($F30=0,"—",$F30-PARAMETRES!$C$20)) -> -300
A31: =IF(26>PARAMETRES!$C$16,"",DATE(PARAMETRES!$C$12,PARAMETRES!$C$13,26)) -> 46260 | B31: =IF($A31="","",CHOOSE(WEEKDAY($A31,2),"Lundi","Mardi","Mercredi","Jeudi","Vendredi","Samedi","Dimanche")) -> Mercredi | C31: =IF($A31="","",SUMIFS(JOURNAL!$H$8:$H$1007,JOURNAL!$E$8:$E$1007,"Vente Caisse",JOURNAL!$B$8:$B$1007,$A31)+SUMIFS(JOURNAL!$H$8:$H$1007,JOURNAL!$E$8:$E$1007,"Terrasse",JOURNAL!$B$8:$B$1007,$A31)+SUMIFS(JOURNAL!$H$8:$H$1007,JOURNAL!$E$8:$E$1007,"Autre Recette",JOURNAL!$B$8:$B$1007,$A31)) -> 1713 | D31: =IF($A31="","",SUMIFS(JOURNAL!$H$8:$H$1007,JOURNAL!$E$8:$E$1007,"Glovo Espèce",JOURNAL!$B$8:$B$1007,$A31)) -> 0 | E31: =IF($A31="","",SUMIFS(JOURNAL!$H$8:$H$1007,JOURNAL!$E$8:$E$1007,"Glovo Carte",JOURNAL!$B$8:$B$1007,$A31)) -> 0 | F31: =IF($A31="","",SUM($C31:$E31)) -> 1713 | G31: =IF($A31="","",SUMIFS(JOURNAL!$H$8:$H$1007,JOURNAL!$E$8:$E$1007,"Boissons",JOURNAL!$B$8:$B$1007,$A31)+SUMIFS(JOURNAL!$H$8:$H$1007,JOURNAL!$E$8:$E$1007,"Café & Torréfaction",JOURNAL!$B$8:$B$1007,$A31)+SUMIFS(JOURNAL!$H$8:$H$1007,JOURNAL!$E$8:$E$1007,"Boulangerie",JOURNAL!$B$8:$B$1007,$A31)+SUMIFS(JOURNAL!$H$8:$H$1007,JOURNAL!$E$8:$E$1007,"Fruits & Légumes",JOURNAL!$B$8:$B$1007,$A31)+SUMIFS(JOURNAL!$H$8:$H$1007,JOURNAL!$E$8:$E$1007,"Épicerie & Divers",JOURNAL!$B$8:$B$1007,$A31)) -> 1286 | H31: =IF($A31="","",SUMIFS(JOURNAL!$H$8:$H$1007,JOURNAL!$E$8:$E$1007,"Nettoyage",JOURNAL!$B$8:$B$1007,$A31)) -> 150 | I31: =IF($A31="","",SUMIFS(JOURNAL!$H$8:$H$1007,JOURNAL!$E$8:$E$1007,"Salaires",JOURNAL!$B$8:$B$1007,$A31)) -> 0 | J31: =IF($A31="","",SUMIFS(JOURNAL!$H$8:$H$1007,JOURNAL!$E$8:$E$1007,"Loyer",JOURNAL!$B$8:$B$1007,$A31)+SUMIFS(JOURNAL!$H$8:$H$1007,JOURNAL!$E$8:$E$1007,"Eau & Électricité",JOURNAL!$B$8:$B$1007,$A31)+SUMIFS(JOURNAL!$H$8:$H$1007,JOURNAL!$E$8:$E$1007,"Internet & Télécom",JOURNAL!$B$8:$B$1007,$A31)+SUMIFS(JOURNAL!$H$8:$H$1007,JOURNAL!$E$8:$E$1007,"Taxes & Impôts",JOURNAL!$B$8:$B$1007,$A31)+SUMIFS(JOURNAL!$H$8:$H$1007,JOURNAL!$E$8:$E$1007,"Abonnements",JOURNAL!$B$8:$B$1007,$A31)+SUMIFS(JOURNAL!$H$8:$H$1007,JOURNAL!$E$8:$E$1007,"Entretien & Réparation",JOURNAL!$B$8:$B$1007,$A31)) -> 0 | K31: =IF($A31="","",SUMIFS(JOURNAL!$H$8:$H$1007,JOURNAL!$E$8:$E$1007,"Virement Banque",JOURNAL!$B$8:$B$1007,$A31)+SUMIFS(JOURNAL!$H$8:$H$1007,JOURNAL!$E$8:$E$1007,"Virement Associés",JOURNAL!$B$8:$B$1007,$A31)) -> 0 | L31: =IF($A31="","",$M31-SUM($G31:$K31)) -> 0 | M31: =IF($A31="","",SUMIFS(JOURNAL!$H$8:$H$1007,JOURNAL!$D$8:$D$1007,"DEPENSE",JOURNAL!$B$8:$B$1007,$A31)) -> 1436 | N31: =IF($A31="","",$F31-$M31) -> 277 | O31: =IF($A31="","",$O30+$N31) -> 3127 | P31: =IF($A31="","",IF($F31=0,"—",$F31-PARAMETRES!$C$20)) -> -487
A32: =IF(27>PARAMETRES!$C$16,"",DATE(PARAMETRES!$C$12,PARAMETRES!$C$13,27)) -> 46261 | B32: =IF($A32="","",CHOOSE(WEEKDAY($A32,2),"Lundi","Mardi","Mercredi","Jeudi","Vendredi","Samedi","Dimanche")) -> Jeudi | C32: =IF($A32="","",SUMIFS(JOURNAL!$H$8:$H$1007,JOURNAL!$E$8:$E$1007,"Vente Caisse",JOURNAL!$B$8:$B$1007,$A32)+SUMIFS(JOURNAL!$H$8:$H$1007,JOURNAL!$E$8:$E$1007,"Terrasse",JOURNAL!$B$8:$B$1007,$A32)+SUMIFS(JOURNAL!$H$8:$H$1007,JOURNAL!$E$8:$E$1007,"Autre Recette",JOURNAL!$B$8:$B$1007,$A32)) -> 1687 | D32: =IF($A32="","",SUMIFS(JOURNAL!$H$8:$H$1007,JOURNAL!$E$8:$E$1007,"Glovo Espèce",JOURNAL!$B$8:$B$1007,$A32)) -> 0 | E32: =IF($A32="","",SUMIFS(JOURNAL!$H$8:$H$1007,JOURNAL!$E$8:$E$1007,"Glovo Carte",JOURNAL!$B$8:$B$1007,$A32)) -> 0 | F32: =IF($A32="","",SUM($C32:$E32)) -> 1687 | G32: =IF($A32="","",SUMIFS(JOURNAL!$H$8:$H$1007,JOURNAL!$E$8:$E$1007,"Boissons",JOURNAL!$B$8:$B$1007,$A32)+SUMIFS(JOURNAL!$H$8:$H$1007,JOURNAL!$E$8:$E$1007,"Café & Torréfaction",JOURNAL!$B$8:$B$1007,$A32)+SUMIFS(JOURNAL!$H$8:$H$1007,JOURNAL!$E$8:$E$1007,"Boulangerie",JOURNAL!$B$8:$B$1007,$A32)+SUMIFS(JOURNAL!$H$8:$H$1007,JOURNAL!$E$8:$E$1007,"Fruits & Légumes",JOURNAL!$B$8:$B$1007,$A32)+SUMIFS(JOURNAL!$H$8:$H$1007,JOURNAL!$E$8:$E$1007,"Épicerie & Divers",JOURNAL!$B$8:$B$1007,$A32)) -> 441 | H32: =IF($A32="","",SUMIFS(JOURNAL!$H$8:$H$1007,JOURNAL!$E$8:$E$1007,"Nettoyage",JOURNAL!$B$8:$B$1007,$A32)) -> 150 | I32: =IF($A32="","",SUMIFS(JOURNAL!$H$8:$H$1007,JOURNAL!$E$8:$E$1007,"Salaires",JOURNAL!$B$8:$B$1007,$A32)) -> 0 | J32: =IF($A32="","",SUMIFS(JOURNAL!$H$8:$H$1007,JOURNAL!$E$8:$E$1007,"Loyer",JOURNAL!$B$8:$B$1007,$A32)+SUMIFS(JOURNAL!$H$8:$H$1007,JOURNAL!$E$8:$E$1007,"Eau & Électricité",JOURNAL!$B$8:$B$1007,$A32)+SUMIFS(JOURNAL!$H$8:$H$1007,JOURNAL!$E$8:$E$1007,"Internet & Télécom",JOURNAL!$B$8:$B$1007,$A32)+SUMIFS(JOURNAL!$H$8:$H$1007,JOURNAL!$E$8:$E$1007,"Taxes & Impôts",JOURNAL!$B$8:$B$1007,$A32)+SUMIFS(JOURNAL!$H$8:$H$1007,JOURNAL!$E$8:$E$1007,"Abonnements",JOURNAL!$B$8:$B$1007,$A32)+SUMIFS(JOURNAL!$H$8:$H$1007,JOURNAL!$E$8:$E$1007,"Entretien & Réparation",JOURNAL!$B$8:$B$1007,$A32)) -> 0 | K32: =IF($A32="","",SUMIFS(JOURNAL!$H$8:$H$1007,JOURNAL!$E$8:$E$1007,"Virement Banque",JOURNAL!$B$8:$B$1007,$A32)+SUMIFS(JOURNAL!$H$8:$H$1007,JOURNAL!$E$8:$E$1007,"Virement Associés",JOURNAL!$B$8:$B$1007,$A32)) -> 0 | L32: =IF($A32="","",$M32-SUM($G32:$K32)) -> 0 | M32: =IF($A32="","",SUMIFS(JOURNAL!$H$8:$H$1007,JOURNAL!$D$8:$D$1007,"DEPENSE",JOURNAL!$B$8:$B$1007,$A32)) -> 591 | N32: =IF($A32="","",$F32-$M32) -> 1096 | O32: =IF($A32="","",$O31+$N32) -> 4223 | P32: =IF($A32="","",IF($F32=0,"—",$F32-PARAMETRES!$C$20)) -> -513
A33: =IF(28>PARAMETRES!$C$16,"",DATE(PARAMETRES!$C$12,PARAMETRES!$C$13,28)) -> 46262 | B33: =IF($A33="","",CHOOSE(WEEKDAY($A33,2),"Lundi","Mardi","Mercredi","Jeudi","Vendredi","Samedi","Dimanche")) -> Vendredi | C33: =IF($A33="","",SUMIFS(JOURNAL!$H$8:$H$1007,JOURNAL!$E$8:$E$1007,"Vente Caisse",JOURNAL!$B$8:$B$1007,$A33)+SUMIFS(JOURNAL!$H$8:$H$1007,JOURNAL!$E$8:$E$1007,"Terrasse",JOURNAL!$B$8:$B$1007,$A33)+SUMIFS(JOURNAL!$H$8:$H$1007,JOURNAL!$E$8:$E$1007,"Autre Recette",JOURNAL!$B$8:$B$1007,$A33)) -> 0 | D33: =IF($A33="","",SUMIFS(JOURNAL!$H$8:$H$1007,JOURNAL!$E$8:$E$1007,"Glovo Espèce",JOURNAL!$B$8:$B$1007,$A33)) -> 0 | E33: =IF($A33="","",SUMIFS(JOURNAL!$H$8:$H$1007,JOURNAL!$E$8:$E$1007,"Glovo Carte",JOURNAL!$B$8:$B$1007,$A33)) -> 0 | F33: =IF($A33="","",SUM($C33:$E33)) -> 0 | G33: =IF($A33="","",SUMIFS(JOURNAL!$H$8:$H$1007,JOURNAL!$E$8:$E$1007,"Boissons",JOURNAL!$B$8:$B$1007,$A33)+SUMIFS(JOURNAL!$H$8:$H$1007,JOURNAL!$E$8:$E$1007,"Café & Torréfaction",JOURNAL!$B$8:$B$1007,$A33)+SUMIFS(JOURNAL!$H$8:$H$1007,JOURNAL!$E$8:$E$1007,"Boulangerie",JOURNAL!$B$8:$B$1007,$A33)+SUMIFS(JOURNAL!$H$8:$H$1007,JOURNAL!$E$8:$E$1007,"Fruits & Légumes",JOURNAL!$B$8:$B$1007,$A33)+SUMIFS(JOURNAL!$H$8:$H$1007,JOURNAL!$E$8:$E$1007,"Épicerie & Divers",JOURNAL!$B$8:$B$1007,$A33)) -> 0 | H33: =IF($A33="","",SUMIFS(JOURNAL!$H$8:$H$1007,JOURNAL!$E$8:$E$1007,"Nettoyage",JOURNAL!$B$8:$B$1007,$A33)) -> 0 | I33: =IF($A33="","",SUMIFS(JOURNAL!$H$8:$H$1007,JOURNAL!$E$8:$E$1007,"Salaires",JOURNAL!$B$8:$B$1007,$A33)) -> 0 | J33: =IF($A33="","",SUMIFS(JOURNAL!$H$8:$H$1007,JOURNAL!$E$8:$E$1007,"Loyer",JOURNAL!$B$8:$B$1007,$A33)+SUMIFS(JOURNAL!$H$8:$H$1007,JOURNAL!$E$8:$E$1007,"Eau & Électricité",JOURNAL!$B$8:$B$1007,$A33)+SUMIFS(JOURNAL!$H$8:$H$1007,JOURNAL!$E$8:$E$1007,"Internet & Télécom",JOURNAL!$B$8:$B$1007,$A33)+SUMIFS(JOURNAL!$H$8:$H$1007,JOURNAL!$E$8:$E$1007,"Taxes & Impôts",JOURNAL!$B$8:$B$1007,$A33)+SUMIFS(JOURNAL!$H$8:$H$1007,JOURNAL!$E$8:$E$1007,"Abonnements",JOURNAL!$B$8:$B$1007,$A33)+SUMIFS(JOURNAL!$H$8:$H$1007,JOURNAL!$E$8:$E$1007,"Entretien & Réparation",JOURNAL!$B$8:$B$1007,$A33)) -> 0 | K33: =IF($A33="","",SUMIFS(JOURNAL!$H$8:$H$1007,JOURNAL!$E$8:$E$1007,"Virement Banque",JOURNAL!$B$8:$B$1007,$A33)+SUMIFS(JOURNAL!$H$8:$H$1007,JOURNAL!$E$8:$E$1007,"Virement Associés",JOURNAL!$B$8:$B$1007,$A33)) -> 0 | L33: =IF($A33="","",$M33-SUM($G33:$K33)) -> 0 | M33: =IF($A33="","",SUMIFS(JOURNAL!$H$8:$H$1007,JOURNAL!$D$8:$D$1007,"DEPENSE",JOURNAL!$B$8:$B$1007,$A33)) -> 0 | N33: =IF($A33="","",$F33-$M33) -> 0 | O33: =IF($A33="","",$O32+$N33) -> 4223 | P33: =IF($A33="","",IF($F33=0,"—",$F33-PARAMETRES!$C$20)) -> —
A34: =IF(29>PARAMETRES!$C$16,"",DATE(PARAMETRES!$C$12,PARAMETRES!$C$13,29)) -> 46263 | B34: =IF($A34="","",CHOOSE(WEEKDAY($A34,2),"Lundi","Mardi","Mercredi","Jeudi","Vendredi","Samedi","Dimanche")) -> Samedi | C34: =IF($A34="","",SUMIFS(JOURNAL!$H$8:$H$1007,JOURNAL!$E$8:$E$1007,"Vente Caisse",JOURNAL!$B$8:$B$1007,$A34)+SUMIFS(JOURNAL!$H$8:$H$1007,JOURNAL!$E$8:$E$1007,"Terrasse",JOURNAL!$B$8:$B$1007,$A34)+SUMIFS(JOURNAL!$H$8:$H$1007,JOURNAL!$E$8:$E$1007,"Autre Recette",JOURNAL!$B$8:$B$1007,$A34)) -> 0 | D34: =IF($A34="","",SUMIFS(JOURNAL!$H$8:$H$1007,JOURNAL!$E$8:$E$1007,"Glovo Espèce",JOURNAL!$B$8:$B$1007,$A34)) -> 0 | E34: =IF($A34="","",SUMIFS(JOURNAL!$H$8:$H$1007,JOURNAL!$E$8:$E$1007,"Glovo Carte",JOURNAL!$B$8:$B$1007,$A34)) -> 0 | F34: =IF($A34="","",SUM($C34:$E34)) -> 0 | G34: =IF($A34="","",SUMIFS(JOURNAL!$H$8:$H$1007,JOURNAL!$E$8:$E$1007,"Boissons",JOURNAL!$B$8:$B$1007,$A34)+SUMIFS(JOURNAL!$H$8:$H$1007,JOURNAL!$E$8:$E$1007,"Café & Torréfaction",JOURNAL!$B$8:$B$1007,$A34)+SUMIFS(JOURNAL!$H$8:$H$1007,JOURNAL!$E$8:$E$1007,"Boulangerie",JOURNAL!$B$8:$B$1007,$A34)+SUMIFS(JOURNAL!$H$8:$H$1007,JOURNAL!$E$8:$E$1007,"Fruits & Légumes",JOURNAL!$B$8:$B$1007,$A34)+SUMIFS(JOURNAL!$H$8:$H$1007,JOURNAL!$E$8:$E$1007,"Épicerie & Divers",JOURNAL!$B$8:$B$1007,$A34)) -> 0 | H34: =IF($A34="","",SUMIFS(JOURNAL!$H$8:$H$1007,JOURNAL!$E$8:$E$1007,"Nettoyage",JOURNAL!$B$8:$B$1007,$A34)) -> 0 | I34: =IF($A34="","",SUMIFS(JOURNAL!$H$8:$H$1007,JOURNAL!$E$8:$E$1007,"Salaires",JOURNAL!$B$8:$B$1007,$A34)) -> 0 | J34: =IF($A34="","",SUMIFS(JOURNAL!$H$8:$H$1007,JOURNAL!$E$8:$E$1007,"Loyer",JOURNAL!$B$8:$B$1007,$A34)+SUMIFS(JOURNAL!$H$8:$H$1007,JOURNAL!$E$8:$E$1007,"Eau & Électricité",JOURNAL!$B$8:$B$1007,$A34)+SUMIFS(JOURNAL!$H$8:$H$1007,JOURNAL!$E$8:$E$1007,"Internet & Télécom",JOURNAL!$B$8:$B$1007,$A34)+SUMIFS(JOURNAL!$H$8:$H$1007,JOURNAL!$E$8:$E$1007,"Taxes & Impôts",JOURNAL!$B$8:$B$1007,$A34)+SUMIFS(JOURNAL!$H$8:$H$1007,JOURNAL!$E$8:$E$1007,"Abonnements",JOURNAL!$B$8:$B$1007,$A34)+SUMIFS(JOURNAL!$H$8:$H$1007,JOURNAL!$E$8:$E$1007,"Entretien & Réparation",JOURNAL!$B$8:$B$1007,$A34)) -> 0 | K34: =IF($A34="","",SUMIFS(JOURNAL!$H$8:$H$1007,JOURNAL!$E$8:$E$1007,"Virement Banque",JOURNAL!$B$8:$B$1007,$A34)+SUMIFS(JOURNAL!$H$8:$H$1007,JOURNAL!$E$8:$E$1007,"Virement Associés",JOURNAL!$B$8:$B$1007,$A34)) -> 0 | L34: =IF($A34="","",$M34-SUM($G34:$K34)) -> 0 | M34: =IF($A34="","",SUMIFS(JOURNAL!$H$8:$H$1007,JOURNAL!$D$8:$D$1007,"DEPENSE",JOURNAL!$B$8:$B$1007,$A34)) -> 0 | N34: =IF($A34="","",$F34-$M34) -> 0 | O34: =IF($A34="","",$O33+$N34) -> 4223 | P34: =IF($A34="","",IF($F34=0,"—",$F34-PARAMETRES!$C$20)) -> —
A35: =IF(30>PARAMETRES!$C$16,"",DATE(PARAMETRES!$C$12,PARAMETRES!$C$13,30)) -> 46264 | B35: =IF($A35="","",CHOOSE(WEEKDAY($A35,2),"Lundi","Mardi","Mercredi","Jeudi","Vendredi","Samedi","Dimanche")) -> Dimanche | C35: =IF($A35="","",SUMIFS(JOURNAL!$H$8:$H$1007,JOURNAL!$E$8:$E$1007,"Vente Caisse",JOURNAL!$B$8:$B$1007,$A35)+SUMIFS(JOURNAL!$H$8:$H$1007,JOURNAL!$E$8:$E$1007,"Terrasse",JOURNAL!$B$8:$B$1007,$A35)+SUMIFS(JOURNAL!$H$8:$H$1007,JOURNAL!$E$8:$E$1007,"Autre Recette",JOURNAL!$B$8:$B$1007,$A35)) -> 0 | D35: =IF($A35="","",SUMIFS(JOURNAL!$H$8:$H$1007,JOURNAL!$E$8:$E$1007,"Glovo Espèce",JOURNAL!$B$8:$B$1007,$A35)) -> 0 | E35: =IF($A35="","",SUMIFS(JOURNAL!$H$8:$H$1007,JOURNAL!$E$8:$E$1007,"Glovo Carte",JOURNAL!$B$8:$B$1007,$A35)) -> 0 | F35: =IF($A35="","",SUM($C35:$E35)) -> 0 | G35: =IF($A35="","",SUMIFS(JOURNAL!$H$8:$H$1007,JOURNAL!$E$8:$E$1007,"Boissons",JOURNAL!$B$8:$B$1007,$A35)+SUMIFS(JOURNAL!$H$8:$H$1007,JOURNAL!$E$8:$E$1007,"Café & Torréfaction",JOURNAL!$B$8:$B$1007,$A35)+SUMIFS(JOURNAL!$H$8:$H$1007,JOURNAL!$E$8:$E$1007,"Boulangerie",JOURNAL!$B$8:$B$1007,$A35)+SUMIFS(JOURNAL!$H$8:$H$1007,JOURNAL!$E$8:$E$1007,"Fruits & Légumes",JOURNAL!$B$8:$B$1007,$A35)+SUMIFS(JOURNAL!$H$8:$H$1007,JOURNAL!$E$8:$E$1007,"Épicerie & Divers",JOURNAL!$B$8:$B$1007,$A35)) -> 0 | H35: =IF($A35="","",SUMIFS(JOURNAL!$H$8:$H$1007,JOURNAL!$E$8:$E$1007,"Nettoyage",JOURNAL!$B$8:$B$1007,$A35)) -> 0 | I35: =IF($A35="","",SUMIFS(JOURNAL!$H$8:$H$1007,JOURNAL!$E$8:$E$1007,"Salaires",JOURNAL!$B$8:$B$1007,$A35)) -> 0 | J35: =IF($A35="","",SUMIFS(JOURNAL!$H$8:$H$1007,JOURNAL!$E$8:$E$1007,"Loyer",JOURNAL!$B$8:$B$1007,$A35)+SUMIFS(JOURNAL!$H$8:$H$1007,JOURNAL!$E$8:$E$1007,"Eau & Électricité",JOURNAL!$B$8:$B$1007,$A35)+SUMIFS(JOURNAL!$H$8:$H$1007,JOURNAL!$E$8:$E$1007,"Internet & Télécom",JOURNAL!$B$8:$B$1007,$A35)+SUMIFS(JOURNAL!$H$8:$H$1007,JOURNAL!$E$8:$E$1007,"Taxes & Impôts",JOURNAL!$B$8:$B$1007,$A35)+SUMIFS(JOURNAL!$H$8:$H$1007,JOURNAL!$E$8:$E$1007,"Abonnements",JOURNAL!$B$8:$B$1007,$A35)+SUMIFS(JOURNAL!$H$8:$H$1007,JOURNAL!$E$8:$E$1007,"Entretien & Réparation",JOURNAL!$B$8:$B$1007,$A35)) -> 0 | K35: =IF($A35="","",SUMIFS(JOURNAL!$H$8:$H$1007,JOURNAL!$E$8:$E$1007,"Virement Banque",JOURNAL!$B$8:$B$1007,$A35)+SUMIFS(JOURNAL!$H$8:$H$1007,JOURNAL!$E$8:$E$1007,"Virement Associés",JOURNAL!$B$8:$B$1007,$A35)) -> 0 | L35: =IF($A35="","",$M35-SUM($G35:$K35)) -> 0 | M35: =IF($A35="","",SUMIFS(JOURNAL!$H$8:$H$1007,JOURNAL!$D$8:$D$1007,"DEPENSE",JOURNAL!$B$8:$B$1007,$A35)) -> 0 | N35: =IF($A35="","",$F35-$M35) -> 0 | O35: =IF($A35="","",$O34+$N35) -> 4223 | P35: =IF($A35="","",IF($F35=0,"—",$F35-PARAMETRES!$C$20)) -> —
A36: =IF(31>PARAMETRES!$C$16,"",DATE(PARAMETRES!$C$12,PARAMETRES!$C$13,31)) -> 46265 | B36: =IF($A36="","",CHOOSE(WEEKDAY($A36,2),"Lundi","Mardi","Mercredi","Jeudi","Vendredi","Samedi","Dimanche")) -> Lundi | C36: =IF($A36="","",SUMIFS(JOURNAL!$H$8:$H$1007,JOURNAL!$E$8:$E$1007,"Vente Caisse",JOURNAL!$B$8:$B$1007,$A36)+SUMIFS(JOURNAL!$H$8:$H$1007,JOURNAL!$E$8:$E$1007,"Terrasse",JOURNAL!$B$8:$B$1007,$A36)+SUMIFS(JOURNAL!$H$8:$H$1007,JOURNAL!$E$8:$E$1007,"Autre Recette",JOURNAL!$B$8:$B$1007,$A36)) -> 0 | D36: =IF($A36="","",SUMIFS(JOURNAL!$H$8:$H$1007,JOURNAL!$E$8:$E$1007,"Glovo Espèce",JOURNAL!$B$8:$B$1007,$A36)) -> 0 | E36: =IF($A36="","",SUMIFS(JOURNAL!$H$8:$H$1007,JOURNAL!$E$8:$E$1007,"Glovo Carte",JOURNAL!$B$8:$B$1007,$A36)) -> 0 | F36: =IF($A36="","",SUM($C36:$E36)) -> 0 | G36: =IF($A36="","",SUMIFS(JOURNAL!$H$8:$H$1007,JOURNAL!$E$8:$E$1007,"Boissons",JOURNAL!$B$8:$B$1007,$A36)+SUMIFS(JOURNAL!$H$8:$H$1007,JOURNAL!$E$8:$E$1007,"Café & Torréfaction",JOURNAL!$B$8:$B$1007,$A36)+SUMIFS(JOURNAL!$H$8:$H$1007,JOURNAL!$E$8:$E$1007,"Boulangerie",JOURNAL!$B$8:$B$1007,$A36)+SUMIFS(JOURNAL!$H$8:$H$1007,JOURNAL!$E$8:$E$1007,"Fruits & Légumes",JOURNAL!$B$8:$B$1007,$A36)+SUMIFS(JOURNAL!$H$8:$H$1007,JOURNAL!$E$8:$E$1007,"Épicerie & Divers",JOURNAL!$B$8:$B$1007,$A36)) -> 0 | H36: =IF($A36="","",SUMIFS(JOURNAL!$H$8:$H$1007,JOURNAL!$E$8:$E$1007,"Nettoyage",JOURNAL!$B$8:$B$1007,$A36)) -> 0 | I36: =IF($A36="","",SUMIFS(JOURNAL!$H$8:$H$1007,JOURNAL!$E$8:$E$1007,"Salaires",JOURNAL!$B$8:$B$1007,$A36)) -> 0 | J36: =IF($A36="","",SUMIFS(JOURNAL!$H$8:$H$1007,JOURNAL!$E$8:$E$1007,"Loyer",JOURNAL!$B$8:$B$1007,$A36)+SUMIFS(JOURNAL!$H$8:$H$1007,JOURNAL!$E$8:$E$1007,"Eau & Électricité",JOURNAL!$B$8:$B$1007,$A36)+SUMIFS(JOURNAL!$H$8:$H$1007,JOURNAL!$E$8:$E$1007,"Internet & Télécom",JOURNAL!$B$8:$B$1007,$A36)+SUMIFS(JOURNAL!$H$8:$H$1007,JOURNAL!$E$8:$E$1007,"Taxes & Impôts",JOURNAL!$B$8:$B$1007,$A36)+SUMIFS(JOURNAL!$H$8:$H$1007,JOURNAL!$E$8:$E$1007,"Abonnements",JOURNAL!$B$8:$B$1007,$A36)+SUMIFS(JOURNAL!$H$8:$H$1007,JOURNAL!$E$8:$E$1007,"Entretien & Réparation",JOURNAL!$B$8:$B$1007,$A36)) -> 0 | K36: =IF($A36="","",SUMIFS(JOURNAL!$H$8:$H$1007,JOURNAL!$E$8:$E$1007,"Virement Banque",JOURNAL!$B$8:$B$1007,$A36)+SUMIFS(JOURNAL!$H$8:$H$1007,JOURNAL!$E$8:$E$1007,"Virement Associés",JOURNAL!$B$8:$B$1007,$A36)) -> 0 | L36: =IF($A36="","",$M36-SUM($G36:$K36)) -> 0 | M36: =IF($A36="","",SUMIFS(JOURNAL!$H$8:$H$1007,JOURNAL!$D$8:$D$1007,"DEPENSE",JOURNAL!$B$8:$B$1007,$A36)) -> 0 | N36: =IF($A36="","",$F36-$M36) -> 0 | O36: =IF($A36="","",$O35+$N36) -> 4223 | P36: =IF($A36="","",IF($F36=0,"—",$F36-PARAMETRES!$C$20)) -> —
A37: TOTAL DU MOIS | C37: =SUM(C6:C36) -> 54937 | D37: =SUM(D6:D36) -> 0 | E37: =SUM(E6:E36) -> 0 | F37: =SUM(F6:F36) -> 54937 | G37: =SUM(G6:G36) -> 20479 | H37: =SUM(H6:H36) -> 4050 | I37: =SUM(I6:I36) -> 12400 | J37: =SUM(J6:J36) -> 13785 | ... N37: =SUM(N6:N36) -> 4223 | O37: =$O36 -> 4223 | P37: =SUMIF($F$6:$F$36,">0",$P$6:$P$36) -> -4463
A38: RATIO DÉPENSE / RECETTE | G38: =IFERROR(G37/$F$37,0) -> 0.37277245 | H38: =IFERROR(H37/$F$37,0) -> 0.073720807 | I38: =IFERROR(I37/$F$37,0) -> 0.22571309 | J38: =IFERROR(J37/$F$37,0) -> 0.25092379 | K38: =IFERROR(K37/$F$37,0) -> 0 | M38: =IFERROR(M37/$F$37,0) -> 0.92313013
A40: Lecture : « AUTRES » regroupe les dépenses dont la catégorie ne rentre dans aucun groupe ci-dessus ; si cette colonne n’est pas vide, vérifiez la catégorie des lignes concernées dans le JOURNAL. « CAISSE CUMULÉE » part du solde saisi dans PARAMÈTRES (caisse au 1er du mois) et ajoute chaque jour le résultat. Les lignes grisées sont les samedis et dimanches.

Sheet SUIVI MENSUEL
A1: SUIVI MENSUEL
A2: Comparaison mois par mois. 2025 = historique repris de l’ancien classeur, 2026 = calculé automatiquement depuis le JOURNAL.
A4: MOIS | B4: RECETTE | C4: ACHATS MARCHANDISE | D4: % ACHATS | E4: SALAIRES | F4: CHARGES FIXES | G4: VIREMENTS | H4: TOTAL DÉPENSES | I4: RESULTAT | J4: MARGE | K4: RECETTE MOY./JOUR
A5: 45658 | B5: 58097 | C5: 17550 | D5: =IFERROR($C5/$B5,0) -> 0.302081 | E5: n.d. | F5: n.d. | G5: n.d. | H5: n.d. | I5: n.d. | J5: n.d. | K5: =IFERROR($B5/DAY(EOMONTH($A5,0)),0) -> 1874.0968
A6: 45689 | B6: 47774 | C6: 15723 | D6: =IFERROR($C6/$B6,0) -> 0.32911207 | E6: n.d. | F6: n.d. | G6: n.d. | H6: n.d. | I6: n.d. | J6: n.d. | K6: =IFERROR($B6/DAY(EOMONTH($A6,0)),0) -> 1706.2143
A7: 45717 | B7: 33629 | C7: 19497 | D7: =IFERROR($C7/$B7,0) -> 0.57976746 | E7: n.d. | F7: n.d. | G7: n.d. | H7: n.d. | I7: n.d. | J7: n.d. | K7: =IFERROR($B7/DAY(EOMONTH($A7,0)),0) -> 1084.8065
A8: 45748 | B8: 63101 | C8: 24871 | D8: =IFERROR($C8/$B8,0) -> 0.39414589 | E8: n.d. | F8: n.d. | G8: n.d. | H8: n.d. | I8: n.d. | J8: n.d. | K8: =IFERROR($B8/DAY(EOMONTH($A8,0)),0) -> 2103.3667
A9: 45778 | B9: 67697 | C9: 27947 | D9: =IFERROR($C9/$B9,0) -> 0.41282479 | E9: n.d. | F9: n.d. | G9: n.d. | H9: n.d. | I9: n.d. | J9: n.d. | K9: =IFERROR($B9/DAY(EOMONTH($A9,0)),0) -> 2183.7742
A10: 45809 | B10: 57443 | C10: 23534 | D10: =IFERROR($C10/$B10,0) -> 0.40969309 | E10: n.d. | F10: n.d. | G10: n.d. | H10: n.d. | I10: n.d. | J10: n.d. | K10: =IFERROR($B10/DAY(EOMONTH($A10,0)),0) -> 1914.7667
A11: 45839 | B11: 71948 | C11: 28425 | D11: =IFERROR($C11/$B11,0) -> 0.395077 | E11: n.d. | F11: n.d. | G11: n.d. | H11: n.d. | I11: n.d. | J11: n.d. | K11: =IFERROR($B11/DAY(EOMONTH($A11,0)),0) -> 2320.9032
A12: 45870 | B12: 78294 | C12: 31683 | D12: =IFERROR($C12/$B12,0) -> 0.40466702 | E12: n.d. | F12: n.d. | G12: n.d. | H12: n.d. | I12: n.d. | J12: n.d. | K12: =IFERROR($B12/DAY(EOMONTH($A12,0)),0) -> 2525.6129
A13: 45901 | B13: 53925 | C13: 23474 | D13: =IFERROR($C13/$B13,0) -> 0.4353083 | E13: n.d. | F13: n.d. | G13: n.d. | H13: n.d. | I13: n.d. | J13: n.d. | K13: =IFERROR($B13/DAY(EOMONTH($A13,0)),0) -> 1797.5
A14: 45931 | B14: 52669 | C14: 22122 | D14: =IFERROR($C14/$B14,0) -> 0.42001937 | E14: n.d. | F14: n.d. | G14: n.d. | H14: n.d. | I14: n.d. | J14: n.d. | K14: =IFERROR($B14/DAY(EOMONTH($A14,0)),0) -> 1699
A15: 45962 | D15: =IFERROR($C15/$B15,0) -> 0 | E15: n.d. | F15: n.d. | G15: n.d. | H15: n.d. | I15: n.d. | J15: n.d. | K15: =IFERROR($B15/DAY(EOMONTH($A15,0)),0) -> 0
A16: 45992 | D16: =IFERROR($C16/$B16,0) -> 0 | E16: n.d. | F16: n.d. | G16: n.d. | H16: n.d. | I16: n.d. | J16: n.d. | K16: =IFERROR($B16/DAY(EOMONTH($A16,0)),0) -> 0
A17: 46023 | B17: =SUMIFS(JOURNAL!$H$8:$H$1007,JOURNAL!$D$8:$D$1007,"RECETTE",JOURNAL!$C$8:$C$1007,202601) -> 0 | C17: =SUMIFS(JOURNAL!$H$8:$H$1007,JOURNAL!$E$8:$E$1007,"Boissons",JOURNAL!$C$8:$C$1007,202601)+SUMIFS(JOURNAL!$H$8:$H$1007,JOURNAL!$E$8:$E$1007,"Café & Torréfaction",JOURNAL!$C$8:$C$1007,202601)+SUMIFS(JOURNAL!$H$8:$H$1007,JOURNAL!$E$8:$E$1007,"Boulangerie",JOURNAL!$C$8:$C$1007,202601)+SUMIFS(JOURNAL!$H$8:$H$1007,JOURNAL!$E$8:$E$1007,"Fruits & Légumes",JOURNAL!$C$8:$C$1007,202601)+SUMIFS(JOURNAL!$H$8:$H$1007,JOURNAL!$E$8:$E$1007,"Épicerie & Divers",JOURNAL!$C$8:$C$1007,202601)+SUMIFS(JOURNAL!$H$8:$H$1007,JOURNAL!$E$8:$E$1007,"Nettoyage",JOURNAL!$C$8:$C$1007,202601) -> 0 | D17: =IFERROR($C17/$B17,0) -> 0 | E17: =SUMIFS(JOURNAL!$H$8:$H$1007,JOURNAL!$E$8:$E$1007,"Salaires",JOURNAL!$C$8:$C$1007,202601) -> 0 | F17: =SUMIFS(JOURNAL!$H$8:$H$1007,JOURNAL!$E$8:$E$1007,"Loyer",JOURNAL!$C$8:$C$1007,202601)+SUMIFS(JOURNAL!$H$8:$H$1007,JOURNAL!$E$8:$E$1007,"Eau & Électricité",JOURNAL!$C$8:$C$1007,202601)+SUMIFS(JOURNAL!$H$8:$H$1007,JOURNAL!$E$8:$E$1007,"Internet & Télécom",JOURNAL!$C$8:$C$1007,202601)+SUMIFS(JOURNAL!$H$8:$H$1007,JOURNAL!$E$8:$E$1007,"Taxes & Impôts",JOURNAL!$C$8:$C$1007,202601)+SUMIFS(JOURNAL!$H$8:$H$1007,JOURNAL!$E$8:$E$1007,"Abonnements",JOURNAL!$C$8:$C$1007,202601)+SUMIFS(JOURNAL!$H$8:$H$1007,JOURNAL!$E$8:$E$1007,"Entretien & Réparation",JOURNAL!$C$8:$C$1007,202601) -> 0 | G17: =SUMIFS(JOURNAL!$H$8:$H$1007,JOURNAL!$E$8:$E$1007,"Virement Banque",JOURNAL!$C$8:$C$1007,202601)+SUMIFS(JOURNAL!$H$8:$H$1007,JOURNAL!$E$8:$E$1007,"Virement Associés",JOURNAL!$C$8:$C$1007,202601) -> 0 | H17: =SUMIFS(JOURNAL!$H$8:$H$1007,JOURNAL!$D$8:$D$1007,"DEPENSE",JOURNAL!$C$8:$C$1007,202601) -> 0 | I17: =$B17-$H17 -> 0 | J17: =IFERROR($I17/$B17,0) -> 0 | K17: =IFERROR($B17/DAY(EOMONTH($A17,0)),0) -> 0
A18: 46054 | B18: =SUMIFS(JOURNAL!$H$8:$H$1007,JOURNAL!$D$8:$D$1007,"RECETTE",JOURNAL!$C$8:$C$1007,202602) -> 0 | C18: =SUMIFS(JOURNAL!$H$8:$H$1007,JOURNAL!$E$8:$E$1007,"Boissons",JOURNAL!$C$8:$C$1007,202602)+SUMIFS(JOURNAL!$H$8:$H$1007,JOURNAL!$E$8:$E$1007,"Café & Torréfaction",JOURNAL!$C$8:$C$1007,202602)+SUMIFS(JOURNAL!$H$8:$H$1007,JOURNAL!$E$8:$E$1007,"Boulangerie",JOURNAL!$C$8:$C$1007,202602)+SUMIFS(JOURNAL!$H$8:$H$1007,JOURNAL!$E$8:$E$1007,"Fruits & Légumes",JOURNAL!$C$8:$C$1007,202602)+SUMIFS(JOURNAL!$H$8:$H$1007,JOURNAL!$E$8:$E$1007,"Épicerie & Divers",JOURNAL!$C$8:$C$1007,202602)+SUMIFS(JOURNAL!$H$8:$H$1007,JOURNAL!$E$8:$E$1007,"Nettoyage",JOURNAL!$C$8:$C$1007,202602) -> 0 | D18: =IFERROR($C18/$B18,0) -> 0 | E18: =SUMIFS(JOURNAL!$H$8:$H$1007,JOURNAL!$E$8:$E$1007,"Salaires",JOURNAL!$C$8:$C$1007,202602) -> 0 | F18: =SUMIFS(JOURNAL!$H$8:$H$1007,JOURNAL!$E$8:$E$1007,"Loyer",JOURNAL!$C$8:$C$1007,202602)+SUMIFS(JOURNAL!$H$8:$H$1007,JOURNAL!$E$8:$E$1007,"Eau & Électricité",JOURNAL!$C$8:$C$1007,202602)+SUMIFS(JOURNAL!$H$8:$H$1007,JOURNAL!$E$8:$E$1007,"Internet & Télécom",JOURNAL!$C$8:$C$1007,202602)+SUMIFS(JOURNAL!$H$8:$H$1007,JOURNAL!$E$8:$E$1007,"Taxes & Impôts",JOURNAL!$C$8:$C$1007,202602)+SUMIFS(JOURNAL!$H$8:$H$1007,JOURNAL!$E$8:$E$1007,"Abonnements",JOURNAL!$C$8:$C$1007,202602)+SUMIFS(JOURNAL!$H$8:$H$1007,JOURNAL!$E$8:$E$1007,"Entretien & Réparation",JOURNAL!$C$8:$C$1007,202602) -> 0 | G18: =SUMIFS(JOURNAL!$H$8:$H$1007,JOURNAL!$E$8:$E$1007,"Virement Banque",JOURNAL!$C$8:$C$1007,202602)+SUMIFS(JOURNAL!$H$8:$H$1007,JOURNAL!$E$8:$E$1007,"Virement Associés",JOURNAL!$C$8:$C$1007,202602) -> 0 | H18: =SUMIFS(JOURNAL!$H$8:$H$1007,JOURNAL!$D$8:$D$1007,"DEPENSE",JOURNAL!$C$8:$C$1007,202602) -> 0 | I18: =$B18-$H18 -> 0 | J18: =IFERROR($I18/$B18,0) -> 0 | K18: =IFERROR($B18/DAY(EOMONTH($A18,0)),0) -> 0
A19: 46082 | B19: =SUMIFS(JOURNAL!$H$8:$H$1007,JOURNAL!$D$8:$D$1007,"RECETTE",JOURNAL!$C$8:$C$1007,202603) -> 0 | C19: =SUMIFS(JOURNAL!$H$8:$H$1007,JOURNAL!$E$8:$E$1007,"Boissons",JOURNAL!$C$8:$C$1007,202603)+SUMIFS(JOURNAL!$H$8:$H$1007,JOURNAL!$E$8:$E$1007,"Café & Torréfaction",JOURNAL!$C$8:$C$1007,202603)+SUMIFS(JOURNAL!$H$8:$H$1007,JOURNAL!$E$8:$E$1007,"Boulangerie",JOURNAL!$C$8:$C$1007,202603)+SUMIFS(JOURNAL!$H$8:$H$1007,JOURNAL!$E$8:$E$1007,"Fruits & Légumes",JOURNAL!$C$8:$C$1007,202603)+SUMIFS(JOURNAL!$H$8:$H$1007,JOURNAL!$E$8:$E$1007,"Épicerie & Divers",JOURNAL!$C$8:$C$1007,202603)+SUMIFS(JOURNAL!$H$8:$H$1007,JOURNAL!$E$8:$E$1007,"Nettoyage",JOURNAL!$C$8:$C$1007,202603) -> 0 | D19: =IFERROR($C19/$B19,0) -> 0 | E19: =SUMIFS(JOURNAL!$H$8:$H$1007,JOURNAL!$E$8:$E$1007,"Salaires",JOURNAL!$C$8:$C$1007,202603) -> 0 | F19: =SUMIFS(JOURNAL!$H$8:$H$1007,JOURNAL!$E$8:$E$1007,"Loyer",JOURNAL!$C$8:$C$1007,202603)+SUMIFS(JOURNAL!$H$8:$H$1007,JOURNAL!$E$8:$E$1007,"Eau & Électricité",JOURNAL!$C$8:$C$1007,202603)+SUMIFS(JOURNAL!$H$8:$H$1007,JOURNAL!$E$8:$E$1007,"Internet & Télécom",JOURNAL!$C$8:$C$1007,202603)+SUMIFS(JOURNAL!$H$8:$H$1007,JOURNAL!$E$8:$E$1007,"Taxes & Impôts",JOURNAL!$C$8:$C$1007,202603)+SUMIFS(JOURNAL!$H$8:$H$1007,JOURNAL!$E$8:$E$1007,"Abonnements",JOURNAL!$C$8:$C$1007,202603)+SUMIFS(JOURNAL!$H$8:$H$1007,JOURNAL!$E$8:$E$1007,"Entretien & Réparation",JOURNAL!$C$8:$C$1007,202603) -> 0 | G19: =SUMIFS(JOURNAL!$H$8:$H$1007,JOURNAL!$E$8:$E$1007,"Virement Banque",JOURNAL!$C$8:$C$1007,202603)+SUMIFS(JOURNAL!$H$8:$H$1007,JOURNAL!$E$8:$E$1007,"Virement Associés",JOURNAL!$C$8:$C$1007,202603) -> 0 | H19: =SUMIFS(JOURNAL!$H$8:$H$1007,JOURNAL!$D$8:$D$1007,"DEPENSE",JOURNAL!$C$8:$C$1007,202603) -> 0 | I19: =$B19-$H19 -> 0 | J19: =IFERROR($I19/$B19,0) -> 0 | K19: =IFERROR($B19/DAY(EOMONTH($A19,0)),0) -> 0
A20: 46113 | B20: =SUMIFS(JOURNAL!$H$8:$H$1007,JOURNAL!$D$8:$D$1007,"RECETTE",JOURNAL!$C$8:$C$1007,202604) -> 0 | C20: =SUMIFS(JOURNAL!$H$8:$H$1007,JOURNAL!$E$8:$E$1007,"Boissons",JOURNAL!$C$8:$C$1007,202604)+SUMIFS(JOURNAL!$H$8:$H$1007,JOURNAL!$E$8:$E$1007,"Café & Torréfaction",JOURNAL!$C$8:$C$1007,202604)+SUMIFS(JOURNAL!$H$8:$H$1007,JOURNAL!$E$8:$E$1007,"Boulangerie",JOURNAL!$C$8:$C$1007,202604)+SUMIFS(JOURNAL!$H$8:$H$1007,JOURNAL!$E$8:$E$1007,"Fruits & Légumes",JOURNAL!$C$8:$C$1007,202604)+SUMIFS(JOURNAL!$H$8:$H$1007,JOURNAL!$E$8:$E$1007,"Épicerie & Divers",JOURNAL!$C$8:$C$1007,202604)+SUMIFS(JOURNAL!$H$8:$H$1007,JOURNAL!$E$8:$E$1007,"Nettoyage",JOURNAL!$C$8:$C$1007,202604) -> 0 | D20: =IFERROR($C20/$B20,0) -> 0 | E20: =SUMIFS(JOURNAL!$H$8:$H$1007,JOURNAL!$E$8:$E$1007,"Salaires",JOURNAL!$C$8:$C$1007,202604) -> 0 | F20: =SUMIFS(JOURNAL!$H$8:$H$1007,JOURNAL!$E$8:$E$1007,"Loyer",JOURNAL!$C$8:$C$1007,202604)+SUMIFS(JOURNAL!$H$8:$H$1007,JOURNAL!$E$8:$E$1007,"Eau & Électricité",JOURNAL!$C$8:$C$1007,202604)+SUMIFS(JOURNAL!$H$8:$H$1007,JOURNAL!$E$8:$E$1007,"Internet & Télécom",JOURNAL!$C$8:$C$1007,202604)+SUMIFS(JOURNAL!$H$8:$H$1007,JOURNAL!$E$8:$E$1007,"Taxes & Impôts",JOURNAL!$C$8:$C$1007,202604)+SUMIFS(JOURNAL!$H$8:$H$1007,JOURNAL!$E$8:$E$1007,"Abonnements",JOURNAL!$C$8:$C$1007,202604)+SUMIFS(JOURNAL!$H$8:$H$1007,JOURNAL!$E$8:$E$1007,"Entretien & Réparation",JOURNAL!$C$8:$C$1007,202604) -> 0 | G20: =SUMIFS(JOURNAL!$H$8:$H$1007,JOURNAL!$E$8:$E$1007,"Virement Banque",JOURNAL!$C$8:$C$1007,202604)+SUMIFS(JOURNAL!$H$8:$H$1007,JOURNAL!$E$8:$E$1007,"Virement Associés",JOURNAL!$C$8:$C$1007,202604) -> 0 | H20: =SUMIFS(JOURNAL!$H$8:$H$1007,JOURNAL!$D$8:$D$1007,"DEPENSE",JOURNAL!$C$8:$C$1007,202604) -> 0 | I20: =$B20-$H20 -> 0 | J20: =IFERROR($I20/$B20,0) -> 0 | K20: =IFERROR($B20/DAY(EOMONTH($A20,0)),0) -> 0
A21: 46143 | B21: =SUMIFS(JOURNAL!$H$8:$H$1007,JOURNAL!$D$8:$D$1007,"RECETTE",JOURNAL!$C$8:$C$1007,202605) -> 0 | C21: =SUMIFS(JOURNAL!$H$8:$H$1007,JOURNAL!$E$8:$E$1007,"Boissons",JOURNAL!$C$8:$C$1007,202605)+SUMIFS(JOURNAL!$H$8:$H$1007,JOURNAL!$E$8:$E$1007,"Café & Torréfaction",JOURNAL!$C$8:$C$1007,202605)+SUMIFS(JOURNAL!$H$8:$H$1007,JOURNAL!$E$8:$E$1007,"Boulangerie",JOURNAL!$C$8:$C$1007,202605)+SUMIFS(JOURNAL!$H$8:$H$1007,JOURNAL!$E$8:$E$1007,"Fruits & Légumes",JOURNAL!$C$8:$C$1007,202605)+SUMIFS(JOURNAL!$H$8:$H$1007,JOURNAL!$E$8:$E$1007,"Épicerie & Divers",JOURNAL!$C$8:$C$1007,202605)+SUMIFS(JOURNAL!$H$8:$H$1007,JOURNAL!$E$8:$E$1007,"Nettoyage",JOURNAL!$C$8:$C$1007,202605) -> 0 | D21: =IFERROR($C21/$B21,0) -> 0 | E21: =SUMIFS(JOURNAL!$H$8:$H$1007,JOURNAL!$E$8:$E$1007,"Salaires",JOURNAL!$C$8:$C$1007,202605) -> 0 | F21: =SUMIFS(JOURNAL!$H$8:$H$1007,JOURNAL!$E$8:$E$1007,"Loyer",JOURNAL!$C$8:$C$1007,202605)+SUMIFS(JOURNAL!$H$8:$H$1007,JOURNAL!$E$8:$E$1007,"Eau & Électricité",JOURNAL!$C$8:$C$1007,202605)+SUMIFS(JOURNAL!$H$8:$H$1007,JOURNAL!$E$8:$E$1007,"Internet & Télécom",JOURNAL!$C$8:$C$1007,202605)+SUMIFS(JOURNAL!$H$8:$H$1007,JOURNAL!$E$8:$E$1007,"Taxes & Impôts",JOURNAL!$C$8:$C$1007,202605)+SUMIFS(JOURNAL!$H$8:$H$1007,JOURNAL!$E$8:$E$1007,"Abonnements",JOURNAL!$C$8:$C$1007,202605)+SUMIFS(JOURNAL!$H$8:$H$1007,JOURNAL!$E$8:$E$1007,"Entretien & Réparation",JOURNAL!$C$8:$C$1007,202605) -> 0 | G21: =SUMIFS(JOURNAL!$H$8:$H$1007,JOURNAL!$E$8:$E$1007,"Virement Banque",JOURNAL!$C$8:$C$1007,202605)+SUMIFS(JOURNAL!$H$8:$H$1007,JOURNAL!$E$8:$E$1007,"Virement Associés",JOURNAL!$C$8:$C$1007,202605) -> 0 | H21: =SUMIFS(JOURNAL!$H$8:$H$1007,JOURNAL!$D$8:$D$1007,"DEPENSE",JOURNAL!$C$8:$C$1007,202605) -> 0 | I21: =$B21-$H21 -> 0 | J21: =IFERROR($I21/$B21,0) -> 0 | K21: =IFERROR($B21/DAY(EOMONTH($A21,0)),0) -> 0
A22: 46174 | B22: =SUMIFS(JOURNAL!$H$8:$H$1007,JOURNAL!$D$8:$D$1007,"RECETTE",JOURNAL!$C$8:$C$1007,202606) -> 0 | C22: =SUMIFS(JOURNAL!$H$8:$H$1007,JOURNAL!$E$8:$E$1007,"Boissons",JOURNAL!$C$8:$C$1007,202606)+SUMIFS(JOURNAL!$H$8:$H$1007,JOURNAL!$E$8:$E$1007,"Café & Torréfaction",JOURNAL!$C$8:$C$1007,202606)+SUMIFS(JOURNAL!$H$8:$H$1007,JOURNAL!$E$8:$E$1007,"Boulangerie",JOURNAL!$C$8:$C$1007,202606)+SUMIFS(JOURNAL!$H$8:$H$1007,JOURNAL!$E$8:$E$1007,"Fruits & Légumes",JOURNAL!$C$8:$C$1007,202606)+SUMIFS(JOURNAL!$H$8:$H$1007,JOURNAL!$E$8:$E$1007,"Épicerie & Divers",JOURNAL!$C$8:$C$1007,202606)+SUMIFS(JOURNAL!$H$8:$H$1007,JOURNAL!$E$8:$E$1007,"Nettoyage",JOURNAL!$C$8:$C$1007,202606) -> 0 | D22: =IFERROR($C22/$B22,0) -> 0 | E22: =SUMIFS(JOURNAL!$H$8:$H$1007,JOURNAL!$E$8:$E$1007,"Salaires",JOURNAL!$C$8:$C$1007,202606) -> 0 | F22: =SUMIFS(JOURNAL!$H$8:$H$1007,JOURNAL!$E$8:$E$1007,"Loyer",JOURNAL!$C$8:$C$1007,202606)+SUMIFS(JOURNAL!$H$8:$H$1007,JOURNAL!$E$8:$E$1007,"Eau & Électricité",JOURNAL!$C$8:$C$1007,202606)+SUMIFS(JOURNAL!$H$8:$H$1007,JOURNAL!$E$8:$E$1007,"Internet & Télécom",JOURNAL!$C$8:$C$1007,202606)+SUMIFS(JOURNAL!$H$8:$H$1007,JOURNAL!$E$8:$E$1007,"Taxes & Impôts",JOURNAL!$C$8:$C$1007,202606)+SUMIFS(JOURNAL!$H$8:$H$1007,JOURNAL!$E$8:$E$1007,"Abonnements",JOURNAL!$C$8:$C$1007,202606)+SUMIFS(JOURNAL!$H$8:$H$1007,JOURNAL!$E$8:$E$1007,"Entretien & Réparation",JOURNAL!$C$8:$C$1007,202606) -> 0 | G22: =SUMIFS(JOURNAL!$H$8:$H$1007,JOURNAL!$E$8:$E$1007,"Virement Banque",JOURNAL!$C$8:$C$1007,202606)+SUMIFS(JOURNAL!$H$8:$H$1007,JOURNAL!$E$8:$E$1007,"Virement Associés",JOURNAL!$C$8:$C$1007,202606) -> 0 | H22: =SUMIFS(JOURNAL!$H$8:$H$1007,JOURNAL!$D$8:$D$1007,"DEPENSE",JOURNAL!$C$8:$C$1007,202606) -> 0 | I22: =$B22-$H22 -> 0 | J22: =IFERROR($I22/$B22,0) -> 0 | K22: =IFERROR($B22/DAY(EOMONTH($A22,0)),0) -> 0
A23: 46204 | B23: =SUMIFS(JOURNAL!$H$8:$H$1007,JOURNAL!$D$8:$D$1007,"RECETTE",JOURNAL!$C$8:$C$1007,202607) -> 0 | C23: =SUMIFS(JOURNAL!$H$8:$H$1007,JOURNAL!$E$8:$E$1007,"Boissons",JOURNAL!$C$8:$C$1007,202607)+SUMIFS(JOURNAL!$H$8:$H$1007,JOURNAL!$E$8:$E$1007,"Café & Torréfaction",JOURNAL!$C$8:$C$1007,202607)+SUMIFS(JOURNAL!$H$8:$H$1007,JOURNAL!$E$8:$E$1007,"Boulangerie",JOURNAL!$C$8:$C$1007,202607)+SUMIFS(JOURNAL!$H$8:$H$1007,JOURNAL!$E$8:$E$1007,"Fruits & Légumes",JOURNAL!$C$8:$C$1007,202607)+SUMIFS(JOURNAL!$H$8:$H$1007,JOURNAL!$E$8:$E$1007,"Épicerie & Divers",JOURNAL!$C$8:$C$1007,202607)+SUMIFS(JOURNAL!$H$8:$H$1007,JOURNAL!$E$8:$E$1007,"Nettoyage",JOURNAL!$C$8:$C$1007,202607) -> 0 | D23: =IFERROR($C23/$B23,0) -> 0 | E23: =SUMIFS(JOURNAL!$H$8:$H$1007,JOURNAL!$E$8:$E$1007,"Salaires",JOURNAL!$C$8:$C$1007,202607) -> 0 | F23: =SUMIFS(JOURNAL!$H$8:$H$1007,JOURNAL!$E$8:$E$1007,"Loyer",JOURNAL!$C$8:$C$1007,202607)+SUMIFS(JOURNAL!$H$8:$H$1007,JOURNAL!$E$8:$E$1007,"Eau & Électricité",JOURNAL!$C$8:$C$1007,202607)+SUMIFS(JOURNAL!$H$8:$H$1007,JOURNAL!$E$8:$E$1007,"Internet & Télécom",JOURNAL!$C$8:$C$1007,202607)+SUMIFS(JOURNAL!$H$8:$H$1007,JOURNAL!$E$8:$E$1007,"Taxes & Impôts",JOURNAL!$C$8:$C$1007,202607)+SUMIFS(JOURNAL!$H$8:$H$1007,JOURNAL!$E$8:$E$1007,"Abonnements",JOURNAL!$C$8:$C$1007,202607)+SUMIFS(JOURNAL!$H$8:$H$1007,JOURNAL!$E$8:$E$1007,"Entretien & Réparation",JOURNAL!$C$8:$C$1007,202607) -> 0 | G23: =SUMIFS(JOURNAL!$H$8:$H$1007,JOURNAL!$E$8:$E$1007,"Virement Banque",JOURNAL!$C$8:$C$1007,202607)+SUMIFS(JOURNAL!$H$8:$H$1007,JOURNAL!$E$8:$E$1007,"Virement Associés",JOURNAL!$C$8:$C$1007,202607) -> 0 | H23: =SUMIFS(JOURNAL!$H$8:$H$1007,JOURNAL!$D$8:$D$1007,"DEPENSE",JOURNAL!$C$8:$C$1007,202607) -> 0 | I23: =$B23-$H23 -> 0 | J23: =IFERROR($I23/$B23,0) -> 0 | K23: =IFERROR($B23/DAY(EOMONTH($A23,0)),0) -> 0
A24: 46235 | B24: =SUMIFS(JOURNAL!$H$8:$H$1007,JOURNAL!$D$8:$D$1007,"RECETTE",JOURNAL!$C$8:$C$1007,202608) -> 54937 | C24: =SUMIFS(JOURNAL!$H$8:$H$1007,JOURNAL!$E$8:$E$1007,"Boissons",JOURNAL!$C$8:$C$1007,202608)+SUMIFS(JOURNAL!$H$8:$H$1007,JOURNAL!$E$8:$E$1007,"Café & Torréfaction",JOURNAL!$C$8:$C$1007,202608)+SUMIFS(JOURNAL!$H$8:$H$1007,JOURNAL!$E$8:$E$1007,"Boulangerie",JOURNAL!$C$8:$C$1007,202608)+SUMIFS(JOURNAL!$H$8:$H$1007,JOURNAL!$E$8:$E$1007,"Fruits & Légumes",JOURNAL!$C$8:$C$1007,202608)+SUMIFS(JOURNAL!$H$8:$H$1007,JOURNAL!$E$8:$E$1007,"Épicerie & Divers",JOURNAL!$C$8:$C$1007,202608)+SUMIFS(JOURNAL!$H$8:$H$1007,JOURNAL!$E$8:$E$1007,"Nettoyage",JOURNAL!$C$8:$C$1007,202608) -> 24529 | D24: =IFERROR($C24/$B24,0) -> 0.44649326 | E24: =SUMIFS(JOURNAL!$H$8:$H$1007,JOURNAL!$E$8:$E$1007,"Salaires",JOURNAL!$C$8:$C$1007,202608) -> 12400 | F24: =SUMIFS(JOURNAL!$H$8:$H$1007,JOURNAL!$E$8:$E$1007,"Loyer",JOURNAL!$C$8:$C$1007,202608)+SUMIFS(JOURNAL!$H$8:$H$1007,JOURNAL!$E$8:$E$1007,"Eau & Électricité",JOURNAL!$C$8:$C$1007,202608)+SUMIFS(JOURNAL!$H$8:$H$1007,JOURNAL!$E$8:$E$1007,"Internet & Télécom",JOURNAL!$C$8:$C$1007,202608)+SUMIFS(JOURNAL!$H$8:$H$1007,JOURNAL!$E$8:$E$1007,"Taxes & Impôts",JOURNAL!$C$8:$C$1007,202608)+SUMIFS(JOURNAL!$H$8:$H$1007,JOURNAL!$E$8:$E$1007,"Abonnements",JOURNAL!$C$8:$C$1007,202608)+SUMIFS(JOURNAL!$H$8:$H$1007,JOURNAL!$E$8:$E$1007,"Entretien & Réparation",JOURNAL!$C$8:$C$1007,202608) -> 13785 | G24: =SUMIFS(JOURNAL!$H$8:$H$1007,JOURNAL!$E$8:$E$1007,"Virement Banque",JOURNAL!$C$8:$C$1007,202608)+SUMIFS(JOURNAL!$H$8:$H$1007,JOURNAL!$E$8:$E$1007,"Virement Associés",JOURNAL!$C$8:$C$1007,202608) -> 0 | H24: =SUMIFS(JOURNAL!$H$8:$H$1007,JOURNAL!$D$8:$D$1007,"DEPENSE",JOURNAL!$C$8:$C$1007,202608) -> 50714 | I24: =$B24-$H24 -> 4223 | J24: =IFERROR($I24/$B24,0) -> 0.076869869 | K24: =IFERROR($B24/DAY(EOMONTH($A24,0)),0) -> 1772.1613
A25: 46266 | B25: =SUMIFS(JOURNAL!$H$8:$H$1007,JOURNAL!$D$8:$D$1007,"RECETTE",JOURNAL!$C$8:$C$1007,202609) -> 0 | C25: =SUMIFS(JOURNAL!$H$8:$H$1007,JOURNAL!$E$8:$E$1007,"Boissons",JOURNAL!$C$8:$C$1007,202609)+SUMIFS(JOURNAL!$H$8:$H$1007,JOURNAL!$E$8:$E$1007,"Café & Torréfaction",JOURNAL!$C$8:$C$1007,202609)+SUMIFS(JOURNAL!$H$8:$H$1007,JOURNAL!$E$8:$E$1007,"Boulangerie",JOURNAL!$C$8:$C$1007,202609)+SUMIFS(JOURNAL!$H$8:$H$1007,JOURNAL!$E$8:$E$1007,"Fruits & Légumes",JOURNAL!$C$8:$C$1007,202609)+SUMIFS(JOURNAL!$H$8:$H$1007,JOURNAL!$E$8:$E$1007,"Épicerie & Divers",JOURNAL!$C$8:$C$1007,202609)+SUMIFS(JOURNAL!$H$8:$H$1007,JOURNAL!$E$8:$E$1007,"Nettoyage",JOURNAL!$C$8:$C$1007,202609) -> 0 | D25: =IFERROR($C25/$B25,0) -> 0 | E25: =SUMIFS(JOURNAL!$H$8:$H$1007,JOURNAL!$E$8:$E$1007,"Salaires",JOURNAL!$C$8:$C$1007,202609) -> 0 | F25: =SUMIFS(JOURNAL!$H$8:$H$1007,JOURNAL!$E$8:$E$1007,"Loyer",JOURNAL!$C$8:$C$1007,202609)+SUMIFS(JOURNAL!$H$8:$H$1007,JOURNAL!$E$8:$E$1007,"Eau & Électricité",JOURNAL!$C$8:$C$1007,202609)+SUMIFS(JOURNAL!$H$8:$H$1007,JOURNAL!$E$8:$E$1007,"Internet & Télécom",JOURNAL!$C$8:$C$1007,202609)+SUMIFS(JOURNAL!$H$8:$H$1007,JOURNAL!$E$8:$E$1007,"Taxes & Impôts",JOURNAL!$C$8:$C$1007,202609)+SUMIFS(JOURNAL!$H$8:$H$1007,JOURNAL!$E$8:$E$1007,"Abonnements",JOURNAL!$C$8:$C$1007,202609)+SUMIFS(JOURNAL!$H$8:$H$1007,JOURNAL!$E$8:$E$1007,"Entretien & Réparation",JOURNAL!$C$8:$C$1007,202609) -> 0 | G25: =SUMIFS(JOURNAL!$H$8:$H$1007,JOURNAL!$E$8:$E$1007,"Virement Banque",JOURNAL!$C$8:$C$1007,202609)+SUMIFS(JOURNAL!$H$8:$H$1007,JOURNAL!$E$8:$E$1007,"Virement Associés",JOURNAL!$C$8:$C$1007,202609) -> 0 | H25: =SUMIFS(JOURNAL!$H$8:$H$1007,JOURNAL!$D$8:$D$1007,"DEPENSE",JOURNAL!$C$8:$C$1007,202609) -> 0 | I25: =$B25-$H25 -> 0 | J25: =IFERROR($I25/$B25,0) -> 0 | K25: =IFERROR($B25/DAY(EOMONTH($A25,0)),0) -> 0
A26: 46296 | B26: =SUMIFS(JOURNAL!$H$8:$H$1007,JOURNAL!$D$8:$D$1007,"RECETTE",JOURNAL!$C$8:$C$1007,202610) -> 0 | C26: =SUMIFS(JOURNAL!$H$8:$H$1007,JOURNAL!$E$8:$E$1007,"Boissons",JOURNAL!$C$8:$C$1007,202610)+SUMIFS(JOURNAL!$H$8:$H$1007,JOURNAL!$E$8:$E$1007,"Café & Torréfaction",JOURNAL!$C$8:$C$1007,202610)+SUMIFS(JOURNAL!$H$8:$H$1007,JOURNAL!$E$8:$E$1007,"Boulangerie",JOURNAL!$C$8:$C$1007,202610)+SUMIFS(JOURNAL!$H$8:$H$1007,JOURNAL!$E$8:$E$1007,"Fruits & Légumes",JOURNAL!$C$8:$C$1007,202610)+SUMIFS(JOURNAL!$H$8:$H$1007,JOURNAL!$E$8:$E$1007,"Épicerie & Divers",JOURNAL!$C$8:$C$1007,202610)+SUMIFS(JOURNAL!$H$8:$H$1007,JOURNAL!$E$8:$E$1007,"Nettoyage",JOURNAL!$C$8:$C$1007,202610) -> 0 | D26: =IFERROR($C26/$B26,0) -> 0 | E26: =SUMIFS(JOURNAL!$H$8:$H$1007,JOURNAL!$E$8:$E$1007,"Salaires",JOURNAL!$C$8:$C$1007,202610) -> 0 | F26: =SUMIFS(JOURNAL!$H$8:$H$1007,JOURNAL!$E$8:$E$1007,"Loyer",JOURNAL!$C$8:$C$1007,202610)+SUMIFS(JOURNAL!$H$8:$H$1007,JOURNAL!$E$8:$E$1007,"Eau & Électricité",JOURNAL!$C$8:$C$1007,202610)+SUMIFS(JOURNAL!$H$8:$H$1007,JOURNAL!$E$8:$E$1007,"Internet & Télécom",JOURNAL!$C$8:$C$1007,202610)+SUMIFS(JOURNAL!$H$8:$H$1007,JOURNAL!$E$8:$E$1007,"Taxes & Impôts",JOURNAL!$C$8:$C$1007,202610)+SUMIFS(JOURNAL!$H$8:$H$1007,JOURNAL!$E$8:$E$1007,"Abonnements",JOURNAL!$C$8:$C$1007,202610)+SUMIFS(JOURNAL!$H$8:$H$1007,JOURNAL!$E$8:$E$1007,"Entretien & Réparation",JOURNAL!$C$8:$C$1007,202610) -> 0 | G26: =SUMIFS(JOURNAL!$H$8:$H$1007,JOURNAL!$E$8:$E$1007,"Virement Banque",JOURNAL!$C$8:$C$1007,202610)+SUMIFS(JOURNAL!$H$8:$H$1007,JOURNAL!$E$8:$E$1007,"Virement Associés",JOURNAL!$C$8:$C$1007,202610) -> 0 | H26: =SUMIFS(JOURNAL!$H$8:$H$1007,JOURNAL!$D$8:$D$1007,"DEPENSE",JOURNAL!$C$8:$C$1007,202610) -> 0 | I26: =$B26-$H26 -> 0 | J26: =IFERROR($I26/$B26,0) -> 0 | K26: =IFERROR($B26/DAY(EOMONTH($A26,0)),0) -> 0
A27: 46327 | B27: =SUMIFS(JOURNAL!$H$8:$H$1007,JOURNAL!$D$8:$D$1007,"RECETTE",JOURNAL!$C$8:$C$1007,202611) -> 0 | C27: =SUMIFS(JOURNAL!$H$8:$H$1007,JOURNAL!$E$8:$E$1007,"Boissons",JOURNAL!$C$8:$C$1007,202611)+SUMIFS(JOURNAL!$H$8:$H$1007,JOURNAL!$E$8:$E$1007,"Café & Torréfaction",JOURNAL!$C$8:$C$1007,202611)+SUMIFS(JOURNAL!$H$8:$H$1007,JOURNAL!$E$8:$E$1007,"Boulangerie",JOURNAL!$C$8:$C$1007,202611)+SUMIFS(JOURNAL!$H$8:$H$1007,JOURNAL!$E$8:$E$1007,"Fruits & Légumes",JOURNAL!$C$8:$C$1007,202611)+SUMIFS(JOURNAL!$H$8:$H$1007,JOURNAL!$E$8:$E$1007,"Épicerie & Divers",JOURNAL!$C$8:$C$1007,202611)+SUMIFS(JOURNAL!$H$8:$H$1007,JOURNAL!$E$8:$E$1007,"Nettoyage",JOURNAL!$C$8:$C$1007,202611) -> 0 | D27: =IFERROR($C27/$B27,0) -> 0 | E27: =SUMIFS(JOURNAL!$H$8:$H$1007,JOURNAL!$E$8:$E$1007,"Salaires",JOURNAL!$C$8:$C$1007,202611) -> 0 | F27: =SUMIFS(JOURNAL!$H$8:$H$1007,JOURNAL!$E$8:$E$1007,"Loyer",JOURNAL!$C$8:$C$1007,202611)+SUMIFS(JOURNAL!$H$8:$H$1007,JOURNAL!$E$8:$E$1007,"Eau & Électricité",JOURNAL!$C$8:$C$1007,202611)+SUMIFS(JOURNAL!$H$8:$H$1007,JOURNAL!$E$8:$E$1007,"Internet & Télécom",JOURNAL!$C$8:$C$1007,202611)+SUMIFS(JOURNAL!$H$8:$H$1007,JOURNAL!$E$8:$E$1007,"Taxes & Impôts",JOURNAL!$C$8:$C$1007,202611)+SUMIFS(JOURNAL!$H$8:$H$1007,JOURNAL!$E$8:$E$1007,"Abonnements",JOURNAL!$C$8:$C$1007,202611)+SUMIFS(JOURNAL!$H$8:$H$1007,JOURNAL!$E$8:$E$1007,"Entretien & Réparation",JOURNAL!$C$8:$C$1007,202611) -> 0 | G27: =SUMIFS(JOURNAL!$H$8:$H$1007,JOURNAL!$E$8:$E$1007,"Virement Banque",JOURNAL!$C$8:$C$1007,202611)+SUMIFS(JOURNAL!$H$8:$H$1007,JOURNAL!$E$8:$E$1007,"Virement Associés",JOURNAL!$C$8:$C$1007,202611) -> 0 | H27: =SUMIFS(JOURNAL!$H$8:$H$1007,JOURNAL!$D$8:$D$1007,"DEPENSE",JOURNAL!$C$8:$C$1007,202611) -> 0 | I27: =$B27-$H27 -> 0 | J27: =IFERROR($I27/$B27,0) -> 0 | K27: =IFERROR($B27/DAY(EOMONTH($A27,0)),0) -> 0
A28: 46357 | B28: =SUMIFS(JOURNAL!$H$8:$H$1007,JOURNAL!$D$8:$D$1007,"RECETTE",JOURNAL!$C$8:$C$1007,202612) -> 0 | C28: =SUMIFS(JOURNAL!$H$8:$H$1007,JOURNAL!$E$8:$E$1007,"Boissons",JOURNAL!$C$8:$C$1007,202612)+SUMIFS(JOURNAL!$H$8:$H$1007,JOURNAL!$E$8:$E$1007,"Café & Torréfaction",JOURNAL!$C$8:$C$1007,202612)+SUMIFS(JOURNAL!$H$8:$H$1007,JOURNAL!$E$8:$E$1007,"Boulangerie",JOURNAL!$C$8:$C$1007,202612)+SUMIFS(JOURNAL!$H$8:$H$1007,JOURNAL!$E$8:$E$1007,"Fruits & Légumes",JOURNAL!$C$8:$C$1007,202612)+SUMIFS(JOURNAL!$H$8:$H$1007,JOURNAL!$E$8:$E$1007,"Épicerie & Divers",JOURNAL!$C$8:$C$1007,202612)+SUMIFS(JOURNAL!$H$8:$H$1007,JOURNAL!$E$8:$E$1007,"Nettoyage",JOURNAL!$C$8:$C$1007,202612) -> 0 | D28: =IFERROR($C28/$B28,0) -> 0 | E28: =SUMIFS(JOURNAL!$H$8:$H$1007,JOURNAL!$E$8:$E$1007,"Salaires",JOURNAL!$C$8:$C$1007,202612) -> 0 | F28: =SUMIFS(JOURNAL!$H$8:$H$1007,JOURNAL!$E$8:$E$1007,"Loyer",JOURNAL!$C$8:$C$1007,202612)+SUMIFS(JOURNAL!$H$8:$H$1007,JOURNAL!$E$8:$E$1007,"Eau & Électricité",JOURNAL!$C$8:$C$1007,202612)+SUMIFS(JOURNAL!$H$8:$H$1007,JOURNAL!$E$8:$E$1007,"Internet & Télécom",JOURNAL!$C$8:$C$1007,202612)+SUMIFS(JOURNAL!$H$8:$H$1007,JOURNAL!$E$8:$E$1007,"Taxes & Impôts",JOURNAL!$C$8:$C$1007,202612)+SUMIFS(JOURNAL!$H$8:$H$1007,JOURNAL!$E$8:$E$1007,"Abonnements",JOURNAL!$C$8:$C$1007,202612)+SUMIFS(JOURNAL!$H$8:$H$1007,JOURNAL!$E$8:$E$1007,"Entretien & Réparation",JOURNAL!$C$8:$C$1007,202612) -> 0 | G28: =SUMIFS(JOURNAL!$H$8:$H$1007,JOURNAL!$E$8:$E$1007,"Virement Banque",JOURNAL!$C$8:$C$1007,202612)+SUMIFS(JOURNAL!$H$8:$H$1007,JOURNAL!$E$8:$E$1007,"Virement Associés",JOURNAL!$C$8:$C$1007,202612) -> 0 | H28: =SUMIFS(JOURNAL!$H$8:$H$1007,JOURNAL!$D$8:$D$1007,"DEPENSE",JOURNAL!$C$8:$C$1007,202612) -> 0 | I28: =$B28-$H28 -> 0 | J28: =IFERROR($I28/$B28,0) -> 0 | K28: =IFERROR($B28/DAY(EOMONTH($A28,0)),0) -> 0
A29: TOTAL 2025 | B29: =SUM(B5:B16) -> 584577 | C29: =SUM(C5:C16) -> 234826 | D29: =IFERROR($C29/$B29,0) -> 0.40170243 | E29: n.d. | F29: n.d. | G29: n.d. | H29: n.d. | I29: n.d. | J29: n.d. | K29: =IFERROR(AVERAGE($K5:$K16),0) -> 1600.8368
A30: TOTAL 2026 | B30: =SUM(B17:B28) -> 54937 | C30: =SUM(C17:C28) -> 24529 | D30: =IFERROR($C30/$B30,0) -> 0.44649326 | E30: =SUM(E17:E28) -> 12400 | F30: =SUM(F17:F28) -> 13785 | G30: =SUM(G17:G28) -> 0 | H30: =SUM(H17:H28) -> 50714 | I30: =SUM(I17:I28) -> 4223 | J30: =IFERROR($I30/$B30,0) -> 0.076869869 | K30: =IFERROR(AVERAGE($K17:$K28),0) -> 147.68011
A32: « n.d. » = non disponible : l’ancien classeur (feuille Feuil1) ne suivait en 2025 que la recette et les achats de marchandise, pas les salaires ni les charges fixes. La colonne « % ACHATS » reste donc la seule comparable entre 2025 et 2026. À partir de 2026, toutes les colonnes se remplissent seules dès que vous saisissez dans le JOURNAL.

Sheet CHARGES FIXES
B1: CHARGES FIXES ET ABONNEMENTS
B2: Budget mensuel (à vous de le fixer) comparé au réalisé calculé depuis le JOURNAL.
H3: ABONNEMENTS ANNUELS
B4: POSTE | C4: BUDGET / MOIS | D4: RÉALISÉ DU MOIS | E4: ÉCART | F4: ÉTAT | H4: ABONNEMENT | I4: MONTANT
B5: Loyer | C5: 17000 | D5: =SUMIFS(JOURNAL!$H$8:$H$1007,JOURNAL!$E$8:$E$1007,"Loyer",JOURNAL!$C$8:$C$1007,PARAMETRES!$C$14) -> 5000 | E5: =$C5-$D5 -> 12000 | F5: =IF(N($C5)=0,IF(N($D5)=0,"—","HORS BUDGET"),IF($D5<=$C5,"OK","DEPASSE")) -> OK | H5: BEIN SPORT | I5: 600
B6: Eau + Électricité | C6: 4000 | D6: =SUMIFS(JOURNAL!$H$8:$H$1007,JOURNAL!$E$8:$E$1007,"Eau & Électricité",JOURNAL!$C$8:$C$1007,PARAMETRES!$C$14) -> 3785 | E6: =$C6-$D6 -> 215 | F6: =IF(N($C6)=0,IF(N($D6)=0,"—","HORS BUDGET"),IF($D6<=$C6,"OK","DEPASSE")) -> OK | H6: REMO | I6: 3800
B7: Internet & télécom | C7: 500 | D7: =SUMIFS(JOURNAL!$H$8:$H$1007,JOURNAL!$E$8:$E$1007,"Internet & Télécom",JOURNAL!$C$8:$C$1007,PARAMETRES!$C$14) -> 0 | E7: =$C7-$D7 -> 500 | F7: =IF(N($C7)=0,IF(N($D7)=0,"—","HORS BUDGET"),IF($D7<=$C7,"OK","DEPASSE")) -> OK | H7: NEGOZAR | I7: 700
B8: Achats marchandise (café, eau, épicerie) | C8: 20500 | D8: =SUMIFS(JOURNAL!$H$8:$H$1007,JOURNAL!$E$8:$E$1007,"Boissons",JOURNAL!$C$8:$C$1007,PARAMETRES!$C$14)+SUMIFS(JOURNAL!$H$8:$H$1007,JOURNAL!$E$8:$E$1007,"Café & Torréfaction",JOURNAL!$C$8:$C$1007,PARAMETRES!$C$14)+SUMIFS(JOURNAL!$H$8:$H$1007,JOURNAL!$E$8:$E$1007,"Boulangerie",JOURNAL!$C$8:$C$1007,PARAMETRES!$C$14)+SUMIFS(JOURNAL!$H$8:$H$1007,JOURNAL!$E$8:$E$1007,"Fruits & Légumes",JOURNAL!$C$8:$C$1007,PARAMETRES!$C$14)+SUMIFS(JOURNAL!$H$8:$H$1007,JOURNAL!$E$8:$E$1007,"Épicerie & Divers",JOURNAL!$C$8:$C$1007,PARAMETRES!$C$14) -> 20479 | E8: =$C8-$D8 -> 21 | F8: =IF(N($C8)=0,IF(N($D8)=0,"—","HORS BUDGET"),IF($D8<=$C8,"OK","DEPASSE")) -> OK | H8: BEIN CAN 2025 | I8: 500
B9: Nettoyage (NADAFA) | C9: 4500 | D9: =SUMIFS(JOURNAL!$H$8:$H$1007,JOURNAL!$E$8:$E$1007,"Nettoyage",JOURNAL!$C$8:$C$1007,PARAMETRES!$C$14) -> 4050 | E9: =$C9-$D9 -> 450 | F9: =IF(N($C9)=0,IF(N($D9)=0,"—","HORS BUDGET"),IF($D9<=$C9,"OK","DEPASSE")) -> OK | H9: CAFE DUBOIS | I9: 135
B10: Salaires du personnel | C10: 17000 | D10: =SUMIFS(JOURNAL!$H$8:$H$1007,JOURNAL!$E$8:$E$1007,"Salaires",JOURNAL!$C$8:$C$1007,PARAMETRES!$C$14) -> 12400 | E10: =$C10-$D10 -> 4600 | F10: =IF(N($C10)=0,IF(N($D10)=0,"—","HORS BUDGET"),IF($D10<=$C10,"OK","DEPASSE")) -> OK | H10: TOTAL | I10: =SUM($I$5:$I$9) -> 5735
B11: Taxes et impôts | C11: 0 | D11: =SUMIFS(JOURNAL!$H$8:$H$1007,JOURNAL!$E$8:$E$1007,"Taxes & Impôts",JOURNAL!$C$8:$C$1007,PARAMETRES!$C$14) -> 5000 | E11: =$C11-$D11 -> -5000 | F11: =IF(N($C11)=0,IF(N($D11)=0,"—","HORS BUDGET"),IF($D11<=$C11,"OK","DEPASSE")) -> HORS BUDGET
B12: Abonnements (Bein, Remo…) | C12: 0 | D12: =SUMIFS(JOURNAL!$H$8:$H$1007,JOURNAL!$E$8:$E$1007,"Abonnements",JOURNAL!$C$8:$C$1007,PARAMETRES!$C$14) -> 0 | E12: =$C12-$D12 -> 0 | F12: =IF(N($C12)=0,IF(N($D12)=0,"—","HORS BUDGET"),IF($D12<=$C12,"OK","DEPASSE")) -> — | H12: Repris de la feuille Feuil2 de l’ancien classeur (total 5 735 DH).
B13: Entretien et réparation | C13: 0 | D13: =SUMIFS(JOURNAL!$H$8:$H$1007,JOURNAL!$E$8:$E$1007,"Entretien & Réparation",JOURNAL!$C$8:$C$1007,PARAMETRES!$C$14) -> 0 | E13: =$C13-$D13 -> 0 | F13: =IF(N($C13)=0,IF(N($D13)=0,"—","HORS BUDGET"),IF($D13<=$C13,"OK","DEPASSE")) -> —
B14: TOTAL CHARGES DU MOIS | C14: =SUM(C5:C13) -> 63500 | D14: =SUM(D5:D13) -> 50714 | E14: =SUM(E5:E13) -> 12786
B16: Recette minimum / jour pour couvrir les charges (seuil) | C16: =IFERROR($C14/30,0) -> 2116.6667
B17: Dépenses réelles par jour, ce mois | C17: =IFERROR($D14/COUNTIF('RECAP JOUR'!$F$6:$F$36,">0"),0) -> 1878.2963
B18: Recette moyenne par jour, ce mois | C18: =IFERROR(SUMIFS(JOURNAL!$H$8:$H$1007,JOURNAL!$D$8:$D$1007,"RECETTE",JOURNAL!$C$8:$C$1007,PARAMETRES!$C$14)/COUNTIF('RECAP JOUR'!$F$6:$F$36,">0"),0) -> 2034.7037
B19: Marge de sécurité par jour | C19: =IFERROR(SUMIFS(JOURNAL!$H$8:$H$1007,JOURNAL!$D$8:$D$1007,"RECETTE",JOURNAL!$C$8:$C$1007,PARAMETRES!$C$14)/COUNTIF('RECAP JOUR'!$F$6:$F$36,">0"),0)-IFERROR($C14/30,0) -> -81.962963
B22: Les budgets en jaune viennent de la feuille CHARGE de l’ancien classeur (colonne « CHARGE FIXE » de droite, total 75 000 DH par mois, associés compris). Ajustez-les librement : le réalisé, lui, est toujours calculé depuis le JOURNAL sur le mois choisi dans PARAMÈTRES.

Sheet SALAIRES
B1: PERSONNEL ET SALAIRES
B2: Salaire convenu par personne, contre ce qui a réellement été versé ce mois-ci.
B4: EMPLOYÉ | C4: POSTE | D4: SALAIRE CONVENU | E4: VERSÉ CE MOIS | F4: RESTE À VERSER | G4: NB VERSEMENTS | H4: PART
B5: ALI | C5: Barman | D5: 2400 | E5: =SUMIFS(JOURNAL!$H$8:$H$1007,JOURNAL!$F$8:$F$1007,$B5,JOURNAL!$E$8:$E$1007,"Salaires",JOURNAL!$C$8:$C$1007,PARAMETRES!$C$14) -> 0 | F5: =IF($D5="","—",$D5-$E5) -> 2400 | G5: =COUNTIFS(JOURNAL!$F$8:$F$1007,$B5,JOURNAL!$E$8:$E$1007,"Salaires",JOURNAL!$C$8:$C$1007,PARAMETRES!$C$14) -> 0 | H5: =IF(N($D5)=0,"—",$E5/$D5) -> 0
B6: LATIFA 1 | C6: Service | D6: 1800 | E6: =SUMIFS(JOURNAL!$H$8:$H$1007,JOURNAL!$F$8:$F$1007,$B6,JOURNAL!$E$8:$E$1007,"Salaires",JOURNAL!$C$8:$C$1007,PARAMETRES!$C$14) -> 0 | F6: =IF($D6="","—",$D6-$E6) -> 1800 | G6: =COUNTIFS(JOURNAL!$F$8:$F$1007,$B6,JOURNAL!$E$8:$E$1007,"Salaires",JOURNAL!$C$8:$C$1007,PARAMETRES!$C$14) -> 0 | H6: =IF(N($D6)=0,"—",$E6/$D6) -> 0
B7: LATIFA 2 | C7: Service | D7: 1800 | E7: =SUMIFS(JOURNAL!$H$8:$H$1007,JOURNAL!$F$8:$F$1007,$B7,JOURNAL!$E$8:$E$1007,"Salaires",JOURNAL!$C$8:$C$1007,PARAMETRES!$C$14) -> 0 | F7: =IF($D7="","—",$D7-$E7) -> 1800 | G7: =COUNTIFS(JOURNAL!$F$8:$F$1007,$B7,JOURNAL!$E$8:$E$1007,"Salaires",JOURNAL!$C$8:$C$1007,PARAMETRES!$C$14) -> 0 | H7: =IF(N($D7)=0,"—",$E7/$D7) -> 0
B8: ABDELLAH | C8: Serveur | D8: 2000 | E8: =SUMIFS(JOURNAL!$H$8:$H$1007,JOURNAL!$F$8:$F$1007,$B8,JOURNAL!$E$8:$E$1007,"Salaires",JOURNAL!$C$8:$C$1007,PARAMETRES!$C$14) -> 2400 | F8: =IF($D8="","—",$D8-$E8) -> -400 | G8: =COUNTIFS(JOURNAL!$F$8:$F$1007,$B8,JOURNAL!$E$8:$E$1007,"Salaires",JOURNAL!$C$8:$C$1007,PARAMETRES!$C$14) -> 4 | H8: =IF(N($D8)=0,"—",$E8/$D8) -> 1.2
B9: HAMZA | C9: Serveur | D9: 2000 | E9: =SUMIFS(JOURNAL!$H$8:$H$1007,JOURNAL!$F$8:$F$1007,$B9,JOURNAL!$E$8:$E$1007,"Salaires",JOURNAL!$C$8:$C$1007,PARAMETRES!$C$14) -> 0 | F9: =IF($D9="","—",$D9-$E9) -> 2000 | G9: =COUNTIFS(JOURNAL!$F$8:$F$1007,$B9,JOURNAL!$E$8:$E$1007,"Salaires",JOURNAL!$C$8:$C$1007,PARAMETRES!$C$14) -> 0 | H9: =IF(N($D9)=0,"—",$E9/$D9) -> 0
B10: AHMED | C10: Gérant | D10: 7000 | E10: =SUMIFS(JOURNAL!$H$8:$H$1007,JOURNAL!$F$8:$F$1007,$B10,JOURNAL!$E$8:$E$1007,"Salaires",JOURNAL!$C$8:$C$1007,PARAMETRES!$C$14) -> 0 | F10: =IF($D10="","—",$D10-$E10) -> 7000 | G10: =COUNTIFS(JOURNAL!$F$8:$F$1007,$B10,JOURNAL!$E$8:$E$1007,"Salaires",JOURNAL!$C$8:$C$1007,PARAMETRES!$C$14) -> 0 | H10: =IF(N($D10)=0,"—",$E10/$D10) -> 0
B11: BAR MEN | C11: Barman | E11: =SUMIFS(JOURNAL!$H$8:$H$1007,JOURNAL!$F$8:$F$1007,$B11,JOURNAL!$E$8:$E$1007,"Salaires",JOURNAL!$C$8:$C$1007,PARAMETRES!$C$14) -> 2400 | F11: =IF($D11="","—",$D11-$E11) -> — | G11: =COUNTIFS(JOURNAL!$F$8:$F$1007,$B11,JOURNAL!$E$8:$E$1007,"Salaires",JOURNAL!$C$8:$C$1007,PARAMETRES!$C$14) -> 4 | H11: =IF(N($D11)=0,"—",$E11/$D11) -> —
B12: BAR MEN ALI | C12: Barman | E12: =SUMIFS(JOURNAL!$H$8:$H$1007,JOURNAL!$F$8:$F$1007,$B12,JOURNAL!$E$8:$E$1007,"Salaires",JOURNAL!$C$8:$C$1007,PARAMETRES!$C$14) -> 4000 | F12: =IF($D12="","—",$D12-$E12) -> — | G12: =COUNTIFS(JOURNAL!$F$8:$F$1007,$B12,JOURNAL!$E$8:$E$1007,"Salaires",JOURNAL!$C$8:$C$1007,PARAMETRES!$C$14) -> 5 | H12: =IF(N($D12)=0,"—",$E12/$D12) -> —
B13: FATIMA | C13: Service | E13: =SUMIFS(JOURNAL!$H$8:$H$1007,JOURNAL!$F$8:$F$1007,$B13,JOURNAL!$E$8:$E$1007,"Salaires",JOURNAL!$C$8:$C$1007,PARAMETRES!$C$14) -> 1600 | F13: =IF($D13="","—",$D13-$E13) -> — | G13: =COUNTIFS(JOURNAL!$F$8:$F$1007,$B13,JOURNAL!$E$8:$E$1007,"Salaires",JOURNAL!$C$8:$C$1007,PARAMETRES!$C$14) -> 4 | H13: =IF(N($D13)=0,"—",$E13/$D13) -> —
B14: LAHCEN | C14: Service | E14: =SUMIFS(JOURNAL!$H$8:$H$1007,JOURNAL!$F$8:$F$1007,$B14,JOURNAL!$E$8:$E$1007,"Salaires",JOURNAL!$C$8:$C$1007,PARAMETRES!$C$14) -> 2000 | F14: =IF($D14="","—",$D14-$E14) -> — | G14: =COUNTIFS(JOURNAL!$F$8:$F$1007,$B14,JOURNAL!$E$8:$E$1007,"Salaires",JOURNAL!$C$8:$C$1007,PARAMETRES!$C$14) -> 4 | H14: =IF(N($D14)=0,"—",$E14/$D14) -> —
B15: MARWA | C15: Service | E15: =SUMIFS(JOURNAL!$H$8:$H$1007,JOURNAL!$F$8:$F$1007,$B15,JOURNAL!$E$8:$E$1007,"Salaires",JOURNAL!$C$8:$C$1007,PARAMETRES!$C$14) -> 0 | F15: =IF($D15="","—",$D15-$E15) -> — | G15: =COUNTIFS(JOURNAL!$F$8:$F$1007,$B15,JOURNAL!$E$8:$E$1007,"Salaires",JOURNAL!$C$8:$C$1007,PARAMETRES!$C$14) -> 0 | H15: =IF(N($D15)=0,"—",$E15/$D15) -> —
B16: TOTAL PERSONNEL | D16: =SUM(D5:D15) -> 17000 | E16: =SUM(E5:E15) -> 12400 | F16: =$D16-$E16 -> 4600 | G16: =SUM(G5:G15) -> 21 | H16: =IFERROR($E16/$D16,0) -> 0.72941176
B18: Total versé en salaires ce mois (toutes personnes) | E18: =SUMIFS(JOURNAL!$H$8:$H$1007,JOURNAL!$E$8:$E$1007,"Salaires",JOURNAL!$C$8:$C$1007,PARAMETRES!$C$14) -> 12400
B19: Dont versements à des personnes hors de la liste ci-dessus | E19: =$E18-$E16 -> 0
B21: Salaires convenus repris de la feuille CHARGE de l’ancien classeur. La colonne « VERSÉ CE MOIS » additionne toutes les lignes du JOURNAL de catégorie « Salaires » au nom de la personne : elle inclut donc les avances. Les noms BAR MEN, BAR MEN ALI, FATIMA, LAHCEN et MARWA ont été ajoutés au tableau car ils apparaissent dans les paiements d’août 2026, mais leur salaire convenu ne figurait nulle part dans l’ancien classeur : renseignez-le dans les cellules jaunes vides, sans quoi le « reste à verser » ne peut pas être calculé et s’affiche « — ».

Sheet MARGES PRODUITS
B1: MARGES PAR PRODUIT
B2: Ce que rapporte chaque boisson. Remplissez le coût matière en jaune pour obtenir la marge réelle.
B4: PRODUIT | C4: PRIX DE VENTE | D4: COÛT MATIÈRE | E4: MARGE UNITAIRE | F4: MARGE % | G4: QTÉ / JOUR | H4: CA / JOUR | I4: MARGE / JOUR
B5: Café Noir | C5: 13 | E5: =IF($D5="","—",$C5-$D5) -> — | F5: =IF($D5="","—",IFERROR(($C5-$D5)/$C5,0)) -> — | G5: 100 | H5: =$C5*$G5 -> 1300 | I5: =IF($D5="","—",($C5-$D5)*$G5) -> —
B6: Café Crème | C6: 13 | E6: =IF($D6="","—",$C6-$D6) -> — | F6: =IF($D6="","—",IFERROR(($C6-$D6)/$C6,0)) -> — | G6: 20 | H6: =$C6*$G6 -> 260 | I6: =IF($D6="","—",($C6-$D6)*$G6) -> —
B7: Petit Déjeuner | C7: 20 | E7: =IF($D7="","—",$C7-$D7) -> — | F7: =IF($D7="","—",IFERROR(($C7-$D7)/$C7,0)) -> — | G7: 8 | H7: =$C7*$G7 -> 160 | I7: =IF($D7="","—",($C7-$D7)*$G7) -> —
B8: Thé | C8: 12 | E8: =IF($D8="","—",$C8-$D8) -> — | F8: =IF($D8="","—",IFERROR(($C8-$D8)/$C8,0)) -> — | G8: 10 | H8: =$C8*$G8 -> 120 | I8: =IF($D8="","—",($C8-$D8)*$G8) -> —
B9: TOTAL | F9: =IF(COUNT($D$5:$D$8)=0,"—",IFERROR($I9/$H9,0)) -> — | G9: =SUM(G5:G8) -> 138 | H9: =SUM(H5:H8) -> 1840 | I9: =IF(COUNT($D$5:$D$8)=0,"—",SUMIF($D$5:$D$8,"<>",$I$5:$I$8)) -> —
B11: CA théorique du mois (30 jours) | C11: =$H9*30 -> 55200
B12: Recette réellement encaissée ce mois | C12: =SUMIFS(JOURNAL!$H$8:$H$1007,JOURNAL!$D$8:$D$1007,"RECETTE",JOURNAL!$C$8:$C$1007,PARAMETRES!$C$14) -> 54937
B13: Écart théorique / réel | C13: =$C12-$C11 -> -263
B15: Prix de vente et quantités journalières repris de la feuille CHARGE de l’ancien classeur (café noir 13 DH × 100, crème 13 DH × 20, petit-déjeuner 20 DH × 8, thé 12 DH × 10). La colonne COÛT MATIÈRE est volontairement vide : renseignez-la (prix de revient d’une tasse) pour que la marge se calcule ; tant qu’elle est vide, les colonnes de marge affichent « — ».

Sheet ASSOCIÉS
B1: COMPTES DES ASSOCIÉS
B2: Apports de chaque associé : achat du fonds de commerce et aménagement du café. Historique repris de la feuille DEPENSE_CAFE.
B4: SYNTHÈSE
C5: POSTE | D5: HAMID | E5: MOUHSSINE | F5: TOTAL
C6: Achat du fonds de commerce (Saadaoui) | D6: =$D$91 -> 397738 | E6: =$E$91 -> 404700 | F6: =$D6+$E6 -> 802438
C7: Aménagement du Café Victor Hugo | D7: =$D$139 -> 148042 | E7: =$E$139 -> 298821 | F7: =$D7+$E7 -> 446863
C8: TOTAL APPORTÉ PAR ASSOCIÉ | D8: =SUM($D$6:$D$7) -> 545780 | E8: =SUM($E$6:$E$7) -> 703521 | F8: =$D8+$E8 -> 1249301
C9: Part théorique due sur le fonds (795 000 DH / 2) | D9: 397500 | E9: 397500 | F9: =$D9+$E9 -> 795000
C10: Reste à payer sur le fonds (+ = doit, - = a trop versé) | D10: =$D9-$D6 -> -238 | E10: =$E9-$E6 -> -7200 | F10: =$D10+$E10 -> -7438
C11: Écart sur le fonds seul (Hamid - Mouhssine) | F11: =$D6-$E6 -> -6962
C12: Écart sur l’aménagement seul (Hamid - Mouhssine) | F12: =$D7-$E7 -> -150779
C13: ÉCART TOTAL ENTRE LES DEUX ASSOCIÉS | F13: =$D8-$E8 -> -157741
B15: Lecture : un « reste à payer » négatif signifie que l’associé a versé plus que sa part. Au dernier pointage de l’ancien classeur, Hamid avait versé 238 DH de trop et Mouhssine 7 200 DH de trop sur l’achat du fonds, soit 6 962 DH d’écart entre eux. Sur l’aménagement du café, Mouhssine a apporté 150 779 DH de plus que Hamid, ce qui porte l’écart cumulé à 157 741 DH.
B28: DÉTAIL — ACHAT DU FONDS DE COMMERCE (SAADAOUI, 795 000 DH)
B29: N° | C29: OPÉRATION | D29: HAMID | E29: MOUHSSINE | F29: TOTAL
B30: 1 | C30: ESPECE(HAMID:10000/MH:90000) HOURI | D30: 10000 | E30: 90000 | F30: =N($D30)+N($E30) -> 100000
B31: 2 | C31: ESPECE | D31: 20000 | F31: =N($D31)+N($E31) -> 20000
B32: 3 | C32: ESPECE | D32: 30000 | F32: =N($D32)+N($E32) -> 30000
B33: 4 | C33: VIREMENT 1 | E33: 20000 | F33: =N($D33)+N($E33) -> 20000
B34: 5 | C34: VIREMENT 2 | E34: 20000 | F34: =N($D34)+N($E34) -> 20000
B35: 6 | C35: cheque ahmed | E35: 20000 | F35: =N($D35)+N($E35) -> 20000
B36: 7 | C36: LOYER NOVEMBRE | E36: 15000 | F36: =N($D36)+N($E36) -> 15000
B37: 8 | C37: NOTAIRE | F37: =N($D37)+N($E37) -> 0
B38: 9 | C38: CHEQUE | E38: 60000 | F38: =N($D38)+N($E38) -> 60000
B39: 10 | C39: cheque ahmed | E39: 20000 | F39: =N($D39)+N($E39) -> 20000
B40: 11 | C40: ESPECE RADIATION SAADAOUI | F40: =N($D40)+N($E40) -> 0
B41: 12 | C41: ESPECE LE 15/06/24 | D41: 25000 | F41: =N($D41)+N($E41) -> 25000
B42: 13 | C42: EAU+ELEC | D42: 7800 | F42: =N($D42)+N($E42) -> 7800
B43: 14 | C43: ESPECE berkane | E43: 60000 | F43: =N($D43)+N($E43) -> 60000
B44: 15 | C44: CHEQUE HAMID(VIREMENT MOUHSSINE) | E44: 20000 | F44: =N($D44)+N($E44) -> 20000
B45: 16 | C45: 43TAXE LE 22/02/2024-DEBIT BOISSON | E45: 3500 | F45: =N($D45)+N($E45) -> 3500
B46: 17 | C46: TAPISSIER CHAISE | E46: 11700 | F46: =N($D46)+N($E46) -> 11700
B47: 18 | C47: credit Paradise à12/07/2024 | D47: 150000 | F47: =N($D47)+N($E47) -> 150000
B48: 19 | C48: ESPECE LE 15/07/24-ateliersaadaoui- | D48: 5000 | F48: =N($D48)+N($E48) -> 5000
B49: 20 | C49: ESPECE LE (BL PARADISE zenata) | D49: 10500 | F49: =N($D49)+N($E49) -> 10500
B50: 21 | C50: ESPECE LE 19/07/24-(BL PARADISE zenata) | D50: 110 | F50: =N($D50)+N($E50) -> 110
B51: 22 | C51: ESPECE LE 22/07/24-ateliersaadaoui- | D51: 30000 | F51: =N($D51)+N($E51) -> 30000
B52: 23 | C52: ESPECE LE 31/07/24-(BL PARADISE zenata) | D52: 681 | F52: =N($D52)+N($E52) -> 681
B53: 24 | C53: ESPECE LE 03/08/24-LABORATOIRE 17- | D53: 10000 | F53: =N($D53)+N($E53) -> 10000
B54: 25 | C54: ESPECE LE 08/08/24-(BL PARADISE zenata) | D54: 531 | F54: =N($D54)+N($E54) -> 531
B55: 26 | C55: ESPECE LE 29/08/24-(BL PARADISE zenata) | D55: 3400 | F55: =N($D55)+N($E55) -> 3400
B56: 27 | C56: ESPECE LE 30/08/24-(BL PARADISE zenata) | D56: 5926 | F56: =N($D56)+N($E56) -> 5926
B57: 28 | C57: ESPECE LE 05/09/24-(BL PARADISE zenata) | D57: 367 | F57: =N($D57)+N($E57) -> 367
B58: 29 | C58: ESPECE LE 06/09/24-(BL PARADISE zenata) | D58: 225 | F58: =N($D58)+N($E58) -> 225
... B69: 40 | C69: ESPECE LE 21/11/24-(BL PARADISE ) | D69: 263 | F69: =N($D69)+N($E69) -> 263
B70: 41 | C70: ESPECE 30/11/2024 | E70: 10000 | F70: =N($D70)+N($E70) -> 10000
B71: 42 | C71: ESPECE LE 04/12/24-(BL PARADISE ) | D71: 767 | F71: =N($D71)+N($E71) -> 767
B72: 43 | C72: ESPECE LE 05/12/24-(BL PARADISE ) | D72: 190 | F72: =N($D72)+N($E72) -> 190
B73: 44 | C73: ESPECE LE 10/12/24-(BL PARADISE ) | D73: 70 | F73: =N($D73)+N($E73) -> 70
B74: 45 | C74: ESPECE LE 24/12/24-(BL PARADISE ) | D74: 240 | F74: =N($D74)+N($E74) -> 240
B75: 46 | C75: ESPECE LE 30/12/24-(BL PARADISE ) | D75: 571 | F75: =N($D75)+N($E75) -> 571
B76: 47 | C76: ESPECE LE 31/12/24-(BL PARADISE ) | D76: 4820 | F76: =N($D76)+N($E76) -> 4820
B77: 48 | C77: ESPECE LE 03/01/25 | E77: 20000 | F77: =N($D77)+N($E77) -> 20000
B78: 49 | C78: ESPECE LE 11/01/25-(BL PARADISE ) | D78: 192 | F78: =N($D78)+N($E78) -> 192
B79: 50 | C79: ESPECE LE 15/01/25-(BL PARADISE ) | D79: 3790 | F79: =N($D79)+N($E79) -> 3790
B80: 51 | C80: ESPECE LE 16/01/25-(BL PARADISE ) | D80: 200 | F80: =N($D80)+N($E80) -> 200
B81: 52 | D81: 673 | F81: =N($D81)+N($E81) -> 673
B82: 53 | C82: ESPECE LE 17/01/25-(BL PARADISE ) | D82: 1020 | F82: =N($D82)+N($E82) -> 1020
B83: 54 | C83: ESPECE LE 28/01/25-(BL PARADISE ) | D83: 500 | F83: =N($D83)+N($E83) -> 500
B84: 55 | C84: ESPECE STATION AFRIQUIA 17 | D84: 5000 | F84: =N($D84)+N($E84) -> 5000
B85: 56 | C85: ESPECE LE 04/02/25-(BL PARADISE ) | D85: 490 | F85: =N($D85)+N($E85) -> 490
B86: 57 | C86: ESPECE LE 19/02/25-(BL PARADISE ) | D86: 1848 | F86: =N($D86)+N($E86) -> 1848
B87: 58 | C87: ESPECE LE 07/03/25-(BL PARADISE ) | D87: 100 | F87: =N($D87)+N($E87) -> 100
B88: 59 | C88: ESPECE LE 13/03/25 atelier 17 | E88: 14500 | F88: =N($D88)+N($E88) -> 14500
B89: 60 | C89: ESPECE LE 07/04/25-(BL PARADISE ) | F89: =N($D89)+N($E89) -> 0
B90: 61 | C90: ESPECE LE 18/04/25-(CAFE VICTOR ) | E90: 20000 | F90: =N($D90)+N($E90) -> 20000
C91: TOTAL | D91: =SUM(D30:D90) -> 397738 | E91: =SUM(E30:E90) -> 404700 | F91: =SUM(F30:F90) -> 802438
B93: DÉTAIL — AMÉNAGEMENT ET ÉQUIPEMENT DU CAFÉ VICTOR HUGO
B94: N° | C94: OPÉRATION | D94: HAMID | E94: MOUHSSINE | F94: TOTAL
B95: 1 | C95: ACHAT STOCK | D95: 7000 | F95: =N($D95)+N($E95) -> 7000
B96: 2 | C96: SARF | D96: 2000 | F96: =N($D96)+N($E96) -> 2000
B97: 3 | C97: FRIGO ASTORIA | D97: 9000 | F97: =N($D97)+N($E97) -> 9000
B98: 4 | C98: MACHINE ASTORIA | D98: 31000 | E98: 20000 | F98: =N($D98)+N($E98) -> 51000
B99: 5 | C99: CONGELATEUR ASWAK SALAM | D99: 2500 | F99: =N($D99)+N($E99) -> 2500
B100: 6 | C100: BEIN SPORT | E100: 3200 | F100: =N($D100)+N($E100) -> 3200
B101: 7 | C101: Travaux Eléctricien | E101: 3000 | F101: =N($D101)+N($E101) -> 3000
B102: 8 | C102: ACHAT TV | E102: 30500 | F102: =N($D102)+N($E102) -> 30500
B103: 9 | C103: HABILLAGE MURE 12000 DH | D103: 12000 | F103: =N($D103)+N($E103) -> 12000
B104: 10 | C104: HABILLAGE DERIERE COMPTOIRE 2300DH | D104: 2300 | F104: =N($D104)+N($E104) -> 2300
B105: 11 | C105: SUPPORT INOX | D105: 1400 | F105: =N($D105)+N($E105) -> 1400
B106: 12 | C106: Travaux Eléctricien SUPPLIMENT | D106: 850 | F106: =N($D106)+N($E106) -> 850
B107: 13 | C107: LOYER decembre | E107: 12750 | F107: =N($D107)+N($E107) -> 12750
B108: 14 | C108: HABILLAGE COMPTOIRE+ENSIGNE | D108: 5000 | E108: 34800 | F108: =N($D108)+N($E108) -> 39800
B109: 15 | C109: achat 7 pots | D109: 2100 | F109: =N($D109)+N($E109) -> 2100
B110: 16 | C110: NOTAIRE | D110: 1000 | E110: 2000 | F110: =N($D110)+N($E110) -> 3000
B111: 17 | C111: achat diffuseur | E111: 5300 | F111: =N($D111)+N($E111) -> 5300
B112: 18 | C112: POSE ALUMINIUM | D112: 13300 | F112: =N($D112)+N($E112) -> 13300
B113: 19 | C113: achat SANITAIRE | D113: 142 | E113: 1000 | F113: =N($D113)+N($E113) -> 1142
B114: 20 | C114: REMPLISSAGE 7 pots | E114: 6000 | F114: =N($D114)+N($E114) -> 6000
B115: 21 | C115: BACHE TERRASSE+CASQUETTE | E115: 32000 | F115: =N($D115)+N($E115) -> 32000
B116: 22 | C116: ACHAT PEINTREUR | D116: 450 | F116: =N($D116)+N($E116) -> 450
B117: 23 | C117: MAIN D ŒUVRE PEINTRE | E117: 2500 | F117: =N($D117)+N($E117) -> 2500
B118: 24 | C118: MACHINE ASTORIA(CHEQUE) | D118: 20000 | F118: =N($D118)+N($E118) -> 20000
B119: 25 | C119: PAYE AUTORISATION CAFE | E119: 1000 | F119: =N($D119)+N($E119) -> 1000
B120: 26 | C120: AVANCE SALAIRE AHMED | E120: 5000 | F120: =N($D120)+N($E120) -> 5000
B121: 27 | C121: REPARATION TV 85 | E121: 10000 | F121: =N($D121)+N($E121) -> 10000
B122: 28 | C122: MACHINE GLACE | D122: 11000 | F122: =N($D122)+N($E122) -> 11000
B123: 29 | C123: LAMPE BRICOMA | E123: 1571 | F123: =N($D123)+N($E123) -> 1571
B124: 30 | C124: CHARGEUR PARFUM | E124: 1200 | F124: =N($D124)+N($E124) -> 1200
B125: 31 | C125: telephone+tablette | E125: 3300 | F125: =N($D125)+N($E125) -> 3300
...

Sheet PARAMETRES
B1: PARAMÈTRES DU COMMERCE
B2: Réglages et listes de référence. Modifiez uniquement les cellules sur fond jaune.
B4: IDENTITÉ | E4: CATÉGORIES RECETTE | G4: CATÉGORIES DEPENSE | I4: FOURNISSEURS / BÉNÉFICIAIRES | L4: MODES DE PAIEMENT | N4: TOUTES CATÉGORIES
B5: Nom du commerce | C5: CAFE VICTOR HUGO | E5: Vente Caisse | G5: Boissons | I5: ABDELLAH | J5: Salaires | L5: Espèce | N5: Vente Caisse
B6: Ville | C6: Mohammedia | E6: Glovo Espèce | G6: Café & Torréfaction | I6: AHMED | J6: Salaires | L6: Carte | N6: Glovo Espèce
B7: Pays | C7: Maroc | E7: Glovo Carte | G7: Boulangerie | I7: AIN SAISS | J7: Boissons | L7: Virement | N7: Glovo Carte
B8: Gérant | C8: AHMED | E8: Terrasse | G8: Fruits & Légumes | I8: AVANCE LOYER | J8: Loyer | L8: Chèque | N8: Terrasse
B9: Devise | C9: DH (MAD) | E9: Autre Recette | G9: Épicerie & Divers | I9: BANQUE | J9: Virement Banque | N9: Autre Recette
G10: Nettoyage | I10: BAR MEN | J10: Salaires | N10: Boissons
B11: PÉRIODE ANALYSÉE | G11: Salaires | I11: BAR MEN ALI | J11: Salaires | N11: Café & Torréfaction
B12: Annee | C12: 2026 | G12: Loyer | I12: BIM | J12: Épicerie & Divers | N12: Boulangerie
B13: Mois (1 a 12) | C13: 8 | G13: Eau & Électricité | I13: BOULANGERIE | J13: Boulangerie | N13: Fruits & Légumes
B14: Clé du mois | C14: =$C$12*100+$C$13 -> 202608 | G14: Internet & Télécom | I14: CAFE | J14: Café & Torréfaction | N14: Épicerie & Divers
B15: Premier jour du mois | C15: =DATE($C$12,$C$13,1) -> 46235 | G15: Taxes & Impôts | I15: CITRIN | J15: Boissons | N15: Nettoyage
B16: Nombre de jours | C16: =DAY(EOMONTH($C$15,0)) -> 31 | G16: Abonnements | I16: CLIENT | J16: Divers | N16: Salaires
G17: Entretien & Réparation | I17: COCA | J17: Boissons | N17: Loyer
B18: CAISSE | G18: Virement Banque | I18: EAU + ELECTRICITE | J18: Eau & Électricité | N18: Eau & Électricité
B19: Caisse au 1er du mois | C19: 0 | G19: Virement Associés | I19: FATIMA | J19: Salaires | N19: Internet & Télécom
B20: Objectif recette / jour | C20: 2200 | G20: Divers | I20: FRUITS | J20: Fruits & Légumes | N20: Taxes & Impôts
B21: Seuil alerte caisse | C21: 500 | I21: HAMID | J21: Virement Associés | N21: Abonnements
I22: HAMZA | J22: Divers | N22: Entretien & Réparation
I23: INTERNET | J23: Internet & Télécom | N23: Virement Banque
B24: LÉGENDE DES COULEURS | I24: KHLII | J24: Épicerie & Divers | N24: Virement Associés
C25: Cellule à remplir par vous | I25: LAHCEN | J25: Salaires | N25: Divers
C26: Cellule calculée automatiquement — ne pas modifier | I26: LATIFA 1 | J26: Divers
C27: Résultat positif / objectif atteint | I27: LATIFA 2 | J27: Divers
C28: Résultat négatif / alerte | I28: LOYER | J28: Loyer
I29: MARWA | J29: Salaires
I30: MECAFE | J30: Café & Torréfaction
I31: MOUHSSINE | J31: Virement Associés
I32: NADAFA | J32: Nettoyage
I33: ORANGE | J33: Fruits & Légumes
I34: OULMES | J34: Boissons
I35: TAXE NADAFA 2026 | J35: Taxes & Impôts

Sheet ARCHIVE
B1: ARCHIVE
B2: Données de l’ancien classeur conservées pour mémoire, sans lien avec l’exploitation du café.
B4: COMMANDE TEST CHINE — environ 25 000 DH | E4: COMMANDE TEST TURQUIE — environ 30 000 DH
B5: DÉSIGNATION | C5: QUANTITÉ | E5: DÉSIGNATION | F5: QUANTITÉ
B6: raccord droit 16 mm | C6: 10000 | E6: filtre disque 2" | F6: 100
B7: te 16 mm | C7: 5000 | E7: filtre tamis 2" | F7: 100
B8: coude 16 mm | C8: 5000 | E8: manometre | F8: 200
B9: bouchon 16 mm | C9: 5000 | E9: regulateur | F9: 200
B10: depart 16 mm | C10: 2000 | E10: vanne | F10: 200
B11: vannette 16 mm | C11: 2000 | E11: raccords PE 32/40/50 mm | F11: 500
B14: Repris tel quel de la feuille « PVC » de l’ancien classeur. Il s’agit d’une commande de matériel d’irrigation, sans rapport avec le café : elle est conservée ici pour ne rien perdre.
