Workbook

Sheet TABLEAU DE BORD
F2: TABLEAU DE BORD DU MOIS
B4: =UPPER(TEXT('RÉCAP DU JOURNAL'!$J$4,"[$-40C]MMMM YYYY"))&" · PARADISE ALUMINIUM SARL · Négoce et transformation d'aluminium · Casablanca"
B6: ACHATS FOURNISSEURS | E6: ENCAISSEMENTS | H6: TOTAL DES SORTIES | K6: RÉSULTAT DE TRÉSORERIE
B7: ='RÉCAP DU JOURNAL'!$D$43 | E7: ='RÉCAP DU JOURNAL'!$M$43 | H7: ='RÉCAP DU JOURNAL'!$L$43 | K7: ='RÉCAP DU JOURNAL'!$M$43-'RÉCAP DU JOURNAL'!$L$43
B8: net à payer, cumul du mois | E8: clients et apports | H8: achats réglés + charges | K8: encaissements – sorties
B10: RESTE DÛ AUX FOURNISSEURS | E10: CHARGES FIXES ET SALAIRES | H10: CAISSE TOTALE EN FIN DE MOIS | K10: ÉCART DE CAISSE CUMULÉ
B11: ='RÉCAP DU JOURNAL'!$H$43 | E11: ='RÉCAP DU JOURNAL'!$I$43+'RÉCAP DU JOURNAL'!$J$43 | H11: ='RÉCAP DU JOURNAL'!$P$43 | K11: ='RÉCAP DU JOURNAL'!$Q$43
B12: crédit fournisseur du mois | E12: le coût de la structure | H12: PARADISE + ZENATA | K12: compté – théorique
B14: LE MOIS EN QUATRE GRAPHIQUES
B54: Tout se calcule à partir des feuilles 01 à 31 : il n'y a rien à saisir sur cette page. Les réglages du mois (année, mois, soldes d'ouverture) sont en haut de RÉCAP DU JOURNAL.

Sheet RÉCAP DU JOURNAL
A1: RÉCAP DU JOURNAL
A2: PARADISE ALUMINIUM SARL · Casablanca · le mois entier, jour par jour — tout vient des feuilles 01 à 31
B3: RÉGLAGES DU MOIS — les seules cases à remplir sur cette feuille
B4: Année | E4: 2026 | G4: Premier jour du mois | J4: =DATE($E$4,$E$5,1) | L4: Changez l'année, le mois et les trois soldes d'ouverture : tout le classeur suit — dates, jours de la semaine, feuilles neutralisées pour un mois de moins de 31 jours.
B5: Mois (1 à 12) | E5: 10 | G5: Nombre de jours du mois | J5: =DAY(EOMONTH($J$4,0))
B6: Caisse PARADISE au 1er du mois | E6: 3000 | G6: Objectif d'achats du mois | J6: 0 | L6: Le report de caisse est le seul lien entre deux mois : le solde du soir du dernier jour devient le solde d'ouverture du mois suivant.
B7: Caisse ZENATA au 1er du mois | E7: 18188 | G7: Objectif d'encaissements du mois | J7: 0
B8: Autre caisse au 1er du mois | E8: -58814.02 | G8: Le mois, en clair | J8: =$J$4
B10: LE MOIS JOUR PAR JOUR
B11: DATE | C11: JOUR | D11: ACHATS FOURNIS- SEURS | E11: DONT ESPÈCE | F11: DONT CHÈQUE | G11: DONT EFFET | H11: RESTE DÛ FOURNISSEURS | I11: CHARGES FIXES | J11: SALAIRES | K11: DÉPENSES & TRAVAUX | L11: TOTAL DES SORTIES | M11: ENCAISSE- MENTS | N11: CAISSE PARADISE | O11: CAISSE ZENATA | P11: CAISSE TOTALE | Q11: ÉCART | S11: Achats fournisseurs | T11: Caisse totale | U11: Encaissements | V11: Sorties
B12: =IF(1>$J$5,"",DATE($E$4,$E$5,1)) | C12: =IF($B12="","",$B12) | D12: =IF($B12="","",'01'!D28) | E12: =IF($B12="","",'01'!E28) | F12: =IF($B12="","",'01'!F28) | G12: =IF($B12="","",'01'!H28) | H12: =IF($B12="","",'01'!J28) | I12: =IF($B12="","",'01'!M20) | J12: =IF($B12="","",'01'!M30) | K12: =IF($B12="","",'01'!M44) | L12: =IF($B12="","",'01'!M56) | M12: =IF($B12="","",'01'!J42) | N12: =IF($B12="","",'01'!D56) | O12: =IF($B12="","",'01'!G56) | P12: =IF($B12="","",'01'!J50) | Q12: =IF($B12="","",'01'!J51) | S12: =IF($B12="",NA(),$D12) | T12: =IF($B12="",NA(),$P12) | U12: =IF($B12="",NA(),$M12) | V12: =IF($B12="",NA(),$L12)
B13: =IF(2>$J$5,"",DATE($E$4,$E$5,2)) | C13: =IF($B13="","",$B13) | D13: =IF($B13="","",'02'!D28) | E13: =IF($B13="","",'02'!E28) | F13: =IF($B13="","",'02'!F28) | G13: =IF($B13="","",'02'!H28) | H13: =IF($B13="","",'02'!J28) | I13: =IF($B13="","",'02'!M20) | J13: =IF($B13="","",'02'!M30) | K13: =IF($B13="","",'02'!M44) | L13: =IF($B13="","",'02'!M56) | M13: =IF($B13="","",'02'!J42) | N13: =IF($B13="","",'02'!D56) | O13: =IF($B13="","",'02'!G56) | P13: =IF($B13="","",'02'!J50) | Q13: =IF($B13="","",'02'!J51) | S13: =IF($B13="",NA(),$D13) | T13: =IF($B13="",T12,$P13) | U13: =IF($B13="",NA(),$M13) | V13: =IF($B13="",NA(),$L13)
B14: =IF(3>$J$5,"",DATE($E$4,$E$5,3)) | C14: =IF($B14="","",$B14) | D14: =IF($B14="","",'03'!D28) | E14: =IF($B14="","",'03'!E28) | F14: =IF($B14="","",'03'!F28) | G14: =IF($B14="","",'03'!H28) | H14: =IF($B14="","",'03'!J28) | I14: =IF($B14="","",'03'!M20) | J14: =IF($B14="","",'03'!M30) | K14: =IF($B14="","",'03'!M44) | L14: =IF($B14="","",'03'!M56) | M14: =IF($B14="","",'03'!J42) | N14: =IF($B14="","",'03'!D56) | O14: =IF($B14="","",'03'!G56) | P14: =IF($B14="","",'03'!J50) | Q14: =IF($B14="","",'03'!J51) | S14: =IF($B14="",NA(),$D14) | T14: =IF($B14="",T13,$P14) | U14: =IF($B14="",NA(),$M14) | V14: =IF($B14="",NA(),$L14)
B15: =IF(4>$J$5,"",DATE($E$4,$E$5,4)) | C15: =IF($B15="","",$B15) | D15: =IF($B15="","",'04'!D28) | E15: =IF($B15="","",'04'!E28) | F15: =IF($B15="","",'04'!F28) | G15: =IF($B15="","",'04'!H28) | H15: =IF($B15="","",'04'!J28) | I15: =IF($B15="","",'04'!M20) | J15: =IF($B15="","",'04'!M30) | K15: =IF($B15="","",'04'!M44) | L15: =IF($B15="","",'04'!M56) | M15: =IF($B15="","",'04'!J42) | N15: =IF($B15="","",'04'!D56) | O15: =IF($B15="","",'04'!G56) | P15: =IF($B15="","",'04'!J50) | Q15: =IF($B15="","",'04'!J51) | S15: =IF($B15="",NA(),$D15) | T15: =IF($B15="",T14,$P15) | U15: =IF($B15="",NA(),$M15) | V15: =IF($B15="",NA(),$L15)
B16: =IF(5>$J$5,"",DATE($E$4,$E$5,5)) | C16: =IF($B16="","",$B16) | D16: =IF($B16="","",'05'!D28) | E16: =IF($B16="","",'05'!E28) | F16: =IF($B16="","",'05'!F28) | G16: =IF($B16="","",'05'!H28) | H16: =IF($B16="","",'05'!J28) | I16: =IF($B16="","",'05'!M20) | J16: =IF($B16="","",'05'!M30) | K16: =IF($B16="","",'05'!M44) | L16: =IF($B16="","",'05'!M56) | M16: =IF($B16="","",'05'!J42) | N16: =IF($B16="","",'05'!D56) | O16: =IF($B16="","",'05'!G56) | P16: =IF($B16="","",'05'!J50) | Q16: =IF($B16="","",'05'!J51) | S16: =IF($B16="",NA(),$D16) | T16: =IF($B16="",T15,$P16) | U16: =IF($B16="",NA(),$M16) | V16: =IF($B16="",NA(),$L16)
B17: =IF(6>$J$5,"",DATE($E$4,$E$5,6)) | C17: =IF($B17="","",$B17) | D17: =IF($B17="","",'06'!D28) | E17: =IF($B17="","",'06'!E28) | F17: =IF($B17="","",'06'!F28) | G17: =IF($B17="","",'06'!H28) | H17: =IF($B17="","",'06'!J28) | I17: =IF($B17="","",'06'!M20) | J17: =IF($B17="","",'06'!M30) | K17: =IF($B17="","",'06'!M44) | L17: =IF($B17="","",'06'!M56) | M17: =IF($B17="","",'06'!J42) | N17: =IF($B17="","",'06'!D56) | O17: =IF($B17="","",'06'!G56) | P17: =IF($B17="","",'06'!J50) | Q17: =IF($B17="","",'06'!J51) | S17: =IF($B17="",NA(),$D17) | T17: =IF($B17="",T16,$P17) | U17: =IF($B17="",NA(),$M17) | V17: =IF($B17="",NA(),$L17)
B18: =IF(7>$J$5,"",DATE($E$4,$E$5,7)) | C18: =IF($B18="","",$B18) | D18: =IF($B18="","",'07'!D28) | E18: =IF($B18="","",'07'!E28) | F18: =IF($B18="","",'07'!F28) | G18: =IF($B18="","",'07'!H28) | H18: =IF($B18="","",'07'!J28) | I18: =IF($B18="","",'07'!M20) | J18: =IF($B18="","",'07'!M30) | K18: =IF($B18="","",'07'!M44) | L18: =IF($B18="","",'07'!M56) | M18: =IF($B18="","",'07'!J42) | N18: =IF($B18="","",'07'!D56) | O18: =IF($B18="","",'07'!G56) | P18: =IF($B18="","",'07'!J50) | Q18: =IF($B18="","",'07'!J51) | S18: =IF($B18="",NA(),$D18) | T18: =IF($B18="",T17,$P18) | U18: =IF($B18="",NA(),$M18) | V18: =IF($B18="",NA(),$L18)
B19: =IF(8>$J$5,"",DATE($E$4,$E$5,8)) | C19: =IF($B19="","",$B19) | D19: =IF($B19="","",'08'!D28) | E19: =IF($B19="","",'08'!E28) | F19: =IF($B19="","",'08'!F28) | G19: =IF($B19="","",'08'!H28) | H19: =IF($B19="","",'08'!J28) | I19: =IF($B19="","",'08'!M20) | J19: =IF($B19="","",'08'!M30) | K19: =IF($B19="","",'08'!M44) | L19: =IF($B19="","",'08'!M56) | M19: =IF($B19="","",'08'!J42) | N19: =IF($B19="","",'08'!D56) | O19: =IF($B19="","",'08'!G56) | P19: =IF($B19="","",'08'!J50) | Q19: =IF($B19="","",'08'!J51) | S19: =IF($B19="",NA(),$D19) | T19: =IF($B19="",T18,$P19) | U19: =IF($B19="",NA(),$M19) | V19: =IF($B19="",NA(),$L19)
B20: =IF(9>$J$5,"",DATE($E$4,$E$5,9)) | C20: =IF($B20="","",$B20) | D20: =IF($B20="","",'09'!D28) | E20: =IF($B20="","",'09'!E28) | F20: =IF($B20="","",'09'!F28) | G20: =IF($B20="","",'09'!H28) | H20: =IF($B20="","",'09'!J28) | I20: =IF($B20="","",'09'!M20) | J20: =IF($B20="","",'09'!M30) | K20: =IF($B20="","",'09'!M44) | L20: =IF($B20="","",'09'!M56) | M20: =IF($B20="","",'09'!J42) | N20: =IF($B20="","",'09'!D56) | O20: =IF($B20="","",'09'!G56) | P20: =IF($B20="","",'09'!J50) | Q20: =IF($B20="","",'09'!J51) | S20: =IF($B20="",NA(),$D20) | T20: =IF($B20="",T19,$P20) | U20: =IF($B20="",NA(),$M20) | V20: =IF($B20="",NA(),$L20)
B21: =IF(10>$J$5,"",DATE($E$4,$E$5,10)) | C21: =IF($B21="","",$B21) | D21: =IF($B21="","",'10'!D28) | E21: =IF($B21="","",'10'!E28) | F21: =IF($B21="","",'10'!F28) | G21: =IF($B21="","",'10'!H28) | H21: =IF($B21="","",'10'!J28) | I21: =IF($B21="","",'10'!M20) | J21: =IF($B21="","",'10'!M30) | K21: =IF($B21="","",'10'!M44) | L21: =IF($B21="","",'10'!M56) | M21: =IF($B21="","",'10'!J42) | N21: =IF($B21="","",'10'!D56) | O21: =IF($B21="","",'10'!G56) | P21: =IF($B21="","",'10'!J50) | Q21: =IF($B21="","",'10'!J51) | S21: =IF($B21="",NA(),$D21) | T21: =IF($B21="",T20,$P21) | U21: =IF($B21="",NA(),$M21) | V21: =IF($B21="",NA(),$L21)
B22: =IF(11>$J$5,"",DATE($E$4,$E$5,11)) | C22: =IF($B22="","",$B22) | D22: =IF($B22="","",'11'!D28) | E22: =IF($B22="","",'11'!E28) | F22: =IF($B22="","",'11'!F28) | G22: =IF($B22="","",'11'!H28) | H22: =IF($B22="","",'11'!J28) | I22: =IF($B22="","",'11'!M20) | J22: =IF($B22="","",'11'!M30) | K22: =IF($B22="","",'11'!M44) | L22: =IF($B22="","",'11'!M56) | M22: =IF($B22="","",'11'!J42) | N22: =IF($B22="","",'11'!D56) | O22: =IF($B22="","",'11'!G56) | P22: =IF($B22="","",'11'!J50) | Q22: =IF($B22="","",'11'!J51) | S22: =IF($B22="",NA(),$D22) | T22: =IF($B22="",T21,$P22) | U22: =IF($B22="",NA(),$M22) | V22: =IF($B22="",NA(),$L22)
B23: =IF(12>$J$5,"",DATE($E$4,$E$5,12)) | C23: =IF($B23="","",$B23) | D23: =IF($B23="","",'12'!D28) | E23: =IF($B23="","",'12'!E28) | F23: =IF($B23="","",'12'!F28) | G23: =IF($B23="","",'12'!H28) | H23: =IF($B23="","",'12'!J28) | I23: =IF($B23="","",'12'!M20) | J23: =IF($B23="","",'12'!M30) | K23: =IF($B23="","",'12'!M44) | L23: =IF($B23="","",'12'!M56) | M23: =IF($B23="","",'12'!J42) | N23: =IF($B23="","",'12'!D56) | O23: =IF($B23="","",'12'!G56) | P23: =IF($B23="","",'12'!J50) | Q23: =IF($B23="","",'12'!J51) | S23: =IF($B23="",NA(),$D23) | T23: =IF($B23="",T22,$P23) | U23: =IF($B23="",NA(),$M23) | V23: =IF($B23="",NA(),$L23)
B24: =IF(13>$J$5,"",DATE($E$4,$E$5,13)) | C24: =IF($B24="","",$B24) | D24: =IF($B24="","",'13'!D28) | E24: =IF($B24="","",'13'!E28) | F24: =IF($B24="","",'13'!F28) | G24: =IF($B24="","",'13'!H28) | H24: =IF($B24="","",'13'!J28) | I24: =IF($B24="","",'13'!M20) | J24: =IF($B24="","",'13'!M30) | K24: =IF($B24="","",'13'!M44) | L24: =IF($B24="","",'13'!M56) | M24: =IF($B24="","",'13'!J42) | N24: =IF($B24="","",'13'!D56) | O24: =IF($B24="","",'13'!G56) | P24: =IF($B24="","",'13'!J50) | Q24: =IF($B24="","",'13'!J51) | S24: =IF($B24="",NA(),$D24) | T24: =IF($B24="",T23,$P24) | U24: =IF($B24="",NA(),$M24) | V24: =IF($B24="",NA(),$L24)
B25: =IF(14>$J$5,"",DATE($E$4,$E$5,14)) | C25: =IF($B25="","",$B25) | D25: =IF($B25="","",'14'!D28) | E25: =IF($B25="","",'14'!E28) | F25: =IF($B25="","",'14'!F28) | G25: =IF($B25="","",'14'!H28) | H25: =IF($B25="","",'14'!J28) | I25: =IF($B25="","",'14'!M20) | J25: =IF($B25="","",'14'!M30) | K25: =IF($B25="","",'14'!M44) | L25: =IF($B25="","",'14'!M56) | M25: =IF($B25="","",'14'!J42) | N25: =IF($B25="","",'14'!D56) | O25: =IF($B25="","",'14'!G56) | P25: =IF($B25="","",'14'!J50) | Q25: =IF($B25="","",'14'!J51) | S25: =IF($B25="",NA(),$D25) | T25: =IF($B25="",T24,$P25) | U25: =IF($B25="",NA(),$M25) | V25: =IF($B25="",NA(),$L25)
B26: =IF(15>$J$5,"",DATE($E$4,$E$5,15)) | C26: =IF($B26="","",$B26) | D26: =IF($B26="","",'15'!D28) | E26: =IF($B26="","",'15'!E28) | F26: =IF($B26="","",'15'!F28) | G26: =IF($B26="","",'15'!H28) | H26: =IF($B26="","",'15'!J28) | I26: =IF($B26="","",'15'!M20) | J26: =IF($B26="","",'15'!M30) | K26: =IF($B26="","",'15'!M44) | L26: =IF($B26="","",'15'!M56) | M26: =IF($B26="","",'15'!J42) | N26: =IF($B26="","",'15'!D56) | O26: =IF($B26="","",'15'!G56) | P26: =IF($B26="","",'15'!J50) | Q26: =IF($B26="","",'15'!J51) | S26: =IF($B26="",NA(),$D26) | T26: =IF($B26="",T25,$P26) | U26: =IF($B26="",NA(),$M26) | V26: =IF($B26="",NA(),$L26)
B27: =IF(16>$J$5,"",DATE($E$4,$E$5,16)) | C27: =IF($B27="","",$B27) | D27: =IF($B27="","",'16'!D28) | E27: =IF($B27="","",'16'!E28) | F27: =IF($B27="","",'16'!F28) | G27: =IF($B27="","",'16'!H28) | H27: =IF($B27="","",'16'!J28) | I27: =IF($B27="","",'16'!M20) | J27: =IF($B27="","",'16'!M30) | K27: =IF($B27="","",'16'!M44) | L27: =IF($B27="","",'16'!M56) | M27: =IF($B27="","",'16'!J42) | N27: =IF($B27="","",'16'!D56) | O27: =IF($B27="","",'16'!G56) | P27: =IF($B27="","",'16'!J50) | Q27: =IF($B27="","",'16'!J51) | S27: =IF($B27="",NA(),$D27) | T27: =IF($B27="",T26,$P27) | U27: =IF($B27="",NA(),$M27) | V27: =IF($B27="",NA(),$L27)
B28: =IF(17>$J$5,"",DATE($E$4,$E$5,17)) | C28: =IF($B28="","",$B28) | D28: =IF($B28="","",'17'!D28) | E28: =IF($B28="","",'17'!E28) | F28: =IF($B28="","",'17'!F28) | G28: =IF($B28="","",'17'!H28) | H28: =IF($B28="","",'17'!J28) | I28: =IF($B28="","",'17'!M20) | J28: =IF($B28="","",'17'!M30) | K28: =IF($B28="","",'17'!M44) | L28: =IF($B28="","",'17'!M56) | M28: =IF($B28="","",'17'!J42) | N28: =IF($B28="","",'17'!D56) | O28: =IF($B28="","",'17'!G56) | P28: =IF($B28="","",'17'!J50) | Q28: =IF($B28="","",'17'!J51) | S28: =IF($B28="",NA(),$D28) | T28: =IF($B28="",T27,$P28) | U28: =IF($B28="",NA(),$M28) | V28: =IF($B28="",NA(),$L28)
B29: =IF(18>$J$5,"",DATE($E$4,$E$5,18)) | C29: =IF($B29="","",$B29) | D29: =IF($B29="","",'18'!D28) | E29: =IF($B29="","",'18'!E28) | F29: =IF($B29="","",'18'!F28) | G29: =IF($B29="","",'18'!H28) | H29: =IF($B29="","",'18'!J28) | I29: =IF($B29="","",'18'!M20) | J29: =IF($B29="","",'18'!M30) | K29: =IF($B29="","",'18'!M44) | L29: =IF($B29="","",'18'!M56) | M29: =IF($B29="","",'18'!J42) | N29: =IF($B29="","",'18'!D56) | O29: =IF($B29="","",'18'!G56) | P29: =IF($B29="","",'18'!J50) | Q29: =IF($B29="","",'18'!J51) | S29: =IF($B29="",NA(),$D29) | T29: =IF($B29="",T28,$P29) | U29: =IF($B29="",NA(),$M29) | V29: =IF($B29="",NA(),$L29)
B30: =IF(19>$J$5,"",DATE($E$4,$E$5,19)) | C30: =IF($B30="","",$B30) | D30: =IF($B30="","",'19'!D28) | E30: =IF($B30="","",'19'!E28) | F30: =IF($B30="","",'19'!F28) | G30: =IF($B30="","",'19'!H28) | H30: =IF($B30="","",'19'!J28) | I30: =IF($B30="","",'19'!M20) | J30: =IF($B30="","",'19'!M30) | K30: =IF($B30="","",'19'!M44) | L30: =IF($B30="","",'19'!M56) | M30: =IF($B30="","",'19'!J42) | N30: =IF($B30="","",'19'!D56) | O30: =IF($B30="","",'19'!G56) | P30: =IF($B30="","",'19'!J50) | Q30: =IF($B30="","",'19'!J51) | S30: =IF($B30="",NA(),$D30) | T30: =IF($B30="",T29,$P30) | U30: =IF($B30="",NA(),$M30) | V30: =IF($B30="",NA(),$L30)
B31: =IF(20>$J$5,"",DATE($E$4,$E$5,20)) | C31: =IF($B31="","",$B31) | D31: =IF($B31="","",'20'!D28) | E31: =IF($B31="","",'20'!E28) | F31: =IF($B31="","",'20'!F28) | G31: =IF($B31="","",'20'!H28) | H31: =IF($B31="","",'20'!J28) | I31: =IF($B31="","",'20'!M20) | J31: =IF($B31="","",'20'!M30) | K31: =IF($B31="","",'20'!M44) | L31: =IF($B31="","",'20'!M56) | M31: =IF($B31="","",'20'!J42) | N31: =IF($B31="","",'20'!D56) | O31: =IF($B31="","",'20'!G56) | P31: =IF($B31="","",'20'!J50) | Q31: =IF($B31="","",'20'!J51) | S31: =IF($B31="",NA(),$D31) | T31: =IF($B31="",T30,$P31) | U31: =IF($B31="",NA(),$M31) | V31: =IF($B31="",NA(),$L31)
B32: =IF(21>$J$5,"",DATE($E$4,$E$5,21)) | C32: =IF($B32="","",$B32) | D32: =IF($B32="","",'21'!D28) | E32: =IF($B32="","",'21'!E28) | F32: =IF($B32="","",'21'!F28) | G32: =IF($B32="","",'21'!H28) | H32: =IF($B32="","",'21'!J28) | I32: =IF($B32="","",'21'!M20) | J32: =IF($B32="","",'21'!M30) | K32: =IF($B32="","",'21'!M44) | L32: =IF($B32="","",'21'!M56) | M32: =IF($B32="","",'21'!J42) | N32: =IF($B32="","",'21'!D56) | O32: =IF($B32="","",'21'!G56) | P32: =IF($B32="","",'21'!J50) | Q32: =IF($B32="","",'21'!J51) | S32: =IF($B32="",NA(),$D32) | T32: =IF($B32="",T31,$P32) | U32: =IF($B32="",NA(),$M32) | V32: =IF($B32="",NA(),$L32)
B33: =IF(22>$J$5,"",DATE($E$4,$E$5,22)) | C33: =IF($B33="","",$B33) | D33: =IF($B33="","",'22'!D28) | E33: =IF($B33="","",'22'!E28) | F33: =IF($B33="","",'22'!F28) | G33: =IF($B33="","",'22'!H28) | H33: =IF($B33="","",'22'!J28) | I33: =IF($B33="","",'22'!M20) | J33: =IF($B33="","",'22'!M30) | K33: =IF($B33="","",'22'!M44) | L33: =IF($B33="","",'22'!M56) | M33: =IF($B33="","",'22'!J42) | N33: =IF($B33="","",'22'!D56) | O33: =IF($B33="","",'22'!G56) | P33: =IF($B33="","",'22'!J50) | Q33: =IF($B33="","",'22'!J51) | S33: =IF($B33="",NA(),$D33) | T33: =IF($B33="",T32,$P33) | U33: =IF($B33="",NA(),$M33) | V33: =IF($B33="",NA(),$L33)
B34: =IF(23>$J$5,"",DATE($E$4,$E$5,23)) | C34: =IF($B34="","",$B34) | D34: =IF($B34="","",'23'!D28) | E34: =IF($B34="","",'23'!E28) | F34: =IF($B34="","",'23'!F28) | G34: =IF($B34="","",'23'!H28) | H34: =IF($B34="","",'23'!J28) | I34: =IF($B34="","",'23'!M20) | J34: =IF($B34="","",'23'!M30) | K34: =IF($B34="","",'23'!M44) | L34: =IF($B34="","",'23'!M56) | M34: =IF($B34="","",'23'!J42) | N34: =IF($B34="","",'23'!D56) | O34: =IF($B34="","",'23'!G56) | P34: =IF($B34="","",'23'!J50) | Q34: =IF($B34="","",'23'!J51) | S34: =IF($B34="",NA(),$D34) | T34: =IF($B34="",T33,$P34) | U34: =IF($B34="",NA(),$M34) | V34: =IF($B34="",NA(),$L34)
B35: =IF(24>$J$5,"",DATE($E$4,$E$5,24)) | C35: =IF($B35="","",$B35) | D35: =IF($B35="","",'24'!D28) | E35: =IF($B35="","",'24'!E28) | F35: =IF($B35="","",'24'!F28) | G35: =IF($B35="","",'24'!H28) | H35: =IF($B35="","",'24'!J28) | I35: =IF($B35="","",'24'!M20) | J35: =IF($B35="","",'24'!M30) | K35: =IF($B35="","",'24'!M44) | L35: =IF($B35="","",'24'!M56) | M35: =IF($B35="","",'24'!J42) | N35: =IF($B35="","",'24'!D56) | O35: =IF($B35="","",'24'!G56) | P35: =IF($B35="","",'24'!J50) | Q35: =IF($B35="","",'24'!J51) | S35: =IF($B35="",NA(),$D35) | T35: =IF($B35="",T34,$P35) | U35: =IF($B35="",NA(),$M35) | V35: =IF($B35="",NA(),$L35)
B36: =IF(25>$J$5,"",DATE($E$4,$E$5,25)) | C36: =IF($B36="","",$B36) | D36: =IF($B36="","",'25'!D28) | E36: =IF($B36="","",'25'!E28) | F36: =IF($B36="","",'25'!F28) | G36: =IF($B36="","",'25'!H28) | H36: =IF($B36="","",'25'!J28) | I36: =IF($B36="","",'25'!M20) | J36: =IF($B36="","",'25'!M30) | K36: =IF($B36="","",'25'!M44) | L36: =IF($B36="","",'25'!M56) | M36: =IF($B36="","",'25'!J42) | N36: =IF($B36="","",'25'!D56) | O36: =IF($B36="","",'25'!G56) | P36: =IF($B36="","",'25'!J50) | Q36: =IF($B36="","",'25'!J51) | S36: =IF($B36="",NA(),$D36) | T36: =IF($B36="",T35,$P36) | U36: =IF($B36="",NA(),$M36) | V36: =IF($B36="",NA(),$L36)
B37: =IF(26>$J$5,"",DATE($E$4,$E$5,26)) | C37: =IF($B37="","",$B37) | D37: =IF($B37="","",'26'!D28) | E37: =IF($B37="","",'26'!E28) | F37: =IF($B37="","",'26'!F28) | G37: =IF($B37="","",'26'!H28) | H37: =IF($B37="","",'26'!J28) | I37: =IF($B37="","",'26'!M20) | J37: =IF($B37="","",'26'!M30) | K37: =IF($B37="","",'26'!M44) | L37: =IF($B37="","",'26'!M56) | M37: =IF($B37="","",'26'!J42) | N37: =IF($B37="","",'26'!D56) | O37: =IF($B37="","",'26'!G56) | P37: =IF($B37="","",'26'!J50) | Q37: =IF($B37="","",'26'!J51) | S37: =IF($B37="",NA(),$D37) | T37: =IF($B37="",T36,$P37) | U37: =IF($B37="",NA(),$M37) | V37: =IF($B37="",NA(),$L37)
B38: =IF(27>$J$5,"",DATE($E$4,$E$5,27)) | C38: =IF($B38="","",$B38) | D38: =IF($B38="","",'27'!D28) | E38: =IF($B38="","",'27'!E28) | F38: =IF($B38="","",'27'!F28) | G38: =IF($B38="","",'27'!H28) | H38: =IF($B38="","",'27'!J28) | I38: =IF($B38="","",'27'!M20) | J38: =IF($B38="","",'27'!M30) | K38: =IF($B38="","",'27'!M44) | L38: =IF($B38="","",'27'!M56) | M38: =IF($B38="","",'27'!J42) | N38: =IF($B38="","",'27'!D56) | O38: =IF($B38="","",'27'!G56) | P38: =IF($B38="","",'27'!J50) | Q38: =IF($B38="","",'27'!J51) | S38: =IF($B38="",NA(),$D38) | T38: =IF($B38="",T37,$P38) | U38: =IF($B38="",NA(),$M38) | V38: =IF($B38="",NA(),$L38)
B39: =IF(28>$J$5,"",DATE($E$4,$E$5,28)) | C39: =IF($B39="","",$B39) | D39: =IF($B39="","",'28'!D28) | E39: =IF($B39="","",'28'!E28) | F39: =IF($B39="","",'28'!F28) | G39: =IF($B39="","",'28'!H28) | H39: =IF($B39="","",'28'!J28) | I39: =IF($B39="","",'28'!M20) | J39: =IF($B39="","",'28'!M30) | K39: =IF($B39="","",'28'!M44) | L39: =IF($B39="","",'28'!M56) | M39: =IF($B39="","",'28'!J42) | N39: =IF($B39="","",'28'!D56) | O39: =IF($B39="","",'28'!G56) | P39: =IF($B39="","",'28'!J50) | Q39: =IF($B39="","",'28'!J51) | S39: =IF($B39="",NA(),$D39) | T39: =IF($B39="",T38,$P39) | U39: =IF($B39="",NA(),$M39) | V39: =IF($B39="",NA(),$L39)
B40: =IF(29>$J$5,"",DATE($E$4,$E$5,29)) | C40: =IF($B40="","",$B40) | D40: =IF($B40="","",'29'!D28) | E40: =IF($B40="","",'29'!E28) | F40: =IF($B40="","",'29'!F28) | G40: =IF($B40="","",'29'!H28) | H40: =IF($B40="","",'29'!J28) | I40: =IF($B40="","",'29'!M20) | J40: =IF($B40="","",'29'!M30) | K40: =IF($B40="","",'29'!M44) | L40: =IF($B40="","",'29'!M56) | M40: =IF($B40="","",'29'!J42) | N40: =IF($B40="","",'29'!D56) | O40: =IF($B40="","",'29'!G56) | P40: =IF($B40="","",'29'!J50) | Q40: =IF($B40="","",'29'!J51) | S40: =IF($B40="",NA(),$D40) | T40: =IF($B40="",T39,$P40) | U40: =IF($B40="",NA(),$M40) | V40: =IF($B40="",NA(),$L40)
B41: =IF(30>$J$5,"",DATE($E$4,$E$5,30)) | C41: =IF($B41="","",$B41) | D41: =IF($B41="","",'30'!D28) | E41: =IF($B41="","",'30'!E28) | F41: =IF($B41="","",'30'!F28) | G41: =IF($B41="","",'30'!H28) | H41: =IF($B41="","",'30'!J28) | I41: =IF($B41="","",'30'!M20) | J41: =IF($B41="","",'30'!M30) | K41: =IF($B41="","",'30'!M44) | L41: =IF($B41="","",'30'!M56) | M41: =IF($B41="","",'30'!J42) | N41: =IF($B41="","",'30'!D56) | O41: =IF($B41="","",'30'!G56) | P41: =IF($B41="","",'30'!J50) | Q41: =IF($B41="","",'30'!J51) | S41: =IF($B41="",NA(),$D41) | T41: =IF($B41="",T40,$P41) | U41: =IF($B41="",NA(),$M41) | V41: =IF($B41="",NA(),$L41)
B42: =IF(31>$J$5,"",DATE($E$4,$E$5,31)) | C42: =IF($B42="","",$B42) | D42: =IF($B42="","",'31'!D28) | E42: =IF($B42="","",'31'!E28) | F42: =IF($B42="","",'31'!F28) | G42: =IF($B42="","",'31'!H28) | H42: =IF($B42="","",'31'!J28) | I42: =IF($B42="","",'31'!M20) | J42: =IF($B42="","",'31'!M30) | K42: =IF($B42="","",'31'!M44) | L42: =IF($B42="","",'31'!M56) | M42: =IF($B42="","",'31'!J42) | N42: =IF($B42="","",'31'!D56) | O42: =IF($B42="","",'31'!G56) | P42: =IF($B42="","",'31'!J50) | Q42: =IF($B42="","",'31'!J51) | S42: =IF($B42="",NA(),$D42) | T42: =IF($B42="",T41,$P42) | U42: =IF($B42="",NA(),$M42) | V42: =IF($B42="",NA(),$L42)
B43: TOTAL DU MOIS | D43: =SUM(D12:D42) | E43: =SUM(E12:E42) | F43: =SUM(F12:F42) | G43: =SUM(G12:G42) | H43: =SUM(H12:H42) | I43: =SUM(I12:I42) | J43: =SUM(J12:J42) | K43: =SUM(K12:K42) | ... M43: =SUM(M12:M42) | N43: =INDEX(N12:N42,$J$5) | O43: =INDEX(O12:O42,$J$5) | P43: =INDEX(P12:P42,$J$5) | Q43: =SUM(Q12:Q42)
B44: Les trois colonnes de caisse ne s'additionnent pas : la ligne de total reprend le solde du dernier jour du mois, c'est-à-dire ce qui reste réellement en caisse.

Sheet 01
A1: JOURNAL DE CAISSE DU JOUR | H1: PARADISE ALUMINIUM SARL · Casablanca
A2: =IF(1>'RÉCAP DU JOURNAL'!$J$5,"— ce jour n'existe pas dans le mois —",DATE('RÉCAP DU JOURNAL'!$E$4,'RÉCAP DU JOURNAL'!$E$5,1)) | H2: Feuille 01 · aluminium, accessoires et vitrage
A4: À REMPLIR ▸ les achats fournisseurs du jour, les charges, les salaires, les dépenses, les encaissements, puis les espèces comptées le soir dans chaque caisse. Cases jaunes = à vous ; cases blanches = calculées.
B6: ACHATS FOURNISSEURS DU JOUR | L6: CHARGES FIXES DU JOUR
B7: BL N° | C7: FOURNISSEUR | D7: NET À PAYER | E7: ESPÈCE | F7: CHÈQUE | G7: N° DU CHÈQUE | H7: EFFET | I7: N° DE L'EFFET | J7: RESTE À PAYER | L7: POSTE DE CHARGE | M7: MONTANT
J8: =IF(C8="","",D8-E8-F8-H8) | L8: LOYER DU LOCAL
J9: =IF(C9="","",D9-E9-F9-H9) | L9: EAU + ÉLECTRICITÉ
J10: =IF(C10="","",D10-E10-F10-H10) | L10: TÉLÉPHONE & INTERNET
J11: =IF(C11="","",D11-E11-F11-H11) | L11: CNSS
J12: =IF(C12="","",D12-E12-F12-H12) | L12: TVA & IMPÔTS
J13: =IF(C13="","",D13-E13-F13-H13) | L13: ASSURANCES
J14: =IF(C14="","",D14-E14-F14-H14) | L14: COMPTABLE & HONORAIRES
J15: =IF(C15="","",D15-E15-F15-H15) | L15: CARBURANT & VÉHICULE
J16: =IF(C16="","",D16-E16-F16-H16) | L16: TRANSPORT & LIVRAISON
J17: =IF(C17="","",D17-E17-F17-H17) | L17: ENTRETIEN & RÉPARATION
J18: =IF(C18="","",D18-E18-F18-H18) | L18: FOURNITURES DE BUREAU
J19: =IF(C19="","",D19-E19-F19-H19) | L19: AUTRE CHARGE FIXE
J20: =IF(C20="","",D20-E20-F20-H20) | L20: TOTAL | M20: =SUM(M8:M19)
J21: =IF(C21="","",D21-E21-F21-H21)
J22: =IF(C22="","",D22-E22-F22-H22) | L22: SALAIRES ET AVANCES
J23: =IF(C23="","",D23-E23-F23-H23) | L23: PERSONNE | M23: MONTANT
J24: =IF(C24="","",D24-E24-F24-H24) | L24: HOUSSEIN
J25: =IF(C25="","",D25-E25-F25-H25) | L25: AYOUB
J26: =IF(C26="","",D26-E26-F26-H26) | L26: OUVRIER 1
J27: =IF(C27="","",D27-E27-F27-H27) | L27: OUVRIER 2
B28: TOTAL DES ACHATS DU JOUR | D28: =SUM(D8:D27) | E28: =SUM(E8:E27) | F28: =SUM(F8:F27) | H28: =SUM(H8:H27) | J28: =SUM(J8:J27) | L28: AVANCE / PRIME
L29: AUTRE SALAIRE
B30: RÈGLEMENT DES ACHATS | F30: ENCAISSEMENTS DU JOUR | L30: TOTAL | M30: =SUM(M24:M29)
B31: Réglé en espèce | D31: =E28 | F31: CLIENT / ORIGINE | H31: ESPÈCE | I31: CHÈQUE / VIREMENT | J31: TOTAL
B32: Réglé par chèque | D32: =F28 | J32: =IF(F32="","",H32+I32) | L32: DÉPENSES TRAVAUX ET DIVERS
B33: Réglé par effet | D33: =H28 | J33: =IF(F33="","",H33+I33) | L33: DÉSIGNATION | M33: MONTANT
B34: TOTAL RÉGLÉ | D34: =E28+F28+H28 | J34: =IF(F34="","",H34+I34)
B35: RESTE DÛ (crédit fournisseur) | D35: =J28 | J35: =IF(F35="","",H35+I35)
J36: =IF(F36="","",H36+I36)
B37: OBSERVATIONS DU JOUR | J37: =IF(F37="","",H37+I37)
J38: =IF(F38="","",H38+I38)
J39: =IF(F39="","",H39+I39)
J40: =IF(F40="","",H40+I40)
J41: =IF(F41="","",H41+I41)
F42: TOTAL ENCAISSÉ | H42: =SUM(H32:H41) | I42: =SUM(I32:I41) | J42: =SUM(J32:J41)
L44: TOTAL | M44: =SUM(M34:M43)
B46: LES CAISSES ET LE RÉSUMÉ DU SOIR
B47: CAISSE PARADISE | E47: CAISSE ZENATA | H47: CONTRÔLE ET AUTRE CAISSE | L47: RÉSUMÉ DU JOUR
B48: Solde de la veille | D48: ='RÉCAP DU JOURNAL'!$E$6 | E48: Solde de la veille | G48: ='RÉCAP DU JOURNAL'!$E$7 | H48: Caisse PARADISE du soir | J48: =D56 | L48: Achats fournisseurs du jour | M48: =D28
B49: + Encaissements en espèce | D49: =H42 | E49: + Encaissements du jour | H49: Caisse ZENATA du soir | J49: =G56 | L49: dont réglé en espèce | M49: =E28
B50: + Apports et entrées divers | E50: + Apports et entrées divers | H50: CAISSE TOTALE DU SOIR | J50: =D56+G56 | L50: dont réglé par chèque | M50: =F28
B51: – Achats réglés en espèce | D51: =E28 | E51: – Achats réglés en espèce | H51: Écart total constaté | J51: =D58+G58 | L51: dont réglé par effet | M51: =H28
B52: – Charges fixes du jour | D52: =M20 | E52: – Charges et frais du jour | L52: RESTE DÛ (crédit fournisseur) | M52: =J28
B53: – Salaires et avances | D53: =M30 | E53: – Salaires et avances | H53: AUTRE CAISSE — solde précédent | J53: ='RÉCAP DU JOURNAL'!$E$8 | L53: Charges fixes | M53: =M20
B54: – Dépenses travaux et divers | D54: =M44 | E54: – Dépenses travaux et divers | H54: + Entrées du jour | L54: Salaires et avances | M54: =M30
B55: – Versement banque / sorties | E55: – Versement banque / sorties | H55: – Sorties du jour | L55: Dépenses travaux et divers | M55: =M44
B56: SOLDE DU SOIR | D56: =D48+D49+D50-D51-D52-D53-D54-D55 | E56: SOLDE DU SOIR | G56: =G48+G49+G50-G51-G52-G53-G54-G55 | H56: NOUVEAU SOLDE | J56: =J53+J54-J55 | L56: TOTAL DES SORTIES DU JOUR | M56: =M49+M50+M51+M53+M54+M55
B57: Espèces réellement comptées | E57: Espèces réellement comptées | L57: Encaissements du jour | M57: =J42
B58: ÉCART (compté – théorique) | D58: =IF(D57=0,0,D57-D56) | E58: ÉCART (compté – théorique) | G58: =IF(G57=0,0,G57-G56) | L58: CAISSE TOTALE DU SOIR | M58: =D56+G56

Sheet 02
A1: JOURNAL DE CAISSE DU JOUR | H1: PARADISE ALUMINIUM SARL · Casablanca
A2: =IF(2>'RÉCAP DU JOURNAL'!$J$5,"— ce jour n'existe pas dans le mois —",DATE('RÉCAP DU JOURNAL'!$E$4,'RÉCAP DU JOURNAL'!$E$5,2)) | H2: Feuille 02 · aluminium, accessoires et vitrage
A4: À REMPLIR ▸ les achats fournisseurs du jour, les charges, les salaires, les dépenses, les encaissements, puis les espèces comptées le soir dans chaque caisse. Cases jaunes = à vous ; cases blanches = calculées.
B6: ACHATS FOURNISSEURS DU JOUR | L6: CHARGES FIXES DU JOUR
B7: BL N° | C7: FOURNISSEUR | D7: NET À PAYER | E7: ESPÈCE | F7: CHÈQUE | G7: N° DU CHÈQUE | H7: EFFET | I7: N° DE L'EFFET | J7: RESTE À PAYER | L7: POSTE DE CHARGE | M7: MONTANT
J8: =IF(C8="","",D8-E8-F8-H8) | L8: LOYER DU LOCAL
J9: =IF(C9="","",D9-E9-F9-H9) | L9: EAU + ÉLECTRICITÉ
J10: =IF(C10="","",D10-E10-F10-H10) | L10: TÉLÉPHONE & INTERNET
J11: =IF(C11="","",D11-E11-F11-H11) | L11: CNSS
J12: =IF(C12="","",D12-E12-F12-H12) | L12: TVA & IMPÔTS
J13: =IF(C13="","",D13-E13-F13-H13) | L13: ASSURANCES
J14: =IF(C14="","",D14-E14-F14-H14) | L14: COMPTABLE & HONORAIRES
J15: =IF(C15="","",D15-E15-F15-H15) | L15: CARBURANT & VÉHICULE
J16: =IF(C16="","",D16-E16-F16-H16) | L16: TRANSPORT & LIVRAISON
J17: =IF(C17="","",D17-E17-F17-H17) | L17: ENTRETIEN & RÉPARATION
J18: =IF(C18="","",D18-E18-F18-H18) | L18: FOURNITURES DE BUREAU
J19: =IF(C19="","",D19-E19-F19-H19) | L19: AUTRE CHARGE FIXE
J20: =IF(C20="","",D20-E20-F20-H20) | L20: TOTAL | M20: =SUM(M8:M19)
J21: =IF(C21="","",D21-E21-F21-H21)
J22: =IF(C22="","",D22-E22-F22-H22) | L22: SALAIRES ET AVANCES
J23: =IF(C23="","",D23-E23-F23-H23) | L23: PERSONNE | M23: MONTANT
J24: =IF(C24="","",D24-E24-F24-H24) | L24: HOUSSEIN
J25: =IF(C25="","",D25-E25-F25-H25) | L25: AYOUB
J26: =IF(C26="","",D26-E26-F26-H26) | L26: OUVRIER 1
J27: =IF(C27="","",D27-E27-F27-H27) | L27: OUVRIER 2
B28: TOTAL DES ACHATS DU JOUR | D28: =SUM(D8:D27) | E28: =SUM(E8:E27) | F28: =SUM(F8:F27) | H28: =SUM(H8:H27) | J28: =SUM(J8:J27) | L28: AVANCE / PRIME
L29: AUTRE SALAIRE
B30: RÈGLEMENT DES ACHATS | F30: ENCAISSEMENTS DU JOUR | L30: TOTAL | M30: =SUM(M24:M29)
B31: Réglé en espèce | D31: =E28 | F31: CLIENT / ORIGINE | H31: ESPÈCE | I31: CHÈQUE / VIREMENT | J31: TOTAL
B32: Réglé par chèque | D32: =F28 | J32: =IF(F32="","",H32+I32) | L32: DÉPENSES TRAVAUX ET DIVERS
B33: Réglé par effet | D33: =H28 | J33: =IF(F33="","",H33+I33) | L33: DÉSIGNATION | M33: MONTANT
B34: TOTAL RÉGLÉ | D34: =E28+F28+H28 | J34: =IF(F34="","",H34+I34)
B35: RESTE DÛ (crédit fournisseur) | D35: =J28 | J35: =IF(F35="","",H35+I35)
J36: =IF(F36="","",H36+I36)
B37: OBSERVATIONS DU JOUR | J37: =IF(F37="","",H37+I37)
J38: =IF(F38="","",H38+I38)
J39: =IF(F39="","",H39+I39)
J40: =IF(F40="","",H40+I40)
J41: =IF(F41="","",H41+I41)
F42: TOTAL ENCAISSÉ | H42: =SUM(H32:H41) | I42: =SUM(I32:I41) | J42: =SUM(J32:J41)
L44: TOTAL | M44: =SUM(M34:M43)
B46: LES CAISSES ET LE RÉSUMÉ DU SOIR
B47: CAISSE PARADISE | E47: CAISSE ZENATA | H47: CONTRÔLE ET AUTRE CAISSE | L47: RÉSUMÉ DU JOUR
B48: Solde de la veille | D48: ='01'!$D$56 | E48: Solde de la veille | G48: ='01'!$G$56 | H48: Caisse PARADISE du soir | J48: =D56 | L48: Achats fournisseurs du jour | M48: =D28
B49: + Encaissements en espèce | D49: =H42 | E49: + Encaissements du jour | H49: Caisse ZENATA du soir | J49: =G56 | L49: dont réglé en espèce | M49: =E28
B50: + Apports et entrées divers | E50: + Apports et entrées divers | H50: CAISSE TOTALE DU SOIR | J50: =D56+G56 | L50: dont réglé par chèque | M50: =F28
B51: – Achats réglés en espèce | D51: =E28 | E51: – Achats réglés en espèce | H51: Écart total constaté | J51: =D58+G58 | L51: dont réglé par effet | M51: =H28
B52: – Charges fixes du jour | D52: =M20 | E52: – Charges et frais du jour | L52: RESTE DÛ (crédit fournisseur) | M52: =J28
B53: – Salaires et avances | D53: =M30 | E53: – Salaires et avances | H53: AUTRE CAISSE — solde précédent | J53: ='01'!$J$56 | L53: Charges fixes | M53: =M20
B54: – Dépenses travaux et divers | D54: =M44 | E54: – Dépenses travaux et divers | H54: + Entrées du jour | L54: Salaires et avances | M54: =M30
B55: – Versement banque / sorties | E55: – Versement banque / sorties | H55: – Sorties du jour | L55: Dépenses travaux et divers | M55: =M44
B56: SOLDE DU SOIR | D56: =D48+D49+D50-D51-D52-D53-D54-D55 | E56: SOLDE DU SOIR | G56: =G48+G49+G50-G51-G52-G53-G54-G55 | H56: NOUVEAU SOLDE | J56: =J53+J54-J55 | L56: TOTAL DES SORTIES DU JOUR | M56: =M49+M50+M51+M53+M54+M55
B57: Espèces réellement comptées | E57: Espèces réellement comptées | L57: Encaissements du jour | M57: =J42
B58: ÉCART (compté – théorique) | D58: =IF(D57=0,0,D57-D56) | E58: ÉCART (compté – théorique) | G58: =IF(G57=0,0,G57-G56) | L58: CAISSE TOTALE DU SOIR | M58: =D56+G56

Sheet 03
A1: JOURNAL DE CAISSE DU JOUR | H1: PARADISE ALUMINIUM SARL · Casablanca
A2: =IF(3>'RÉCAP DU JOURNAL'!$J$5,"— ce jour n'existe pas dans le mois —",DATE('RÉCAP DU JOURNAL'!$E$4,'RÉCAP DU JOURNAL'!$E$5,3)) | H2: Feuille 03 · aluminium, accessoires et vitrage
A4: À REMPLIR ▸ les achats fournisseurs du jour, les charges, les salaires, les dépenses, les encaissements, puis les espèces comptées le soir dans chaque caisse. Cases jaunes = à vous ; cases blanches = calculées.
B6: ACHATS FOURNISSEURS DU JOUR | L6: CHARGES FIXES DU JOUR
B7: BL N° | C7: FOURNISSEUR | D7: NET À PAYER | E7: ESPÈCE | F7: CHÈQUE | G7: N° DU CHÈQUE | H7: EFFET | I7: N° DE L'EFFET | J7: RESTE À PAYER | L7: POSTE DE CHARGE | M7: MONTANT
J8: =IF(C8="","",D8-E8-F8-H8) | L8: LOYER DU LOCAL
J9: =IF(C9="","",D9-E9-F9-H9) | L9: EAU + ÉLECTRICITÉ
J10: =IF(C10="","",D10-E10-F10-H10) | L10: TÉLÉPHONE & INTERNET
J11: =IF(C11="","",D11-E11-F11-H11) | L11: CNSS
J12: =IF(C12="","",D12-E12-F12-H12) | L12: TVA & IMPÔTS
J13: =IF(C13="","",D13-E13-F13-H13) | L13: ASSURANCES
J14: =IF(C14="","",D14-E14-F14-H14) | L14: COMPTABLE & HONORAIRES
J15: =IF(C15="","",D15-E15-F15-H15) | L15: CARBURANT & VÉHICULE
J16: =IF(C16="","",D16-E16-F16-H16) | L16: TRANSPORT & LIVRAISON
J17: =IF(C17="","",D17-E17-F17-H17) | L17: ENTRETIEN & RÉPARATION
J18: =IF(C18="","",D18-E18-F18-H18) | L18: FOURNITURES DE BUREAU
J19: =IF(C19="","",D19-E19-F19-H19) | L19: AUTRE CHARGE FIXE
J20: =IF(C20="","",D20-E20-F20-H20) | L20: TOTAL | M20: =SUM(M8:M19)
J21: =IF(C21="","",D21-E21-F21-H21)
J22: =IF(C22="","",D22-E22-F22-H22) | L22: SALAIRES ET AVANCES
J23: =IF(C23="","",D23-E23-F23-H23) | L23: PERSONNE | M23: MONTANT
J24: =IF(C24="","",D24-E24-F24-H24) | L24: HOUSSEIN
J25: =IF(C25="","",D25-E25-F25-H25) | L25: AYOUB
J26: =IF(C26="","",D26-E26-F26-H26) | L26: OUVRIER 1
J27: =IF(C27="","",D27-E27-F27-H27) | L27: OUVRIER 2
B28: TOTAL DES ACHATS DU JOUR | D28: =SUM(D8:D27) | E28: =SUM(E8:E27) | F28: =SUM(F8:F27) | H28: =SUM(H8:H27) | J28: =SUM(J8:J27) | L28: AVANCE / PRIME
L29: AUTRE SALAIRE
B30: RÈGLEMENT DES ACHATS | F30: ENCAISSEMENTS DU JOUR | L30: TOTAL | M30: =SUM(M24:M29)
B31: Réglé en espèce | D31: =E28 | F31: CLIENT / ORIGINE | H31: ESPÈCE | I31: CHÈQUE / VIREMENT | J31: TOTAL
B32: Réglé par chèque | D32: =F28 | J32: =IF(F32="","",H32+I32) | L32: DÉPENSES TRAVAUX ET DIVERS
B33: Réglé par effet | D33: =H28 | J33: =IF(F33="","",H33+I33) | L33: DÉSIGNATION | M33: MONTANT
B34: TOTAL RÉGLÉ | D34: =E28+F28+H28 | J34: =IF(F34="","",H34+I34)
B35: RESTE DÛ (crédit fournisseur) | D35: =J28 | J35: =IF(F35="","",H35+I35)
J36: =IF(F36="","",H36+I36)
B37: OBSERVATIONS DU JOUR | J37: =IF(F37="","",H37+I37)
J38: =IF(F38="","",H38+I38)
J39: =IF(F39="","",H39+I39)
J40: =IF(F40="","",H40+I40)
J41: =IF(F41="","",H41+I41)
F42: TOTAL ENCAISSÉ | H42: =SUM(H32:H41) | I42: =SUM(I32:I41) | J42: =SUM(J32:J41)
L44: TOTAL | M44: =SUM(M34:M43)
B46: LES CAISSES ET LE RÉSUMÉ DU SOIR
B47: CAISSE PARADISE | E47: CAISSE ZENATA | H47: CONTRÔLE ET AUTRE CAISSE | L47: RÉSUMÉ DU JOUR
B48: Solde de la veille | D48: ='02'!$D$56 | E48: Solde de la veille | G48: ='02'!$G$56 | H48: Caisse PARADISE du soir | J48: =D56 | L48: Achats fournisseurs du jour | M48: =D28
B49: + Encaissements en espèce | D49: =H42 | E49: + Encaissements du jour | H49: Caisse ZENATA du soir | J49: =G56 | L49: dont réglé en espèce | M49: =E28
B50: + Apports et entrées divers | E50: + Apports et entrées divers | H50: CAISSE TOTALE DU SOIR | J50: =D56+G56 | L50: dont réglé par chèque | M50: =F28
B51: – Achats réglés en espèce | D51: =E28 | E51: – Achats réglés en espèce | H51: Écart total constaté | J51: =D58+G58 | L51: dont réglé par effet | M51: =H28
B52: – Charges fixes du jour | D52: =M20 | E52: – Charges et frais du jour | L52: RESTE DÛ (crédit fournisseur) | M52: =J28
B53: – Salaires et avances | D53: =M30 | E53: – Salaires et avances | H53: AUTRE CAISSE — solde précédent | J53: ='02'!$J$56 | L53: Charges fixes | M53: =M20
B54: – Dépenses travaux et divers | D54: =M44 | E54: – Dépenses travaux et divers | H54: + Entrées du jour | L54: Salaires et avances | M54: =M30
B55: – Versement banque / sorties | E55: – Versement banque / sorties | H55: – Sorties du jour | L55: Dépenses travaux et divers | M55: =M44
B56: SOLDE DU SOIR | D56: =D48+D49+D50-D51-D52-D53-D54-D55 | E56: SOLDE DU SOIR | G56: =G48+G49+G50-G51-G52-G53-G54-G55 | H56: NOUVEAU SOLDE | J56: =J53+J54-J55 | L56: TOTAL DES SORTIES DU JOUR | M56: =M49+M50+M51+M53+M54+M55
B57: Espèces réellement comptées | E57: Espèces réellement comptées | L57: Encaissements du jour | M57: =J42
B58: ÉCART (compté – théorique) | D58: =IF(D57=0,0,D57-D56) | E58: ÉCART (compté – théorique) | G58: =IF(G57=0,0,G57-G56) | L58: CAISSE TOTALE DU SOIR | M58: =D56+G56

Sheet 04
A1: JOURNAL DE CAISSE DU JOUR | H1: PARADISE ALUMINIUM SARL · Casablanca
A2: =IF(4>'RÉCAP DU JOURNAL'!$J$5,"— ce jour n'existe pas dans le mois —",DATE('RÉCAP DU JOURNAL'!$E$4,'RÉCAP DU JOURNAL'!$E$5,4)) | H2: Feuille 04 · aluminium, accessoires et vitrage
A4: À REMPLIR ▸ les achats fournisseurs du jour, les charges, les salaires, les dépenses, les encaissements, puis les espèces comptées le soir dans chaque caisse. Cases jaunes = à vous ; cases blanches = calculées.
B6: ACHATS FOURNISSEURS DU JOUR | L6: CHARGES FIXES DU JOUR
B7: BL N° | C7: FOURNISSEUR | D7: NET À PAYER | E7: ESPÈCE | F7: CHÈQUE | G7: N° DU CHÈQUE | H7: EFFET | I7: N° DE L'EFFET | J7: RESTE À PAYER | L7: POSTE DE CHARGE | M7: MONTANT
J8: =IF(C8="","",D8-E8-F8-H8) | L8: LOYER DU LOCAL
J9: =IF(C9="","",D9-E9-F9-H9) | L9: EAU + ÉLECTRICITÉ
J10: =IF(C10="","",D10-E10-F10-H10) | L10: TÉLÉPHONE & INTERNET
J11: =IF(C11="","",D11-E11-F11-H11) | L11: CNSS
J12: =IF(C12="","",D12-E12-F12-H12) | L12: TVA & IMPÔTS
J13: =IF(C13="","",D13-E13-F13-H13) | L13: ASSURANCES
J14: =IF(C14="","",D14-E14-F14-H14) | L14: COMPTABLE & HONORAIRES
J15: =IF(C15="","",D15-E15-F15-H15) | L15: CARBURANT & VÉHICULE
J16: =IF(C16="","",D16-E16-F16-H16) | L16: TRANSPORT & LIVRAISON
J17: =IF(C17="","",D17-E17-F17-H17) | L17: ENTRETIEN & RÉPARATION
J18: =IF(C18="","",D18-E18-F18-H18) | L18: FOURNITURES DE BUREAU
J19: =IF(C19="","",D19-E19-F19-H19) | L19: AUTRE CHARGE FIXE
J20: =IF(C20="","",D20-E20-F20-H20) | L20: TOTAL | M20: =SUM(M8:M19)
J21: =IF(C21="","",D21-E21-F21-H21)
J22: =IF(C22="","",D22-E22-F22-H22) | L22: SALAIRES ET AVANCES
J23: =IF(C23="","",D23-E23-F23-H23) | L23: PERSONNE | M23: MONTANT
J24: =IF(C24="","",D24-E24-F24-H24) | L24: HOUSSEIN
J25: =IF(C25="","",D25-E25-F25-H25) | L25: AYOUB
J26: =IF(C26="","",D26-E26-F26-H26) | L26: OUVRIER 1
J27: =IF(C27="","",D27-E27-F27-H27) | L27: OUVRIER 2
B28: TOTAL DES ACHATS DU JOUR | D28: =SUM(D8:D27) | E28: =SUM(E8:E27) | F28: =SUM(F8:F27) | H28: =SUM(H8:H27) | J28: =SUM(J8:J27) | L28: AVANCE / PRIME
L29: AUTRE SALAIRE
B30: RÈGLEMENT DES ACHATS | F30: ENCAISSEMENTS DU JOUR | L30: TOTAL | M30: =SUM(M24:M29)
B31: Réglé en espèce | D31: =E28 | F31: CLIENT / ORIGINE | H31: ESPÈCE | I31: CHÈQUE / VIREMENT | J31: TOTAL
B32: Réglé par chèque | D32: =F28 | J32: =IF(F32="","",H32+I32) | L32: DÉPENSES TRAVAUX ET DIVERS
B33: Réglé par effet | D33: =H28 | J33: =IF(F33="","",H33+I33) | L33: DÉSIGNATION | M33: MONTANT
B34: TOTAL RÉGLÉ | D34: =E28+F28+H28 | J34: =IF(F34="","",H34+I34)
B35: RESTE DÛ (crédit fournisseur) | D35: =J28 | J35: =IF(F35="","",H35+I35)
J36: =IF(F36="","",H36+I36)
B37: OBSERVATIONS DU JOUR | J37: =IF(F37="","",H37+I37)
J38: =IF(F38="","",H38+I38)
J39: =IF(F39="","",H39+I39)
J40: =IF(F40="","",H40+I40)
J41: =IF(F41="","",H41+I41)
F42: TOTAL ENCAISSÉ | H42: =SUM(H32:H41) | I42: =SUM(I32:I41) | J42: =SUM(J32:J41)
L44: TOTAL | M44: =SUM(M34:M43)
B46: LES CAISSES ET LE RÉSUMÉ DU SOIR
B47: CAISSE PARADISE | E47: CAISSE ZENATA | H47: CONTRÔLE ET AUTRE CAISSE | L47: RÉSUMÉ DU JOUR
B48: Solde de la veille | D48: ='03'!$D$56 | E48: Solde de la veille | G48: ='03'!$G$56 | H48: Caisse PARADISE du soir | J48: =D56 | L48: Achats fournisseurs du jour | M48: =D28
B49: + Encaissements en espèce | D49: =H42 | E49: + Encaissements du jour | H49: Caisse ZENATA du soir | J49: =G56 | L49: dont réglé en espèce | M49: =E28
B50: + Apports et entrées divers | E50: + Apports et entrées divers | H50: CAISSE TOTALE DU SOIR | J50: =D56+G56 | L50: dont réglé par chèque | M50: =F28
B51: – Achats réglés en espèce | D51: =E28 | E51: – Achats réglés en espèce | H51: Écart total constaté | J51: =D58+G58 | L51: dont réglé par effet | M51: =H28
B52: – Charges fixes du jour | D52: =M20 | E52: – Charges et frais du jour | L52: RESTE DÛ (crédit fournisseur) | M52: =J28
B53: – Salaires et avances | D53: =M30 | E53: – Salaires et avances | H53: AUTRE CAISSE — solde précédent | J53: ='03'!$J$56 | L53: Charges fixes | M53: =M20
B54: – Dépenses travaux et divers | D54: =M44 | E54: – Dépenses travaux et divers | H54: + Entrées du jour | L54: Salaires et avances | M54: =M30
B55: – Versement banque / sorties | E55: – Versement banque / sorties | H55: – Sorties du jour | L55: Dépenses travaux et divers | M55: =M44
B56: SOLDE DU SOIR | D56: =D48+D49+D50-D51-D52-D53-D54-D55 | E56: SOLDE DU SOIR | G56: =G48+G49+G50-G51-G52-G53-G54-G55 | H56: NOUVEAU SOLDE | J56: =J53+J54-J55 | L56: TOTAL DES SORTIES DU JOUR | M56: =M49+M50+M51+M53+M54+M55
B57: Espèces réellement comptées | E57: Espèces réellement comptées | L57: Encaissements du jour | M57: =J42
B58: ÉCART (compté – théorique) | D58: =IF(D57=0,0,D57-D56) | E58: ÉCART (compté – théorique) | G58: =IF(G57=0,0,G57-G56) | L58: CAISSE TOTALE DU SOIR | M58: =D56+G56

Sheet 05
A1: JOURNAL DE CAISSE DU JOUR | H1: PARADISE ALUMINIUM SARL · Casablanca
A2: =IF(5>'RÉCAP DU JOURNAL'!$J$5,"— ce jour n'existe pas dans le mois —",DATE('RÉCAP DU JOURNAL'!$E$4,'RÉCAP DU JOURNAL'!$E$5,5)) | H2: Feuille 05 · aluminium, accessoires et vitrage
A4: À REMPLIR ▸ les achats fournisseurs du jour, les charges, les salaires, les dépenses, les encaissements, puis les espèces comptées le soir dans chaque caisse. Cases jaunes = à vous ; cases blanches = calculées.
B6: ACHATS FOURNISSEURS DU JOUR | L6: CHARGES FIXES DU JOUR
B7: BL N° | C7: FOURNISSEUR | D7: NET À PAYER | E7: ESPÈCE | F7: CHÈQUE | G7: N° DU CHÈQUE | H7: EFFET | I7: N° DE L'EFFET | J7: RESTE À PAYER | L7: POSTE DE CHARGE | M7: MONTANT
J8: =IF(C8="","",D8-E8-F8-H8) | L8: LOYER DU LOCAL
J9: =IF(C9="","",D9-E9-F9-H9) | L9: EAU + ÉLECTRICITÉ
J10: =IF(C10="","",D10-E10-F10-H10) | L10: TÉLÉPHONE & INTERNET
J11: =IF(C11="","",D11-E11-F11-H11) | L11: CNSS
J12: =IF(C12="","",D12-E12-F12-H12) | L12: TVA & IMPÔTS
J13: =IF(C13="","",D13-E13-F13-H13) | L13: ASSURANCES
J14: =IF(C14="","",D14-E14-F14-H14) | L14: COMPTABLE & HONORAIRES
J15: =IF(C15="","",D15-E15-F15-H15) | L15: CARBURANT & VÉHICULE
J16: =IF(C16="","",D16-E16-F16-H16) | L16: TRANSPORT & LIVRAISON
J17: =IF(C17="","",D17-E17-F17-H17) | L17: ENTRETIEN & RÉPARATION
J18: =IF(C18="","",D18-E18-F18-H18) | L18: FOURNITURES DE BUREAU
J19: =IF(C19="","",D19-E19-F19-H19) | L19: AUTRE CHARGE FIXE
J20: =IF(C20="","",D20-E20-F20-H20) | L20: TOTAL | M20: =SUM(M8:M19)
J21: =IF(C21="","",D21-E21-F21-H21)
J22: =IF(C22="","",D22-E22-F22-H22) | L22: SALAIRES ET AVANCES
J23: =IF(C23="","",D23-E23-F23-H23) | L23: PERSONNE | M23: MONTANT
J24: =IF(C24="","",D24-E24-F24-H24) | L24: HOUSSEIN
J25: =IF(C25="","",D25-E25-F25-H25) | L25: AYOUB
J26: =IF(C26="","",D26-E26-F26-H26) | L26: OUVRIER 1
J27: =IF(C27="","",D27-E27-F27-H27) | L27: OUVRIER 2
B28: TOTAL DES ACHATS DU JOUR | D28: =SUM(D8:D27) | E28: =SUM(E8:E27) | F28: =SUM(F8:F27) | H28: =SUM(H8:H27) | J28: =SUM(J8:J27) | L28: AVANCE / PRIME
L29: AUTRE SALAIRE
B30: RÈGLEMENT DES ACHATS | F30: ENCAISSEMENTS DU JOUR | L30: TOTAL | M30: =SUM(M24:M29)
B31: Réglé en espèce | D31: =E28 | F31: CLIENT / ORIGINE | H31: ESPÈCE | I31: CHÈQUE / VIREMENT | J31: TOTAL
B32: Réglé par chèque | D32: =F28 | J32: =IF(F32="","",H32+I32) | L32: DÉPENSES TRAVAUX ET DIVERS
B33: Réglé par effet | D33: =H28 | J33: =IF(F33="","",H33+I33) | L33: DÉSIGNATION | M33: MONTANT
B34: TOTAL RÉGLÉ | D34: =E28+F28+H28 | J34: =IF(F34="","",H34+I34)
B35: RESTE DÛ (crédit fournisseur) | D35: =J28 | J35: =IF(F35="","",H35+I35)
J36: =IF(F36="","",H36+I36)
B37: OBSERVATIONS DU JOUR | J37: =IF(F37="","",H37+I37)
J38: =IF(F38="","",H38+I38)
J39: =IF(F39="","",H39+I39)
J40: =IF(F40="","",H40+I40)
J41: =IF(F41="","",H41+I41)
F42: TOTAL ENCAISSÉ | H42: =SUM(H32:H41) | I42: =SUM(I32:I41) | J42: =SUM(J32:J41)
L44: TOTAL | M44: =SUM(M34:M43)
B46: LES CAISSES ET LE RÉSUMÉ DU SOIR
B47: CAISSE PARADISE | E47: CAISSE ZENATA | H47: CONTRÔLE ET AUTRE CAISSE | L47: RÉSUMÉ DU JOUR
B48: Solde de la veille | D48: ='04'!$D$56 | E48: Solde de la veille | G48: ='04'!$G$56 | H48: Caisse PARADISE du soir | J48: =D56 | L48: Achats fournisseurs du jour | M48: =D28
B49: + Encaissements en espèce | D49: =H42 | E49: + Encaissements du jour | H49: Caisse ZENATA du soir | J49: =G56 | L49: dont réglé en espèce | M49: =E28
B50: + Apports et entrées divers | E50: + Apports et entrées divers | H50: CAISSE TOTALE DU SOIR | J50: =D56+G56 | L50: dont réglé par chèque | M50: =F28
B51: – Achats réglés en espèce | D51: =E28 | E51: – Achats réglés en espèce | H51: Écart total constaté | J51: =D58+G58 | L51: dont réglé par effet | M51: =H28
B52: – Charges fixes du jour | D52: =M20 | E52: – Charges et frais du jour | L52: RESTE DÛ (crédit fournisseur) | M52: =J28
B53: – Salaires et avances | D53: =M30 | E53: – Salaires et avances | H53: AUTRE CAISSE — solde précédent | J53: ='04'!$J$56 | L53: Charges fixes | M53: =M20
B54: – Dépenses travaux et divers | D54: =M44 | E54: – Dépenses travaux et divers | H54: + Entrées du jour | L54: Salaires et avances | M54: =M30
B55: – Versement banque / sorties | E55: – Versement banque / sorties | H55: – Sorties du jour | L55: Dépenses travaux et divers | M55: =M44
B56: SOLDE DU SOIR | D56: =D48+D49+D50-D51-D52-D53-D54-D55 | E56: SOLDE DU SOIR | G56: =G48+G49+G50-G51-G52-G53-G54-G55 | H56: NOUVEAU SOLDE | J56: =J53+J54-J55 | L56: TOTAL DES SORTIES DU JOUR | M56: =M49+M50+M51+M53+M54+M55
B57: Espèces réellement comptées | E57: Espèces réellement comptées | L57: Encaissements du jour | M57: =J42
B58: ÉCART (compté – théorique) | D58: =IF(D57=0,0,D57-D56) | E58: ÉCART (compté – théorique) | G58: =IF(G57=0,0,G57-G56) | L58: CAISSE TOTALE DU SOIR | M58: =D56+G56

Sheet 06
A1: JOURNAL DE CAISSE DU JOUR | H1: PARADISE ALUMINIUM SARL · Casablanca
A2: =IF(6>'RÉCAP DU JOURNAL'!$J$5,"— ce jour n'existe pas dans le mois —",DATE('RÉCAP DU JOURNAL'!$E$4,'RÉCAP DU JOURNAL'!$E$5,6)) | H2: Feuille 06 · aluminium, accessoires et vitrage
A4: À REMPLIR ▸ les achats fournisseurs du jour, les charges, les salaires, les dépenses, les encaissements, puis les espèces comptées le soir dans chaque caisse. Cases jaunes = à vous ; cases blanches = calculées.
B6: ACHATS FOURNISSEURS DU JOUR | L6: CHARGES FIXES DU JOUR
B7: BL N° | C7: FOURNISSEUR | D7: NET À PAYER | E7: ESPÈCE | F7: CHÈQUE | G7: N° DU CHÈQUE | H7: EFFET | I7: N° DE L'EFFET | J7: RESTE À PAYER | L7: POSTE DE CHARGE | M7: MONTANT
J8: =IF(C8="","",D8-E8-F8-H8) | L8: LOYER DU LOCAL
J9: =IF(C9="","",D9-E9-F9-H9) | L9: EAU + ÉLECTRICITÉ
J10: =IF(C10="","",D10-E10-F10-H10) | L10: TÉLÉPHONE & INTERNET
J11: =IF(C11="","",D11-E11-F11-H11) | L11: CNSS
J12: =IF(C12="","",D12-E12-F12-H12) | L12: TVA & IMPÔTS
J13: =IF(C13="","",D13-E13-F13-H13) | L13: ASSURANCES
J14: =IF(C14="","",D14-E14-F14-H14) | L14: COMPTABLE & HONORAIRES
J15: =IF(C15="","",D15-E15-F15-H15) | L15: CARBURANT & VÉHICULE
J16: =IF(C16="","",D16-E16-F16-H16) | L16: TRANSPORT & LIVRAISON
J17: =IF(C17="","",D17-E17-F17-H17) | L17: ENTRETIEN & RÉPARATION
J18: =IF(C18="","",D18-E18-F18-H18) | L18: FOURNITURES DE BUREAU
J19: =IF(C19="","",D19-E19-F19-H19) | L19: AUTRE CHARGE FIXE
J20: =IF(C20="","",D20-E20-F20-H20) | L20: TOTAL | M20: =SUM(M8:M19)
J21: =IF(C21="","",D21-E21-F21-H21)
J22: =IF(C22="","",D22-E22-F22-H22) | L22: SALAIRES ET AVANCES
J23: =IF(C23="","",D23-E23-F23-H23) | L23: PERSONNE | M23: MONTANT
J24: =IF(C24="","",D24-E24-F24-H24) | L24: HOUSSEIN
J25: =IF(C25="","",D25-E25-F25-H25) | L25: AYOUB
J26: =IF(C26="","",D26-E26-F26-H26) | L26: OUVRIER 1
J27: =IF(C27="","",D27-E27-F27-H27) | L27: OUVRIER 2
B28: TOTAL DES ACHATS DU JOUR | D28: =SUM(D8:D27) | E28: =SUM(E8:E27) | F28: =SUM(F8:F27) | H28: =SUM(H8:H27) | J28: =SUM(J8:J27) | L28: AVANCE / PRIME
L29: AUTRE SALAIRE
B30: RÈGLEMENT DES ACHATS | F30: ENCAISSEMENTS DU JOUR | L30: TOTAL | M30: =SUM(M24:M29)
B31: Réglé en espèce | D31: =E28 | F31: CLIENT / ORIGINE | H31: ESPÈCE | I31: CHÈQUE / VIREMENT | J31: TOTAL
B32: Réglé par chèque | D32: =F28 | J32: =IF(F32="","",H32+I32) | L32: DÉPENSES TRAVAUX ET DIVERS
B33: Réglé par effet | D33: =H28 | J33: =IF(F33="","",H33+I33) | L33: DÉSIGNATION | M33: MONTANT
B34: TOTAL RÉGLÉ | D34: =E28+F28+H28 | J34: =IF(F34="","",H34+I34)
B35: RESTE DÛ (crédit fournisseur) | D35: =J28 | J35: =IF(F35="","",H35+I35)
J36: =IF(F36="","",H36+I36)
B37: OBSERVATIONS DU JOUR | J37: =IF(F37="","",H37+I37)
J38: =IF(F38="","",H38+I38)
J39: =IF(F39="","",H39+I39)
J40: =IF(F40="","",H40+I40)
J41: =IF(F41="","",H41+I41)
F42: TOTAL ENCAISSÉ | H42: =SUM(H32:H41) | I42: =SUM(I32:I41) | J42: =SUM(J32:J41)
L44: TOTAL | M44: =SUM(M34:M43)
B46: LES CAISSES ET LE RÉSUMÉ DU SOIR
B47: CAISSE PARADISE | E47: CAISSE ZENATA | H47: CONTRÔLE ET AUTRE CAISSE | L47: RÉSUMÉ DU JOUR
B48: Solde de la veille | D48: ='05'!$D$56 | E48: Solde de la veille | G48: ='05'!$G$56 | H48: Caisse PARADISE du soir | J48: =D56 | L48: Achats fournisseurs du jour | M48: =D28
B49: + Encaissements en espèce | D49: =H42 | E49: + Encaissements du jour | H49: Caisse ZENATA du soir | J49: =G56 | L49: dont réglé en espèce | M49: =E28
B50: + Apports et entrées divers | E50: + Apports et entrées divers | H50: CAISSE TOTALE DU SOIR | J50: =D56+G56 | L50: dont réglé par chèque | M50: =F28
B51: – Achats réglés en espèce | D51: =E28 | E51: – Achats réglés en espèce | H51: Écart total constaté | J51: =D58+G58 | L51: dont réglé par effet | M51: =H28
B52: – Charges fixes du jour | D52: =M20 | E52: – Charges et frais du jour | L52: RESTE DÛ (crédit fournisseur) | M52: =J28
B53: – Salaires et avances | D53: =M30 | E53: – Salaires et avances | H53: AUTRE CAISSE — solde précédent | J53: ='05'!$J$56 | L53: Charges fixes | M53: =M20
B54: – Dépenses travaux et divers | D54: =M44 | E54: – Dépenses travaux et divers | H54: + Entrées du jour | L54: Salaires et avances | M54: =M30
B55: – Versement banque / sorties | E55: – Versement banque / sorties | H55: – Sorties du jour | L55: Dépenses travaux et divers | M55: =M44
B56: SOLDE DU SOIR | D56: =D48+D49+D50-D51-D52-D53-D54-D55 | E56: SOLDE DU SOIR | G56: =G48+G49+G50-G51-G52-G53-G54-G55 | H56: NOUVEAU SOLDE | J56: =J53+J54-J55 | L56: TOTAL DES SORTIES DU JOUR | M56: =M49+M50+M51+M53+M54+M55
B57: Espèces réellement comptées | E57: Espèces réellement comptées | L57: Encaissements du jour | M57: =J42
B58: ÉCART (compté – théorique) | D58: =IF(D57=0,0,D57-D56) | E58: ÉCART (compté – théorique) | G58: =IF(G57=0,0,G57-G56) | L58: CAISSE TOTALE DU SOIR | M58: =D56+G56

Sheet 07
A1: JOURNAL DE CAISSE DU JOUR | H1: PARADISE ALUMINIUM SARL · Casablanca
A2: =IF(7>'RÉCAP DU JOURNAL'!$J$5,"— ce jour n'existe pas dans le mois —",DATE('RÉCAP DU JOURNAL'!$E$4,'RÉCAP DU JOURNAL'!$E$5,7)) | H2: Feuille 07 · aluminium, accessoires et vitrage
A4: À REMPLIR ▸ les achats fournisseurs du jour, les charges, les salaires, les dépenses, les encaissements, puis les espèces comptées le soir dans chaque caisse. Cases jaunes = à vous ; cases blanches = calculées.
B6: ACHATS FOURNISSEURS DU JOUR | L6: CHARGES FIXES DU JOUR
B7: BL N° | C7: FOURNISSEUR | D7: NET À PAYER | E7: ESPÈCE | F7: CHÈQUE | G7: N° DU CHÈQUE | H7: EFFET | I7: N° DE L'EFFET | J7: RESTE À PAYER | L7: POSTE DE CHARGE | M7: MONTANT
J8: =IF(C8="","",D8-E8-F8-H8) | L8: LOYER DU LOCAL
J9: =IF(C9="","",D9-E9-F9-H9) | L9: EAU + ÉLECTRICITÉ
J10: =IF(C10="","",D10-E10-F10-H10) | L10: TÉLÉPHONE & INTERNET
J11: =IF(C11="","",D11-E11-F11-H11) | L11: CNSS
J12: =IF(C12="","",D12-E12-F12-H12) | L12: TVA & IMPÔTS
J13: =IF(C13="","",D13-E13-F13-H13) | L13: ASSURANCES
J14: =IF(C14="","",D14-E14-F14-H14) | L14: COMPTABLE & HONORAIRES
J15: =IF(C15="","",D15-E15-F15-H15) | L15: CARBURANT & VÉHICULE
J16: =IF(C16="","",D16-E16-F16-H16) | L16: TRANSPORT & LIVRAISON
J17: =IF(C17="","",D17-E17-F17-H17) | L17: ENTRETIEN & RÉPARATION
J18: =IF(C18="","",D18-E18-F18-H18) | L18: FOURNITURES DE BUREAU
J19: =IF(C19="","",D19-E19-F19-H19) | L19: AUTRE CHARGE FIXE
J20: =IF(C20="","",D20-E20-F20-H20) | L20: TOTAL | M20: =SUM(M8:M19)
J21: =IF(C21="","",D21-E21-F21-H21)
J22: =IF(C22="","",D22-E22-F22-H22) | L22: SALAIRES ET AVANCES
J23: =IF(C23="","",D23-E23-F23-H23) | L23: PERSONNE | M23: MONTANT
J24: =IF(C24="","",D24-E24-F24-H24) | L24: HOUSSEIN
J25: =IF(C25="","",D25-E25-F25-H25) | L25: AYOUB
J26: =IF(C26="","",D26-E26-F26-H26) | L26: OUVRIER 1
J27: =IF(C27="","",D27-E27-F27-H27) | L27: OUVRIER 2
B28: TOTAL DES ACHATS DU JOUR | D28: =SUM(D8:D27) | E28: =SUM(E8:E27) | F28: =SUM(F8:F27) | H28: =SUM(H8:H27) | J28: =SUM(J8:J27) | L28: AVANCE / PRIME
L29: AUTRE SALAIRE
B30: RÈGLEMENT DES ACHATS | F30: ENCAISSEMENTS DU JOUR | L30: TOTAL | M30: =SUM(M24:M29)
B31: Réglé en espèce | D31: =E28 | F31: CLIENT / ORIGINE | H31: ESPÈCE | I31: CHÈQUE / VIREMENT | J31: TOTAL
B32: Réglé par chèque | D32: =F28 | J32: =IF(F32="","",H32+I32) | L32: DÉPENSES TRAVAUX ET DIVERS
B33: Réglé par effet | D33: =H28 | J33: =IF(F33="","",H33+I33) | L33: DÉSIGNATION | M33: MONTANT
B34: TOTAL RÉGLÉ | D34: =E28+F28+H28 | J34: =IF(F34="","",H34+I34)
B35: RESTE DÛ (crédit fournisseur) | D35: =J28 | J35: =IF(F35="","",H35+I35)
J36: =IF(F36="","",H36+I36)
B37: OBSERVATIONS DU JOUR | J37: =IF(F37="","",H37+I37)
J38: =IF(F38="","",H38+I38)
J39: =IF(F39="","",H39+I39)
J40: =IF(F40="","",H40+I40)
J41: =IF(F41="","",H41+I41)
F42: TOTAL ENCAISSÉ | H42: =SUM(H32:H41) | I42: =SUM(I32:I41) | J42: =SUM(J32:J41)
L44: TOTAL | M44: =SUM(M34:M43)
B46: LES CAISSES ET LE RÉSUMÉ DU SOIR
B47: CAISSE PARADISE | E47: CAISSE ZENATA | H47: CONTRÔLE ET AUTRE CAISSE | L47: RÉSUMÉ DU JOUR
B48: Solde de la veille | D48: ='06'!$D$56 | E48: Solde de la veille | G48: ='06'!$G$56 | H48: Caisse PARADISE du soir | J48: =D56 | L48: Achats fournisseurs du jour | M48: =D28
B49: + Encaissements en espèce | D49: =H42 | E49: + Encaissements du jour | H49: Caisse ZENATA du soir | J49: =G56 | L49: dont réglé en espèce | M49: =E28
B50: + Apports et entrées divers | E50: + Apports et entrées divers | H50: CAISSE TOTALE DU SOIR | J50: =D56+G56 | L50: dont réglé par chèque | M50: =F28
B51: – Achats réglés en espèce | D51: =E28 | E51: – Achats réglés en espèce | H51: Écart total constaté | J51: =D58+G58 | L51: dont réglé par effet | M51: =H28
B52: – Charges fixes du jour | D52: =M20 | E52: – Charges et frais du jour | L52: RESTE DÛ (crédit fournisseur) | M52: =J28
B53: – Salaires et avances | D53: =M30 | E53: – Salaires et avances | H53: AUTRE CAISSE — solde précédent | J53: ='06'!$J$56 | L53: Charges fixes | M53: =M20
B54: – Dépenses travaux et divers | D54: =M44 | E54: – Dépenses travaux et divers | H54: + Entrées du jour | L54: Salaires et avances | M54: =M30
B55: – Versement banque / sorties | E55: – Versement banque / sorties | H55: – Sorties du jour | L55: Dépenses travaux et divers | M55: =M44
B56: SOLDE DU SOIR | D56: =D48+D49+D50-D51-D52-D53-D54-D55 | E56: SOLDE DU SOIR | G56: =G48+G49+G50-G51-G52-G53-G54-G55 | H56: NOUVEAU SOLDE | J56: =J53+J54-J55 | L56: TOTAL DES SORTIES DU JOUR | M56: =M49+M50+M51+M53+M54+M55
B57: Espèces réellement comptées | E57: Espèces réellement comptées | L57: Encaissements du jour | M57: =J42
B58: ÉCART (compté – théorique) | D58: =IF(D57=0,0,D57-D56) | E58: ÉCART (compté – théorique) | G58: =IF(G57=0,0,G57-G56) | L58: CAISSE TOTALE DU SOIR | M58: =D56+G56

Sheet 08
A1: JOURNAL DE CAISSE DU JOUR | H1: PARADISE ALUMINIUM SARL · Casablanca
A2: =IF(8>'RÉCAP DU JOURNAL'!$J$5,"— ce jour n'existe pas dans le mois —",DATE('RÉCAP DU JOURNAL'!$E$4,'RÉCAP DU JOURNAL'!$E$5,8)) | H2: Feuille 08 · aluminium, accessoires et vitrage
A4: À REMPLIR ▸ les achats fournisseurs du jour, les charges, les salaires, les dépenses, les encaissements, puis les espèces comptées le soir dans chaque caisse. Cases jaunes = à vous ; cases blanches = calculées.
B6: ACHATS FOURNISSEURS DU JOUR | L6: CHARGES FIXES DU JOUR
B7: BL N° | C7: FOURNISSEUR | D7: NET À PAYER | E7: ESPÈCE | F7: CHÈQUE | G7: N° DU CHÈQUE | H7: EFFET | I7: N° DE L'EFFET | J7: RESTE À PAYER | L7: POSTE DE CHARGE | M7: MONTANT
J8: =IF(C8="","",D8-E8-F8-H8) | L8: LOYER DU LOCAL
J9: =IF(C9="","",D9-E9-F9-H9) | L9: EAU + ÉLECTRICITÉ
J10: =IF(C10="","",D10-E10-F10-H10) | L10: TÉLÉPHONE & INTERNET
J11: =IF(C11="","",D11-E11-F11-H11) | L11: CNSS
J12: =IF(C12="","",D12-E12-F12-H12) | L12: TVA & IMPÔTS
J13: =IF(C13="","",D13-E13-F13-H13) | L13: ASSURANCES
J14: =IF(C14="","",D14-E14-F14-H14) | L14: COMPTABLE & HONORAIRES
J15: =IF(C15="","",D15-E15-F15-H15) | L15: CARBURANT & VÉHICULE
J16: =IF(C16="","",D16-E16-F16-H16) | L16: TRANSPORT & LIVRAISON
J17: =IF(C17="","",D17-E17-F17-H17) | L17: ENTRETIEN & RÉPARATION
J18: =IF(C18="","",D18-E18-F18-H18) | L18: FOURNITURES DE BUREAU
J19: =IF(C19="","",D19-E19-F19-H19) | L19: AUTRE CHARGE FIXE
J20: =IF(C20="","",D20-E20-F20-H20) | L20: TOTAL | M20: =SUM(M8:M19)
J21: =IF(C21="","",D21-E21-F21-H21)
J22: =IF(C22="","",D22-E22-F22-H22) | L22: SALAIRES ET AVANCES
J23: =IF(C23="","",D23-E23-F23-H23) | L23: PERSONNE | M23: MONTANT
J24: =IF(C24="","",D24-E24-F24-H24) | L24: HOUSSEIN
J25: =IF(C25="","",D25-E25-F25-H25) | L25: AYOUB
J26: =IF(C26="","",D26-E26-F26-H26) | L26: OUVRIER 1
J27: =IF(C27="","",D27-E27-F27-H27) | L27: OUVRIER 2
B28: TOTAL DES ACHATS DU JOUR | D28: =SUM(D8:D27) | E28: =SUM(E8:E27) | F28: =SUM(F8:F27) | H28: =SUM(H8:H27) | J28: =SUM(J8:J27) | L28: AVANCE / PRIME
L29: AUTRE SALAIRE
B30: RÈGLEMENT DES ACHATS | F30: ENCAISSEMENTS DU JOUR | L30: TOTAL | M30: =SUM(M24:M29)
B31: Réglé en espèce | D31: =E28 | F31: CLIENT / ORIGINE | H31: ESPÈCE | I31: CHÈQUE / VIREMENT | J31: TOTAL
B32: Réglé par chèque | D32: =F28 | J32: =IF(F32="","",H32+I32) | L32: DÉPENSES TRAVAUX ET DIVERS
B33: Réglé par effet | D33: =H28 | J33: =IF(F33="","",H33+I33) | L33: DÉSIGNATION | M33: MONTANT
B34: TOTAL RÉGLÉ | D34: =E28+F28+H28 | J34: =IF(F34="","",H34+I34)
B35: RESTE DÛ (crédit fournisseur) | D35: =J28 | J35: =IF(F35="","",H35+I35)
J36: =IF(F36="","",H36+I36)
B37: OBSERVATIONS DU JOUR | J37: =IF(F37="","",H37+I37)
J38: =IF(F38="","",H38+I38)
J39: =IF(F39="","",H39+I39)
J40: =IF(F40="","",H40+I40)
J41: =IF(F41="","",H41+I41)
F42: TOTAL ENCAISSÉ | H42: =SUM(H32:H41) | I42: =SUM(I32:I41) | J42: =SUM(J32:J41)
L44: TOTAL | M44: =SUM(M34:M43)
B46: LES CAISSES ET LE RÉSUMÉ DU SOIR
B47: CAISSE PARADISE | E47: CAISSE ZENATA | H47: CONTRÔLE ET AUTRE CAISSE | L47: RÉSUMÉ DU JOUR
B48: Solde de la veille | D48: ='07'!$D$56 | E48: Solde de la veille | G48: ='07'!$G$56 | H48: Caisse PARADISE du soir | J48: =D56 | L48: Achats fournisseurs du jour | M48: =D28
B49: + Encaissements en espèce | D49: =H42 | E49: + Encaissements du jour | H49: Caisse ZENATA du soir | J49: =G56 | L49: dont réglé en espèce | M49: =E28
B50: + Apports et entrées divers | E50: + Apports et entrées divers | H50: CAISSE TOTALE DU SOIR | J50: =D56+G56 | L50: dont réglé par chèque | M50: =F28
B51: – Achats réglés en espèce | D51: =E28 | E51: – Achats réglés en espèce | H51: Écart total constaté | J51: =D58+G58 | L51: dont réglé par effet | M51: =H28
B52: – Charges fixes du jour | D52: =M20 | E52: – Charges et frais du jour | L52: RESTE DÛ (crédit fournisseur) | M52: =J28
B53: – Salaires et avances | D53: =M30 | E53: – Salaires et avances | H53: AUTRE CAISSE — solde précédent | J53: ='07'!$J$56 | L53: Charges fixes | M53: =M20
B54: – Dépenses travaux et divers | D54: =M44 | E54: – Dépenses travaux et divers | H54: + Entrées du jour | L54: Salaires et avances | M54: =M30
B55: – Versement banque / sorties | E55: – Versement banque / sorties | H55: – Sorties du jour | L55: Dépenses travaux et divers | M55: =M44
B56: SOLDE DU SOIR | D56: =D48+D49+D50-D51-D52-D53-D54-D55 | E56: SOLDE DU SOIR | G56: =G48+G49+G50-G51-G52-G53-G54-G55 | H56: NOUVEAU SOLDE | J56: =J53+J54-J55 | L56: TOTAL DES SORTIES DU JOUR | M56: =M49+M50+M51+M53+M54+M55
B57: Espèces réellement comptées | E57: Espèces réellement comptées | L57: Encaissements du jour | M57: =J42
B58: ÉCART (compté – théorique) | D58: =IF(D57=0,0,D57-D56) | E58: ÉCART (compté – théorique) | G58: =IF(G57=0,0,G57-G56) | L58: CAISSE TOTALE DU SOIR | M58: =D56+G56

Sheet 09
A1: JOURNAL DE CAISSE DU JOUR | H1: PARADISE ALUMINIUM SARL · Casablanca
A2: =IF(9>'RÉCAP DU JOURNAL'!$J$5,"— ce jour n'existe pas dans le mois —",DATE('RÉCAP DU JOURNAL'!$E$4,'RÉCAP DU JOURNAL'!$E$5,9)) | H2: Feuille 09 · aluminium, accessoires et vitrage
A4: À REMPLIR ▸ les achats fournisseurs du jour, les charges, les salaires, les dépenses, les encaissements, puis les espèces comptées le soir dans chaque caisse. Cases jaunes = à vous ; cases blanches = calculées.
B6: ACHATS FOURNISSEURS DU JOUR | L6: CHARGES FIXES DU JOUR
B7: BL N° | C7: FOURNISSEUR | D7: NET À PAYER | E7: ESPÈCE | F7: CHÈQUE | G7: N° DU CHÈQUE | H7: EFFET | I7: N° DE L'EFFET | J7: RESTE À PAYER | L7: POSTE DE CHARGE | M7: MONTANT
J8: =IF(C8="","",D8-E8-F8-H8) | L8: LOYER DU LOCAL
J9: =IF(C9="","",D9-E9-F9-H9) | L9: EAU + ÉLECTRICITÉ
J10: =IF(C10="","",D10-E10-F10-H10) | L10: TÉLÉPHONE & INTERNET
J11: =IF(C11="","",D11-E11-F11-H11) | L11: CNSS
J12: =IF(C12="","",D12-E12-F12-H12) | L12: TVA & IMPÔTS
J13: =IF(C13="","",D13-E13-F13-H13) | L13: ASSURANCES
J14: =IF(C14="","",D14-E14-F14-H14) | L14: COMPTABLE & HONORAIRES
J15: =IF(C15="","",D15-E15-F15-H15) | L15: CARBURANT & VÉHICULE
J16: =IF(C16="","",D16-E16-F16-H16) | L16: TRANSPORT & LIVRAISON
J17: =IF(C17="","",D17-E17-F17-H17) | L17: ENTRETIEN & RÉPARATION
J18: =IF(C18="","",D18-E18-F18-H18) | L18: FOURNITURES DE BUREAU
J19: =IF(C19="","",D19-E19-F19-H19) | L19: AUTRE CHARGE FIXE
J20: =IF(C20="","",D20-E20-F20-H20) | L20: TOTAL | M20: =SUM(M8:M19)
J21: =IF(C21="","",D21-E21-F21-H21)
J22: =IF(C22="","",D22-E22-F22-H22) | L22: SALAIRES ET AVANCES
J23: =IF(C23="","",D23-E23-F23-H23) | L23: PERSONNE | M23: MONTANT
J24: =IF(C24="","",D24-E24-F24-H24) | L24: HOUSSEIN
J25: =IF(C25="","",D25-E25-F25-H25) | L25: AYOUB
J26: =IF(C26="","",D26-E26-F26-H26) | L26: OUVRIER 1
J27: =IF(C27="","",D27-E27-F27-H27) | L27: OUVRIER 2
B28: TOTAL DES ACHATS DU JOUR | D28: =SUM(D8:D27) | E28: =SUM(E8:E27) | F28: =SUM(F8:F27) | H28: =SUM(H8:H27) | J28: =SUM(J8:J27) | L28: AVANCE / PRIME
L29: AUTRE SALAIRE
B30: RÈGLEMENT DES ACHATS | F30: ENCAISSEMENTS DU JOUR | L30: TOTAL | M30: =SUM(M24:M29)
B31: Réglé en espèce | D31: =E28 | F31: CLIENT / ORIGINE | H31: ESPÈCE | I31: CHÈQUE / VIREMENT | J31: TOTAL
B32: Réglé par chèque | D32: =F28 | J32: =IF(F32="","",H32+I32) | L32: DÉPENSES TRAVAUX ET DIVERS
B33: Réglé par effet | D33: =H28 | J33: =IF(F33="","",H33+I33) | L33: DÉSIGNATION | M33: MONTANT
B34: TOTAL RÉGLÉ | D34: =E28+F28+H28 | J34: =IF(F34="","",H34+I34)
B35: RESTE DÛ (crédit fournisseur) | D35: =J28 | J35: =IF(F35="","",H35+I35)
J36: =IF(F36="","",H36+I36)
B37: OBSERVATIONS DU JOUR | J37: =IF(F37="","",H37+I37)
J38: =IF(F38="","",H38+I38)
J39: =IF(F39="","",H39+I39)
J40: =IF(F40="","",H40+I40)
J41: =IF(F41="","",H41+I41)
F42: TOTAL ENCAISSÉ | H42: =SUM(H32:H41) | I42: =SUM(I32:I41) | J42: =SUM(J32:J41)
L44: TOTAL | M44: =SUM(M34:M43)
B46: LES CAISSES ET LE RÉSUMÉ DU SOIR
B47: CAISSE PARADISE | E47: CAISSE ZENATA | H47: CONTRÔLE ET AUTRE CAISSE | L47: RÉSUMÉ DU JOUR
B48: Solde de la veille | D48: ='08'!$D$56 | E48: Solde de la veille | G48: ='08'!$G$56 | H48: Caisse PARADISE du soir | J48: =D56 | L48: Achats fournisseurs du jour | M48: =D28
B49: + Encaissements en espèce | D49: =H42 | E49: + Encaissements du jour | H49: Caisse ZENATA du soir | J49: =G56 | L49: dont réglé en espèce | M49: =E28
B50: + Apports et entrées divers | E50: + Apports et entrées divers | H50: CAISSE TOTALE DU SOIR | J50: =D56+G56 | L50: dont réglé par chèque | M50: =F28
B51: – Achats réglés en espèce | D51: =E28 | E51: – Achats réglés en espèce | H51: Écart total constaté | J51: =D58+G58 | L51: dont réglé par effet | M51: =H28
B52: – Charges fixes du jour | D52: =M20 | E52: – Charges et frais du jour | L52: RESTE DÛ (crédit fournisseur) | M52: =J28
B53: – Salaires et avances | D53: =M30 | E53: – Salaires et avances | H53: AUTRE CAISSE — solde précédent | J53: ='08'!$J$56 | L53: Charges fixes | M53: =M20
B54: – Dépenses travaux et divers | D54: =M44 | E54: – Dépenses travaux et divers | H54: + Entrées du jour | L54: Salaires et avances | M54: =M30
B55: – Versement banque / sorties | E55: – Versement banque / sorties | H55: – Sorties du jour | L55: Dépenses travaux et divers | M55: =M44
B56: SOLDE DU SOIR | D56: =D48+D49+D50-D51-D52-D53-D54-D55 | E56: SOLDE DU SOIR | G56: =G48+G49+G50-G51-G52-G53-G54-G55 | H56: NOUVEAU SOLDE | J56: =J53+J54-J55 | L56: TOTAL DES SORTIES DU JOUR | M56: =M49+M50+M51+M53+M54+M55
B57: Espèces réellement comptées | E57: Espèces réellement comptées | L57: Encaissements du jour | M57: =J42
B58: ÉCART (compté – théorique) | D58: =IF(D57=0,0,D57-D56) | E58: ÉCART (compté – théorique) | G58: =IF(G57=0,0,G57-G56) | L58: CAISSE TOTALE DU SOIR | M58: =D56+G56

Sheet 10
A1: JOURNAL DE CAISSE DU JOUR | H1: PARADISE ALUMINIUM SARL · Casablanca
A2: =IF(10>'RÉCAP DU JOURNAL'!$J$5,"— ce jour n'existe pas dans le mois —",DATE('RÉCAP DU JOURNAL'!$E$4,'RÉCAP DU JOURNAL'!$E$5,10)) | H2: Feuille 10 · aluminium, accessoires et vitrage
A4: À REMPLIR ▸ les achats fournisseurs du jour, les charges, les salaires, les dépenses, les encaissements, puis les espèces comptées le soir dans chaque caisse. Cases jaunes = à vous ; cases blanches = calculées.
B6: ACHATS FOURNISSEURS DU JOUR | L6: CHARGES FIXES DU JOUR
B7: BL N° | C7: FOURNISSEUR | D7: NET À PAYER | E7: ESPÈCE | F7: CHÈQUE | G7: N° DU CHÈQUE | H7: EFFET | I7: N° DE L'EFFET | J7: RESTE À PAYER | L7: POSTE DE CHARGE | M7: MONTANT
J8: =IF(C8="","",D8-E8-F8-H8) | L8: LOYER DU LOCAL
J9: =IF(C9="","",D9-E9-F9-H9) | L9: EAU + ÉLECTRICITÉ
J10: =IF(C10="","",D10-E10-F10-H10) | L10: TÉLÉPHONE & INTERNET
J11: =IF(C11="","",D11-E11-F11-H11) | L11: CNSS
J12: =IF(C12="","",D12-E12-F12-H12) | L12: TVA & IMPÔTS
J13: =IF(C13="","",D13-E13-F13-H13) | L13: ASSURANCES
J14: =IF(C14="","",D14-E14-F14-H14) | L14: COMPTABLE & HONORAIRES
J15: =IF(C15="","",D15-E15-F15-H15) | L15: CARBURANT & VÉHICULE
J16: =IF(C16="","",D16-E16-F16-H16) | L16: TRANSPORT & LIVRAISON
J17: =IF(C17="","",D17-E17-F17-H17) | L17: ENTRETIEN & RÉPARATION
J18: =IF(C18="","",D18-E18-F18-H18) | L18: FOURNITURES DE BUREAU
J19: =IF(C19="","",D19-E19-F19-H19) | L19: AUTRE CHARGE FIXE
J20: =IF(C20="","",D20-E20-F20-H20) | L20: TOTAL | M20: =SUM(M8:M19)
J21: =IF(C21="","",D21-E21-F21-H21)
J22: =IF(C22="","",D22-E22-F22-H22) | L22: SALAIRES ET AVANCES
J23: =IF(C23="","",D23-E23-F23-H23) | L23: PERSONNE | M23: MONTANT
J24: =IF(C24="","",D24-E24-F24-H24) | L24: HOUSSEIN
J25: =IF(C25="","",D25-E25-F25-H25) | L25: AYOUB
J26: =IF(C26="","",D26-E26-F26-H26) | L26: OUVRIER 1
J27: =IF(C27="","",D27-E27-F27-H27) | L27: OUVRIER 2
B28: TOTAL DES ACHATS DU JOUR | D28: =SUM(D8:D27) | E28: =SUM(E8:E27) | F28: =SUM(F8:F27) | H28: =SUM(H8:H27) | J28: =SUM(J8:J27) | L28: AVANCE / PRIME
L29: AUTRE SALAIRE
B30: RÈGLEMENT DES ACHATS | F30: ENCAISSEMENTS DU JOUR | L30: TOTAL | M30: =SUM(M24:M29)
B31: Réglé en espèce | D31: =E28 | F31: CLIENT / ORIGINE | H31: ESPÈCE | I31: CHÈQUE / VIREMENT | J31: TOTAL
B32: Réglé par chèque | D32: =F28 | J32: =IF(F32="","",H32+I32) | L32: DÉPENSES TRAVAUX ET DIVERS
B33: Réglé par effet | D33: =H28 | J33: =IF(F33="","",H33+I33) | L33: DÉSIGNATION | M33: MONTANT
B34: TOTAL RÉGLÉ | D34: =E28+F28+H28 | J34: =IF(F34="","",H34+I34)
B35: RESTE DÛ (crédit fournisseur) | D35: =J28 | J35: =IF(F35="","",H35+I35)
J36: =IF(F36="","",H36+I36)
B37: OBSERVATIONS DU JOUR | J37: =IF(F37="","",H37+I37)
J38: =IF(F38="","",H38+I38)
J39: =IF(F39="","",H39+I39)
J40: =IF(F40="","",H40+I40)
J41: =IF(F41="","",H41+I41)
F42: TOTAL ENCAISSÉ | H42: =SUM(H32:H41) | I42: =SUM(I32:I41) | J42: =SUM(J32:J41)
L44: TOTAL | M44: =SUM(M34:M43)
B46: LES CAISSES ET LE RÉSUMÉ DU SOIR
B47: CAISSE PARADISE | E47: CAISSE ZENATA | H47: CONTRÔLE ET AUTRE CAISSE | L47: RÉSUMÉ DU JOUR
B48: Solde de la veille | D48: ='09'!$D$56 | E48: Solde de la veille | G48: ='09'!$G$56 | H48: Caisse PARADISE du soir | J48: =D56 | L48: Achats fournisseurs du jour | M48: =D28
B49: + Encaissements en espèce | D49: =H42 | E49: + Encaissements du jour | H49: Caisse ZENATA du soir | J49: =G56 | L49: dont réglé en espèce | M49: =E28
B50: + Apports et entrées divers | E50: + Apports et entrées divers | H50: CAISSE TOTALE DU SOIR | J50: =D56+G56 | L50: dont réglé par chèque | M50: =F28
B51: – Achats réglés en espèce | D51: =E28 | E51: – Achats réglés en espèce | H51: Écart total constaté | J51: =D58+G58 | L51: dont réglé par effet | M51: =H28
B52: – Charges fixes du jour | D52: =M20 | E52: – Charges et frais du jour | L52: RESTE DÛ (crédit fournisseur) | M52: =J28
B53: – Salaires et avances | D53: =M30 | E53: – Salaires et avances | H53: AUTRE CAISSE — solde précédent | J53: ='09'!$J$56 | L53: Charges fixes | M53: =M20
B54: – Dépenses travaux et divers | D54: =M44 | E54: – Dépenses travaux et divers | H54: + Entrées du jour | L54: Salaires et avances | M54: =M30
B55: – Versement banque / sorties | E55: – Versement banque / sorties | H55: – Sorties du jour | L55: Dépenses travaux et divers | M55: =M44
B56: SOLDE DU SOIR | D56: =D48+D49+D50-D51-D52-D53-D54-D55 | E56: SOLDE DU SOIR | G56: =G48+G49+G50-G51-G52-G53-G54-G55 | H56: NOUVEAU SOLDE | J56: =J53+J54-J55 | L56: TOTAL DES SORTIES DU JOUR | M56: =M49+M50+M51+M53+M54+M55
B57: Espèces réellement comptées | E57: Espèces réellement comptées | L57: Encaissements du jour | M57: =J42
B58: ÉCART (compté – théorique) | D58: =IF(D57=0,0,D57-D56) | E58: ÉCART (compté – théorique) | G58: =IF(G57=0,0,G57-G56) | L58: CAISSE TOTALE DU SOIR | M58: =D56+G56

Sheet 11
A1: JOURNAL DE CAISSE DU JOUR | H1: PARADISE ALUMINIUM SARL · Casablanca
A2: =IF(11>'RÉCAP DU JOURNAL'!$J$5,"— ce jour n'existe pas dans le mois —",DATE('RÉCAP DU JOURNAL'!$E$4,'RÉCAP DU JOURNAL'!$E$5,11)) | H2: Feuille 11 · aluminium, accessoires et vitrage
A4: À REMPLIR ▸ les achats fournisseurs du jour, les charges, les salaires, les dépenses, les encaissements, puis les espèces comptées le soir dans chaque caisse. Cases jaunes = à vous ; cases blanches = calculées.
B6: ACHATS FOURNISSEURS DU JOUR | L6: CHARGES FIXES DU JOUR
B7: BL N° | C7: FOURNISSEUR | D7: NET À PAYER | E7: ESPÈCE | F7: CHÈQUE | G7: N° DU CHÈQUE | H7: EFFET | I7: N° DE L'EFFET | J7: RESTE À PAYER | L7: POSTE DE CHARGE | M7: MONTANT
J8: =IF(C8="","",D8-E8-F8-H8) | L8: LOYER DU LOCAL
J9: =IF(C9="","",D9-E9-F9-H9) | L9: EAU + ÉLECTRICITÉ
J10: =IF(C10="","",D10-E10-F10-H10) | L10: TÉLÉPHONE & INTERNET
J11: =IF(C11="","",D11-E11-F11-H11) | L11: CNSS
J12: =IF(C12="","",D12-E12-F12-H12) | L12: TVA & IMPÔTS
J13: =IF(C13="","",D13-E13-F13-H13) | L13: ASSURANCES
J14: =IF(C14="","",D14-E14-F14-H14) | L14: COMPTABLE & HONORAIRES
J15: =IF(C15="","",D15-E15-F15-H15) | L15: CARBURANT & VÉHICULE
J16: =IF(C16="","",D16-E16-F16-H16) | L16: TRANSPORT & LIVRAISON
J17: =IF(C17="","",D17-E17-F17-H17) | L17: ENTRETIEN & RÉPARATION
J18: =IF(C18="","",D18-E18-F18-H18) | L18: FOURNITURES DE BUREAU
J19: =IF(C19="","",D19-E19-F19-H19) | L19: AUTRE CHARGE FIXE
J20: =IF(C20="","",D20-E20-F20-H20) | L20: TOTAL | M20: =SUM(M8:M19)
J21: =IF(C21="","",D21-E21-F21-H21)
J22: =IF(C22="","",D22-E22-F22-H22) | L22: SALAIRES ET AVANCES
J23: =IF(C23="","",D23-E23-F23-H23) | L23: PERSONNE | M23: MONTANT
J24: =IF(C24="","",D24-E24-F24-H24) | L24: HOUSSEIN
J25: =IF(C25="","",D25-E25-F25-H25) | L25: AYOUB
J26: =IF(C26="","",D26-E26-F26-H26) | L26: OUVRIER 1
J27: =IF(C27="","",D27-E27-F27-H27) | L27: OUVRIER 2
B28: TOTAL DES ACHATS DU JOUR | D28: =SUM(D8:D27) | E28: =SUM(E8:E27) | F28: =SUM(F8:F27) | H28: =SUM(H8:H27) | J28: =SUM(J8:J27) | L28: AVANCE / PRIME
L29: AUTRE SALAIRE
B30: RÈGLEMENT DES ACHATS | F30: ENCAISSEMENTS DU JOUR | L30: TOTAL | M30: =SUM(M24:M29)
B31: Réglé en espèce | D31: =E28 | F31: CLIENT / ORIGINE | H31: ESPÈCE | I31: CHÈQUE / VIREMENT | J31: TOTAL
B32: Réglé par chèque | D32: =F28 | J32: =IF(F32="","",H32+I32) | L32: DÉPENSES TRAVAUX ET DIVERS
B33: Réglé par effet | D33: =H28 | J33: =IF(F33="","",H33+I33) | L33: DÉSIGNATION | M33: MONTANT
B34: TOTAL RÉGLÉ | D34: =E28+F28+H28 | J34: =IF(F34="","",H34+I34)
B35: RESTE DÛ (crédit fournisseur) | D35: =J28 | J35: =IF(F35="","",H35+I35)
J36: =IF(F36="","",H36+I36)
B37: OBSERVATIONS DU JOUR | J37: =IF(F37="","",H37+I37)
J38: =IF(F38="","",H38+I38)
J39: =IF(F39="","",H39+I39)
J40: =IF(F40="","",H40+I40)
J41: =IF(F41="","",H41+I41)
F42: TOTAL ENCAISSÉ | H42: =SUM(H32:H41) | I42: =SUM(I32:I41) | J42: =SUM(J32:J41)
L44: TOTAL | M44: =SUM(M34:M43)
B46: LES CAISSES ET LE RÉSUMÉ DU SOIR
B47: CAISSE PARADISE | E47: CAISSE ZENATA | H47: CONTRÔLE ET AUTRE CAISSE | L47: RÉSUMÉ DU JOUR
B48: Solde de la veille | D48: ='10'!$D$56 | E48: Solde de la veille | G48: ='10'!$G$56 | H48: Caisse PARADISE du soir | J48: =D56 | L48: Achats fournisseurs du jour | M48: =D28
B49: + Encaissements en espèce | D49: =H42 | E49: + Encaissements du jour | H49: Caisse ZENATA du soir | J49: =G56 | L49: dont réglé en espèce | M49: =E28
B50: + Apports et entrées divers | E50: + Apports et entrées divers | H50: CAISSE TOTALE DU SOIR | J50: =D56+G56 | L50: dont réglé par chèque | M50: =F28
B51: – Achats réglés en espèce | D51: =E28 | E51: – Achats réglés en espèce | H51: Écart total constaté | J51: =D58+G58 | L51: dont réglé par effet | M51: =H28
B52: – Charges fixes du jour | D52: =M20 | E52: – Charges et frais du jour | L52: RESTE DÛ (crédit fournisseur) | M52: =J28
B53: – Salaires et avances | D53: =M30 | E53: – Salaires et avances | H53: AUTRE CAISSE — solde précédent | J53: ='10'!$J$56 | L53: Charges fixes | M53: =M20
B54: – Dépenses travaux et divers | D54: =M44 | E54: – Dépenses travaux et divers | H54: + Entrées du jour | L54: Salaires et avances | M54: =M30
B55: – Versement banque / sorties | E55: – Versement banque / sorties | H55: – Sorties du jour | L55: Dépenses travaux et divers | M55: =M44
B56: SOLDE DU SOIR | D56: =D48+D49+D50-D51-D52-D53-D54-D55 | E56: SOLDE DU SOIR | G56: =G48+G49+G50-G51-G52-G53-G54-G55 | H56: NOUVEAU SOLDE | J56: =J53+J54-J55 | L56: TOTAL DES SORTIES DU JOUR | M56: =M49+M50+M51+M53+M54+M55
B57: Espèces réellement comptées | E57: Espèces réellement comptées | L57: Encaissements du jour | M57: =J42
B58: ÉCART (compté – théorique) | D58: =IF(D57=0,0,D57-D56) | E58: ÉCART (compté – théorique) | G58: =IF(G57=0,0,G57-G56) | L58: CAISSE TOTALE DU SOIR | M58: =D56+G56

Sheet 12
A1: JOURNAL DE CAISSE DU JOUR | H1: PARADISE ALUMINIUM SARL · Casablanca
A2: =IF(12>'RÉCAP DU JOURNAL'!$J$5,"— ce jour n'existe pas dans le mois —",DATE('RÉCAP DU JOURNAL'!$E$4,'RÉCAP DU JOURNAL'!$E$5,12)) | H2: Feuille 12 · aluminium, accessoires et vitrage
A4: À REMPLIR ▸ les achats fournisseurs du jour, les charges, les salaires, les dépenses, les encaissements, puis les espèces comptées le soir dans chaque caisse. Cases jaunes = à vous ; cases blanches = calculées.
B6: ACHATS FOURNISSEURS DU JOUR | L6: CHARGES FIXES DU JOUR
B7: BL N° | C7: FOURNISSEUR | D7: NET À PAYER | E7: ESPÈCE | F7: CHÈQUE | G7: N° DU CHÈQUE | H7: EFFET | I7: N° DE L'EFFET | J7: RESTE À PAYER | L7: POSTE DE CHARGE | M7: MONTANT
J8: =IF(C8="","",D8-E8-F8-H8) | L8: LOYER DU LOCAL
J9: =IF(C9="","",D9-E9-F9-H9) | L9: EAU + ÉLECTRICITÉ
J10: =IF(C10="","",D10-E10-F10-H10) | L10: TÉLÉPHONE & INTERNET
J11: =IF(C11="","",D11-E11-F11-H11) | L11: CNSS
J12: =IF(C12="","",D12-E12-F12-H12) | L12: TVA & IMPÔTS
J13: =IF(C13="","",D13-E13-F13-H13) | L13: ASSURANCES
J14: =IF(C14="","",D14-E14-F14-H14) | L14: COMPTABLE & HONORAIRES
J15: =IF(C15="","",D15-E15-F15-H15) | L15: CARBURANT & VÉHICULE
J16: =IF(C16="","",D16-E16-F16-H16) | L16: TRANSPORT & LIVRAISON
J17: =IF(C17="","",D17-E17-F17-H17) | L17: ENTRETIEN & RÉPARATION
J18: =IF(C18="","",D18-E18-F18-H18) | L18: FOURNITURES DE BUREAU
J19: =IF(C19="","",D19-E19-F19-H19) | L19: AUTRE CHARGE FIXE
J20: =IF(C20="","",D20-E20-F20-H20) | L20: TOTAL | M20: =SUM(M8:M19)
J21: =IF(C21="","",D21-E21-F21-H21)
J22: =IF(C22="","",D22-E22-F22-H22) | L22: SALAIRES ET AVANCES
J23: =IF(C23="","",D23-E23-F23-H23) | L23: PERSONNE | M23: MONTANT
J24: =IF(C24="","",D24-E24-F24-H24) | L24: HOUSSEIN
J25: =IF(C25="","",D25-E25-F25-H25) | L25: AYOUB
J26: =IF(C26="","",D26-E26-F26-H26) | L26: OUVRIER 1
J27: =IF(C27="","",D27-E27-F27-H27) | L27: OUVRIER 2
B28: TOTAL DES ACHATS DU JOUR | D28: =SUM(D8:D27) | E28: =SUM(E8:E27) | F28: =SUM(F8:F27) | H28: =SUM(H8:H27) | J28: =SUM(J8:J27) | L28: AVANCE / PRIME
L29: AUTRE SALAIRE
B30: RÈGLEMENT DES ACHATS | F30: ENCAISSEMENTS DU JOUR | L30: TOTAL | M30: =SUM(M24:M29)
B31: Réglé en espèce | D31: =E28 | F31: CLIENT / ORIGINE | H31: ESPÈCE | I31: CHÈQUE / VIREMENT | J31: TOTAL
B32: Réglé par chèque | D32: =F28 | J32: =IF(F32="","",H32+I32) | L32: DÉPENSES TRAVAUX ET DIVERS
B33: Réglé par effet | D33: =H28 | J33: =IF(F33="","",H33+I33) | L33: DÉSIGNATION | M33: MONTANT
B34: TOTAL RÉGLÉ | D34: =E28+F28+H28 | J34: =IF(F34="","",H34+I34)
B35: RESTE DÛ (crédit fournisseur) | D35: =J28 | J35: =IF(F35="","",H35+I35)
J36: =IF(F36="","",H36+I36)
B37: OBSERVATIONS DU JOUR | J37: =IF(F37="","",H37+I37)
J38: =IF(F38="","",H38+I38)
J39: =IF(F39="","",H39+I39)
J40: =IF(F40="","",H40+I40)
J41: =IF(F41="","",H41+I41)
F42: TOTAL ENCAISSÉ | H42: =SUM(H32:H41) | I42: =SUM(I32:I41) | J42: =SUM(J32:J41)
L44: TOTAL | M44: =SUM(M34:M43)
B46: LES CAISSES ET LE RÉSUMÉ DU SOIR
B47: CAISSE PARADISE | E47: CAISSE ZENATA | H47: CONTRÔLE ET AUTRE CAISSE | L47: RÉSUMÉ DU JOUR
B48: Solde de la veille | D48: ='11'!$D$56 | E48: Solde de la veille | G48: ='11'!$G$56 | H48: Caisse PARADISE du soir | J48: =D56 | L48: Achats fournisseurs du jour | M48: =D28
B49: + Encaissements en espèce | D49: =H42 | E49: + Encaissements du jour | H49: Caisse ZENATA du soir | J49: =G56 | L49: dont réglé en espèce | M49: =E28
B50: + Apports et entrées divers | E50: + Apports et entrées divers | H50: CAISSE TOTALE DU SOIR | J50: =D56+G56 | L50: dont réglé par chèque | M50: =F28
B51: – Achats réglés en espèce | D51: =E28 | E51: – Achats réglés en espèce | H51: Écart total constaté | J51: =D58+G58 | L51: dont réglé par effet | M51: =H28
B52: – Charges fixes du jour | D52: =M20 | E52: – Charges et frais du jour | L52: RESTE DÛ (crédit fournisseur) | M52: =J28
B53: – Salaires et avances | D53: =M30 | E53: – Salaires et avances | H53: AUTRE CAISSE — solde précédent | J53: ='11'!$J$56 | L53: Charges fixes | M53: =M20
B54: – Dépenses travaux et divers | D54: =M44 | E54: – Dépenses travaux et divers | H54: + Entrées du jour | L54: Salaires et avances | M54: =M30
B55: – Versement banque / sorties | E55: – Versement banque / sorties | H55: – Sorties du jour | L55: Dépenses travaux et divers | M55: =M44
B56: SOLDE DU SOIR | D56: =D48+D49+D50-D51-D52-D53-D54-D55 | E56: SOLDE DU SOIR | G56: =G48+G49+G50-G51-G52-G53-G54-G55 | H56: NOUVEAU SOLDE | J56: =J53+J54-J55 | L56: TOTAL DES SORTIES DU JOUR | M56: =M49+M50+M51+M53+M54+M55
B57: Espèces réellement comptées | E57: Espèces réellement comptées | L57: Encaissements du jour | M57: =J42
B58: ÉCART (compté – théorique) | D58: =IF(D57=0,0,D57-D56) | E58: ÉCART (compté – théorique) | G58: =IF(G57=0,0,G57-G56) | L58: CAISSE TOTALE DU SOIR | M58: =D56+G56

Sheet 13
A1: JOURNAL DE CAISSE DU JOUR | H1: PARADISE ALUMINIUM SARL · Casablanca
A2: =IF(13>'RÉCAP DU JOURNAL'!$J$5,"— ce jour n'existe pas dans le mois —",DATE('RÉCAP DU JOURNAL'!$E$4,'RÉCAP DU JOURNAL'!$E$5,13)) | H2: Feuille 13 · aluminium, accessoires et vitrage
A4: À REMPLIR ▸ les achats fournisseurs du jour, les charges, les salaires, les dépenses, les encaissements, puis les espèces comptées le soir dans chaque caisse. Cases jaunes = à vous ; cases blanches = calculées.
B6: ACHATS FOURNISSEURS DU JOUR | L6: CHARGES FIXES DU JOUR
B7: BL N° | C7: FOURNISSEUR | D7: NET À PAYER | E7: ESPÈCE | F7: CHÈQUE | G7: N° DU CHÈQUE | H7: EFFET | I7: N° DE L'EFFET | J7: RESTE À PAYER | L7: POSTE DE CHARGE | M7: MONTANT
J8: =IF(C8="","",D8-E8-F8-H8) | L8: LOYER DU LOCAL
J9: =IF(C9="","",D9-E9-F9-H9) | L9: EAU + ÉLECTRICITÉ
J10: =IF(C10="","",D10-E10-F10-H10) | L10: TÉLÉPHONE & INTERNET
J11: =IF(C11="","",D11-E11-F11-H11) | L11: CNSS
J12: =IF(C12="","",D12-E12-F12-H12) | L12: TVA & IMPÔTS
J13: =IF(C13="","",D13-E13-F13-H13) | L13: ASSURANCES
J14: =IF(C14="","",D14-E14-F14-H14) | L14: COMPTABLE & HONORAIRES
J15: =IF(C15="","",D15-E15-F15-H15) | L15: CARBURANT & VÉHICULE
J16: =IF(C16="","",D16-E16-F16-H16) | L16: TRANSPORT & LIVRAISON
J17: =IF(C17="","",D17-E17-F17-H17) | L17: ENTRETIEN & RÉPARATION
J18: =IF(C18="","",D18-E18-F18-H18) | L18: FOURNITURES DE BUREAU
J19: =IF(C19="","",D19-E19-F19-H19) | L19: AUTRE CHARGE FIXE
J20: =IF(C20="","",D20-E20-F20-H20) | L20: TOTAL | M20: =SUM(M8:M19)
J21: =IF(C21="","",D21-E21-F21-H21)
J22: =IF(C22="","",D22-E22-F22-H22) | L22: SALAIRES ET AVANCES
J23: =IF(C23="","",D23-E23-F23-H23) | L23: PERSONNE | M23: MONTANT
J24: =IF(C24="","",D24-E24-F24-H24) | L24: HOUSSEIN
J25: =IF(C25="","",D25-E25-F25-H25) | L25: AYOUB
J26: =IF(C26="","",D26-E26-F26-H26) | L26: OUVRIER 1
J27: =IF(C27="","",D27-E27-F27-H27) | L27: OUVRIER 2
B28: TOTAL DES ACHATS DU JOUR | D28: =SUM(D8:D27) | E28: =SUM(E8:E27) | F28: =SUM(F8:F27) | H28: =SUM(H8:H27) | J28: =SUM(J8:J27) | L28: AVANCE / PRIME
L29: AUTRE SALAIRE
B30: RÈGLEMENT DES ACHATS | F30: ENCAISSEMENTS DU JOUR | L30: TOTAL | M30: =SUM(M24:M29)
B31: Réglé en espèce | D31: =E28 | F31: CLIENT / ORIGINE | H31: ESPÈCE | I31: CHÈQUE / VIREMENT | J31: TOTAL
B32: Réglé par chèque | D32: =F28 | J32: =IF(F32="","",H32+I32) | L32: DÉPENSES TRAVAUX ET DIVERS
B33: Réglé par effet | D33: =H28 | J33: =IF(F33="","",H33+I33) | L33: DÉSIGNATION | M33: MONTANT
B34: TOTAL RÉGLÉ | D34: =E28+F28+H28 | J34: =IF(F34="","",H34+I34)
B35: RESTE DÛ (crédit fournisseur) | D35: =J28 | J35: =IF(F35="","",H35+I35)
J36: =IF(F36="","",H36+I36)
B37: OBSERVATIONS DU JOUR | J37: =IF(F37="","",H37+I37)
J38: =IF(F38="","",H38+I38)
J39: =IF(F39="","",H39+I39)
J40: =IF(F40="","",H40+I40)
J41: =IF(F41="","",H41+I41)
F42: TOTAL ENCAISSÉ | H42: =SUM(H32:H41) | I42: =SUM(I32:I41) | J42: =SUM(J32:J41)
L44: TOTAL | M44: =SUM(M34:M43)
B46: LES CAISSES ET LE RÉSUMÉ DU SOIR
B47: CAISSE PARADISE | E47: CAISSE ZENATA | H47: CONTRÔLE ET AUTRE CAISSE | L47: RÉSUMÉ DU JOUR
B48: Solde de la veille | D48: ='12'!$D$56 | E48: Solde de la veille | G48: ='12'!$G$56 | H48: Caisse PARADISE du soir | J48: =D56 | L48: Achats fournisseurs du jour | M48: =D28
B49: + Encaissements en espèce | D49: =H42 | E49: + Encaissements du jour | H49: Caisse ZENATA du soir | J49: =G56 | L49: dont réglé en espèce | M49: =E28
B50: + Apports et entrées divers | E50: + Apports et entrées divers | H50: CAISSE TOTALE DU SOIR | J50: =D56+G56 | L50: dont réglé par chèque | M50: =F28
B51: – Achats réglés en espèce | D51: =E28 | E51: – Achats réglés en espèce | H51: Écart total constaté | J51: =D58+G58 | L51: dont réglé par effet | M51: =H28
B52: – Charges fixes du jour | D52: =M20 | E52: – Charges et frais du jour | L52: RESTE DÛ (crédit fournisseur) | M52: =J28
B53: – Salaires et avances | D53: =M30 | E53: – Salaires et avances | H53: AUTRE CAISSE — solde précédent | J53: ='12'!$J$56 | L53: Charges fixes | M53: =M20
B54: – Dépenses travaux et divers | D54: =M44 | E54: – Dépenses travaux et divers | H54: + Entrées du jour | L54: Salaires et avances | M54: =M30
B55: – Versement banque / sorties | E55: – Versement banque / sorties | H55: – Sorties du jour | L55: Dépenses travaux et divers | M55: =M44
B56: SOLDE DU SOIR | D56: =D48+D49+D50-D51-D52-D53-D54-D55 | E56: SOLDE DU SOIR | G56: =G48+G49+G50-G51-G52-G53-G54-G55 | H56: NOUVEAU SOLDE | J56: =J53+J54-J55 | L56: TOTAL DES SORTIES DU JOUR | M56: =M49+M50+M51+M53+M54+M55
B57: Espèces réellement comptées | E57: Espèces réellement comptées | L57: Encaissements du jour | M57: =J42
B58: ÉCART (compté – théorique) | D58: =IF(D57=0,0,D57-D56) | E58: ÉCART (compté – théorique) | G58: =IF(G57=0,0,G57-G56) | L58: CAISSE TOTALE DU SOIR | M58: =D56+G56

Sheet 14
A1: JOURNAL DE CAISSE DU JOUR | H1: PARADISE ALUMINIUM SARL · Casablanca
A2: =IF(14>'RÉCAP DU JOURNAL'!$J$5,"— ce jour n'existe pas dans le mois —",DATE('RÉCAP DU JOURNAL'!$E$4,'RÉCAP DU JOURNAL'!$E$5,14)) | H2: Feuille 14 · aluminium, accessoires et vitrage
A4: À REMPLIR ▸ les achats fournisseurs du jour, les charges, les salaires, les dépenses, les encaissements, puis les espèces comptées le soir dans chaque caisse. Cases jaunes = à vous ; cases blanches = calculées.
B6: ACHATS FOURNISSEURS DU JOUR | L6: CHARGES FIXES DU JOUR
B7: BL N° | C7: FOURNISSEUR | D7: NET À PAYER | E7: ESPÈCE | F7: CHÈQUE | G7: N° DU CHÈQUE | H7: EFFET | I7: N° DE L'EFFET | J7: RESTE À PAYER | L7: POSTE DE CHARGE | M7: MONTANT
J8: =IF(C8="","",D8-E8-F8-H8) | L8: LOYER DU LOCAL
J9: =IF(C9="","",D9-E9-F9-H9) | L9: EAU + ÉLECTRICITÉ
J10: =IF(C10="","",D10-E10-F10-H10) | L10: TÉLÉPHONE & INTERNET
J11: =IF(C11="","",D11-E11-F11-H11) | L11: CNSS
J12: =IF(C12="","",D12-E12-F12-H12) | L12: TVA & IMPÔTS
J13: =IF(C13="","",D13-E13-F13-H13) | L13: ASSURANCES
J14: =IF(C14="","",D14-E14-F14-H14) | L14: COMPTABLE & HONORAIRES
J15: =IF(C15="","",D15-E15-F15-H15) | L15: CARBURANT & VÉHICULE
J16: =IF(C16="","",D16-E16-F16-H16) | L16: TRANSPORT & LIVRAISON
J17: =IF(C17="","",D17-E17-F17-H17) | L17: ENTRETIEN & RÉPARATION
J18: =IF(C18="","",D18-E18-F18-H18) | L18: FOURNITURES DE BUREAU
J19: =IF(C19="","",D19-E19-F19-H19) | L19: AUTRE CHARGE FIXE
J20: =IF(C20="","",D20-E20-F20-H20) | L20: TOTAL | M20: =SUM(M8:M19)
J21: =IF(C21="","",D21-E21-F21-H21)
J22: =IF(C22="","",D22-E22-F22-H22) | L22: SALAIRES ET AVANCES
J23: =IF(C23="","",D23-E23-F23-H23) | L23: PERSONNE | M23: MONTANT
J24: =IF(C24="","",D24-E24-F24-H24) | L24: HOUSSEIN
J25: =IF(C25="","",D25-E25-F25-H25) | L25: AYOUB
J26: =IF(C26="","",D26-E26-F26-H26) | L26: OUVRIER 1
J27: =IF(C27="","",D27-E27-F27-H27) | L27: OUVRIER 2
B28: TOTAL DES ACHATS DU JOUR | D28: =SUM(D8:D27) | E28: =SUM(E8:E27) | F28: =SUM(F8:F27) | H28: =SUM(H8:H27) | J28: =SUM(J8:J27) | L28: AVANCE / PRIME
L29: AUTRE SALAIRE
B30: RÈGLEMENT DES ACHATS | F30: ENCAISSEMENTS DU JOUR | L30: TOTAL | M30: =SUM(M24:M29)
B31: Réglé en espèce | D31: =E28 | F31: CLIENT / ORIGINE | H31: ESPÈCE | I31: CHÈQUE / VIREMENT | J31: TOTAL
B32: Réglé par chèque | D32: =F28 | J32: =IF(F32="","",H32+I32) | L32: DÉPENSES TRAVAUX ET DIVERS
B33: Réglé par effet | D33: =H28 | J33: =IF(F33="","",H33+I33) | L33: DÉSIGNATION | M33: MONTANT
B34: TOTAL RÉGLÉ | D34: =E28+F28+H28 | J34: =IF(F34="","",H34+I34)
B35: RESTE DÛ (crédit fournisseur) | D35: =J28 | J35: =IF(F35="","",H35+I35)
J36: =IF(F36="","",H36+I36)
B37: OBSERVATIONS DU JOUR | J37: =IF(F37="","",H37+I37)
J38: =IF(F38="","",H38+I38)
J39: =IF(F39="","",H39+I39)
J40: =IF(F40="","",H40+I40)
J41: =IF(F41="","",H41+I41)
F42: TOTAL ENCAISSÉ | H42: =SUM(H32:H41) | I42: =SUM(I32:I41) | J42: =SUM(J32:J41)
L44: TOTAL | M44: =SUM(M34:M43)
B46: LES CAISSES ET LE RÉSUMÉ DU SOIR
B47: CAISSE PARADISE | E47: CAISSE ZENATA | H47: CONTRÔLE ET AUTRE CAISSE | L47: RÉSUMÉ DU JOUR
B48: Solde de la veille | D48: ='13'!$D$56 | E48: Solde de la veille | G48: ='13'!$G$56 | H48: Caisse PARADISE du soir | J48: =D56 | L48: Achats fournisseurs du jour | M48: =D28
B49: + Encaissements en espèce | D49: =H42 | E49: + Encaissements du jour | H49: Caisse ZENATA du soir | J49: =G56 | L49: dont réglé en espèce | M49: =E28
B50: + Apports et entrées divers | E50: + Apports et entrées divers | H50: CAISSE TOTALE DU SOIR | J50: =D56+G56 | L50: dont réglé par chèque | M50: =F28
B51: – Achats réglés en espèce | D51: =E28 | E51: – Achats réglés en espèce | H51: Écart total constaté | J51: =D58+G58 | L51: dont réglé par effet | M51: =H28
B52: – Charges fixes du jour | D52: =M20 | E52: – Charges et frais du jour | L52: RESTE DÛ (crédit fournisseur) | M52: =J28
B53: – Salaires et avances | D53: =M30 | E53: – Salaires et avances | H53: AUTRE CAISSE — solde précédent | J53: ='13'!$J$56 | L53: Charges fixes | M53: =M20
B54: – Dépenses travaux et divers | D54: =M44 | E54: – Dépenses travaux et divers | H54: + Entrées du jour | L54: Salaires et avances | M54: =M30
B55: – Versement banque / sorties | E55: – Versement banque / sorties | H55: – Sorties du jour | L55: Dépenses travaux et divers | M55: =M44
B56: SOLDE DU SOIR | D56: =D48+D49+D50-D51-D52-D53-D54-D55 | E56: SOLDE DU SOIR | G56: =G48+G49+G50-G51-G52-G53-G54-G55 | H56: NOUVEAU SOLDE | J56: =J53+J54-J55 | L56: TOTAL DES SORTIES DU JOUR | M56: =M49+M50+M51+M53+M54+M55
B57: Espèces réellement comptées | E57: Espèces réellement comptées | L57: Encaissements du jour | M57: =J42
B58: ÉCART (compté – théorique) | D58: =IF(D57=0,0,D57-D56) | E58: ÉCART (compté – théorique) | G58: =IF(G57=0,0,G57-G56) | L58: CAISSE TOTALE DU SOIR | M58: =D56+G56

Sheet 15
A1: JOURNAL DE CAISSE DU JOUR | H1: PARADISE ALUMINIUM SARL · Casablanca
A2: =IF(15>'RÉCAP DU JOURNAL'!$J$5,"— ce jour n'existe pas dans le mois —",DATE('RÉCAP DU JOURNAL'!$E$4,'RÉCAP DU JOURNAL'!$E$5,15)) | H2: Feuille 15 · aluminium, accessoires et vitrage
A4: À REMPLIR ▸ les achats fournisseurs du jour, les charges, les salaires, les dépenses, les encaissements, puis les espèces comptées le soir dans chaque caisse. Cases jaunes = à vous ; cases blanches = calculées.
B6: ACHATS FOURNISSEURS DU JOUR | L6: CHARGES FIXES DU JOUR
B7: BL N° | C7: FOURNISSEUR | D7: NET À PAYER | E7: ESPÈCE | F7: CHÈQUE | G7: N° DU CHÈQUE | H7: EFFET | I7: N° DE L'EFFET | J7: RESTE À PAYER | L7: POSTE DE CHARGE | M7: MONTANT
J8: =IF(C8="","",D8-E8-F8-H8) | L8: LOYER DU LOCAL
J9: =IF(C9="","",D9-E9-F9-H9) | L9: EAU + ÉLECTRICITÉ
J10: =IF(C10="","",D10-E10-F10-H10) | L10: TÉLÉPHONE & INTERNET
J11: =IF(C11="","",D11-E11-F11-H11) | L11: CNSS
J12: =IF(C12="","",D12-E12-F12-H12) | L12: TVA & IMPÔTS
J13: =IF(C13="","",D13-E13-F13-H13) | L13: ASSURANCES
J14: =IF(C14="","",D14-E14-F14-H14) | L14: COMPTABLE & HONORAIRES
J15: =IF(C15="","",D15-E15-F15-H15) | L15: CARBURANT & VÉHICULE
J16: =IF(C16="","",D16-E16-F16-H16) | L16: TRANSPORT & LIVRAISON
J17: =IF(C17="","",D17-E17-F17-H17) | L17: ENTRETIEN & RÉPARATION
J18: =IF(C18="","",D18-E18-F18-H18) | L18: FOURNITURES DE BUREAU
J19: =IF(C19="","",D19-E19-F19-H19) | L19: AUTRE CHARGE FIXE
J20: =IF(C20="","",D20-E20-F20-H20) | L20: TOTAL | M20: =SUM(M8:M19)
J21: =IF(C21="","",D21-E21-F21-H21)
J22: =IF(C22="","",D22-E22-F22-H22) | L22: SALAIRES ET AVANCES
J23: =IF(C23="","",D23-E23-F23-H23) | L23: PERSONNE | M23: MONTANT
J24: =IF(C24="","",D24-E24-F24-H24) | L24: HOUSSEIN
J25: =IF(C25="","",D25-E25-F25-H25) | L25: AYOUB
J26: =IF(C26="","",D26-E26-F26-H26) | L26: OUVRIER 1
J27: =IF(C27="","",D27-E27-F27-H27) | L27: OUVRIER 2
B28: TOTAL DES ACHATS DU JOUR | D28: =SUM(D8:D27) | E28: =SUM(E8:E27) | F28: =SUM(F8:F27) | H28: =SUM(H8:H27) | J28: =SUM(J8:J27) | L28: AVANCE / PRIME
L29: AUTRE SALAIRE
B30: RÈGLEMENT DES ACHATS | F30: ENCAISSEMENTS DU JOUR | L30: TOTAL | M30: =SUM(M24:M29)
B31: Réglé en espèce | D31: =E28 | F31: CLIENT / ORIGINE | H31: ESPÈCE | I31: CHÈQUE / VIREMENT | J31: TOTAL
B32: Réglé par chèque | D32: =F28 | J32: =IF(F32="","",H32+I32) | L32: DÉPENSES TRAVAUX ET DIVERS
B33: Réglé par effet | D33: =H28 | J33: =IF(F33="","",H33+I33) | L33: DÉSIGNATION | M33: MONTANT
B34: TOTAL RÉGLÉ | D34: =E28+F28+H28 | J34: =IF(F34="","",H34+I34)
B35: RESTE DÛ (crédit fournisseur) | D35: =J28 | J35: =IF(F35="","",H35+I35)
J36: =IF(F36="","",H36+I36)
B37: OBSERVATIONS DU JOUR | J37: =IF(F37="","",H37+I37)
J38: =IF(F38="","",H38+I38)
J39: =IF(F39="","",H39+I39)
J40: =IF(F40="","",H40+I40)
J41: =IF(F41="","",H41+I41)
F42: TOTAL ENCAISSÉ | H42: =SUM(H32:H41) | I42: =SUM(I32:I41) | J42: =SUM(J32:J41)
L44: TOTAL | M44: =SUM(M34:M43)
B46: LES CAISSES ET LE RÉSUMÉ DU SOIR
B47: CAISSE PARADISE | E47: CAISSE ZENATA | H47: CONTRÔLE ET AUTRE CAISSE | L47: RÉSUMÉ DU JOUR
B48: Solde de la veille | D48: ='14'!$D$56 | E48: Solde de la veille | G48: ='14'!$G$56 | H48: Caisse PARADISE du soir | J48: =D56 | L48: Achats fournisseurs du jour | M48: =D28
B49: + Encaissements en espèce | D49: =H42 | E49: + Encaissements du jour | H49: Caisse ZENATA du soir | J49: =G56 | L49: dont réglé en espèce | M49: =E28
B50: + Apports et entrées divers | E50: + Apports et entrées divers | H50: CAISSE TOTALE DU SOIR | J50: =D56+G56 | L50: dont réglé par chèque | M50: =F28
B51: – Achats réglés en espèce | D51: =E28 | E51: – Achats réglés en espèce | H51: Écart total constaté | J51: =D58+G58 | L51: dont réglé par effet | M51: =H28
B52: – Charges fixes du jour | D52: =M20 | E52: – Charges et frais du jour | L52: RESTE DÛ (crédit fournisseur) | M52: =J28
B53: – Salaires et avances | D53: =M30 | E53: – Salaires et avances | H53: AUTRE CAISSE — solde précédent | J53: ='14'!$J$56 | L53: Charges fixes | M53: =M20
B54: – Dépenses travaux et divers | D54: =M44 | E54: – Dépenses travaux et divers | H54: + Entrées du jour | L54: Salaires et avances | M54: =M30
B55: – Versement banque / sorties | E55: – Versement banque / sorties | H55: – Sorties du jour | L55: Dépenses travaux et divers | M55: =M44
B56: SOLDE DU SOIR | D56: =D48+D49+D50-D51-D52-D53-D54-D55 | E56: SOLDE DU SOIR | G56: =G48+G49+G50-G51-G52-G53-G54-G55 | H56: NOUVEAU SOLDE | J56: =J53+J54-J55 | L56: TOTAL DES SORTIES DU JOUR | M56: =M49+M50+M51+M53+M54+M55
B57: Espèces réellement comptées | E57: Espèces réellement comptées | L57: Encaissements du jour | M57: =J42
B58: ÉCART (compté – théorique) | D58: =IF(D57=0,0,D57-D56) | E58: ÉCART (compté – théorique) | G58: =IF(G57=0,0,G57-G56) | L58: CAISSE TOTALE DU SOIR | M58: =D56+G56

Sheet 16
A1: JOURNAL DE CAISSE DU JOUR | H1: PARADISE ALUMINIUM SARL · Casablanca
A2: =IF(16>'RÉCAP DU JOURNAL'!$J$5,"— ce jour n'existe pas dans le mois —",DATE('RÉCAP DU JOURNAL'!$E$4,'RÉCAP DU JOURNAL'!$E$5,16)) | H2: Feuille 16 · aluminium, accessoires et vitrage
A4: À REMPLIR ▸ les achats fournisseurs du jour, les charges, les salaires, les dépenses, les encaissements, puis les espèces comptées le soir dans chaque caisse. Cases jaunes = à vous ; cases blanches = calculées.
B6: ACHATS FOURNISSEURS DU JOUR | L6: CHARGES FIXES DU JOUR
B7: BL N° | C7: FOURNISSEUR | D7: NET À PAYER | E7: ESPÈCE | F7: CHÈQUE | G7: N° DU CHÈQUE | H7: EFFET | I7: N° DE L'EFFET | J7: RESTE À PAYER | L7: POSTE DE CHARGE | M7: MONTANT
J8: =IF(C8="","",D8-E8-F8-H8) | L8: LOYER DU LOCAL
J9: =IF(C9="","",D9-E9-F9-H9) | L9: EAU + ÉLECTRICITÉ
J10: =IF(C10="","",D10-E10-F10-H10) | L10: TÉLÉPHONE & INTERNET
J11: =IF(C11="","",D11-E11-F11-H11) | L11: CNSS
J12: =IF(C12="","",D12-E12-F12-H12) | L12: TVA & IMPÔTS
J13: =IF(C13="","",D13-E13-F13-H13) | L13: ASSURANCES
J14: =IF(C14="","",D14-E14-F14-H14) | L14: COMPTABLE & HONORAIRES
J15: =IF(C15="","",D15-E15-F15-H15) | L15: CARBURANT & VÉHICULE
J16: =IF(C16="","",D16-E16-F16-H16) | L16: TRANSPORT & LIVRAISON
J17: =IF(C17="","",D17-E17-F17-H17) | L17: ENTRETIEN & RÉPARATION
J18: =IF(C18="","",D18-E18-F18-H18) | L18: FOURNITURES DE BUREAU
J19: =IF(C19="","",D19-E19-F19-H19) | L19: AUTRE CHARGE FIXE
J20: =IF(C20="","",D20-E20-F20-H20) | L20: TOTAL | M20: =SUM(M8:M19)
J21: =IF(C21="","",D21-E21-F21-H21)
J22: =IF(C22="","",D22-E22-F22-H22) | L22: SALAIRES ET AVANCES
J23: =IF(C23="","",D23-E23-F23-H23) | L23: PERSONNE | M23: MONTANT
J24: =IF(C24="","",D24-E24-F24-H24) | L24: HOUSSEIN
J25: =IF(C25="","",D25-E25-F25-H25) | L25: AYOUB
J26: =IF(C26="","",D26-E26-F26-H26) | L26: OUVRIER 1
J27: =IF(C27="","",D27-E27-F27-H27) | L27: OUVRIER 2
B28: TOTAL DES ACHATS DU JOUR | D28: =SUM(D8:D27) | E28: =SUM(E8:E27) | F28: =SUM(F8:F27) | H28: =SUM(H8:H27) | J28: =SUM(J8:J27) | L28: AVANCE / PRIME
L29: AUTRE SALAIRE
B30: RÈGLEMENT DES ACHATS | F30: ENCAISSEMENTS DU JOUR | L30: TOTAL | M30: =SUM(M24:M29)
B31: Réglé en espèce | D31: =E28 | F31: CLIENT / ORIGINE | H31: ESPÈCE | I31: CHÈQUE / VIREMENT | J31: TOTAL
B32: Réglé par chèque | D32: =F28 | J32: =IF(F32="","",H32+I32) | L32: DÉPENSES TRAVAUX ET DIVERS
B33: Réglé par effet | D33: =H28 | J33: =IF(F33="","",H33+I33) | L33: DÉSIGNATION | M33: MONTANT
B34: TOTAL RÉGLÉ | D34: =E28+F28+H28 | J34: =IF(F34="","",H34+I34)
B35: RESTE DÛ (crédit fournisseur) | D35: =J28 | J35: =IF(F35="","",H35+I35)
J36: =IF(F36="","",H36+I36)
B37: OBSERVATIONS DU JOUR | J37: =IF(F37="","",H37+I37)
J38: =IF(F38="","",H38+I38)
J39: =IF(F39="","",H39+I39)
J40: =IF(F40="","",H40+I40)
J41: =IF(F41="","",H41+I41)
F42: TOTAL ENCAISSÉ | H42: =SUM(H32:H41) | I42: =SUM(I32:I41) | J42: =SUM(J32:J41)
L44: TOTAL | M44: =SUM(M34:M43)
B46: LES CAISSES ET LE RÉSUMÉ DU SOIR
B47: CAISSE PARADISE | E47: CAISSE ZENATA | H47: CONTRÔLE ET AUTRE CAISSE | L47: RÉSUMÉ DU JOUR
B48: Solde de la veille | D48: ='15'!$D$56 | E48: Solde de la veille | G48: ='15'!$G$56 | H48: Caisse PARADISE du soir | J48: =D56 | L48: Achats fournisseurs du jour | M48: =D28
B49: + Encaissements en espèce | D49: =H42 | E49: + Encaissements du jour | H49: Caisse ZENATA du soir | J49: =G56 | L49: dont réglé en espèce | M49: =E28
B50: + Apports et entrées divers | E50: + Apports et entrées divers | H50: CAISSE TOTALE DU SOIR | J50: =D56+G56 | L50: dont réglé par chèque | M50: =F28
B51: – Achats réglés en espèce | D51: =E28 | E51: – Achats réglés en espèce | H51: Écart total constaté | J51: =D58+G58 | L51: dont réglé par effet | M51: =H28
B52: – Charges fixes du jour | D52: =M20 | E52: – Charges et frais du jour | L52: RESTE DÛ (crédit fournisseur) | M52: =J28
B53: – Salaires et avances | D53: =M30 | E53: – Salaires et avances | H53: AUTRE CAISSE — solde précédent | J53: ='15'!$J$56 | L53: Charges fixes | M53: =M20
B54: – Dépenses travaux et divers | D54: =M44 | E54: – Dépenses travaux et divers | H54: + Entrées du jour | L54: Salaires et avances | M54: =M30
B55: – Versement banque / sorties | E55: – Versement banque / sorties | H55: – Sorties du jour | L55: Dépenses travaux et divers | M55: =M44
B56: SOLDE DU SOIR | D56: =D48+D49+D50-D51-D52-D53-D54-D55 | E56: SOLDE DU SOIR | G56: =G48+G49+G50-G51-G52-G53-G54-G55 | H56: NOUVEAU SOLDE | J56: =J53+J54-J55 | L56: TOTAL DES SORTIES DU JOUR | M56: =M49+M50+M51+M53+M54+M55
B57: Espèces réellement comptées | E57: Espèces réellement comptées | L57: Encaissements du jour | M57: =J42
B58: ÉCART (compté – théorique) | D58: =IF(D57=0,0,D57-D56) | E58: ÉCART (compté – théorique) | G58: =IF(G57=0,0,G57-G56) | L58: CAISSE TOTALE DU SOIR | M58: =D56+G56

Sheet 17
A1: JOURNAL DE CAISSE DU JOUR | H1: PARADISE ALUMINIUM SARL · Casablanca
A2: =IF(17>'RÉCAP DU JOURNAL'!$J$5,"— ce jour n'existe pas dans le mois —",DATE('RÉCAP DU JOURNAL'!$E$4,'RÉCAP DU JOURNAL'!$E$5,17)) | H2: Feuille 17 · aluminium, accessoires et vitrage
A4: À REMPLIR ▸ les achats fournisseurs du jour, les charges, les salaires, les dépenses, les encaissements, puis les espèces comptées le soir dans chaque caisse. Cases jaunes = à vous ; cases blanches = calculées.
B6: ACHATS FOURNISSEURS DU JOUR | L6: CHARGES FIXES DU JOUR
B7: BL N° | C7: FOURNISSEUR | D7: NET À PAYER | E7: ESPÈCE | F7: CHÈQUE | G7: N° DU CHÈQUE | H7: EFFET | I7: N° DE L'EFFET | J7: RESTE À PAYER | L7: POSTE DE CHARGE | M7: MONTANT
J8: =IF(C8="","",D8-E8-F8-H8) | L8: LOYER DU LOCAL
J9: =IF(C9="","",D9-E9-F9-H9) | L9: EAU + ÉLECTRICITÉ
J10: =IF(C10="","",D10-E10-F10-H10) | L10: TÉLÉPHONE & INTERNET
J11: =IF(C11="","",D11-E11-F11-H11) | L11: CNSS
J12: =IF(C12="","",D12-E12-F12-H12) | L12: TVA & IMPÔTS
J13: =IF(C13="","",D13-E13-F13-H13) | L13: ASSURANCES
J14: =IF(C14="","",D14-E14-F14-H14) | L14: COMPTABLE & HONORAIRES
J15: =IF(C15="","",D15-E15-F15-H15) | L15: CARBURANT & VÉHICULE
J16: =IF(C16="","",D16-E16-F16-H16) | L16: TRANSPORT & LIVRAISON
J17: =IF(C17="","",D17-E17-F17-H17) | L17: ENTRETIEN & RÉPARATION
J18: =IF(C18="","",D18-E18-F18-H18) | L18: FOURNITURES DE BUREAU
J19: =IF(C19="","",D19-E19-F19-H19) | L19: AUTRE CHARGE FIXE
J20: =IF(C20="","",D20-E20-F20-H20) | L20: TOTAL | M20: =SUM(M8:M19)
J21: =IF(C21="","",D21-E21-F21-H21)
J22: =IF(C22="","",D22-E22-F22-H22) | L22: SALAIRES ET AVANCES
J23: =IF(C23="","",D23-E23-F23-H23) | L23: PERSONNE | M23: MONTANT
J24: =IF(C24="","",D24-E24-F24-H24) | L24: HOUSSEIN
J25: =IF(C25="","",D25-E25-F25-H25) | L25: AYOUB
J26: =IF(C26="","",D26-E26-F26-H26) | L26: OUVRIER 1
J27: =IF(C27="","",D27-E27-F27-H27) | L27: OUVRIER 2
B28: TOTAL DES ACHATS DU JOUR | D28: =SUM(D8:D27) | E28: =SUM(E8:E27) | F28: =SUM(F8:F27) | H28: =SUM(H8:H27) | J28: =SUM(J8:J27) | L28: AVANCE / PRIME
L29: AUTRE SALAIRE
B30: RÈGLEMENT DES ACHATS | F30: ENCAISSEMENTS DU JOUR | L30: TOTAL | M30: =SUM(M24:M29)
B31: Réglé en espèce | D31: =E28 | F31: CLIENT / ORIGINE | H31: ESPÈCE | I31: CHÈQUE / VIREMENT | J31: TOTAL
B32: Réglé par chèque | D32: =F28 | J32: =IF(F32="","",H32+I32) | L32: DÉPENSES TRAVAUX ET DIVERS
B33: Réglé par effet | D33: =H28 | J33: =IF(F33="","",H33+I33) | L33: DÉSIGNATION | M33: MONTANT
B34: TOTAL RÉGLÉ | D34: =E28+F28+H28 | J34: =IF(F34="","",H34+I34)
B35: RESTE DÛ (crédit fournisseur) | D35: =J28 | J35: =IF(F35="","",H35+I35)
J36: =IF(F36="","",H36+I36)
B37: OBSERVATIONS DU JOUR | J37: =IF(F37="","",H37+I37)
J38: =IF(F38="","",H38+I38)
J39: =IF(F39="","",H39+I39)
J40: =IF(F40="","",H40+I40)
J41: =IF(F41="","",H41+I41)
F42: TOTAL ENCAISSÉ | H42: =SUM(H32:H41) | I42: =SUM(I32:I41) | J42: =SUM(J32:J41)
L44: TOTAL | M44: =SUM(M34:M43)
B46: LES CAISSES ET LE RÉSUMÉ DU SOIR
B47: CAISSE PARADISE | E47: CAISSE ZENATA | H47: CONTRÔLE ET AUTRE CAISSE | L47: RÉSUMÉ DU JOUR
B48: Solde de la veille | D48: ='16'!$D$56 | E48: Solde de la veille | G48: ='16'!$G$56 | H48: Caisse PARADISE du soir | J48: =D56 | L48: Achats fournisseurs du jour | M48: =D28
B49: + Encaissements en espèce | D49: =H42 | E49: + Encaissements du jour | H49: Caisse ZENATA du soir | J49: =G56 | L49: dont réglé en espèce | M49: =E28
B50: + Apports et entrées divers | E50: + Apports et entrées divers | H50: CAISSE TOTALE DU SOIR | J50: =D56+G56 | L50: dont réglé par chèque | M50: =F28
B51: – Achats réglés en espèce | D51: =E28 | E51: – Achats réglés en espèce | H51: Écart total constaté | J51: =D58+G58 | L51: dont réglé par effet | M51: =H28
B52: – Charges fixes du jour | D52: =M20 | E52: – Charges et frais du jour | L52: RESTE DÛ (crédit fournisseur) | M52: =J28
B53: – Salaires et avances | D53: =M30 | E53: – Salaires et avances | H53: AUTRE CAISSE — solde précédent | J53: ='16'!$J$56 | L53: Charges fixes | M53: =M20
B54: – Dépenses travaux et divers | D54: =M44 | E54: – Dépenses travaux et divers | H54: + Entrées du jour | L54: Salaires et avances | M54: =M30
B55: – Versement banque / sorties | E55: – Versement banque / sorties | H55: – Sorties du jour | L55: Dépenses travaux et divers | M55: =M44
B56: SOLDE DU SOIR | D56: =D48+D49+D50-D51-D52-D53-D54-D55 | E56: SOLDE DU SOIR | G56: =G48+G49+G50-G51-G52-G53-G54-G55 | H56: NOUVEAU SOLDE | J56: =J53+J54-J55 | L56: TOTAL DES SORTIES DU JOUR | M56: =M49+M50+M51+M53+M54+M55
B57: Espèces réellement comptées | E57: Espèces réellement comptées | L57: Encaissements du jour | M57: =J42
B58: ÉCART (compté – théorique) | D58: =IF(D57=0,0,D57-D56) | E58: ÉCART (compté – théorique) | G58: =IF(G57=0,0,G57-G56) | L58: CAISSE TOTALE DU SOIR | M58: =D56+G56

Sheet 18
A1: JOURNAL DE CAISSE DU JOUR | H1: PARADISE ALUMINIUM SARL · Casablanca
A2: =IF(18>'RÉCAP DU JOURNAL'!$J$5,"— ce jour n'existe pas dans le mois —",DATE('RÉCAP DU JOURNAL'!$E$4,'RÉCAP DU JOURNAL'!$E$5,18)) | H2: Feuille 18 · aluminium, accessoires et vitrage
A4: À REMPLIR ▸ les achats fournisseurs du jour, les charges, les salaires, les dépenses, les encaissements, puis les espèces comptées le soir dans chaque caisse. Cases jaunes = à vous ; cases blanches = calculées.
B6: ACHATS FOURNISSEURS DU JOUR | L6: CHARGES FIXES DU JOUR
B7: BL N° | C7: FOURNISSEUR | D7: NET À PAYER | E7: ESPÈCE | F7: CHÈQUE | G7: N° DU CHÈQUE | H7: EFFET | I7: N° DE L'EFFET | J7: RESTE À PAYER | L7: POSTE DE CHARGE | M7: MONTANT
J8: =IF(C8="","",D8-E8-F8-H8) | L8: LOYER DU LOCAL
J9: =IF(C9="","",D9-E9-F9-H9) | L9: EAU + ÉLECTRICITÉ
J10: =IF(C10="","",D10-E10-F10-H10) | L10: TÉLÉPHONE & INTERNET
J11: =IF(C11="","",D11-E11-F11-H11) | L11: CNSS
J12: =IF(C12="","",D12-E12-F12-H12) | L12: TVA & IMPÔTS
J13: =IF(C13="","",D13-E13-F13-H13) | L13: ASSURANCES
J14: =IF(C14="","",D14-E14-F14-H14) | L14: COMPTABLE & HONORAIRES
J15: =IF(C15="","",D15-E15-F15-H15) | L15: CARBURANT & VÉHICULE
J16: =IF(C16="","",D16-E16-F16-H16) | L16: TRANSPORT & LIVRAISON
J17: =IF(C17="","",D17-E17-F17-H17) | L17: ENTRETIEN & RÉPARATION
J18: =IF(C18="","",D18-E18-F18-H18) | L18: FOURNITURES DE BUREAU
J19: =IF(C19="","",D19-E19-F19-H19) | L19: AUTRE CHARGE FIXE
J20: =IF(C20="","",D20-E20-F20-H20) | L20: TOTAL | M20: =SUM(M8:M19)
J21: =IF(C21="","",D21-E21-F21-H21)
J22: =IF(C22="","",D22-E22-F22-H22) | L22: SALAIRES ET AVANCES
J23: =IF(C23="","",D23-E23-F23-H23) | L23: PERSONNE | M23: MONTANT
J24: =IF(C24="","",D24-E24-F24-H24) | L24: HOUSSEIN
J25: =IF(C25="","",D25-E25-F25-H25) | L25: AYOUB
J26: =IF(C26="","",D26-E26-F26-H26) | L26: OUVRIER 1
J27: =IF(C27="","",D27-E27-F27-H27) | L27: OUVRIER 2
B28: TOTAL DES ACHATS DU JOUR | D28: =SUM(D8:D27) | E28: =SUM(E8:E27) | F28: =SUM(F8:F27) | H28: =SUM(H8:H27) | J28: =SUM(J8:J27) | L28: AVANCE / PRIME
L29: AUTRE SALAIRE
B30: RÈGLEMENT DES ACHATS | F30: ENCAISSEMENTS DU JOUR | L30: TOTAL | M30: =SUM(M24:M29)
B31: Réglé en espèce | D31: =E28 | F31: CLIENT / ORIGINE | H31: ESPÈCE | I31: CHÈQUE / VIREMENT | J31: TOTAL
B32: Réglé par chèque | D32: =F28 | J32: =IF(F32="","",H32+I32) | L32: DÉPENSES TRAVAUX ET DIVERS
B33: Réglé par effet | D33: =H28 | J33: =IF(F33="","",H33+I33) | L33: DÉSIGNATION | M33: MONTANT
B34: TOTAL RÉGLÉ | D34: =E28+F28+H28 | J34: =IF(F34="","",H34+I34)
B35: RESTE DÛ (crédit fournisseur) | D35: =J28 | J35: =IF(F35="","",H35+I35)
J36: =IF(F36="","",H36+I36)
B37: OBSERVATIONS DU JOUR | J37: =IF(F37="","",H37+I37)
J38: =IF(F38="","",H38+I38)
J39: =IF(F39="","",H39+I39)
J40: =IF(F40="","",H40+I40)
J41: =IF(F41="","",H41+I41)
F42: TOTAL ENCAISSÉ | H42: =SUM(H32:H41) | I42: =SUM(I32:I41) | J42: =SUM(J32:J41)
L44: TOTAL | M44: =SUM(M34:M43)
B46: LES CAISSES ET LE RÉSUMÉ DU SOIR
B47: CAISSE PARADISE | E47: CAISSE ZENATA | H47: CONTRÔLE ET AUTRE CAISSE | L47: RÉSUMÉ DU JOUR
B48: Solde de la veille | D48: ='17'!$D$56 | E48: Solde de la veille | G48: ='17'!$G$56 | H48: Caisse PARADISE du soir | J48: =D56 | L48: Achats fournisseurs du jour | M48: =D28
B49: + Encaissements en espèce | D49: =H42 | E49: + Encaissements du jour | H49: Caisse ZENATA du soir | J49: =G56 | L49: dont réglé en espèce | M49: =E28
B50: + Apports et entrées divers | E50: + Apports et entrées divers | H50: CAISSE TOTALE DU SOIR | J50: =D56+G56 | L50: dont réglé par chèque | M50: =F28
B51: – Achats réglés en espèce | D51: =E28 | E51: – Achats réglés en espèce | H51: Écart total constaté | J51: =D58+G58 | L51: dont réglé par effet | M51: =H28
B52: – Charges fixes du jour | D52: =M20 | E52: – Charges et frais du jour | L52: RESTE DÛ (crédit fournisseur) | M52: =J28
B53: – Salaires et avances | D53: =M30 | E53: – Salaires et avances | H53: AUTRE CAISSE — solde précédent | J53: ='17'!$J$56 | L53: Charges fixes | M53: =M20
B54: – Dépenses travaux et divers | D54: =M44 | E54: – Dépenses travaux et divers | H54: + Entrées du jour | L54: Salaires et avances | M54: =M30
B55: – Versement banque / sorties | E55: – Versement banque / sorties | H55: – Sorties du jour | L55: Dépenses travaux et divers | M55: =M44
B56: SOLDE DU SOIR | D56: =D48+D49+D50-D51-D52-D53-D54-D55 | E56: SOLDE DU SOIR | G56: =G48+G49+G50-G51-G52-G53-G54-G55 | H56: NOUVEAU SOLDE | J56: =J53+J54-J55 | L56: TOTAL DES SORTIES DU JOUR | M56: =M49+M50+M51+M53+M54+M55
B57: Espèces réellement comptées | E57: Espèces réellement comptées | L57: Encaissements du jour | M57: =J42
B58: ÉCART (compté – théorique) | D58: =IF(D57=0,0,D57-D56) | E58: ÉCART (compté – théorique) | G58: =IF(G57=0,0,G57-G56) | L58: CAISSE TOTALE DU SOIR | M58: =D56+G56

Sheet 19
A1: JOURNAL DE CAISSE DU JOUR | H1: PARADISE ALUMINIUM SARL · Casablanca
A2: =IF(19>'RÉCAP DU JOURNAL'!$J$5,"— ce jour n'existe pas dans le mois —",DATE('RÉCAP DU JOURNAL'!$E$4,'RÉCAP DU JOURNAL'!$E$5,19)) | H2: Feuille 19 · aluminium, accessoires et vitrage
A4: À REMPLIR ▸ les achats fournisseurs du jour, les charges, les salaires, les dépenses, les encaissements, puis les espèces comptées le soir dans chaque caisse. Cases jaunes = à vous ; cases blanches = calculées.
B6: ACHATS FOURNISSEURS DU JOUR | L6: CHARGES FIXES DU JOUR
B7: BL N° | C7: FOURNISSEUR | D7: NET À PAYER | E7: ESPÈCE | F7: CHÈQUE | G7: N° DU CHÈQUE | H7: EFFET | I7: N° DE L'EFFET | J7: RESTE À PAYER | L7: POSTE DE CHARGE | M7: MONTANT
J8: =IF(C8="","",D8-E8-F8-H8) | L8: LOYER DU LOCAL
J9: =IF(C9="","",D9-E9-F9-H9) | L9: EAU + ÉLECTRICITÉ
J10: =IF(C10="","",D10-E10-F10-H10) | L10: TÉLÉPHONE & INTERNET
J11: =IF(C11="","",D11-E11-F11-H11) | L11: CNSS
J12: =IF(C12="","",D12-E12-F12-H12) | L12: TVA & IMPÔTS
J13: =IF(C13="","",D13-E13-F13-H13) | L13: ASSURANCES
J14: =IF(C14="","",D14-E14-F14-H14) | L14: COMPTABLE & HONORAIRES
J15: =IF(C15="","",D15-E15-F15-H15) | L15: CARBURANT & VÉHICULE
J16: =IF(C16="","",D16-E16-F16-H16) | L16: TRANSPORT & LIVRAISON
J17: =IF(C17="","",D17-E17-F17-H17) | L17: ENTRETIEN & RÉPARATION
J18: =IF(C18="","",D18-E18-F18-H18) | L18: FOURNITURES DE BUREAU
J19: =IF(C19="","",D19-E19-F19-H19) | L19: AUTRE CHARGE FIXE
J20: =IF(C20="","",D20-E20-F20-H20) | L20: TOTAL | M20: =SUM(M8:M19)
J21: =IF(C21="","",D21-E21-F21-H21)
J22: =IF(C22="","",D22-E22-F22-H22) | L22: SALAIRES ET AVANCES
J23: =IF(C23="","",D23-E23-F23-H23) | L23: PERSONNE | M23: MONTANT
J24: =IF(C24="","",D24-E24-F24-H24) | L24: HOUSSEIN
J25: =IF(C25="","",D25-E25-F25-H25) | L25: AYOUB
J26: =IF(C26="","",D26-E26-F26-H26) | L26: OUVRIER 1
J27: =IF(C27="","",D27-E27-F27-H27) | L27: OUVRIER 2
B28: TOTAL DES ACHATS DU JOUR | D28: =SUM(D8:D27) | E28: =SUM(E8:E27) | F28: =SUM(F8:F27) | H28: =SUM(H8:H27) | J28: =SUM(J8:J27) | L28: AVANCE / PRIME
L29: AUTRE SALAIRE
B30: RÈGLEMENT DES ACHATS | F30: ENCAISSEMENTS DU JOUR | L30: TOTAL | M30: =SUM(M24:M29)
B31: Réglé en espèce | D31: =E28 | F31: CLIENT / ORIGINE | H31: ESPÈCE | I31: CHÈQUE / VIREMENT | J31: TOTAL
B32: Réglé par chèque | D32: =F28 | J32: =IF(F32="","",H32+I32) | L32: DÉPENSES TRAVAUX ET DIVERS
B33: Réglé par effet | D33: =H28 | J33: =IF(F33="","",H33+I33) | L33: DÉSIGNATION | M33: MONTANT
B34: TOTAL RÉGLÉ | D34: =E28+F28+H28 | J34: =IF(F34="","",H34+I34)
B35: RESTE DÛ (crédit fournisseur) | D35: =J28 | J35: =IF(F35="","",H35+I35)
J36: =IF(F36="","",H36+I36)
B37: OBSERVATIONS DU JOUR | J37: =IF(F37="","",H37+I37)
J38: =IF(F38="","",H38+I38)
J39: =IF(F39="","",H39+I39)
J40: =IF(F40="","",H40+I40)
J41: =IF(F41="","",H41+I41)
F42: TOTAL ENCAISSÉ | H42: =SUM(H32:H41) | I42: =SUM(I32:I41) | J42: =SUM(J32:J41)
L44: TOTAL | M44: =SUM(M34:M43)
B46: LES CAISSES ET LE RÉSUMÉ DU SOIR
B47: CAISSE PARADISE | E47: CAISSE ZENATA | H47: CONTRÔLE ET AUTRE CAISSE | L47: RÉSUMÉ DU JOUR
B48: Solde de la veille | D48: ='18'!$D$56 | E48: Solde de la veille | G48: ='18'!$G$56 | H48: Caisse PARADISE du soir | J48: =D56 | L48: Achats fournisseurs du jour | M48: =D28
B49: + Encaissements en espèce | D49: =H42 | E49: + Encaissements du jour | H49: Caisse ZENATA du soir | J49: =G56 | L49: dont réglé en espèce | M49: =E28
B50: + Apports et entrées divers | E50: + Apports et entrées divers | H50: CAISSE TOTALE DU SOIR | J50: =D56+G56 | L50: dont réglé par chèque | M50: =F28
B51: – Achats réglés en espèce | D51: =E28 | E51: – Achats réglés en espèce | H51: Écart total constaté | J51: =D58+G58 | L51: dont réglé par effet | M51: =H28
B52: – Charges fixes du jour | D52: =M20 | E52: – Charges et frais du jour | L52: RESTE DÛ (crédit fournisseur) | M52: =J28
B53: – Salaires et avances | D53: =M30 | E53: – Salaires et avances | H53: AUTRE CAISSE — solde précédent | J53: ='18'!$J$56 | L53: Charges fixes | M53: =M20
B54: – Dépenses travaux et divers | D54: =M44 | E54: – Dépenses travaux et divers | H54: + Entrées du jour | L54: Salaires et avances | M54: =M30
B55: – Versement banque / sorties | E55: – Versement banque / sorties | H55: – Sorties du jour | L55: Dépenses travaux et divers | M55: =M44
B56: SOLDE DU SOIR | D56: =D48+D49+D50-D51-D52-D53-D54-D55 | E56: SOLDE DU SOIR | G56: =G48+G49+G50-G51-G52-G53-G54-G55 | H56: NOUVEAU SOLDE | J56: =J53+J54-J55 | L56: TOTAL DES SORTIES DU JOUR | M56: =M49+M50+M51+M53+M54+M55
B57: Espèces réellement comptées | E57: Espèces réellement comptées | L57: Encaissements du jour | M57: =J42
B58: ÉCART (compté – théorique) | D58: =IF(D57=0,0,D57-D56) | E58: ÉCART (compté – théorique) | G58: =IF(G57=0,0,G57-G56) | L58: CAISSE TOTALE DU SOIR | M58: =D56+G56

Sheet 20
A1: JOURNAL DE CAISSE DU JOUR | H1: PARADISE ALUMINIUM SARL · Casablanca
A2: =IF(20>'RÉCAP DU JOURNAL'!$J$5,"— ce jour n'existe pas dans le mois —",DATE('RÉCAP DU JOURNAL'!$E$4,'RÉCAP DU JOURNAL'!$E$5,20)) | H2: Feuille 20 · aluminium, accessoires et vitrage
A4: À REMPLIR ▸ les achats fournisseurs du jour, les charges, les salaires, les dépenses, les encaissements, puis les espèces comptées le soir dans chaque caisse. Cases jaunes = à vous ; cases blanches = calculées.
B6: ACHATS FOURNISSEURS DU JOUR | L6: CHARGES FIXES DU JOUR
B7: BL N° | C7: FOURNISSEUR | D7: NET À PAYER | E7: ESPÈCE | F7: CHÈQUE | G7: N° DU CHÈQUE | H7: EFFET | I7: N° DE L'EFFET | J7: RESTE À PAYER | L7: POSTE DE CHARGE | M7: MONTANT
J8: =IF(C8="","",D8-E8-F8-H8) | L8: LOYER DU LOCAL
J9: =IF(C9="","",D9-E9-F9-H9) | L9: EAU + ÉLECTRICITÉ
J10: =IF(C10="","",D10-E10-F10-H10) | L10: TÉLÉPHONE & INTERNET
J11: =IF(C11="","",D11-E11-F11-H11) | L11: CNSS
J12: =IF(C12="","",D12-E12-F12-H12) | L12: TVA & IMPÔTS
J13: =IF(C13="","",D13-E13-F13-H13) | L13: ASSURANCES
J14: =IF(C14="","",D14-E14-F14-H14) | L14: COMPTABLE & HONORAIRES
J15: =IF(C15="","",D15-E15-F15-H15) | L15: CARBURANT & VÉHICULE
J16: =IF(C16="","",D16-E16-F16-H16) | L16: TRANSPORT & LIVRAISON
J17: =IF(C17="","",D17-E17-F17-H17) | L17: ENTRETIEN & RÉPARATION
J18: =IF(C18="","",D18-E18-F18-H18) | L18: FOURNITURES DE BUREAU
J19: =IF(C19="","",D19-E19-F19-H19) | L19: AUTRE CHARGE FIXE
J20: =IF(C20="","",D20-E20-F20-H20) | L20: TOTAL | M20: =SUM(M8:M19)
J21: =IF(C21="","",D21-E21-F21-H21)
J22: =IF(C22="","",D22-E22-F22-H22) | L22: SALAIRES ET AVANCES
J23: =IF(C23="","",D23-E23-F23-H23) | L23: PERSONNE | M23: MONTANT
J24: =IF(C24="","",D24-E24-F24-H24) | L24: HOUSSEIN
J25: =IF(C25="","",D25-E25-F25-H25) | L25: AYOUB
J26: =IF(C26="","",D26-E26-F26-H26) | L26: OUVRIER 1
J27: =IF(C27="","",D27-E27-F27-H27) | L27: OUVRIER 2
B28: TOTAL DES ACHATS DU JOUR | D28: =SUM(D8:D27) | E28: =SUM(E8:E27) | F28: =SUM(F8:F27) | H28: =SUM(H8:H27) | J28: =SUM(J8:J27) | L28: AVANCE / PRIME
L29: AUTRE SALAIRE
B30: RÈGLEMENT DES ACHATS | F30: ENCAISSEMENTS DU JOUR | L30: TOTAL | M30: =SUM(M24:M29)
B31: Réglé en espèce | D31: =E28 | F31: CLIENT / ORIGINE | H31: ESPÈCE | I31: CHÈQUE / VIREMENT | J31: TOTAL
B32: Réglé par chèque | D32: =F28 | J32: =IF(F32="","",H32+I32) | L32: DÉPENSES TRAVAUX ET DIVERS
B33: Réglé par effet | D33: =H28 | J33: =IF(F33="","",H33+I33) | L33: DÉSIGNATION | M33: MONTANT
B34: TOTAL RÉGLÉ | D34: =E28+F28+H28 | J34: =IF(F34="","",H34+I34)
B35: RESTE DÛ (crédit fournisseur) | D35: =J28 | J35: =IF(F35="","",H35+I35)
J36: =IF(F36="","",H36+I36)
B37: OBSERVATIONS DU JOUR | J37: =IF(F37="","",H37+I37)
J38: =IF(F38="","",H38+I38)
J39: =IF(F39="","",H39+I39)
J40: =IF(F40="","",H40+I40)
J41: =IF(F41="","",H41+I41)
F42: TOTAL ENCAISSÉ | H42: =SUM(H32:H41) | I42: =SUM(I32:I41) | J42: =SUM(J32:J41)
L44: TOTAL | M44: =SUM(M34:M43)
B46: LES CAISSES ET LE RÉSUMÉ DU SOIR
B47: CAISSE PARADISE | E47: CAISSE ZENATA | H47: CONTRÔLE ET AUTRE CAISSE | L47: RÉSUMÉ DU JOUR
B48: Solde de la veille | D48: ='19'!$D$56 | E48: Solde de la veille | G48: ='19'!$G$56 | H48: Caisse PARADISE du soir | J48: =D56 | L48: Achats fournisseurs du jour | M48: =D28
B49: + Encaissements en espèce | D49: =H42 | E49: + Encaissements du jour | H49: Caisse ZENATA du soir | J49: =G56 | L49: dont réglé en espèce | M49: =E28
B50: + Apports et entrées divers | E50: + Apports et entrées divers | H50: CAISSE TOTALE DU SOIR | J50: =D56+G56 | L50: dont réglé par chèque | M50: =F28
B51: – Achats réglés en espèce | D51: =E28 | E51: – Achats réglés en espèce | H51: Écart total constaté | J51: =D58+G58 | L51: dont réglé par effet | M51: =H28
B52: – Charges fixes du jour | D52: =M20 | E52: – Charges et frais du jour | L52: RESTE DÛ (crédit fournisseur) | M52: =J28
B53: – Salaires et avances | D53: =M30 | E53: – Salaires et avances | H53: AUTRE CAISSE — solde précédent | J53: ='19'!$J$56 | L53: Charges fixes | M53: =M20
B54: – Dépenses travaux et divers | D54: =M44 | E54: – Dépenses travaux et divers | H54: + Entrées du jour | L54: Salaires et avances | M54: =M30
B55: – Versement banque / sorties | E55: – Versement banque / sorties | H55: – Sorties du jour | L55: Dépenses travaux et divers | M55: =M44
B56: SOLDE DU SOIR | D56: =D48+D49+D50-D51-D52-D53-D54-D55 | E56: SOLDE DU SOIR | G56: =G48+G49+G50-G51-G52-G53-G54-G55 | H56: NOUVEAU SOLDE | J56: =J53+J54-J55 | L56: TOTAL DES SORTIES DU JOUR | M56: =M49+M50+M51+M53+M54+M55
B57: Espèces réellement comptées | E57: Espèces réellement comptées | L57: Encaissements du jour | M57: =J42
B58: ÉCART (compté – théorique) | D58: =IF(D57=0,0,D57-D56) | E58: ÉCART (compté – théorique) | G58: =IF(G57=0,0,G57-G56) | L58: CAISSE TOTALE DU SOIR | M58: =D56+G56

Sheet 21
A1: JOURNAL DE CAISSE DU JOUR | H1: PARADISE ALUMINIUM SARL · Casablanca
A2: =IF(21>'RÉCAP DU JOURNAL'!$J$5,"— ce jour n'existe pas dans le mois —",DATE('RÉCAP DU JOURNAL'!$E$4,'RÉCAP DU JOURNAL'!$E$5,21)) | H2: Feuille 21 · aluminium, accessoires et vitrage
A4: À REMPLIR ▸ les achats fournisseurs du jour, les charges, les salaires, les dépenses, les encaissements, puis les espèces comptées le soir dans chaque caisse. Cases jaunes = à vous ; cases blanches = calculées.
B6: ACHATS FOURNISSEURS DU JOUR | L6: CHARGES FIXES DU JOUR
B7: BL N° | C7: FOURNISSEUR | D7: NET À PAYER | E7: ESPÈCE | F7: CHÈQUE | G7: N° DU CHÈQUE | H7: EFFET | I7: N° DE L'EFFET | J7: RESTE À PAYER | L7: POSTE DE CHARGE | M7: MONTANT
J8: =IF(C8="","",D8-E8-F8-H8) | L8: LOYER DU LOCAL
J9: =IF(C9="","",D9-E9-F9-H9) | L9: EAU + ÉLECTRICITÉ
J10: =IF(C10="","",D10-E10-F10-H10) | L10: TÉLÉPHONE & INTERNET
J11: =IF(C11="","",D11-E11-F11-H11) | L11: CNSS
J12: =IF(C12="","",D12-E12-F12-H12) | L12: TVA & IMPÔTS
J13: =IF(C13="","",D13-E13-F13-H13) | L13: ASSURANCES
J14: =IF(C14="","",D14-E14-F14-H14) | L14: COMPTABLE & HONORAIRES
J15: =IF(C15="","",D15-E15-F15-H15) | L15: CARBURANT & VÉHICULE
J16: =IF(C16="","",D16-E16-F16-H16) | L16: TRANSPORT & LIVRAISON
J17: =IF(C17="","",D17-E17-F17-H17) | L17: ENTRETIEN & RÉPARATION
J18: =IF(C18="","",D18-E18-F18-H18) | L18: FOURNITURES DE BUREAU
J19: =IF(C19="","",D19-E19-F19-H19) | L19: AUTRE CHARGE FIXE
J20: =IF(C20="","",D20-E20-F20-H20) | L20: TOTAL | M20: =SUM(M8:M19)
J21: =IF(C21="","",D21-E21-F21-H21)
J22: =IF(C22="","",D22-E22-F22-H22) | L22: SALAIRES ET AVANCES
J23: =IF(C23="","",D23-E23-F23-H23) | L23: PERSONNE | M23: MONTANT
J24: =IF(C24="","",D24-E24-F24-H24) | L24: HOUSSEIN
J25: =IF(C25="","",D25-E25-F25-H25) | L25: AYOUB
J26: =IF(C26="","",D26-E26-F26-H26) | L26: OUVRIER 1
J27: =IF(C27="","",D27-E27-F27-H27) | L27: OUVRIER 2
B28: TOTAL DES ACHATS DU JOUR | D28: =SUM(D8:D27) | E28: =SUM(E8:E27) | F28: =SUM(F8:F27) | H28: =SUM(H8:H27) | J28: =SUM(J8:J27) | L28: AVANCE / PRIME
L29: AUTRE SALAIRE
B30: RÈGLEMENT DES ACHATS | F30: ENCAISSEMENTS DU JOUR | L30: TOTAL | M30: =SUM(M24:M29)
B31: Réglé en espèce | D31: =E28 | F31: CLIENT / ORIGINE | H31: ESPÈCE | I31: CHÈQUE / VIREMENT | J31: TOTAL
B32: Réglé par chèque | D32: =F28 | J32: =IF(F32="","",H32+I32) | L32: DÉPENSES TRAVAUX ET DIVERS
B33: Réglé par effet | D33: =H28 | J33: =IF(F33="","",H33+I33) | L33: DÉSIGNATION | M33: MONTANT
B34: TOTAL RÉGLÉ | D34: =E28+F28+H28 | J34: =IF(F34="","",H34+I34)
B35: RESTE DÛ (crédit fournisseur) | D35: =J28 | J35: =IF(F35="","",H35+I35)
J36: =IF(F36="","",H36+I36)
B37: OBSERVATIONS DU JOUR | J37: =IF(F37="","",H37+I37)
J38: =IF(F38="","",H38+I38)
J39: =IF(F39="","",H39+I39)
J40: =IF(F40="","",H40+I40)
J41: =IF(F41="","",H41+I41)
F42: TOTAL ENCAISSÉ | H42: =SUM(H32:H41) | I42: =SUM(I32:I41) | J42: =SUM(J32:J41)
L44: TOTAL | M44: =SUM(M34:M43)
B46: LES CAISSES ET LE RÉSUMÉ DU SOIR
B47: CAISSE PARADISE | E47: CAISSE ZENATA | H47: CONTRÔLE ET AUTRE CAISSE | L47: RÉSUMÉ DU JOUR
B48: Solde de la veille | D48: ='20'!$D$56 | E48: Solde de la veille | G48: ='20'!$G$56 | H48: Caisse PARADISE du soir | J48: =D56 | L48: Achats fournisseurs du jour | M48: =D28
B49: + Encaissements en espèce | D49: =H42 | E49: + Encaissements du jour | H49: Caisse ZENATA du soir | J49: =G56 | L49: dont réglé en espèce | M49: =E28
B50: + Apports et entrées divers | E50: + Apports et entrées divers | H50: CAISSE TOTALE DU SOIR | J50: =D56+G56 | L50: dont réglé par chèque | M50: =F28
B51: – Achats réglés en espèce | D51: =E28 | E51: – Achats réglés en espèce | H51: Écart total constaté | J51: =D58+G58 | L51: dont réglé par effet | M51: =H28
B52: – Charges fixes du jour | D52: =M20 | E52: – Charges et frais du jour | L52: RESTE DÛ (crédit fournisseur) | M52: =J28
B53: – Salaires et avances | D53: =M30 | E53: – Salaires et avances | H53: AUTRE CAISSE — solde précédent | J53: ='20'!$J$56 | L53: Charges fixes | M53: =M20
B54: – Dépenses travaux et divers | D54: =M44 | E54: – Dépenses travaux et divers | H54: + Entrées du jour | L54: Salaires et avances | M54: =M30
B55: – Versement banque / sorties | E55: – Versement banque / sorties | H55: – Sorties du jour | L55: Dépenses travaux et divers | M55: =M44
B56: SOLDE DU SOIR | D56: =D48+D49+D50-D51-D52-D53-D54-D55 | E56: SOLDE DU SOIR | G56: =G48+G49+G50-G51-G52-G53-G54-G55 | H56: NOUVEAU SOLDE | J56: =J53+J54-J55 | L56: TOTAL DES SORTIES DU JOUR | M56: =M49+M50+M51+M53+M54+M55
B57: Espèces réellement comptées | E57: Espèces réellement comptées | L57: Encaissements du jour | M57: =J42
B58: ÉCART (compté – théorique) | D58: =IF(D57=0,0,D57-D56) | E58: ÉCART (compté – théorique) | G58: =IF(G57=0,0,G57-G56) | L58: CAISSE TOTALE DU SOIR | M58: =D56+G56

Sheet 22
A1: JOURNAL DE CAISSE DU JOUR | H1: PARADISE ALUMINIUM SARL · Casablanca
A2: =IF(22>'RÉCAP DU JOURNAL'!$J$5,"— ce jour n'existe pas dans le mois —",DATE('RÉCAP DU JOURNAL'!$E$4,'RÉCAP DU JOURNAL'!$E$5,22)) | H2: Feuille 22 · aluminium, accessoires et vitrage
A4: À REMPLIR ▸ les achats fournisseurs du jour, les charges, les salaires, les dépenses, les encaissements, puis les espèces comptées le soir dans chaque caisse. Cases jaunes = à vous ; cases blanches = calculées.
B6: ACHATS FOURNISSEURS DU JOUR | L6: CHARGES FIXES DU JOUR
B7: BL N° | C7: FOURNISSEUR | D7: NET À PAYER | E7: ESPÈCE | F7: CHÈQUE | G7: N° DU CHÈQUE | H7: EFFET | I7: N° DE L'EFFET | J7: RESTE À PAYER | L7: POSTE DE CHARGE | M7: MONTANT
J8: =IF(C8="","",D8-E8-F8-H8) | L8: LOYER DU LOCAL
J9: =IF(C9="","",D9-E9-F9-H9) | L9: EAU + ÉLECTRICITÉ
J10: =IF(C10="","",D10-E10-F10-H10) | L10: TÉLÉPHONE & INTERNET
J11: =IF(C11="","",D11-E11-F11-H11) | L11: CNSS
J12: =IF(C12="","",D12-E12-F12-H12) | L12: TVA & IMPÔTS
J13: =IF(C13="","",D13-E13-F13-H13) | L13: ASSURANCES
J14: =IF(C14="","",D14-E14-F14-H14) | L14: COMPTABLE & HONORAIRES
J15: =IF(C15="","",D15-E15-F15-H15) | L15: CARBURANT & VÉHICULE
J16: =IF(C16="","",D16-E16-F16-H16) | L16: TRANSPORT & LIVRAISON
J17: =IF(C17="","",D17-E17-F17-H17) | L17: ENTRETIEN & RÉPARATION
J18: =IF(C18="","",D18-E18-F18-H18) | L18: FOURNITURES DE BUREAU
J19: =IF(C19="","",D19-E19-F19-H19) | L19: AUTRE CHARGE FIXE
J20: =IF(C20="","",D20-E20-F20-H20) | L20: TOTAL | M20: =SUM(M8:M19)
J21: =IF(C21="","",D21-E21-F21-H21)
J22: =IF(C22="","",D22-E22-F22-H22) | L22: SALAIRES ET AVANCES
J23: =IF(C23="","",D23-E23-F23-H23) | L23: PERSONNE | M23: MONTANT
J24: =IF(C24="","",D24-E24-F24-H24) | L24: HOUSSEIN
J25: =IF(C25="","",D25-E25-F25-H25) | L25: AYOUB
J26: =IF(C26="","",D26-E26-F26-H26) | L26: OUVRIER 1
J27: =IF(C27="","",D27-E27-F27-H27) | L27: OUVRIER 2
B28: TOTAL DES ACHATS DU JOUR | D28: =SUM(D8:D27) | E28: =SUM(E8:E27) | F28: =SUM(F8:F27) | H28: =SUM(H8:H27) | J28: =SUM(J8:J27) | L28: AVANCE / PRIME
L29: AUTRE SALAIRE
B30: RÈGLEMENT DES ACHATS | F30: ENCAISSEMENTS DU JOUR | L30: TOTAL | M30: =SUM(M24:M29)
B31: Réglé en espèce | D31: =E28 | F31: CLIENT / ORIGINE | H31: ESPÈCE | I31: CHÈQUE / VIREMENT | J31: TOTAL
B32: Réglé par chèque | D32: =F28 | J32: =IF(F32="","",H32+I32) | L32: DÉPENSES TRAVAUX ET DIVERS
B33: Réglé par effet | D33: =H28 | J33: =IF(F33="","",H33+I33) | L33: DÉSIGNATION | M33: MONTANT
B34: TOTAL RÉGLÉ | D34: =E28+F28+H28 | J34: =IF(F34="","",H34+I34)
B35: RESTE DÛ (crédit fournisseur) | D35: =J28 | J35: =IF(F35="","",H35+I35)
J36: =IF(F36="","",H36+I36)
B37: OBSERVATIONS DU JOUR | J37: =IF(F37="","",H37+I37)
J38: =IF(F38="","",H38+I38)
J39: =IF(F39="","",H39+I39)
J40: =IF(F40="","",H40+I40)
J41: =IF(F41="","",H41+I41)
F42: TOTAL ENCAISSÉ | H42: =SUM(H32:H41) | I42: =SUM(I32:I41) | J42: =SUM(J32:J41)
L44: TOTAL | M44: =SUM(M34:M43)
B46: LES CAISSES ET LE RÉSUMÉ DU SOIR
B47: CAISSE PARADISE | E47: CAISSE ZENATA | H47: CONTRÔLE ET AUTRE CAISSE | L47: RÉSUMÉ DU JOUR
B48: Solde de la veille | D48: ='21'!$D$56 | E48: Solde de la veille | G48: ='21'!$G$56 | H48: Caisse PARADISE du soir | J48: =D56 | L48: Achats fournisseurs du jour | M48: =D28
B49: + Encaissements en espèce | D49: =H42 | E49: + Encaissements du jour | H49: Caisse ZENATA du soir | J49: =G56 | L49: dont réglé en espèce | M49: =E28
B50: + Apports et entrées divers | E50: + Apports et entrées divers | H50: CAISSE TOTALE DU SOIR | J50: =D56+G56 | L50: dont réglé par chèque | M50: =F28
B51: – Achats réglés en espèce | D51: =E28 | E51: – Achats réglés en espèce | H51: Écart total constaté | J51: =D58+G58 | L51: dont réglé par effet | M51: =H28
B52: – Charges fixes du jour | D52: =M20 | E52: – Charges et frais du jour | L52: RESTE DÛ (crédit fournisseur) | M52: =J28
B53: – Salaires et avances | D53: =M30 | E53: – Salaires et avances | H53: AUTRE CAISSE — solde précédent | J53: ='21'!$J$56 | L53: Charges fixes | M53: =M20
B54: – Dépenses travaux et divers | D54: =M44 | E54: – Dépenses travaux et divers | H54: + Entrées du jour | L54: Salaires et avances | M54: =M30
B55: – Versement banque / sorties | E55: – Versement banque / sorties | H55: – Sorties du jour | L55: Dépenses travaux et divers | M55: =M44
B56: SOLDE DU SOIR | D56: =D48+D49+D50-D51-D52-D53-D54-D55 | E56: SOLDE DU SOIR | G56: =G48+G49+G50-G51-G52-G53-G54-G55 | H56: NOUVEAU SOLDE | J56: =J53+J54-J55 | L56: TOTAL DES SORTIES DU JOUR | M56: =M49+M50+M51+M53+M54+M55
B57: Espèces réellement comptées | E57: Espèces réellement comptées | L57: Encaissements du jour | M57: =J42
B58: ÉCART (compté – théorique) | D58: =IF(D57=0,0,D57-D56) | E58: ÉCART (compté – théorique) | G58: =IF(G57=0,0,G57-G56) | L58: CAISSE TOTALE DU SOIR | M58: =D56+G56

Sheet 23
A1: JOURNAL DE CAISSE DU JOUR | H1: PARADISE ALUMINIUM SARL · Casablanca
A2: =IF(23>'RÉCAP DU JOURNAL'!$J$5,"— ce jour n'existe pas dans le mois —",DATE('RÉCAP DU JOURNAL'!$E$4,'RÉCAP DU JOURNAL'!$E$5,23)) | H2: Feuille 23 · aluminium, accessoires et vitrage
A4: À REMPLIR ▸ les achats fournisseurs du jour, les charges, les salaires, les dépenses, les encaissements, puis les espèces comptées le soir dans chaque caisse. Cases jaunes = à vous ; cases blanches = calculées.
B6: ACHATS FOURNISSEURS DU JOUR | L6: CHARGES FIXES DU JOUR
B7: BL N° | C7: FOURNISSEUR | D7: NET À PAYER | E7: ESPÈCE | F7: CHÈQUE | G7: N° DU CHÈQUE | H7: EFFET | I7: N° DE L'EFFET | J7: RESTE À PAYER | L7: POSTE DE CHARGE | M7: MONTANT
J8: =IF(C8="","",D8-E8-F8-H8) | L8: LOYER DU LOCAL
J9: =IF(C9="","",D9-E9-F9-H9) | L9: EAU + ÉLECTRICITÉ
J10: =IF(C10="","",D10-E10-F10-H10) | L10: TÉLÉPHONE & INTERNET
J11: =IF(C11="","",D11-E11-F11-H11) | L11: CNSS
J12: =IF(C12="","",D12-E12-F12-H12) | L12: TVA & IMPÔTS
J13: =IF(C13="","",D13-E13-F13-H13) | L13: ASSURANCES
J14: =IF(C14="","",D14-E14-F14-H14) | L14: COMPTABLE & HONORAIRES
J15: =IF(C15="","",D15-E15-F15-H15) | L15: CARBURANT & VÉHICULE
J16: =IF(C16="","",D16-E16-F16-H16) | L16: TRANSPORT & LIVRAISON
J17: =IF(C17="","",D17-E17-F17-H17) | L17: ENTRETIEN & RÉPARATION
J18: =IF(C18="","",D18-E18-F18-H18) | L18: FOURNITURES DE BUREAU
J19: =IF(C19="","",D19-E19-F19-H19) | L19: AUTRE CHARGE FIXE
J20: =IF(C20="","",D20-E20-F20-H20) | L20: TOTAL | M20: =SUM(M8:M19)
J21: =IF(C21="","",D21-E21-F21-H21)
J22: =IF(C22="","",D22-E22-F22-H22) | L22: SALAIRES ET AVANCES
J23: =IF(C23="","",D23-E23-F23-H23) | L23: PERSONNE | M23: MONTANT
J24: =IF(C24="","",D24-E24-F24-H24) | L24: HOUSSEIN
J25: =IF(C25="","",D25-E25-F25-H25) | L25: AYOUB
J26: =IF(C26="","",D26-E26-F26-H26) | L26: OUVRIER 1
J27: =IF(C27="","",D27-E27-F27-H27) | L27: OUVRIER 2
B28: TOTAL DES ACHATS DU JOUR | D28: =SUM(D8:D27) | E28: =SUM(E8:E27) | F28: =SUM(F8:F27) | H28: =SUM(H8:H27) | J28: =SUM(J8:J27) | L28: AVANCE / PRIME
L29: AUTRE SALAIRE
B30: RÈGLEMENT DES ACHATS | F30: ENCAISSEMENTS DU JOUR | L30: TOTAL | M30: =SUM(M24:M29)
B31: Réglé en espèce | D31: =E28 | F31: CLIENT / ORIGINE | H31: ESPÈCE | I31: CHÈQUE / VIREMENT | J31: TOTAL
B32: Réglé par chèque | D32: =F28 | J32: =IF(F32="","",H32+I32) | L32: DÉPENSES TRAVAUX ET DIVERS
B33: Réglé par effet | D33: =H28 | J33: =IF(F33="","",H33+I33) | L33: DÉSIGNATION | M33: MONTANT
B34: TOTAL RÉGLÉ | D34: =E28+F28+H28 | J34: =IF(F34="","",H34+I34)
B35: RESTE DÛ (crédit fournisseur) | D35: =J28 | J35: =IF(F35="","",H35+I35)
J36: =IF(F36="","",H36+I36)
B37: OBSERVATIONS DU JOUR | J37: =IF(F37="","",H37+I37)
J38: =IF(F38="","",H38+I38)
J39: =IF(F39="","",H39+I39)
J40: =IF(F40="","",H40+I40)
J41: =IF(F41="","",H41+I41)
F42: TOTAL ENCAISSÉ | H42: =SUM(H32:H41) | I42: =SUM(I32:I41) | J42: =SUM(J32:J41)
L44: TOTAL | M44: =SUM(M34:M43)
B46: LES CAISSES ET LE RÉSUMÉ DU SOIR
B47: CAISSE PARADISE | E47: CAISSE ZENATA | H47: CONTRÔLE ET AUTRE CAISSE | L47: RÉSUMÉ DU JOUR
B48: Solde de la veille | D48: ='22'!$D$56 | E48: Solde de la veille | G48: ='22'!$G$56 | H48: Caisse PARADISE du soir | J48: =D56 | L48: Achats fournisseurs du jour | M48: =D28
B49: + Encaissements en espèce | D49: =H42 | E49: + Encaissements du jour | H49: Caisse ZENATA du soir | J49: =G56 | L49: dont réglé en espèce | M49: =E28
B50: + Apports et entrées divers | E50: + Apports et entrées divers | H50: CAISSE TOTALE DU SOIR | J50: =D56+G56 | L50: dont réglé par chèque | M50: =F28
B51: – Achats réglés en espèce | D51: =E28 | E51: – Achats réglés en espèce | H51: Écart total constaté | J51: =D58+G58 | L51: dont réglé par effet | M51: =H28
B52: – Charges fixes du jour | D52: =M20 | E52: – Charges et frais du jour | L52: RESTE DÛ (crédit fournisseur) | M52: =J28
B53: – Salaires et avances | D53: =M30 | E53: – Salaires et avances | H53: AUTRE CAISSE — solde précédent | J53: ='22'!$J$56 | L53: Charges fixes | M53: =M20
B54: – Dépenses travaux et divers | D54: =M44 | E54: – Dépenses travaux et divers | H54: + Entrées du jour | L54: Salaires et avances | M54: =M30
B55: – Versement banque / sorties | E55: – Versement banque / sorties | H55: – Sorties du jour | L55: Dépenses travaux et divers | M55: =M44
B56: SOLDE DU SOIR | D56: =D48+D49+D50-D51-D52-D53-D54-D55 | E56: SOLDE DU SOIR | G56: =G48+G49+G50-G51-G52-G53-G54-G55 | H56: NOUVEAU SOLDE | J56: =J53+J54-J55 | L56: TOTAL DES SORTIES DU JOUR | M56: =M49+M50+M51+M53+M54+M55
B57: Espèces réellement comptées | E57: Espèces réellement comptées | L57: Encaissements du jour | M57: =J42
B58: ÉCART (compté – théorique) | D58: =IF(D57=0,0,D57-D56) | E58: ÉCART (compté – théorique) | G58: =IF(G57=0,0,G57-G56) | L58: CAISSE TOTALE DU SOIR | M58: =D56+G56

Sheet 24
A1: JOURNAL DE CAISSE DU JOUR | H1: PARADISE ALUMINIUM SARL · Casablanca
A2: =IF(24>'RÉCAP DU JOURNAL'!$J$5,"— ce jour n'existe pas dans le mois —",DATE('RÉCAP DU JOURNAL'!$E$4,'RÉCAP DU JOURNAL'!$E$5,24)) | H2: Feuille 24 · aluminium, accessoires et vitrage
A4: À REMPLIR ▸ les achats fournisseurs du jour, les charges, les salaires, les dépenses, les encaissements, puis les espèces comptées le soir dans chaque caisse. Cases jaunes = à vous ; cases blanches = calculées.
B6: ACHATS FOURNISSEURS DU JOUR | L6: CHARGES FIXES DU JOUR
B7: BL N° | C7: FOURNISSEUR | D7: NET À PAYER | E7: ESPÈCE | F7: CHÈQUE | G7: N° DU CHÈQUE | H7: EFFET | I7: N° DE L'EFFET | J7: RESTE À PAYER | L7: POSTE DE CHARGE | M7: MONTANT
J8: =IF(C8="","",D8-E8-F8-H8) | L8: LOYER DU LOCAL
J9: =IF(C9="","",D9-E9-F9-H9) | L9: EAU + ÉLECTRICITÉ
J10: =IF(C10="","",D10-E10-F10-H10) | L10: TÉLÉPHONE & INTERNET
J11: =IF(C11="","",D11-E11-F11-H11) | L11: CNSS
J12: =IF(C12="","",D12-E12-F12-H12) | L12: TVA & IMPÔTS
J13: =IF(C13="","",D13-E13-F13-H13) | L13: ASSURANCES
J14: =IF(C14="","",D14-E14-F14-H14) | L14: COMPTABLE & HONORAIRES
J15: =IF(C15="","",D15-E15-F15-H15) | L15: CARBURANT & VÉHICULE
J16: =IF(C16="","",D16-E16-F16-H16) | L16: TRANSPORT & LIVRAISON
J17: =IF(C17="","",D17-E17-F17-H17) | L17: ENTRETIEN & RÉPARATION
J18: =IF(C18="","",D18-E18-F18-H18) | L18: FOURNITURES DE BUREAU
J19: =IF(C19="","",D19-E19-F19-H19) | L19: AUTRE CHARGE FIXE
J20: =IF(C20="","",D20-E20-F20-H20) | L20: TOTAL | M20: =SUM(M8:M19)
J21: =IF(C21="","",D21-E21-F21-H21)
J22: =IF(C22="","",D22-E22-F22-H22) | L22: SALAIRES ET AVANCES
J23: =IF(C23="","",D23-E23-F23-H23) | L23: PERSONNE | M23: MONTANT
J24: =IF(C24="","",D24-E24-F24-H24) | L24: HOUSSEIN
J25: =IF(C25="","",D25-E25-F25-H25) | L25: AYOUB
J26: =IF(C26="","",D26-E26-F26-H26) | L26: OUVRIER 1
J27: =IF(C27="","",D27-E27-F27-H27) | L27: OUVRIER 2
B28: TOTAL DES ACHATS DU JOUR | D28: =SUM(D8:D27) | E28: =SUM(E8:E27) | F28: =SUM(F8:F27) | H28: =SUM(H8:H27) | J28: =SUM(J8:J27) | L28: AVANCE / PRIME
L29: AUTRE SALAIRE
B30: RÈGLEMENT DES ACHATS | F30: ENCAISSEMENTS DU JOUR | L30: TOTAL | M30: =SUM(M24:M29)
B31: Réglé en espèce | D31: =E28 | F31: CLIENT / ORIGINE | H31: ESPÈCE | I31: CHÈQUE / VIREMENT | J31: TOTAL
B32: Réglé par chèque | D32: =F28 | J32: =IF(F32="","",H32+I32) | L32: DÉPENSES TRAVAUX ET DIVERS
B33: Réglé par effet | D33: =H28 | J33: =IF(F33="","",H33+I33) | L33: DÉSIGNATION | M33: MONTANT
B34: TOTAL RÉGLÉ | D34: =E28+F28+H28 | J34: =IF(F34="","",H34+I34)
B35: RESTE DÛ (crédit fournisseur) | D35: =J28 | J35: =IF(F35="","",H35+I35)
J36: =IF(F36="","",H36+I36)
B37: OBSERVATIONS DU JOUR | J37: =IF(F37="","",H37+I37)
J38: =IF(F38="","",H38+I38)
J39: =IF(F39="","",H39+I39)
J40: =IF(F40="","",H40+I40)
J41: =IF(F41="","",H41+I41)
F42: TOTAL ENCAISSÉ | H42: =SUM(H32:H41) | I42: =SUM(I32:I41) | J42: =SUM(J32:J41)
L44: TOTAL | M44: =SUM(M34:M43)
B46: LES CAISSES ET LE RÉSUMÉ DU SOIR
B47: CAISSE PARADISE | E47: CAISSE ZENATA | H47: CONTRÔLE ET AUTRE CAISSE | L47: RÉSUMÉ DU JOUR
B48: Solde de la veille | D48: ='23'!$D$56 | E48: Solde de la veille | G48: ='23'!$G$56 | H48: Caisse PARADISE du soir | J48: =D56 | L48: Achats fournisseurs du jour | M48: =D28
B49: + Encaissements en espèce | D49: =H42 | E49: + Encaissements du jour | H49: Caisse ZENATA du soir | J49: =G56 | L49: dont réglé en espèce | M49: =E28
B50: + Apports et entrées divers | E50: + Apports et entrées divers | H50: CAISSE TOTALE DU SOIR | J50: =D56+G56 | L50: dont réglé par chèque | M50: =F28
B51: – Achats réglés en espèce | D51: =E28 | E51: – Achats réglés en espèce | H51: Écart total constaté | J51: =D58+G58 | L51: dont réglé par effet | M51: =H28
B52: – Charges fixes du jour | D52: =M20 | E52: – Charges et frais du jour | L52: RESTE DÛ (crédit fournisseur) | M52: =J28
B53: – Salaires et avances | D53: =M30 | E53: – Salaires et avances | H53: AUTRE CAISSE — solde précédent | J53: ='23'!$J$56 | L53: Charges fixes | M53: =M20
B54: – Dépenses travaux et divers | D54: =M44 | E54: – Dépenses travaux et divers | H54: + Entrées du jour | L54: Salaires et avances | M54: =M30
B55: – Versement banque / sorties | E55: – Versement banque / sorties | H55: – Sorties du jour | L55: Dépenses travaux et divers | M55: =M44
B56: SOLDE DU SOIR | D56: =D48+D49+D50-D51-D52-D53-D54-D55 | E56: SOLDE DU SOIR | G56: =G48+G49+G50-G51-G52-G53-G54-G55 | H56: NOUVEAU SOLDE | J56: =J53+J54-J55 | L56: TOTAL DES SORTIES DU JOUR | M56: =M49+M50+M51+M53+M54+M55
B57: Espèces réellement comptées | E57: Espèces réellement comptées | L57: Encaissements du jour | M57: =J42
B58: ÉCART (compté – théorique) | D58: =IF(D57=0,0,D57-D56) | E58: ÉCART (compté – théorique) | G58: =IF(G57=0,0,G57-G56) | L58: CAISSE TOTALE DU SOIR | M58: =D56+G56

Sheet 25
A1: JOURNAL DE CAISSE DU JOUR | H1: PARADISE ALUMINIUM SARL · Casablanca
A2: =IF(25>'RÉCAP DU JOURNAL'!$J$5,"— ce jour n'existe pas dans le mois —",DATE('RÉCAP DU JOURNAL'!$E$4,'RÉCAP DU JOURNAL'!$E$5,25)) | H2: Feuille 25 · aluminium, accessoires et vitrage
A4: À REMPLIR ▸ les achats fournisseurs du jour, les charges, les salaires, les dépenses, les encaissements, puis les espèces comptées le soir dans chaque caisse. Cases jaunes = à vous ; cases blanches = calculées.
B6: ACHATS FOURNISSEURS DU JOUR | L6: CHARGES FIXES DU JOUR
B7: BL N° | C7: FOURNISSEUR | D7: NET À PAYER | E7: ESPÈCE | F7: CHÈQUE | G7: N° DU CHÈQUE | H7: EFFET | I7: N° DE L'EFFET | J7: RESTE À PAYER | L7: POSTE DE CHARGE | M7: MONTANT
J8: =IF(C8="","",D8-E8-F8-H8) | L8: LOYER DU LOCAL
J9: =IF(C9="","",D9-E9-F9-H9) | L9: EAU + ÉLECTRICITÉ
J10: =IF(C10="","",D10-E10-F10-H10) | L10: TÉLÉPHONE & INTERNET
J11: =IF(C11="","",D11-E11-F11-H11) | L11: CNSS
J12: =IF(C12="","",D12-E12-F12-H12) | L12: TVA & IMPÔTS
J13: =IF(C13="","",D13-E13-F13-H13) | L13: ASSURANCES
J14: =IF(C14="","",D14-E14-F14-H14) | L14: COMPTABLE & HONORAIRES
J15: =IF(C15="","",D15-E15-F15-H15) | L15: CARBURANT & VÉHICULE
J16: =IF(C16="","",D16-E16-F16-H16) | L16: TRANSPORT & LIVRAISON
J17: =IF(C17="","",D17-E17-F17-H17) | L17: ENTRETIEN & RÉPARATION
J18: =IF(C18="","",D18-E18-F18-H18) | L18: FOURNITURES DE BUREAU
J19: =IF(C19="","",D19-E19-F19-H19) | L19: AUTRE CHARGE FIXE
J20: =IF(C20="","",D20-E20-F20-H20) | L20: TOTAL | M20: =SUM(M8:M19)
J21: =IF(C21="","",D21-E21-F21-H21)
J22: =IF(C22="","",D22-E22-F22-H22) | L22: SALAIRES ET AVANCES
J23: =IF(C23="","",D23-E23-F23-H23) | L23: PERSONNE | M23: MONTANT
J24: =IF(C24="","",D24-E24-F24-H24) | L24: HOUSSEIN
J25: =IF(C25="","",D25-E25-F25-H25) | L25: AYOUB
J26: =IF(C26="","",D26-E26-F26-H26) | L26: OUVRIER 1
J27: =IF(C27="","",D27-E27-F27-H27) | L27: OUVRIER 2
B28: TOTAL DES ACHATS DU JOUR | D28: =SUM(D8:D27) | E28: =SUM(E8:E27) | F28: =SUM(F8:F27) | H28: =SUM(H8:H27) | J28: =SUM(J8:J27) | L28: AVANCE / PRIME
L29: AUTRE SALAIRE
B30: RÈGLEMENT DES ACHATS | F30: ENCAISSEMENTS DU JOUR | L30: TOTAL | M30: =SUM(M24:M29)
B31: Réglé en espèce | D31: =E28 | F31: CLIENT / ORIGINE | H31: ESPÈCE | I31: CHÈQUE / VIREMENT | J31: TOTAL
B32: Réglé par chèque | D32: =F28 | J32: =IF(F32="","",H32+I32) | L32: DÉPENSES TRAVAUX ET DIVERS
B33: Réglé par effet | D33: =H28 | J33: =IF(F33="","",H33+I33) | L33: DÉSIGNATION | M33: MONTANT
B34: TOTAL RÉGLÉ | D34: =E28+F28+H28 | J34: =IF(F34="","",H34+I34)
B35: RESTE DÛ (crédit fournisseur) | D35: =J28 | J35: =IF(F35="","",H35+I35)
J36: =IF(F36="","",H36+I36)
B37: OBSERVATIONS DU JOUR | J37: =IF(F37="","",H37+I37)
J38: =IF(F38="","",H38+I38)
J39: =IF(F39="","",H39+I39)
J40: =IF(F40="","",H40+I40)
J41: =IF(F41="","",H41+I41)
F42: TOTAL ENCAISSÉ | H42: =SUM(H32:H41) | I42: =SUM(I32:I41) | J42: =SUM(J32:J41)
L44: TOTAL | M44: =SUM(M34:M43)
B46: LES CAISSES ET LE RÉSUMÉ DU SOIR
B47: CAISSE PARADISE | E47: CAISSE ZENATA | H47: CONTRÔLE ET AUTRE CAISSE | L47: RÉSUMÉ DU JOUR
B48: Solde de la veille | D48: ='24'!$D$56 | E48: Solde de la veille | G48: ='24'!$G$56 | H48: Caisse PARADISE du soir | J48: =D56 | L48: Achats fournisseurs du jour | M48: =D28
B49: + Encaissements en espèce | D49: =H42 | E49: + Encaissements du jour | H49: Caisse ZENATA du soir | J49: =G56 | L49: dont réglé en espèce | M49: =E28
B50: + Apports et entrées divers | E50: + Apports et entrées divers | H50: CAISSE TOTALE DU SOIR | J50: =D56+G56 | L50: dont réglé par chèque | M50: =F28
B51: – Achats réglés en espèce | D51: =E28 | E51: – Achats réglés en espèce | H51: Écart total constaté | J51: =D58+G58 | L51: dont réglé par effet | M51: =H28
B52: – Charges fixes du jour | D52: =M20 | E52: – Charges et frais du jour | L52: RESTE DÛ (crédit fournisseur) | M52: =J28
B53: – Salaires et avances | D53: =M30 | E53: – Salaires et avances | H53: AUTRE CAISSE — solde précédent | J53: ='24'!$J$56 | L53: Charges fixes | M53: =M20
B54: – Dépenses travaux et divers | D54: =M44 | E54: – Dépenses travaux et divers | H54: + Entrées du jour | L54: Salaires et avances | M54: =M30
B55: – Versement banque / sorties | E55: – Versement banque / sorties | H55: – Sorties du jour | L55: Dépenses travaux et divers | M55: =M44
B56: SOLDE DU SOIR | D56: =D48+D49+D50-D51-D52-D53-D54-D55 | E56: SOLDE DU SOIR | G56: =G48+G49+G50-G51-G52-G53-G54-G55 | H56: NOUVEAU SOLDE | J56: =J53+J54-J55 | L56: TOTAL DES SORTIES DU JOUR | M56: =M49+M50+M51+M53+M54+M55
B57: Espèces réellement comptées | E57: Espèces réellement comptées | L57: Encaissements du jour | M57: =J42
B58: ÉCART (compté – théorique) | D58: =IF(D57=0,0,D57-D56) | E58: ÉCART (compté – théorique) | G58: =IF(G57=0,0,G57-G56) | L58: CAISSE TOTALE DU SOIR | M58: =D56+G56

Sheet 26
A1: JOURNAL DE CAISSE DU JOUR | H1: PARADISE ALUMINIUM SARL · Casablanca
A2: =IF(26>'RÉCAP DU JOURNAL'!$J$5,"— ce jour n'existe pas dans le mois —",DATE('RÉCAP DU JOURNAL'!$E$4,'RÉCAP DU JOURNAL'!$E$5,26)) | H2: Feuille 26 · aluminium, accessoires et vitrage
A4: À REMPLIR ▸ les achats fournisseurs du jour, les charges, les salaires, les dépenses, les encaissements, puis les espèces comptées le soir dans chaque caisse. Cases jaunes = à vous ; cases blanches = calculées.
B6: ACHATS FOURNISSEURS DU JOUR | L6: CHARGES FIXES DU JOUR
B7: BL N° | C7: FOURNISSEUR | D7: NET À PAYER | E7: ESPÈCE | F7: CHÈQUE | G7: N° DU CHÈQUE | H7: EFFET | I7: N° DE L'EFFET | J7: RESTE À PAYER | L7: POSTE DE CHARGE | M7: MONTANT
J8: =IF(C8="","",D8-E8-F8-H8) | L8: LOYER DU LOCAL
J9: =IF(C9="","",D9-E9-F9-H9) | L9: EAU + ÉLECTRICITÉ
J10: =IF(C10="","",D10-E10-F10-H10) | L10: TÉLÉPHONE & INTERNET
J11: =IF(C11="","",D11-E11-F11-H11) | L11: CNSS
J12: =IF(C12="","",D12-E12-F12-H12) | L12: TVA & IMPÔTS
J13: =IF(C13="","",D13-E13-F13-H13) | L13: ASSURANCES
J14: =IF(C14="","",D14-E14-F14-H14) | L14: COMPTABLE & HONORAIRES
J15: =IF(C15="","",D15-E15-F15-H15) | L15: CARBURANT & VÉHICULE
J16: =IF(C16="","",D16-E16-F16-H16) | L16: TRANSPORT & LIVRAISON
J17: =IF(C17="","",D17-E17-F17-H17) | L17: ENTRETIEN & RÉPARATION
J18: =IF(C18="","",D18-E18-F18-H18) | L18: FOURNITURES DE BUREAU
J19: =IF(C19="","",D19-E19-F19-H19) | L19: AUTRE CHARGE FIXE
J20: =IF(C20="","",D20-E20-F20-H20) | L20: TOTAL | M20: =SUM(M8:M19)
J21: =IF(C21="","",D21-E21-F21-H21)
J22: =IF(C22="","",D22-E22-F22-H22) | L22: SALAIRES ET AVANCES
J23: =IF(C23="","",D23-E23-F23-H23) | L23: PERSONNE | M23: MONTANT
J24: =IF(C24="","",D24-E24-F24-H24) | L24: HOUSSEIN
J25: =IF(C25="","",D25-E25-F25-H25) | L25: AYOUB
J26: =IF(C26="","",D26-E26-F26-H26) | L26: OUVRIER 1
J27: =IF(C27="","",D27-E27-F27-H27) | L27: OUVRIER 2
B28: TOTAL DES ACHATS DU JOUR | D28: =SUM(D8:D27) | E28: =SUM(E8:E27) | F28: =SUM(F8:F27) | H28: =SUM(H8:H27) | J28: =SUM(J8:J27) | L28: AVANCE / PRIME
L29: AUTRE SALAIRE
B30: RÈGLEMENT DES ACHATS | F30: ENCAISSEMENTS DU JOUR | L30: TOTAL | M30: =SUM(M24:M29)
B31: Réglé en espèce | D31: =E28 | F31: CLIENT / ORIGINE | H31: ESPÈCE | I31: CHÈQUE / VIREMENT | J31: TOTAL
B32: Réglé par chèque | D32: =F28 | J32: =IF(F32="","",H32+I32) | L32: DÉPENSES TRAVAUX ET DIVERS
B33: Réglé par effet | D33: =H28 | J33: =IF(F33="","",H33+I33) | L33: DÉSIGNATION | M33: MONTANT
B34: TOTAL RÉGLÉ | D34: =E28+F28+H28 | J34: =IF(F34="","",H34+I34)
B35: RESTE DÛ (crédit fournisseur) | D35: =J28 | J35: =IF(F35="","",H35+I35)
J36: =IF(F36="","",H36+I36)
B37: OBSERVATIONS DU JOUR | J37: =IF(F37="","",H37+I37)
J38: =IF(F38="","",H38+I38)
J39: =IF(F39="","",H39+I39)
J40: =IF(F40="","",H40+I40)
J41: =IF(F41="","",H41+I41)
F42: TOTAL ENCAISSÉ | H42: =SUM(H32:H41) | I42: =SUM(I32:I41) | J42: =SUM(J32:J41)
L44: TOTAL | M44: =SUM(M34:M43)
B46: LES CAISSES ET LE RÉSUMÉ DU SOIR
B47: CAISSE PARADISE | E47: CAISSE ZENATA | H47: CONTRÔLE ET AUTRE CAISSE | L47: RÉSUMÉ DU JOUR
B48: Solde de la veille | D48: ='25'!$D$56 | E48: Solde de la veille | G48: ='25'!$G$56 | H48: Caisse PARADISE du soir | J48: =D56 | L48: Achats fournisseurs du jour | M48: =D28
B49: + Encaissements en espèce | D49: =H42 | E49: + Encaissements du jour | H49: Caisse ZENATA du soir | J49: =G56 | L49: dont réglé en espèce | M49: =E28
B50: + Apports et entrées divers | E50: + Apports et entrées divers | H50: CAISSE TOTALE DU SOIR | J50: =D56+G56 | L50: dont réglé par chèque | M50: =F28
B51: – Achats réglés en espèce | D51: =E28 | E51: – Achats réglés en espèce | H51: Écart total constaté | J51: =D58+G58 | L51: dont réglé par effet | M51: =H28
B52: – Charges fixes du jour | D52: =M20 | E52: – Charges et frais du jour | L52: RESTE DÛ (crédit fournisseur) | M52: =J28
B53: – Salaires et avances | D53: =M30 | E53: – Salaires et avances | H53: AUTRE CAISSE — solde précédent | J53: ='25'!$J$56 | L53: Charges fixes | M53: =M20
B54: – Dépenses travaux et divers | D54: =M44 | E54: – Dépenses travaux et divers | H54: + Entrées du jour | L54: Salaires et avances | M54: =M30
B55: – Versement banque / sorties | E55: – Versement banque / sorties | H55: – Sorties du jour | L55: Dépenses travaux et divers | M55: =M44
B56: SOLDE DU SOIR | D56: =D48+D49+D50-D51-D52-D53-D54-D55 | E56: SOLDE DU SOIR | G56: =G48+G49+G50-G51-G52-G53-G54-G55 | H56: NOUVEAU SOLDE | J56: =J53+J54-J55 | L56: TOTAL DES SORTIES DU JOUR | M56: =M49+M50+M51+M53+M54+M55
B57: Espèces réellement comptées | E57: Espèces réellement comptées | L57: Encaissements du jour | M57: =J42
B58: ÉCART (compté – théorique) | D58: =IF(D57=0,0,D57-D56) | E58: ÉCART (compté – théorique) | G58: =IF(G57=0,0,G57-G56) | L58: CAISSE TOTALE DU SOIR | M58: =D56+G56

Sheet 27
A1: JOURNAL DE CAISSE DU JOUR | H1: PARADISE ALUMINIUM SARL · Casablanca
A2: =IF(27>'RÉCAP DU JOURNAL'!$J$5,"— ce jour n'existe pas dans le mois —",DATE('RÉCAP DU JOURNAL'!$E$4,'RÉCAP DU JOURNAL'!$E$5,27)) | H2: Feuille 27 · aluminium, accessoires et vitrage
A4: À REMPLIR ▸ les achats fournisseurs du jour, les charges, les salaires, les dépenses, les encaissements, puis les espèces comptées le soir dans chaque caisse. Cases jaunes = à vous ; cases blanches = calculées.
B6: ACHATS FOURNISSEURS DU JOUR | L6: CHARGES FIXES DU JOUR
B7: BL N° | C7: FOURNISSEUR | D7: NET À PAYER | E7: ESPÈCE | F7: CHÈQUE | G7: N° DU CHÈQUE | H7: EFFET | I7: N° DE L'EFFET | J7: RESTE À PAYER | L7: POSTE DE CHARGE | M7: MONTANT
J8: =IF(C8="","",D8-E8-F8-H8) | L8: LOYER DU LOCAL
J9: =IF(C9="","",D9-E9-F9-H9) | L9: EAU + ÉLECTRICITÉ
J10: =IF(C10="","",D10-E10-F10-H10) | L10: TÉLÉPHONE & INTERNET
J11: =IF(C11="","",D11-E11-F11-H11) | L11: CNSS
J12: =IF(C12="","",D12-E12-F12-H12) | L12: TVA & IMPÔTS
J13: =IF(C13="","",D13-E13-F13-H13) | L13: ASSURANCES
J14: =IF(C14="","",D14-E14-F14-H14) | L14: COMPTABLE & HONORAIRES
J15: =IF(C15="","",D15-E15-F15-H15) | L15: CARBURANT & VÉHICULE
J16: =IF(C16="","",D16-E16-F16-H16) | L16: TRANSPORT & LIVRAISON
J17: =IF(C17="","",D17-E17-F17-H17) | L17: ENTRETIEN & RÉPARATION
J18: =IF(C18="","",D18-E18-F18-H18) | L18: FOURNITURES DE BUREAU
J19: =IF(C19="","",D19-E19-F19-H19) | L19: AUTRE CHARGE FIXE
J20: =IF(C20="","",D20-E20-F20-H20) | L20: TOTAL | M20: =SUM(M8:M19)
J21: =IF(C21="","",D21-E21-F21-H21)
J22: =IF(C22="","",D22-E22-F22-H22) | L22: SALAIRES ET AVANCES
J23: =IF(C23="","",D23-E23-F23-H23) | L23: PERSONNE | M23: MONTANT
J24: =IF(C24="","",D24-E24-F24-H24) | L24: HOUSSEIN
J25: =IF(C25="","",D25-E25-F25-H25) | L25: AYOUB
J26: =IF(C26="","",D26-E26-F26-H26) | L26: OUVRIER 1
J27: =IF(C27="","",D27-E27-F27-H27) | L27: OUVRIER 2
B28: TOTAL DES ACHATS DU JOUR | D28: =SUM(D8:D27) | E28: =SUM(E8:E27) | F28: =SUM(F8:F27) | H28: =SUM(H8:H27) | J28: =SUM(J8:J27) | L28: AVANCE / PRIME
L29: AUTRE SALAIRE
B30: RÈGLEMENT DES ACHATS | F30: ENCAISSEMENTS DU JOUR | L30: TOTAL | M30: =SUM(M24:M29)
B31: Réglé en espèce | D31: =E28 | F31: CLIENT / ORIGINE | H31: ESPÈCE | I31: CHÈQUE / VIREMENT | J31: TOTAL
B32: Réglé par chèque | D32: =F28 | J32: =IF(F32="","",H32+I32) | L32: DÉPENSES TRAVAUX ET DIVERS
B33: Réglé par effet | D33: =H28 | J33: =IF(F33="","",H33+I33) | L33: DÉSIGNATION | M33: MONTANT
B34: TOTAL RÉGLÉ | D34: =E28+F28+H28 | J34: =IF(F34="","",H34+I34)
B35: RESTE DÛ (crédit fournisseur) | D35: =J28 | J35: =IF(F35="","",H35+I35)
J36: =IF(F36="","",H36+I36)
B37: OBSERVATIONS DU JOUR | J37: =IF(F37="","",H37+I37)
J38: =IF(F38="","",H38+I38)
J39: =IF(F39="","",H39+I39)
J40: =IF(F40="","",H40+I40)
J41: =IF(F41="","",H41+I41)
F42: TOTAL ENCAISSÉ | H42: =SUM(H32:H41) | I42: =SUM(I32:I41) | J42: =SUM(J32:J41)
L44: TOTAL | M44: =SUM(M34:M43)
B46: LES CAISSES ET LE RÉSUMÉ DU SOIR
B47: CAISSE PARADISE | E47: CAISSE ZENATA | H47: CONTRÔLE ET AUTRE CAISSE | L47: RÉSUMÉ DU JOUR
B48: Solde de la veille | D48: ='26'!$D$56 | E48: Solde de la veille | G48: ='26'!$G$56 | H48: Caisse PARADISE du soir | J48: =D56 | L48: Achats fournisseurs du jour | M48: =D28
B49: + Encaissements en espèce | D49: =H42 | E49: + Encaissements du jour | H49: Caisse ZENATA du soir | J49: =G56 | L49: dont réglé en espèce | M49: =E28
B50: + Apports et entrées divers | E50: + Apports et entrées divers | H50: CAISSE TOTALE DU SOIR | J50: =D56+G56 | L50: dont réglé par chèque | M50: =F28
B51: – Achats réglés en espèce | D51: =E28 | E51: – Achats réglés en espèce | H51: Écart total constaté | J51: =D58+G58 | L51: dont réglé par effet | M51: =H28
B52: – Charges fixes du jour | D52: =M20 | E52: – Charges et frais du jour | L52: RESTE DÛ (crédit fournisseur) | M52: =J28
B53: – Salaires et avances | D53: =M30 | E53: – Salaires et avances | H53: AUTRE CAISSE — solde précédent | J53: ='26'!$J$56 | L53: Charges fixes | M53: =M20
B54: – Dépenses travaux et divers | D54: =M44 | E54: – Dépenses travaux et divers | H54: + Entrées du jour | L54: Salaires et avances | M54: =M30
B55: – Versement banque / sorties | E55: – Versement banque / sorties | H55: – Sorties du jour | L55: Dépenses travaux et divers | M55: =M44
B56: SOLDE DU SOIR | D56: =D48+D49+D50-D51-D52-D53-D54-D55 | E56: SOLDE DU SOIR | G56: =G48+G49+G50-G51-G52-G53-G54-G55 | H56: NOUVEAU SOLDE | J56: =J53+J54-J55 | L56: TOTAL DES SORTIES DU JOUR | M56: =M49+M50+M51+M53+M54+M55
B57: Espèces réellement comptées | E57: Espèces réellement comptées | L57: Encaissements du jour | M57: =J42
B58: ÉCART (compté – théorique) | D58: =IF(D57=0,0,D57-D56) | E58: ÉCART (compté – théorique) | G58: =IF(G57=0,0,G57-G56) | L58: CAISSE TOTALE DU SOIR | M58: =D56+G56

Sheet 28
A1: JOURNAL DE CAISSE DU JOUR | H1: PARADISE ALUMINIUM SARL · Casablanca
A2: =IF(28>'RÉCAP DU JOURNAL'!$J$5,"— ce jour n'existe pas dans le mois —",DATE('RÉCAP DU JOURNAL'!$E$4,'RÉCAP DU JOURNAL'!$E$5,28)) | H2: Feuille 28 · aluminium, accessoires et vitrage
A4: À REMPLIR ▸ les achats fournisseurs du jour, les charges, les salaires, les dépenses, les encaissements, puis les espèces comptées le soir dans chaque caisse. Cases jaunes = à vous ; cases blanches = calculées.
B6: ACHATS FOURNISSEURS DU JOUR | L6: CHARGES FIXES DU JOUR
B7: BL N° | C7: FOURNISSEUR | D7: NET À PAYER | E7: ESPÈCE | F7: CHÈQUE | G7: N° DU CHÈQUE | H7: EFFET | I7: N° DE L'EFFET | J7: RESTE À PAYER | L7: POSTE DE CHARGE | M7: MONTANT
J8: =IF(C8="","",D8-E8-F8-H8) | L8: LOYER DU LOCAL
J9: =IF(C9="","",D9-E9-F9-H9) | L9: EAU + ÉLECTRICITÉ
J10: =IF(C10="","",D10-E10-F10-H10) | L10: TÉLÉPHONE & INTERNET
J11: =IF(C11="","",D11-E11-F11-H11) | L11: CNSS
J12: =IF(C12="","",D12-E12-F12-H12) | L12: TVA & IMPÔTS
J13: =IF(C13="","",D13-E13-F13-H13) | L13: ASSURANCES
J14: =IF(C14="","",D14-E14-F14-H14) | L14: COMPTABLE & HONORAIRES
J15: =IF(C15="","",D15-E15-F15-H15) | L15: CARBURANT & VÉHICULE
J16: =IF(C16="","",D16-E16-F16-H16) | L16: TRANSPORT & LIVRAISON
J17: =IF(C17="","",D17-E17-F17-H17) | L17: ENTRETIEN & RÉPARATION
J18: =IF(C18="","",D18-E18-F18-H18) | L18: FOURNITURES DE BUREAU
J19: =IF(C19="","",D19-E19-F19-H19) | L19: AUTRE CHARGE FIXE
J20: =IF(C20="","",D20-E20-F20-H20) | L20: TOTAL | M20: =SUM(M8:M19)
J21: =IF(C21="","",D21-E21-F21-H21)
J22: =IF(C22="","",D22-E22-F22-H22) | L22: SALAIRES ET AVANCES
J23: =IF(C23="","",D23-E23-F23-H23) | L23: PERSONNE | M23: MONTANT
J24: =IF(C24="","",D24-E24-F24-H24) | L24: HOUSSEIN
J25: =IF(C25="","",D25-E25-F25-H25) | L25: AYOUB
J26: =IF(C26="","",D26-E26-F26-H26) | L26: OUVRIER 1
J27: =IF(C27="","",D27-E27-F27-H27) | L27: OUVRIER 2
B28: TOTAL DES ACHATS DU JOUR | D28: =SUM(D8:D27) | E28: =SUM(E8:E27) | F28: =SUM(F8:F27) | H28: =SUM(H8:H27) | J28: =SUM(J8:J27) | L28: AVANCE / PRIME
L29: AUTRE SALAIRE
B30: RÈGLEMENT DES ACHATS | F30: ENCAISSEMENTS DU JOUR | L30: TOTAL | M30: =SUM(M24:M29)
B31: Réglé en espèce | D31: =E28 | F31: CLIENT / ORIGINE | H31: ESPÈCE | I31: CHÈQUE / VIREMENT | J31: TOTAL
B32: Réglé par chèque | D32: =F28 | J32: =IF(F32="","",H32+I32) | L32: DÉPENSES TRAVAUX ET DIVERS
B33: Réglé par effet | D33: =H28 | J33: =IF(F33="","",H33+I33) | L33: DÉSIGNATION | M33: MONTANT
B34: TOTAL RÉGLÉ | D34: =E28+F28+H28 | J34: =IF(F34="","",H34+I34)
B35: RESTE DÛ (crédit fournisseur) | D35: =J28 | J35: =IF(F35="","",H35+I35)
J36: =IF(F36="","",H36+I36)
B37: OBSERVATIONS DU JOUR | J37: =IF(F37="","",H37+I37)
J38: =IF(F38="","",H38+I38)
J39: =IF(F39="","",H39+I39)
J40: =IF(F40="","",H40+I40)
J41: =IF(F41="","",H41+I41)
F42: TOTAL ENCAISSÉ | H42: =SUM(H32:H41) | I42: =SUM(I32:I41) | J42: =SUM(J32:J41)
L44: TOTAL | M44: =SUM(M34:M43)
B46: LES CAISSES ET LE RÉSUMÉ DU SOIR
B47: CAISSE PARADISE | E47: CAISSE ZENATA | H47: CONTRÔLE ET AUTRE CAISSE | L47: RÉSUMÉ DU JOUR
B48: Solde de la veille | D48: ='27'!$D$56 | E48: Solde de la veille | G48: ='27'!$G$56 | H48: Caisse PARADISE du soir | J48: =D56 | L48: Achats fournisseurs du jour | M48: =D28
B49: + Encaissements en espèce | D49: =H42 | E49: + Encaissements du jour | H49: Caisse ZENATA du soir | J49: =G56 | L49: dont réglé en espèce | M49: =E28
B50: + Apports et entrées divers | E50: + Apports et entrées divers | H50: CAISSE TOTALE DU SOIR | J50: =D56+G56 | L50: dont réglé par chèque | M50: =F28
B51: – Achats réglés en espèce | D51: =E28 | E51: – Achats réglés en espèce | H51: Écart total constaté | J51: =D58+G58 | L51: dont réglé par effet | M51: =H28
B52: – Charges fixes du jour | D52: =M20 | E52: – Charges et frais du jour | L52: RESTE DÛ (crédit fournisseur) | M52: =J28
B53: – Salaires et avances | D53: =M30 | E53: – Salaires et avances | H53: AUTRE CAISSE — solde précédent | J53: ='27'!$J$56 | L53: Charges fixes | M53: =M20
B54: – Dépenses travaux et divers | D54: =M44 | E54: – Dépenses travaux et divers | H54: + Entrées du jour | L54: Salaires et avances | M54: =M30
B55: – Versement banque / sorties | E55: – Versement banque / sorties | H55: – Sorties du jour | L55: Dépenses travaux et divers | M55: =M44
B56: SOLDE DU SOIR | D56: =D48+D49+D50-D51-D52-D53-D54-D55 | E56: SOLDE DU SOIR | G56: =G48+G49+G50-G51-G52-G53-G54-G55 | H56: NOUVEAU SOLDE | J56: =J53+J54-J55 | L56: TOTAL DES SORTIES DU JOUR | M56: =M49+M50+M51+M53+M54+M55
B57: Espèces réellement comptées | E57: Espèces réellement comptées | L57: Encaissements du jour | M57: =J42
B58: ÉCART (compté – théorique) | D58: =IF(D57=0,0,D57-D56) | E58: ÉCART (compté – théorique) | G58: =IF(G57=0,0,G57-G56) | L58: CAISSE TOTALE DU SOIR | M58: =D56+G56

Sheet 29
A1: JOURNAL DE CAISSE DU JOUR | H1: PARADISE ALUMINIUM SARL · Casablanca
A2: =IF(29>'RÉCAP DU JOURNAL'!$J$5,"— ce jour n'existe pas dans le mois —",DATE('RÉCAP DU JOURNAL'!$E$4,'RÉCAP DU JOURNAL'!$E$5,29)) | H2: Feuille 29 · aluminium, accessoires et vitrage
A4: À REMPLIR ▸ les achats fournisseurs du jour, les charges, les salaires, les dépenses, les encaissements, puis les espèces comptées le soir dans chaque caisse. Cases jaunes = à vous ; cases blanches = calculées.
B6: ACHATS FOURNISSEURS DU JOUR | L6: CHARGES FIXES DU JOUR
B7: BL N° | C7: FOURNISSEUR | D7: NET À PAYER | E7: ESPÈCE | F7: CHÈQUE | G7: N° DU CHÈQUE | H7: EFFET | I7: N° DE L'EFFET | J7: RESTE À PAYER | L7: POSTE DE CHARGE | M7: MONTANT
J8: =IF(C8="","",D8-E8-F8-H8) | L8: LOYER DU LOCAL
J9: =IF(C9="","",D9-E9-F9-H9) | L9: EAU + ÉLECTRICITÉ
J10: =IF(C10="","",D10-E10-F10-H10) | L10: TÉLÉPHONE & INTERNET
J11: =IF(C11="","",D11-E11-F11-H11) | L11: CNSS
J12: =IF(C12="","",D12-E12-F12-H12) | L12: TVA & IMPÔTS
J13: =IF(C13="","",D13-E13-F13-H13) | L13: ASSURANCES
J14: =IF(C14="","",D14-E14-F14-H14) | L14: COMPTABLE & HONORAIRES
J15: =IF(C15="","",D15-E15-F15-H15) | L15: CARBURANT & VÉHICULE
J16: =IF(C16="","",D16-E16-F16-H16) | L16: TRANSPORT & LIVRAISON
J17: =IF(C17="","",D17-E17-F17-H17) | L17: ENTRETIEN & RÉPARATION
J18: =IF(C18="","",D18-E18-F18-H18) | L18: FOURNITURES DE BUREAU
J19: =IF(C19="","",D19-E19-F19-H19) | L19: AUTRE CHARGE FIXE
J20: =IF(C20="","",D20-E20-F20-H20) | L20: TOTAL | M20: =SUM(M8:M19)
J21: =IF(C21="","",D21-E21-F21-H21)
J22: =IF(C22="","",D22-E22-F22-H22) | L22: SALAIRES ET AVANCES
J23: =IF(C23="","",D23-E23-F23-H23) | L23: PERSONNE | M23: MONTANT
J24: =IF(C24="","",D24-E24-F24-H24) | L24: HOUSSEIN
J25: =IF(C25="","",D25-E25-F25-H25) | L25: AYOUB
J26: =IF(C26="","",D26-E26-F26-H26) | L26: OUVRIER 1
J27: =IF(C27="","",D27-E27-F27-H27) | L27: OUVRIER 2
B28: TOTAL DES ACHATS DU JOUR | D28: =SUM(D8:D27) | E28: =SUM(E8:E27) | F28: =SUM(F8:F27) | H28: =SUM(H8:H27) | J28: =SUM(J8:J27) | L28: AVANCE / PRIME
L29: AUTRE SALAIRE
B30: RÈGLEMENT DES ACHATS | F30: ENCAISSEMENTS DU JOUR | L30: TOTAL | M30: =SUM(M24:M29)
B31: Réglé en espèce | D31: =E28 | F31: CLIENT / ORIGINE | H31: ESPÈCE | I31: CHÈQUE / VIREMENT | J31: TOTAL
B32: Réglé par chèque | D32: =F28 | J32: =IF(F32="","",H32+I32) | L32: DÉPENSES TRAVAUX ET DIVERS
B33: Réglé par effet | D33: =H28 | J33: =IF(F33="","",H33+I33) | L33: DÉSIGNATION | M33: MONTANT
B34: TOTAL RÉGLÉ | D34: =E28+F28+H28 | J34: =IF(F34="","",H34+I34)
B35: RESTE DÛ (crédit fournisseur) | D35: =J28 | J35: =IF(F35="","",H35+I35)
J36: =IF(F36="","",H36+I36)
B37: OBSERVATIONS DU JOUR | J37: =IF(F37="","",H37+I37)
J38: =IF(F38="","",H38+I38)
J39: =IF(F39="","",H39+I39)
J40: =IF(F40="","",H40+I40)
J41: =IF(F41="","",H41+I41)
F42: TOTAL ENCAISSÉ | H42: =SUM(H32:H41) | I42: =SUM(I32:I41) | J42: =SUM(J32:J41)
L44: TOTAL | M44: =SUM(M34:M43)
B46: LES CAISSES ET LE RÉSUMÉ DU SOIR
B47: CAISSE PARADISE | E47: CAISSE ZENATA | H47: CONTRÔLE ET AUTRE CAISSE | L47: RÉSUMÉ DU JOUR
B48: Solde de la veille | D48: ='28'!$D$56 | E48: Solde de la veille | G48: ='28'!$G$56 | H48: Caisse PARADISE du soir | J48: =D56 | L48: Achats fournisseurs du jour | M48: =D28
B49: + Encaissements en espèce | D49: =H42 | E49: + Encaissements du jour | H49: Caisse ZENATA du soir | J49: =G56 | L49: dont réglé en espèce | M49: =E28
B50: + Apports et entrées divers | E50: + Apports et entrées divers | H50: CAISSE TOTALE DU SOIR | J50: =D56+G56 | L50: dont réglé par chèque | M50: =F28
B51: – Achats réglés en espèce | D51: =E28 | E51: – Achats réglés en espèce | H51: Écart total constaté | J51: =D58+G58 | L51: dont réglé par effet | M51: =H28
B52: – Charges fixes du jour | D52: =M20 | E52: – Charges et frais du jour | L52: RESTE DÛ (crédit fournisseur) | M52: =J28
B53: – Salaires et avances | D53: =M30 | E53: – Salaires et avances | H53: AUTRE CAISSE — solde précédent | J53: ='28'!$J$56 | L53: Charges fixes | M53: =M20
B54: – Dépenses travaux et divers | D54: =M44 | E54: – Dépenses travaux et divers | H54: + Entrées du jour | L54: Salaires et avances | M54: =M30
B55: – Versement banque / sorties | E55: – Versement banque / sorties | H55: – Sorties du jour | L55: Dépenses travaux et divers | M55: =M44
B56: SOLDE DU SOIR | D56: =D48+D49+D50-D51-D52-D53-D54-D55 | E56: SOLDE DU SOIR | G56: =G48+G49+G50-G51-G52-G53-G54-G55 | H56: NOUVEAU SOLDE | J56: =J53+J54-J55 | L56: TOTAL DES SORTIES DU JOUR | M56: =M49+M50+M51+M53+M54+M55
B57: Espèces réellement comptées | E57: Espèces réellement comptées | L57: Encaissements du jour | M57: =J42
B58: ÉCART (compté – théorique) | D58: =IF(D57=0,0,D57-D56) | E58: ÉCART (compté – théorique) | G58: =IF(G57=0,0,G57-G56) | L58: CAISSE TOTALE DU SOIR | M58: =D56+G56

Sheet 30
A1: JOURNAL DE CAISSE DU JOUR | H1: PARADISE ALUMINIUM SARL · Casablanca
A2: =IF(30>'RÉCAP DU JOURNAL'!$J$5,"— ce jour n'existe pas dans le mois —",DATE('RÉCAP DU JOURNAL'!$E$4,'RÉCAP DU JOURNAL'!$E$5,30)) | H2: Feuille 30 · aluminium, accessoires et vitrage
A4: À REMPLIR ▸ les achats fournisseurs du jour, les charges, les salaires, les dépenses, les encaissements, puis les espèces comptées le soir dans chaque caisse. Cases jaunes = à vous ; cases blanches = calculées.
B6: ACHATS FOURNISSEURS DU JOUR | L6: CHARGES FIXES DU JOUR
B7: BL N° | C7: FOURNISSEUR | D7: NET À PAYER | E7: ESPÈCE | F7: CHÈQUE | G7: N° DU CHÈQUE | H7: EFFET | I7: N° DE L'EFFET | J7: RESTE À PAYER | L7: POSTE DE CHARGE | M7: MONTANT
J8: =IF(C8="","",D8-E8-F8-H8) | L8: LOYER DU LOCAL
J9: =IF(C9="","",D9-E9-F9-H9) | L9: EAU + ÉLECTRICITÉ
J10: =IF(C10="","",D10-E10-F10-H10) | L10: TÉLÉPHONE & INTERNET
J11: =IF(C11="","",D11-E11-F11-H11) | L11: CNSS
J12: =IF(C12="","",D12-E12-F12-H12) | L12: TVA & IMPÔTS
J13: =IF(C13="","",D13-E13-F13-H13) | L13: ASSURANCES
J14: =IF(C14="","",D14-E14-F14-H14) | L14: COMPTABLE & HONORAIRES
J15: =IF(C15="","",D15-E15-F15-H15) | L15: CARBURANT & VÉHICULE
J16: =IF(C16="","",D16-E16-F16-H16) | L16: TRANSPORT & LIVRAISON
J17: =IF(C17="","",D17-E17-F17-H17) | L17: ENTRETIEN & RÉPARATION
J18: =IF(C18="","",D18-E18-F18-H18) | L18: FOURNITURES DE BUREAU
J19: =IF(C19="","",D19-E19-F19-H19) | L19: AUTRE CHARGE FIXE
J20: =IF(C20="","",D20-E20-F20-H20) | L20: TOTAL | M20: =SUM(M8:M19)
J21: =IF(C21="","",D21-E21-F21-H21)
J22: =IF(C22="","",D22-E22-F22-H22) | L22: SALAIRES ET AVANCES
J23: =IF(C23="","",D23-E23-F23-H23) | L23: PERSONNE | M23: MONTANT
J24: =IF(C24="","",D24-E24-F24-H24) | L24: HOUSSEIN
J25: =IF(C25="","",D25-E25-F25-H25) | L25: AYOUB
J26: =IF(C26="","",D26-E26-F26-H26) | L26: OUVRIER 1
J27: =IF(C27="","",D27-E27-F27-H27) | L27: OUVRIER 2
B28: TOTAL DES ACHATS DU JOUR | D28: =SUM(D8:D27) | E28: =SUM(E8:E27) | F28: =SUM(F8:F27) | H28: =SUM(H8:H27) | J28: =SUM(J8:J27) | L28: AVANCE / PRIME
L29: AUTRE SALAIRE
B30: RÈGLEMENT DES ACHATS | F30: ENCAISSEMENTS DU JOUR | L30: TOTAL | M30: =SUM(M24:M29)
B31: Réglé en espèce | D31: =E28 | F31: CLIENT / ORIGINE | H31: ESPÈCE | I31: CHÈQUE / VIREMENT | J31: TOTAL
B32: Réglé par chèque | D32: =F28 | J32: =IF(F32="","",H32+I32) | L32: DÉPENSES TRAVAUX ET DIVERS
B33: Réglé par effet | D33: =H28 | J33: =IF(F33="","",H33+I33) | L33: DÉSIGNATION | M33: MONTANT
B34: TOTAL RÉGLÉ | D34: =E28+F28+H28 | J34: =IF(F34="","",H34+I34)
B35: RESTE DÛ (crédit fournisseur) | D35: =J28 | J35: =IF(F35="","",H35+I35)
J36: =IF(F36="","",H36+I36)
B37: OBSERVATIONS DU JOUR | J37: =IF(F37="","",H37+I37)
J38: =IF(F38="","",H38+I38)
J39: =IF(F39="","",H39+I39)
J40: =IF(F40="","",H40+I40)
J41: =IF(F41="","",H41+I41)
F42: TOTAL ENCAISSÉ | H42: =SUM(H32:H41) | I42: =SUM(I32:I41) | J42: =SUM(J32:J41)
L44: TOTAL | M44: =SUM(M34:M43)
B46: LES CAISSES ET LE RÉSUMÉ DU SOIR
B47: CAISSE PARADISE | E47: CAISSE ZENATA | H47: CONTRÔLE ET AUTRE CAISSE | L47: RÉSUMÉ DU JOUR
B48: Solde de la veille | D48: ='29'!$D$56 | E48: Solde de la veille | G48: ='29'!$G$56 | H48: Caisse PARADISE du soir | J48: =D56 | L48: Achats fournisseurs du jour | M48: =D28
B49: + Encaissements en espèce | D49: =H42 | E49: + Encaissements du jour | H49: Caisse ZENATA du soir | J49: =G56 | L49: dont réglé en espèce | M49: =E28
B50: + Apports et entrées divers | E50: + Apports et entrées divers | H50: CAISSE TOTALE DU SOIR | J50: =D56+G56 | L50: dont réglé par chèque | M50: =F28
B51: – Achats réglés en espèce | D51: =E28 | E51: – Achats réglés en espèce | H51: Écart total constaté | J51: =D58+G58 | L51: dont réglé par effet | M51: =H28
B52: – Charges fixes du jour | D52: =M20 | E52: – Charges et frais du jour | L52: RESTE DÛ (crédit fournisseur) | M52: =J28
B53: – Salaires et avances | D53: =M30 | E53: – Salaires et avances | H53: AUTRE CAISSE — solde précédent | J53: ='29'!$J$56 | L53: Charges fixes | M53: =M20
B54: – Dépenses travaux et divers | D54: =M44 | E54: – Dépenses travaux et divers | H54: + Entrées du jour | L54: Salaires et avances | M54: =M30
B55: – Versement banque / sorties | E55: – Versement banque / sorties | H55: – Sorties du jour | L55: Dépenses travaux et divers | M55: =M44
B56: SOLDE DU SOIR | D56: =D48+D49+D50-D51-D52-D53-D54-D55 | E56: SOLDE DU SOIR | G56: =G48+G49+G50-G51-G52-G53-G54-G55 | H56: NOUVEAU SOLDE | J56: =J53+J54-J55 | L56: TOTAL DES SORTIES DU JOUR | M56: =M49+M50+M51+M53+M54+M55
B57: Espèces réellement comptées | E57: Espèces réellement comptées | L57: Encaissements du jour | M57: =J42
B58: ÉCART (compté – théorique) | D58: =IF(D57=0,0,D57-D56) | E58: ÉCART (compté – théorique) | G58: =IF(G57=0,0,G57-G56) | L58: CAISSE TOTALE DU SOIR | M58: =D56+G56

Sheet 31
A1: JOURNAL DE CAISSE DU JOUR | H1: PARADISE ALUMINIUM SARL · Casablanca
A2: =IF(31>'RÉCAP DU JOURNAL'!$J$5,"— ce jour n'existe pas dans le mois —",DATE('RÉCAP DU JOURNAL'!$E$4,'RÉCAP DU JOURNAL'!$E$5,31)) | H2: Feuille 31 · aluminium, accessoires et vitrage
A4: À REMPLIR ▸ les achats fournisseurs du jour, les charges, les salaires, les dépenses, les encaissements, puis les espèces comptées le soir dans chaque caisse. Cases jaunes = à vous ; cases blanches = calculées.
B6: ACHATS FOURNISSEURS DU JOUR | L6: CHARGES FIXES DU JOUR
B7: BL N° | C7: FOURNISSEUR | D7: NET À PAYER | E7: ESPÈCE | F7: CHÈQUE | G7: N° DU CHÈQUE | H7: EFFET | I7: N° DE L'EFFET | J7: RESTE À PAYER | L7: POSTE DE CHARGE | M7: MONTANT
J8: =IF(C8="","",D8-E8-F8-H8) | L8: LOYER DU LOCAL
J9: =IF(C9="","",D9-E9-F9-H9) | L9: EAU + ÉLECTRICITÉ
J10: =IF(C10="","",D10-E10-F10-H10) | L10: TÉLÉPHONE & INTERNET
J11: =IF(C11="","",D11-E11-F11-H11) | L11: CNSS
J12: =IF(C12="","",D12-E12-F12-H12) | L12: TVA & IMPÔTS
J13: =IF(C13="","",D13-E13-F13-H13) | L13: ASSURANCES
J14: =IF(C14="","",D14-E14-F14-H14) | L14: COMPTABLE & HONORAIRES
J15: =IF(C15="","",D15-E15-F15-H15) | L15: CARBURANT & VÉHICULE
J16: =IF(C16="","",D16-E16-F16-H16) | L16: TRANSPORT & LIVRAISON
J17: =IF(C17="","",D17-E17-F17-H17) | L17: ENTRETIEN & RÉPARATION
J18: =IF(C18="","",D18-E18-F18-H18) | L18: FOURNITURES DE BUREAU
J19: =IF(C19="","",D19-E19-F19-H19) | L19: AUTRE CHARGE FIXE
J20: =IF(C20="","",D20-E20-F20-H20) | L20: TOTAL | M20: =SUM(M8:M19)
J21: =IF(C21="","",D21-E21-F21-H21)
J22: =IF(C22="","",D22-E22-F22-H22) | L22: SALAIRES ET AVANCES
J23: =IF(C23="","",D23-E23-F23-H23) | L23: PERSONNE | M23: MONTANT
J24: =IF(C24="","",D24-E24-F24-H24) | L24: HOUSSEIN
J25: =IF(C25="","",D25-E25-F25-H25) | L25: AYOUB
J26: =IF(C26="","",D26-E26-F26-H26) | L26: OUVRIER 1
J27: =IF(C27="","",D27-E27-F27-H27) | L27: OUVRIER 2
B28: TOTAL DES ACHATS DU JOUR | D28: =SUM(D8:D27) | E28: =SUM(E8:E27) | F28: =SUM(F8:F27) | H28: =SUM(H8:H27) | J28: =SUM(J8:J27) | L28: AVANCE / PRIME
L29: AUTRE SALAIRE
B30: RÈGLEMENT DES ACHATS | F30: ENCAISSEMENTS DU JOUR | L30: TOTAL | M30: =SUM(M24:M29)
B31: Réglé en espèce | D31: =E28 | F31: CLIENT / ORIGINE | H31: ESPÈCE | I31: CHÈQUE / VIREMENT | J31: TOTAL
B32: Réglé par chèque | D32: =F28 | J32: =IF(F32="","",H32+I32) | L32: DÉPENSES TRAVAUX ET DIVERS
B33: Réglé par effet | D33: =H28 | J33: =IF(F33="","",H33+I33) | L33: DÉSIGNATION | M33: MONTANT
B34: TOTAL RÉGLÉ | D34: =E28+F28+H28 | J34: =IF(F34="","",H34+I34)
B35: RESTE DÛ (crédit fournisseur) | D35: =J28 | J35: =IF(F35="","",H35+I35)
J36: =IF(F36="","",H36+I36)
B37: OBSERVATIONS DU JOUR | J37: =IF(F37="","",H37+I37)
J38: =IF(F38="","",H38+I38)
J39: =IF(F39="","",H39+I39)
J40: =IF(F40="","",H40+I40)
J41: =IF(F41="","",H41+I41)
F42: TOTAL ENCAISSÉ | H42: =SUM(H32:H41) | I42: =SUM(I32:I41) | J42: =SUM(J32:J41)
L44: TOTAL | M44: =SUM(M34:M43)
B46: LES CAISSES ET LE RÉSUMÉ DU SOIR
B47: CAISSE PARADISE | E47: CAISSE ZENATA | H47: CONTRÔLE ET AUTRE CAISSE | L47: RÉSUMÉ DU JOUR
B48: Solde de la veille | D48: ='30'!$D$56 | E48: Solde de la veille | G48: ='30'!$G$56 | H48: Caisse PARADISE du soir | J48: =D56 | L48: Achats fournisseurs du jour | M48: =D28
B49: + Encaissements en espèce | D49: =H42 | E49: + Encaissements du jour | H49: Caisse ZENATA du soir | J49: =G56 | L49: dont réglé en espèce | M49: =E28
B50: + Apports et entrées divers | E50: + Apports et entrées divers | H50: CAISSE TOTALE DU SOIR | J50: =D56+G56 | L50: dont réglé par chèque | M50: =F28
B51: – Achats réglés en espèce | D51: =E28 | E51: – Achats réglés en espèce | H51: Écart total constaté | J51: =D58+G58 | L51: dont réglé par effet | M51: =H28
B52: – Charges fixes du jour | D52: =M20 | E52: – Charges et frais du jour | L52: RESTE DÛ (crédit fournisseur) | M52: =J28
B53: – Salaires et avances | D53: =M30 | E53: – Salaires et avances | H53: AUTRE CAISSE — solde précédent | J53: ='30'!$J$56 | L53: Charges fixes | M53: =M20
B54: – Dépenses travaux et divers | D54: =M44 | E54: – Dépenses travaux et divers | H54: + Entrées du jour | L54: Salaires et avances | M54: =M30
B55: – Versement banque / sorties | E55: – Versement banque / sorties | H55: – Sorties du jour | L55: Dépenses travaux et divers | M55: =M44
B56: SOLDE DU SOIR | D56: =D48+D49+D50-D51-D52-D53-D54-D55 | E56: SOLDE DU SOIR | G56: =G48+G49+G50-G51-G52-G53-G54-G55 | H56: NOUVEAU SOLDE | J56: =J53+J54-J55 | L56: TOTAL DES SORTIES DU JOUR | M56: =M49+M50+M51+M53+M54+M55
B57: Espèces réellement comptées | E57: Espèces réellement comptées | L57: Encaissements du jour | M57: =J42
B58: ÉCART (compté – théorique) | D58: =IF(D57=0,0,D57-D56) | E58: ÉCART (compté – théorique) | G58: =IF(G57=0,0,G57-G56) | L58: CAISSE TOTALE DU SOIR | M58: =D56+G56

Sheet FOURNISSEURS
A1: FOURNISSEURS DU MOIS
A2: Ce que nous leur avons acheté, ce que nous leur avons réglé, et ce que nous leur devons encore
B4: ACHATS ET RÈGLEMENTS PAR FOURNISSEUR
B5: FOURNISSEUR | C5: ACHATS DU MOIS | D5: RÉGLÉ EN ESPÈCE | E5: RÉGLÉ PAR CHÈQUE | F5: RÉGLÉ PAR EFFET | G5: TOTAL RÉGLÉ | H5: RESTE DÛ | I5: PART DES ACHATS | L5: Fournisseur | M5: Achats du mois
B6: ALUMINIUM ELMARWA | C6: =SUMIF('01'!$C$8:$C$27,$B6,'01'!$D$8:$D$27)+SUMIF('02'!$C$8:$C$27,$B6,'02'!$D$8:$D$27)+SUMIF('03'!$C$8:$C$27,$B6,'03'!$D$8:$D$27)+SUMIF('04'!$C$8:$C$27,$B6,'04'!$D$8:$D$27)+SUMIF('05'!$C$8:$C$27,$B6,'05'!$D$8:$D$27)+SUMIF('06'!$C$8:$C$27,$B6,'06'!$D$8:$D$27)+SUMIF('07'!$C$8:$C$27,$B6,'07'!$D$8:$D$27)+SUMIF('08'!$C$8:$C$27,$B6,'08'!$D$8:$D$27)+SUMIF('09'!$C$8:$C$27,$B6,'09'!$D$8:$D$27)+SUMIF('10'!$C$8:$C$27,$B6,'10'!$D$8:$D$27)+SUMIF('11'!$C$8:$C$27,$B6,'11'!$D$8:$D$27)+SUMIF('12'!$C$8:$C$27,$B6,'12'!$D$8:$D$27)+SUMIF('13'!$C$8:$C$27,$B6,'13'!$D$8:$D$27)+SUMIF('14'!$C$8:$C$27,$B6,'14'!$D$8:$D$27)+SUMIF('15'!$C$8:$C$27,$B6,'15'!$D$8:$D$27)+SUMIF('16'!$C$8:$C$27,$B6,'16'!$D$8:$D$27)+SUMIF('17'!$C$8:$C$27,$B6,'17'!$D$8:$D$27)+SUMIF('18'!$C$8:$C$27,$B6,'18'!$D$8:$D$27)+SUMIF('19'!$C$8:$C$27,$B6,'19'!$D$8:$D$27)+SUMIF('20'!$C$8:$C$27,$B6,'20'!$D$8:$D$27)+SUMIF('21'!$C$8:$C$27,$B6,'21'!$D$8:$D$27)+SUMIF('22'!$C$8:$C$27,$B6,'22'!$D$8:$D$27)+SUMIF('23'!$C$8:$C$27,$B6,'23'!$D$8:$D$27)+SUMIF('24'!$C$8:$C$27,$B6,'24'!$D$8:$D$27)+SUMIF('25'!$C$8:$C$27,$B6,'25'!$D$8:$D$27)+SUMIF('26'!$C$8:$C$27,$B6,'26'!$D$8:$D$27)+SUMIF('27'!$C$8:$C$27,$B6,'27'!$D$8:$D$27)+SUMIF('28'!$C$8:$C$27,$B6,'28'!$D$8:$D$27)+SUMIF('29'!$C$8:$C$27,$B6,'29'!$D$8:$D$27)+SUMIF('30'!$C$8:$C$27,$B6,'30'!$D$8:$D$27)+SUMIF('31'!$C$8:$C$27,$B6,'31'!$D$8:$D$27) | D6: =SUMIF('01'!$C$8:$C$27,$B6,'01'!$E$8:$E$27)+SUMIF('02'!$C$8:$C$27,$B6,'02'!$E$8:$E$27)+SUMIF('03'!$C$8:$C$27,$B6,'03'!$E$8:$E$27)+SUMIF('04'!$C$8:$C$27,$B6,'04'!$E$8:$E$27)+SUMIF('05'!$C$8:$C$27,$B6,'05'!$E$8:$E$27)+SUMIF('06'!$C$8:$C$27,$B6,'06'!$E$8:$E$27)+SUMIF('07'!$C$8:$C$27,$B6,'07'!$E$8:$E$27)+SUMIF('08'!$C$8:$C$27,$B6,'08'!$E$8:$E$27)+SUMIF('09'!$C$8:$C$27,$B6,'09'!$E$8:$E$27)+SUMIF('10'!$C$8:$C$27,$B6,'10'!$E$8:$E$27)+SUMIF('11'!$C$8:$C$27,$B6,'11'!$E$8:$E$27)+SUMIF('12'!$C$8:$C$27,$B6,'12'!$E$8:$E$27)+SUMIF('13'!$C$8:$C$27,$B6,'13'!$E$8:$E$27)+SUMIF('14'!$C$8:$C$27,$B6,'14'!$E$8:$E$27)+SUMIF('15'!$C$8:$C$27,$B6,'15'!$E$8:$E$27)+SUMIF('16'!$C$8:$C$27,$B6,'16'!$E$8:$E$27)+SUMIF('17'!$C$8:$C$27,$B6,'17'!$E$8:$E$27)+SUMIF('18'!$C$8:$C$27,$B6,'18'!$E$8:$E$27)+SUMIF('19'!$C$8:$C$27,$B6,'19'!$E$8:$E$27)+SUMIF('20'!$C$8:$C$27,$B6,'20'!$E$8:$E$27)+SUMIF('21'!$C$8:$C$27,$B6,'21'!$E$8:$E$27)+SUMIF('22'!$C$8:$C$27,$B6,'22'!$E$8:$E$27)+SUMIF('23'!$C$8:$C$27,$B6,'23'!$E$8:$E$27)+SUMIF('24'!$C$8:$C$27,$B6,'24'!$E$8:$E$27)+SUMIF('25'!$C$8:$C$27,$B6,'25'!$E$8:$E$27)+SUMIF('26'!$C$8:$C$27,$B6,'26'!$E$8:$E$27)+SUMIF('27'!$C$8:$C$27,$B6,'27'!$E$8:$E$27)+SUMIF('28'!$C$8:$C$27,$B6,'28'!$E$8:$E$27)+SUMIF('29'!$C$8:$C$27,$B6,'29'!$E$8:$E$27)+SUMIF('30'!$C$8:$C$27,$B6,'30'!$E$8:$E$27)+SUMIF('31'!$C$8:$C$27,$B6,'31'!$E$8:$E$27) | E6: =SUMIF('01'!$C$8:$C$27,$B6,'01'!$F$8:$F$27)+SUMIF('02'!$C$8:$C$27,$B6,'02'!$F$8:$F$27)+SUMIF('03'!$C$8:$C$27,$B6,'03'!$F$8:$F$27)+SUMIF('04'!$C$8:$C$27,$B6,'04'!$F$8:$F$27)+SUMIF('05'!$C$8:$C$27,$B6,'05'!$F$8:$F$27)+SUMIF('06'!$C$8:$C$27,$B6,'06'!$F$8:$F$27)+SUMIF('07'!$C$8:$C$27,$B6,'07'!$F$8:$F$27)+SUMIF('08'!$C$8:$C$27,$B6,'08'!$F$8:$F$27)+SUMIF('09'!$C$8:$C$27,$B6,'09'!$F$8:$F$27)+SUMIF('10'!$C$8:$C$27,$B6,'10'!$F$8:$F$27)+SUMIF('11'!$C$8:$C$27,$B6,'11'!$F$8:$F$27)+SUMIF('12'!$C$8:$C$27,$B6,'12'!$F$8:$F$27)+SUMIF('13'!$C$8:$C$27,$B6,'13'!$F$8:$F$27)+SUMIF('14'!$C$8:$C$27,$B6,'14'!$F$8:$F$27)+SUMIF('15'!$C$8:$C$27,$B6,'15'!$F$8:$F$27)+SUMIF('16'!$C$8:$C$27,$B6,'16'!$F$8:$F$27)+SUMIF('17'!$C$8:$C$27,$B6,'17'!$F$8:$F$27)+SUMIF('18'!$C$8:$C$27,$B6,'18'!$F$8:$F$27)+SUMIF('19'!$C$8:$C$27,$B6,'19'!$F$8:$F$27)+SUMIF('20'!$C$8:$C$27,$B6,'20'!$F$8:$F$27)+SUMIF('21'!$C$8:$C$27,$B6,'21'!$F$8:$F$27)+SUMIF('22'!$C$8:$C$27,$B6,'22'!$F$8:$F$27)+SUMIF('23'!$C$8:$C$27,$B6,'23'!$F$8:$F$27)+SUMIF('24'!$C$8:$C$27,$B6,'24'!$F$8:$F$27)+SUMIF('25'!$C$8:$C$27,$B6,'25'!$F$8:$F$27)+SUMIF('26'!$C$8:$C$27,$B6,'26'!$F$8:$F$27)+SUMIF('27'!$C$8:$C$27,$B6,'27'!$F$8:$F$27)+SUMIF('28'!$C$8:$C$27,$B6,'28'!$F$8:$F$27)+SUMIF('29'!$C$8:$C$27,$B6,'29'!$F$8:$F$27)+SUMIF('30'!$C$8:$C$27,$B6,'30'!$F$8:$F$27)+SUMIF('31'!$C$8:$C$27,$B6,'31'!$F$8:$F$27) | F6: =SUMIF('01'!$C$8:$C$27,$B6,'01'!$H$8:$H$27)+SUMIF('02'!$C$8:$C$27,$B6,'02'!$H$8:$H$27)+SUMIF('03'!$C$8:$C$27,$B6,'03'!$H$8:$H$27)+SUMIF('04'!$C$8:$C$27,$B6,'04'!$H$8:$H$27)+SUMIF('05'!$C$8:$C$27,$B6,'05'!$H$8:$H$27)+SUMIF('06'!$C$8:$C$27,$B6,'06'!$H$8:$H$27)+SUMIF('07'!$C$8:$C$27,$B6,'07'!$H$8:$H$27)+SUMIF('08'!$C$8:$C$27,$B6,'08'!$H$8:$H$27)+SUMIF('09'!$C$8:$C$27,$B6,'09'!$H$8:$H$27)+SUMIF('10'!$C$8:$C$27,$B6,'10'!$H$8:$H$27)+SUMIF('11'!$C$8:$C$27,$B6,'11'!$H$8:$H$27)+SUMIF('12'!$C$8:$C$27,$B6,'12'!$H$8:$H$27)+SUMIF('13'!$C$8:$C$27,$B6,'13'!$H$8:$H$27)+SUMIF('14'!$C$8:$C$27,$B6,'14'!$H$8:$H$27)+SUMIF('15'!$C$8:$C$27,$B6,'15'!$H$8:$H$27)+SUMIF('16'!$C$8:$C$27,$B6,'16'!$H$8:$H$27)+SUMIF('17'!$C$8:$C$27,$B6,'17'!$H$8:$H$27)+SUMIF('18'!$C$8:$C$27,$B6,'18'!$H$8:$H$27)+SUMIF('19'!$C$8:$C$27,$B6,'19'!$H$8:$H$27)+SUMIF('20'!$C$8:$C$27,$B6,'20'!$H$8:$H$27)+SUMIF('21'!$C$8:$C$27,$B6,'21'!$H$8:$H$27)+SUMIF('22'!$C$8:$C$27,$B6,'22'!$H$8:$H$27)+SUMIF('23'!$C$8:$C$27,$B6,'23'!$H$8:$H$27)+SUMIF('24'!$C$8:$C$27,$B6,'24'!$H$8:$H$27)+SUMIF('25'!$C$8:$C$27,$B6,'25'!$H$8:$H$27)+SUMIF('26'!$C$8:$C$27,$B6,'26'!$H$8:$H$27)+SUMIF('27'!$C$8:$C$27,$B6,'27'!$H$8:$H$27)+SUMIF('28'!$C$8:$C$27,$B6,'28'!$H$8:$H$27)+SUMIF('29'!$C$8:$C$27,$B6,'29'!$H$8:$H$27)+SUMIF('30'!$C$8:$C$27,$B6,'30'!$H$8:$H$27)+SUMIF('31'!$C$8:$C$27,$B6,'31'!$H$8:$H$27) | G6: =D6+E6+F6 | H6: =C6-G6 | I6: =IF($C$26=0,0,C6/$C$26) | J6: =$C6-ROW()/1000000 | L6: =INDEX($B$6:$B$25,MATCH(LARGE($J$6:$J$25,10),$J$6:$J$25,0)) | M6: =INDEX($C$6:$C$25,MATCH(LARGE($J$6:$J$25,10),$J$6:$J$25,0))
B7: FOMALU | C7: =SUMIF('01'!$C$8:$C$27,$B7,'01'!$D$8:$D$27)+SUMIF('02'!$C$8:$C$27,$B7,'02'!$D$8:$D$27)+SUMIF('03'!$C$8:$C$27,$B7,'03'!$D$8:$D$27)+SUMIF('04'!$C$8:$C$27,$B7,'04'!$D$8:$D$27)+SUMIF('05'!$C$8:$C$27,$B7,'05'!$D$8:$D$27)+SUMIF('06'!$C$8:$C$27,$B7,'06'!$D$8:$D$27)+SUMIF('07'!$C$8:$C$27,$B7,'07'!$D$8:$D$27)+SUMIF('08'!$C$8:$C$27,$B7,'08'!$D$8:$D$27)+SUMIF('09'!$C$8:$C$27,$B7,'09'!$D$8:$D$27)+SUMIF('10'!$C$8:$C$27,$B7,'10'!$D$8:$D$27)+SUMIF('11'!$C$8:$C$27,$B7,'11'!$D$8:$D$27)+SUMIF('12'!$C$8:$C$27,$B7,'12'!$D$8:$D$27)+SUMIF('13'!$C$8:$C$27,$B7,'13'!$D$8:$D$27)+SUMIF('14'!$C$8:$C$27,$B7,'14'!$D$8:$D$27)+SUMIF('15'!$C$8:$C$27,$B7,'15'!$D$8:$D$27)+SUMIF('16'!$C$8:$C$27,$B7,'16'!$D$8:$D$27)+SUMIF('17'!$C$8:$C$27,$B7,'17'!$D$8:$D$27)+SUMIF('18'!$C$8:$C$27,$B7,'18'!$D$8:$D$27)+SUMIF('19'!$C$8:$C$27,$B7,'19'!$D$8:$D$27)+SUMIF('20'!$C$8:$C$27,$B7,'20'!$D$8:$D$27)+SUMIF('21'!$C$8:$C$27,$B7,'21'!$D$8:$D$27)+SUMIF('22'!$C$8:$C$27,$B7,'22'!$D$8:$D$27)+SUMIF('23'!$C$8:$C$27,$B7,'23'!$D$8:$D$27)+SUMIF('24'!$C$8:$C$27,$B7,'24'!$D$8:$D$27)+SUMIF('25'!$C$8:$C$27,$B7,'25'!$D$8:$D$27)+SUMIF('26'!$C$8:$C$27,$B7,'26'!$D$8:$D$27)+SUMIF('27'!$C$8:$C$27,$B7,'27'!$D$8:$D$27)+SUMIF('28'!$C$8:$C$27,$B7,'28'!$D$8:$D$27)+SUMIF('29'!$C$8:$C$27,$B7,'29'!$D$8:$D$27)+SUMIF('30'!$C$8:$C$27,$B7,'30'!$D$8:$D$27)+SUMIF('31'!$C$8:$C$27,$B7,'31'!$D$8:$D$27) | D7: =SUMIF('01'!$C$8:$C$27,$B7,'01'!$E$8:$E$27)+SUMIF('02'!$C$8:$C$27,$B7,'02'!$E$8:$E$27)+SUMIF('03'!$C$8:$C$27,$B7,'03'!$E$8:$E$27)+SUMIF('04'!$C$8:$C$27,$B7,'04'!$E$8:$E$27)+SUMIF('05'!$C$8:$C$27,$B7,'05'!$E$8:$E$27)+SUMIF('06'!$C$8:$C$27,$B7,'06'!$E$8:$E$27)+SUMIF('07'!$C$8:$C$27,$B7,'07'!$E$8:$E$27)+SUMIF('08'!$C$8:$C$27,$B7,'08'!$E$8:$E$27)+SUMIF('09'!$C$8:$C$27,$B7,'09'!$E$8:$E$27)+SUMIF('10'!$C$8:$C$27,$B7,'10'!$E$8:$E$27)+SUMIF('11'!$C$8:$C$27,$B7,'11'!$E$8:$E$27)+SUMIF('12'!$C$8:$C$27,$B7,'12'!$E$8:$E$27)+SUMIF('13'!$C$8:$C$27,$B7,'13'!$E$8:$E$27)+SUMIF('14'!$C$8:$C$27,$B7,'14'!$E$8:$E$27)+SUMIF('15'!$C$8:$C$27,$B7,'15'!$E$8:$E$27)+SUMIF('16'!$C$8:$C$27,$B7,'16'!$E$8:$E$27)+SUMIF('17'!$C$8:$C$27,$B7,'17'!$E$8:$E$27)+SUMIF('18'!$C$8:$C$27,$B7,'18'!$E$8:$E$27)+SUMIF('19'!$C$8:$C$27,$B7,'19'!$E$8:$E$27)+SUMIF('20'!$C$8:$C$27,$B7,'20'!$E$8:$E$27)+SUMIF('21'!$C$8:$C$27,$B7,'21'!$E$8:$E$27)+SUMIF('22'!$C$8:$C$27,$B7,'22'!$E$8:$E$27)+SUMIF('23'!$C$8:$C$27,$B7,'23'!$E$8:$E$27)+SUMIF('24'!$C$8:$C$27,$B7,'24'!$E$8:$E$27)+SUMIF('25'!$C$8:$C$27,$B7,'25'!$E$8:$E$27)+SUMIF('26'!$C$8:$C$27,$B7,'26'!$E$8:$E$27)+SUMIF('27'!$C$8:$C$27,$B7,'27'!$E$8:$E$27)+SUMIF('28'!$C$8:$C$27,$B7,'28'!$E$8:$E$27)+SUMIF('29'!$C$8:$C$27,$B7,'29'!$E$8:$E$27)+SUMIF('30'!$C$8:$C$27,$B7,'30'!$E$8:$E$27)+SUMIF('31'!$C$8:$C$27,$B7,'31'!$E$8:$E$27) | E7: =SUMIF('01'!$C$8:$C$27,$B7,'01'!$F$8:$F$27)+SUMIF('02'!$C$8:$C$27,$B7,'02'!$F$8:$F$27)+SUMIF('03'!$C$8:$C$27,$B7,'03'!$F$8:$F$27)+SUMIF('04'!$C$8:$C$27,$B7,'04'!$F$8:$F$27)+SUMIF('05'!$C$8:$C$27,$B7,'05'!$F$8:$F$27)+SUMIF('06'!$C$8:$C$27,$B7,'06'!$F$8:$F$27)+SUMIF('07'!$C$8:$C$27,$B7,'07'!$F$8:$F$27)+SUMIF('08'!$C$8:$C$27,$B7,'08'!$F$8:$F$27)+SUMIF('09'!$C$8:$C$27,$B7,'09'!$F$8:$F$27)+SUMIF('10'!$C$8:$C$27,$B7,'10'!$F$8:$F$27)+SUMIF('11'!$C$8:$C$27,$B7,'11'!$F$8:$F$27)+SUMIF('12'!$C$8:$C$27,$B7,'12'!$F$8:$F$27)+SUMIF('13'!$C$8:$C$27,$B7,'13'!$F$8:$F$27)+SUMIF('14'!$C$8:$C$27,$B7,'14'!$F$8:$F$27)+SUMIF('15'!$C$8:$C$27,$B7,'15'!$F$8:$F$27)+SUMIF('16'!$C$8:$C$27,$B7,'16'!$F$8:$F$27)+SUMIF('17'!$C$8:$C$27,$B7,'17'!$F$8:$F$27)+SUMIF('18'!$C$8:$C$27,$B7,'18'!$F$8:$F$27)+SUMIF('19'!$C$8:$C$27,$B7,'19'!$F$8:$F$27)+SUMIF('20'!$C$8:$C$27,$B7,'20'!$F$8:$F$27)+SUMIF('21'!$C$8:$C$27,$B7,'21'!$F$8:$F$27)+SUMIF('22'!$C$8:$C$27,$B7,'22'!$F$8:$F$27)+SUMIF('23'!$C$8:$C$27,$B7,'23'!$F$8:$F$27)+SUMIF('24'!$C$8:$C$27,$B7,'24'!$F$8:$F$27)+SUMIF('25'!$C$8:$C$27,$B7,'25'!$F$8:$F$27)+SUMIF('26'!$C$8:$C$27,$B7,'26'!$F$8:$F$27)+SUMIF('27'!$C$8:$C$27,$B7,'27'!$F$8:$F$27)+SUMIF('28'!$C$8:$C$27,$B7,'28'!$F$8:$F$27)+SUMIF('29'!$C$8:$C$27,$B7,'29'!$F$8:$F$27)+SUMIF('30'!$C$8:$C$27,$B7,'30'!$F$8:$F$27)+SUMIF('31'!$C$8:$C$27,$B7,'31'!$F$8:$F$27) | F7: =SUMIF('01'!$C$8:$C$27,$B7,'01'!$H$8:$H$27)+SUMIF('02'!$C$8:$C$27,$B7,'02'!$H$8:$H$27)+SUMIF('03'!$C$8:$C$27,$B7,'03'!$H$8:$H$27)+SUMIF('04'!$C$8:$C$27,$B7,'04'!$H$8:$H$27)+SUMIF('05'!$C$8:$C$27,$B7,'05'!$H$8:$H$27)+SUMIF('06'!$C$8:$C$27,$B7,'06'!$H$8:$H$27)+SUMIF('07'!$C$8:$C$27,$B7,'07'!$H$8:$H$27)+SUMIF('08'!$C$8:$C$27,$B7,'08'!$H$8:$H$27)+SUMIF('09'!$C$8:$C$27,$B7,'09'!$H$8:$H$27)+SUMIF('10'!$C$8:$C$27,$B7,'10'!$H$8:$H$27)+SUMIF('11'!$C$8:$C$27,$B7,'11'!$H$8:$H$27)+SUMIF('12'!$C$8:$C$27,$B7,'12'!$H$8:$H$27)+SUMIF('13'!$C$8:$C$27,$B7,'13'!$H$8:$H$27)+SUMIF('14'!$C$8:$C$27,$B7,'14'!$H$8:$H$27)+SUMIF('15'!$C$8:$C$27,$B7,'15'!$H$8:$H$27)+SUMIF('16'!$C$8:$C$27,$B7,'16'!$H$8:$H$27)+SUMIF('17'!$C$8:$C$27,$B7,'17'!$H$8:$H$27)+SUMIF('18'!$C$8:$C$27,$B7,'18'!$H$8:$H$27)+SUMIF('19'!$C$8:$C$27,$B7,'19'!$H$8:$H$27)+SUMIF('20'!$C$8:$C$27,$B7,'20'!$H$8:$H$27)+SUMIF('21'!$C$8:$C$27,$B7,'21'!$H$8:$H$27)+SUMIF('22'!$C$8:$C$27,$B7,'22'!$H$8:$H$27)+SUMIF('23'!$C$8:$C$27,$B7,'23'!$H$8:$H$27)+SUMIF('24'!$C$8:$C$27,$B7,'24'!$H$8:$H$27)+SUMIF('25'!$C$8:$C$27,$B7,'25'!$H$8:$H$27)+SUMIF('26'!$C$8:$C$27,$B7,'26'!$H$8:$H$27)+SUMIF('27'!$C$8:$C$27,$B7,'27'!$H$8:$H$27)+SUMIF('28'!$C$8:$C$27,$B7,'28'!$H$8:$H$27)+SUMIF('29'!$C$8:$C$27,$B7,'29'!$H$8:$H$27)+SUMIF('30'!$C$8:$C$27,$B7,'30'!$H$8:$H$27)+SUMIF('31'!$C$8:$C$27,$B7,'31'!$H$8:$H$27) | G7: =D7+E7+F7 | H7: =C7-G7 | I7: =IF($C$26=0,0,C7/$C$26) | J7: =$C7-ROW()/1000000 | L7: =INDEX($B$6:$B$25,MATCH(LARGE($J$6:$J$25,9),$J$6:$J$25,0)) | M7: =INDEX($C$6:$C$25,MATCH(LARGE($J$6:$J$25,9),$J$6:$J$25,0))
B8: LAMASTORE | C8: =SUMIF('01'!$C$8:$C$27,$B8,'01'!$D$8:$D$27)+SUMIF('02'!$C$8:$C$27,$B8,'02'!$D$8:$D$27)+SUMIF('03'!$C$8:$C$27,$B8,'03'!$D$8:$D$27)+SUMIF('04'!$C$8:$C$27,$B8,'04'!$D$8:$D$27)+SUMIF('05'!$C$8:$C$27,$B8,'05'!$D$8:$D$27)+SUMIF('06'!$C$8:$C$27,$B8,'06'!$D$8:$D$27)+SUMIF('07'!$C$8:$C$27,$B8,'07'!$D$8:$D$27)+SUMIF('08'!$C$8:$C$27,$B8,'08'!$D$8:$D$27)+SUMIF('09'!$C$8:$C$27,$B8,'09'!$D$8:$D$27)+SUMIF('10'!$C$8:$C$27,$B8,'10'!$D$8:$D$27)+SUMIF('11'!$C$8:$C$27,$B8,'11'!$D$8:$D$27)+SUMIF('12'!$C$8:$C$27,$B8,'12'!$D$8:$D$27)+SUMIF('13'!$C$8:$C$27,$B8,'13'!$D$8:$D$27)+SUMIF('14'!$C$8:$C$27,$B8,'14'!$D$8:$D$27)+SUMIF('15'!$C$8:$C$27,$B8,'15'!$D$8:$D$27)+SUMIF('16'!$C$8:$C$27,$B8,'16'!$D$8:$D$27)+SUMIF('17'!$C$8:$C$27,$B8,'17'!$D$8:$D$27)+SUMIF('18'!$C$8:$C$27,$B8,'18'!$D$8:$D$27)+SUMIF('19'!$C$8:$C$27,$B8,'19'!$D$8:$D$27)+SUMIF('20'!$C$8:$C$27,$B8,'20'!$D$8:$D$27)+SUMIF('21'!$C$8:$C$27,$B8,'21'!$D$8:$D$27)+SUMIF('22'!$C$8:$C$27,$B8,'22'!$D$8:$D$27)+SUMIF('23'!$C$8:$C$27,$B8,'23'!$D$8:$D$27)+SUMIF('24'!$C$8:$C$27,$B8,'24'!$D$8:$D$27)+SUMIF('25'!$C$8:$C$27,$B8,'25'!$D$8:$D$27)+SUMIF('26'!$C$8:$C$27,$B8,'26'!$D$8:$D$27)+SUMIF('27'!$C$8:$C$27,$B8,'27'!$D$8:$D$27)+SUMIF('28'!$C$8:$C$27,$B8,'28'!$D$8:$D$27)+SUMIF('29'!$C$8:$C$27,$B8,'29'!$D$8:$D$27)+SUMIF('30'!$C$8:$C$27,$B8,'30'!$D$8:$D$27)+SUMIF('31'!$C$8:$C$27,$B8,'31'!$D$8:$D$27) | D8: =SUMIF('01'!$C$8:$C$27,$B8,'01'!$E$8:$E$27)+SUMIF('02'!$C$8:$C$27,$B8,'02'!$E$8:$E$27)+SUMIF('03'!$C$8:$C$27,$B8,'03'!$E$8:$E$27)+SUMIF('04'!$C$8:$C$27,$B8,'04'!$E$8:$E$27)+SUMIF('05'!$C$8:$C$27,$B8,'05'!$E$8:$E$27)+SUMIF('06'!$C$8:$C$27,$B8,'06'!$E$8:$E$27)+SUMIF('07'!$C$8:$C$27,$B8,'07'!$E$8:$E$27)+SUMIF('08'!$C$8:$C$27,$B8,'08'!$E$8:$E$27)+SUMIF('09'!$C$8:$C$27,$B8,'09'!$E$8:$E$27)+SUMIF('10'!$C$8:$C$27,$B8,'10'!$E$8:$E$27)+SUMIF('11'!$C$8:$C$27,$B8,'11'!$E$8:$E$27)+SUMIF('12'!$C$8:$C$27,$B8,'12'!$E$8:$E$27)+SUMIF('13'!$C$8:$C$27,$B8,'13'!$E$8:$E$27)+SUMIF('14'!$C$8:$C$27,$B8,'14'!$E$8:$E$27)+SUMIF('15'!$C$8:$C$27,$B8,'15'!$E$8:$E$27)+SUMIF('16'!$C$8:$C$27,$B8,'16'!$E$8:$E$27)+SUMIF('17'!$C$8:$C$27,$B8,'17'!$E$8:$E$27)+SUMIF('18'!$C$8:$C$27,$B8,'18'!$E$8:$E$27)+SUMIF('19'!$C$8:$C$27,$B8,'19'!$E$8:$E$27)+SUMIF('20'!$C$8:$C$27,$B8,'20'!$E$8:$E$27)+SUMIF('21'!$C$8:$C$27,$B8,'21'!$E$8:$E$27)+SUMIF('22'!$C$8:$C$27,$B8,'22'!$E$8:$E$27)+SUMIF('23'!$C$8:$C$27,$B8,'23'!$E$8:$E$27)+SUMIF('24'!$C$8:$C$27,$B8,'24'!$E$8:$E$27)+SUMIF('25'!$C$8:$C$27,$B8,'25'!$E$8:$E$27)+SUMIF('26'!$C$8:$C$27,$B8,'26'!$E$8:$E$27)+SUMIF('27'!$C$8:$C$27,$B8,'27'!$E$8:$E$27)+SUMIF('28'!$C$8:$C$27,$B8,'28'!$E$8:$E$27)+SUMIF('29'!$C$8:$C$27,$B8,'29'!$E$8:$E$27)+SUMIF('30'!$C$8:$C$27,$B8,'30'!$E$8:$E$27)+SUMIF('31'!$C$8:$C$27,$B8,'31'!$E$8:$E$27) | E8: =SUMIF('01'!$C$8:$C$27,$B8,'01'!$F$8:$F$27)+SUMIF('02'!$C$8:$C$27,$B8,'02'!$F$8:$F$27)+SUMIF('03'!$C$8:$C$27,$B8,'03'!$F$8:$F$27)+SUMIF('04'!$C$8:$C$27,$B8,'04'!$F$8:$F$27)+SUMIF('05'!$C$8:$C$27,$B8,'05'!$F$8:$F$27)+SUMIF('06'!$C$8:$C$27,$B8,'06'!$F$8:$F$27)+SUMIF('07'!$C$8:$C$27,$B8,'07'!$F$8:$F$27)+SUMIF('08'!$C$8:$C$27,$B8,'08'!$F$8:$F$27)+SUMIF('09'!$C$8:$C$27,$B8,'09'!$F$8:$F$27)+SUMIF('10'!$C$8:$C$27,$B8,'10'!$F$8:$F$27)+SUMIF('11'!$C$8:$C$27,$B8,'11'!$F$8:$F$27)+SUMIF('12'!$C$8:$C$27,$B8,'12'!$F$8:$F$27)+SUMIF('13'!$C$8:$C$27,$B8,'13'!$F$8:$F$27)+SUMIF('14'!$C$8:$C$27,$B8,'14'!$F$8:$F$27)+SUMIF('15'!$C$8:$C$27,$B8,'15'!$F$8:$F$27)+SUMIF('16'!$C$8:$C$27,$B8,'16'!$F$8:$F$27)+SUMIF('17'!$C$8:$C$27,$B8,'17'!$F$8:$F$27)+SUMIF('18'!$C$8:$C$27,$B8,'18'!$F$8:$F$27)+SUMIF('19'!$C$8:$C$27,$B8,'19'!$F$8:$F$27)+SUMIF('20'!$C$8:$C$27,$B8,'20'!$F$8:$F$27)+SUMIF('21'!$C$8:$C$27,$B8,'21'!$F$8:$F$27)+SUMIF('22'!$C$8:$C$27,$B8,'22'!$F$8:$F$27)+SUMIF('23'!$C$8:$C$27,$B8,'23'!$F$8:$F$27)+SUMIF('24'!$C$8:$C$27,$B8,'24'!$F$8:$F$27)+SUMIF('25'!$C$8:$C$27,$B8,'25'!$F$8:$F$27)+SUMIF('26'!$C$8:$C$27,$B8,'26'!$F$8:$F$27)+SUMIF('27'!$C$8:$C$27,$B8,'27'!$F$8:$F$27)+SUMIF('28'!$C$8:$C$27,$B8,'28'!$F$8:$F$27)+SUMIF('29'!$C$8:$C$27,$B8,'29'!$F$8:$F$27)+SUMIF('30'!$C$8:$C$27,$B8,'30'!$F$8:$F$27)+SUMIF('31'!$C$8:$C$27,$B8,'31'!$F$8:$F$27) | F8: =SUMIF('01'!$C$8:$C$27,$B8,'01'!$H$8:$H$27)+SUMIF('02'!$C$8:$C$27,$B8,'02'!$H$8:$H$27)+SUMIF('03'!$C$8:$C$27,$B8,'03'!$H$8:$H$27)+SUMIF('04'!$C$8:$C$27,$B8,'04'!$H$8:$H$27)+SUMIF('05'!$C$8:$C$27,$B8,'05'!$H$8:$H$27)+SUMIF('06'!$C$8:$C$27,$B8,'06'!$H$8:$H$27)+SUMIF('07'!$C$8:$C$27,$B8,'07'!$H$8:$H$27)+SUMIF('08'!$C$8:$C$27,$B8,'08'!$H$8:$H$27)+SUMIF('09'!$C$8:$C$27,$B8,'09'!$H$8:$H$27)+SUMIF('10'!$C$8:$C$27,$B8,'10'!$H$8:$H$27)+SUMIF('11'!$C$8:$C$27,$B8,'11'!$H$8:$H$27)+SUMIF('12'!$C$8:$C$27,$B8,'12'!$H$8:$H$27)+SUMIF('13'!$C$8:$C$27,$B8,'13'!$H$8:$H$27)+SUMIF('14'!$C$8:$C$27,$B8,'14'!$H$8:$H$27)+SUMIF('15'!$C$8:$C$27,$B8,'15'!$H$8:$H$27)+SUMIF('16'!$C$8:$C$27,$B8,'16'!$H$8:$H$27)+SUMIF('17'!$C$8:$C$27,$B8,'17'!$H$8:$H$27)+SUMIF('18'!$C$8:$C$27,$B8,'18'!$H$8:$H$27)+SUMIF('19'!$C$8:$C$27,$B8,'19'!$H$8:$H$27)+SUMIF('20'!$C$8:$C$27,$B8,'20'!$H$8:$H$27)+SUMIF('21'!$C$8:$C$27,$B8,'21'!$H$8:$H$27)+SUMIF('22'!$C$8:$C$27,$B8,'22'!$H$8:$H$27)+SUMIF('23'!$C$8:$C$27,$B8,'23'!$H$8:$H$27)+SUMIF('24'!$C$8:$C$27,$B8,'24'!$H$8:$H$27)+SUMIF('25'!$C$8:$C$27,$B8,'25'!$H$8:$H$27)+SUMIF('26'!$C$8:$C$27,$B8,'26'!$H$8:$H$27)+SUMIF('27'!$C$8:$C$27,$B8,'27'!$H$8:$H$27)+SUMIF('28'!$C$8:$C$27,$B8,'28'!$H$8:$H$27)+SUMIF('29'!$C$8:$C$27,$B8,'29'!$H$8:$H$27)+SUMIF('30'!$C$8:$C$27,$B8,'30'!$H$8:$H$27)+SUMIF('31'!$C$8:$C$27,$B8,'31'!$H$8:$H$27) | G8: =D8+E8+F8 | H8: =C8-G8 | I8: =IF($C$26=0,0,C8/$C$26) | J8: =$C8-ROW()/1000000 | L8: =INDEX($B$6:$B$25,MATCH(LARGE($J$6:$J$25,8),$J$6:$J$25,0)) | M8: =INDEX($C$6:$C$25,MATCH(LARGE($J$6:$J$25,8),$J$6:$J$25,0))
B9: FATALUM | C9: =SUMIF('01'!$C$8:$C$27,$B9,'01'!$D$8:$D$27)+SUMIF('02'!$C$8:$C$27,$B9,'02'!$D$8:$D$27)+SUMIF('03'!$C$8:$C$27,$B9,'03'!$D$8:$D$27)+SUMIF('04'!$C$8:$C$27,$B9,'04'!$D$8:$D$27)+SUMIF('05'!$C$8:$C$27,$B9,'05'!$D$8:$D$27)+SUMIF('06'!$C$8:$C$27,$B9,'06'!$D$8:$D$27)+SUMIF('07'!$C$8:$C$27,$B9,'07'!$D$8:$D$27)+SUMIF('08'!$C$8:$C$27,$B9,'08'!$D$8:$D$27)+SUMIF('09'!$C$8:$C$27,$B9,'09'!$D$8:$D$27)+SUMIF('10'!$C$8:$C$27,$B9,'10'!$D$8:$D$27)+SUMIF('11'!$C$8:$C$27,$B9,'11'!$D$8:$D$27)+SUMIF('12'!$C$8:$C$27,$B9,'12'!$D$8:$D$27)+SUMIF('13'!$C$8:$C$27,$B9,'13'!$D$8:$D$27)+SUMIF('14'!$C$8:$C$27,$B9,'14'!$D$8:$D$27)+SUMIF('15'!$C$8:$C$27,$B9,'15'!$D$8:$D$27)+SUMIF('16'!$C$8:$C$27,$B9,'16'!$D$8:$D$27)+SUMIF('17'!$C$8:$C$27,$B9,'17'!$D$8:$D$27)+SUMIF('18'!$C$8:$C$27,$B9,'18'!$D$8:$D$27)+SUMIF('19'!$C$8:$C$27,$B9,'19'!$D$8:$D$27)+SUMIF('20'!$C$8:$C$27,$B9,'20'!$D$8:$D$27)+SUMIF('21'!$C$8:$C$27,$B9,'21'!$D$8:$D$27)+SUMIF('22'!$C$8:$C$27,$B9,'22'!$D$8:$D$27)+SUMIF('23'!$C$8:$C$27,$B9,'23'!$D$8:$D$27)+SUMIF('24'!$C$8:$C$27,$B9,'24'!$D$8:$D$27)+SUMIF('25'!$C$8:$C$27,$B9,'25'!$D$8:$D$27)+SUMIF('26'!$C$8:$C$27,$B9,'26'!$D$8:$D$27)+SUMIF('27'!$C$8:$C$27,$B9,'27'!$D$8:$D$27)+SUMIF('28'!$C$8:$C$27,$B9,'28'!$D$8:$D$27)+SUMIF('29'!$C$8:$C$27,$B9,'29'!$D$8:$D$27)+SUMIF('30'!$C$8:$C$27,$B9,'30'!$D$8:$D$27)+SUMIF('31'!$C$8:$C$27,$B9,'31'!$D$8:$D$27) | D9: =SUMIF('01'!$C$8:$C$27,$B9,'01'!$E$8:$E$27)+SUMIF('02'!$C$8:$C$27,$B9,'02'!$E$8:$E$27)+SUMIF('03'!$C$8:$C$27,$B9,'03'!$E$8:$E$27)+SUMIF('04'!$C$8:$C$27,$B9,'04'!$E$8:$E$27)+SUMIF('05'!$C$8:$C$27,$B9,'05'!$E$8:$E$27)+SUMIF('06'!$C$8:$C$27,$B9,'06'!$E$8:$E$27)+SUMIF('07'!$C$8:$C$27,$B9,'07'!$E$8:$E$27)+SUMIF('08'!$C$8:$C$27,$B9,'08'!$E$8:$E$27)+SUMIF('09'!$C$8:$C$27,$B9,'09'!$E$8:$E$27)+SUMIF('10'!$C$8:$C$27,$B9,'10'!$E$8:$E$27)+SUMIF('11'!$C$8:$C$27,$B9,'11'!$E$8:$E$27)+SUMIF('12'!$C$8:$C$27,$B9,'12'!$E$8:$E$27)+SUMIF('13'!$C$8:$C$27,$B9,'13'!$E$8:$E$27)+SUMIF('14'!$C$8:$C$27,$B9,'14'!$E$8:$E$27)+SUMIF('15'!$C$8:$C$27,$B9,'15'!$E$8:$E$27)+SUMIF('16'!$C$8:$C$27,$B9,'16'!$E$8:$E$27)+SUMIF('17'!$C$8:$C$27,$B9,'17'!$E$8:$E$27)+SUMIF('18'!$C$8:$C$27,$B9,'18'!$E$8:$E$27)+SUMIF('19'!$C$8:$C$27,$B9,'19'!$E$8:$E$27)+SUMIF('20'!$C$8:$C$27,$B9,'20'!$E$8:$E$27)+SUMIF('21'!$C$8:$C$27,$B9,'21'!$E$8:$E$27)+SUMIF('22'!$C$8:$C$27,$B9,'22'!$E$8:$E$27)+SUMIF('23'!$C$8:$C$27,$B9,'23'!$E$8:$E$27)+SUMIF('24'!$C$8:$C$27,$B9,'24'!$E$8:$E$27)+SUMIF('25'!$C$8:$C$27,$B9,'25'!$E$8:$E$27)+SUMIF('26'!$C$8:$C$27,$B9,'26'!$E$8:$E$27)+SUMIF('27'!$C$8:$C$27,$B9,'27'!$E$8:$E$27)+SUMIF('28'!$C$8:$C$27,$B9,'28'!$E$8:$E$27)+SUMIF('29'!$C$8:$C$27,$B9,'29'!$E$8:$E$27)+SUMIF('30'!$C$8:$C$27,$B9,'30'!$E$8:$E$27)+SUMIF('31'!$C$8:$C$27,$B9,'31'!$E$8:$E$27) | E9: =SUMIF('01'!$C$8:$C$27,$B9,'01'!$F$8:$F$27)+SUMIF('02'!$C$8:$C$27,$B9,'02'!$F$8:$F$27)+SUMIF('03'!$C$8:$C$27,$B9,'03'!$F$8:$F$27)+SUMIF('04'!$C$8:$C$27,$B9,'04'!$F$8:$F$27)+SUMIF('05'!$C$8:$C$27,$B9,'05'!$F$8:$F$27)+SUMIF('06'!$C$8:$C$27,$B9,'06'!$F$8:$F$27)+SUMIF('07'!$C$8:$C$27,$B9,'07'!$F$8:$F$27)+SUMIF('08'!$C$8:$C$27,$B9,'08'!$F$8:$F$27)+SUMIF('09'!$C$8:$C$27,$B9,'09'!$F$8:$F$27)+SUMIF('10'!$C$8:$C$27,$B9,'10'!$F$8:$F$27)+SUMIF('11'!$C$8:$C$27,$B9,'11'!$F$8:$F$27)+SUMIF('12'!$C$8:$C$27,$B9,'12'!$F$8:$F$27)+SUMIF('13'!$C$8:$C$27,$B9,'13'!$F$8:$F$27)+SUMIF('14'!$C$8:$C$27,$B9,'14'!$F$8:$F$27)+SUMIF('15'!$C$8:$C$27,$B9,'15'!$F$8:$F$27)+SUMIF('16'!$C$8:$C$27,$B9,'16'!$F$8:$F$27)+SUMIF('17'!$C$8:$C$27,$B9,'17'!$F$8:$F$27)+SUMIF('18'!$C$8:$C$27,$B9,'18'!$F$8:$F$27)+SUMIF('19'!$C$8:$C$27,$B9,'19'!$F$8:$F$27)+SUMIF('20'!$C$8:$C$27,$B9,'20'!$F$8:$F$27)+SUMIF('21'!$C$8:$C$27,$B9,'21'!$F$8:$F$27)+SUMIF('22'!$C$8:$C$27,$B9,'22'!$F$8:$F$27)+SUMIF('23'!$C$8:$C$27,$B9,'23'!$F$8:$F$27)+SUMIF('24'!$C$8:$C$27,$B9,'24'!$F$8:$F$27)+SUMIF('25'!$C$8:$C$27,$B9,'25'!$F$8:$F$27)+SUMIF('26'!$C$8:$C$27,$B9,'26'!$F$8:$F$27)+SUMIF('27'!$C$8:$C$27,$B9,'27'!$F$8:$F$27)+SUMIF('28'!$C$8:$C$27,$B9,'28'!$F$8:$F$27)+SUMIF('29'!$C$8:$C$27,$B9,'29'!$F$8:$F$27)+SUMIF('30'!$C$8:$C$27,$B9,'30'!$F$8:$F$27)+SUMIF('31'!$C$8:$C$27,$B9,'31'!$F$8:$F$27) | F9: =SUMIF('01'!$C$8:$C$27,$B9,'01'!$H$8:$H$27)+SUMIF('02'!$C$8:$C$27,$B9,'02'!$H$8:$H$27)+SUMIF('03'!$C$8:$C$27,$B9,'03'!$H$8:$H$27)+SUMIF('04'!$C$8:$C$27,$B9,'04'!$H$8:$H$27)+SUMIF('05'!$C$8:$C$27,$B9,'05'!$H$8:$H$27)+SUMIF('06'!$C$8:$C$27,$B9,'06'!$H$8:$H$27)+SUMIF('07'!$C$8:$C$27,$B9,'07'!$H$8:$H$27)+SUMIF('08'!$C$8:$C$27,$B9,'08'!$H$8:$H$27)+SUMIF('09'!$C$8:$C$27,$B9,'09'!$H$8:$H$27)+SUMIF('10'!$C$8:$C$27,$B9,'10'!$H$8:$H$27)+SUMIF('11'!$C$8:$C$27,$B9,'11'!$H$8:$H$27)+SUMIF('12'!$C$8:$C$27,$B9,'12'!$H$8:$H$27)+SUMIF('13'!$C$8:$C$27,$B9,'13'!$H$8:$H$27)+SUMIF('14'!$C$8:$C$27,$B9,'14'!$H$8:$H$27)+SUMIF('15'!$C$8:$C$27,$B9,'15'!$H$8:$H$27)+SUMIF('16'!$C$8:$C$27,$B9,'16'!$H$8:$H$27)+SUMIF('17'!$C$8:$C$27,$B9,'17'!$H$8:$H$27)+SUMIF('18'!$C$8:$C$27,$B9,'18'!$H$8:$H$27)+SUMIF('19'!$C$8:$C$27,$B9,'19'!$H$8:$H$27)+SUMIF('20'!$C$8:$C$27,$B9,'20'!$H$8:$H$27)+SUMIF('21'!$C$8:$C$27,$B9,'21'!$H$8:$H$27)+SUMIF('22'!$C$8:$C$27,$B9,'22'!$H$8:$H$27)+SUMIF('23'!$C$8:$C$27,$B9,'23'!$H$8:$H$27)+SUMIF('24'!$C$8:$C$27,$B9,'24'!$H$8:$H$27)+SUMIF('25'!$C$8:$C$27,$B9,'25'!$H$8:$H$27)+SUMIF('26'!$C$8:$C$27,$B9,'26'!$H$8:$H$27)+SUMIF('27'!$C$8:$C$27,$B9,'27'!$H$8:$H$27)+SUMIF('28'!$C$8:$C$27,$B9,'28'!$H$8:$H$27)+SUMIF('29'!$C$8:$C$27,$B9,'29'!$H$8:$H$27)+SUMIF('30'!$C$8:$C$27,$B9,'30'!$H$8:$H$27)+SUMIF('31'!$C$8:$C$27,$B9,'31'!$H$8:$H$27) | G9: =D9+E9+F9 | H9: =C9-G9 | I9: =IF($C$26=0,0,C9/$C$26) | J9: =$C9-ROW()/1000000 | L9: =INDEX($B$6:$B$25,MATCH(LARGE($J$6:$J$25,7),$J$6:$J$25,0)) | M9: =INDEX($C$6:$C$25,MATCH(LARGE($J$6:$J$25,7),$J$6:$J$25,0))
B10: IDRALUM | C10: =SUMIF('01'!$C$8:$C$27,$B10,'01'!$D$8:$D$27)+SUMIF('02'!$C$8:$C$27,$B10,'02'!$D$8:$D$27)+SUMIF('03'!$C$8:$C$27,$B10,'03'!$D$8:$D$27)+SUMIF('04'!$C$8:$C$27,$B10,'04'!$D$8:$D$27)+SUMIF('05'!$C$8:$C$27,$B10,'05'!$D$8:$D$27)+SUMIF('06'!$C$8:$C$27,$B10,'06'!$D$8:$D$27)+SUMIF('07'!$C$8:$C$27,$B10,'07'!$D$8:$D$27)+SUMIF('08'!$C$8:$C$27,$B10,'08'!$D$8:$D$27)+SUMIF('09'!$C$8:$C$27,$B10,'09'!$D$8:$D$27)+SUMIF('10'!$C$8:$C$27,$B10,'10'!$D$8:$D$27)+SUMIF('11'!$C$8:$C$27,$B10,'11'!$D$8:$D$27)+SUMIF('12'!$C$8:$C$27,$B10,'12'!$D$8:$D$27)+SUMIF('13'!$C$8:$C$27,$B10,'13'!$D$8:$D$27)+SUMIF('14'!$C$8:$C$27,$B10,'14'!$D$8:$D$27)+SUMIF('15'!$C$8:$C$27,$B10,'15'!$D$8:$D$27)+SUMIF('16'!$C$8:$C$27,$B10,'16'!$D$8:$D$27)+SUMIF('17'!$C$8:$C$27,$B10,'17'!$D$8:$D$27)+SUMIF('18'!$C$8:$C$27,$B10,'18'!$D$8:$D$27)+SUMIF('19'!$C$8:$C$27,$B10,'19'!$D$8:$D$27)+SUMIF('20'!$C$8:$C$27,$B10,'20'!$D$8:$D$27)+SUMIF('21'!$C$8:$C$27,$B10,'21'!$D$8:$D$27)+SUMIF('22'!$C$8:$C$27,$B10,'22'!$D$8:$D$27)+SUMIF('23'!$C$8:$C$27,$B10,'23'!$D$8:$D$27)+SUMIF('24'!$C$8:$C$27,$B10,'24'!$D$8:$D$27)+SUMIF('25'!$C$8:$C$27,$B10,'25'!$D$8:$D$27)+SUMIF('26'!$C$8:$C$27,$B10,'26'!$D$8:$D$27)+SUMIF('27'!$C$8:$C$27,$B10,'27'!$D$8:$D$27)+SUMIF('28'!$C$8:$C$27,$B10,'28'!$D$8:$D$27)+SUMIF('29'!$C$8:$C$27,$B10,'29'!$D$8:$D$27)+SUMIF('30'!$C$8:$C$27,$B10,'30'!$D$8:$D$27)+SUMIF('31'!$C$8:$C$27,$B10,'31'!$D$8:$D$27) | D10: =SUMIF('01'!$C$8:$C$27,$B10,'01'!$E$8:$E$27)+SUMIF('02'!$C$8:$C$27,$B10,'02'!$E$8:$E$27)+SUMIF('03'!$C$8:$C$27,$B10,'03'!$E$8:$E$27)+SUMIF('04'!$C$8:$C$27,$B10,'04'!$E$8:$E$27)+SUMIF('05'!$C$8:$C$27,$B10,'05'!$E$8:$E$27)+SUMIF('06'!$C$8:$C$27,$B10,'06'!$E$8:$E$27)+SUMIF('07'!$C$8:$C$27,$B10,'07'!$E$8:$E$27)+SUMIF('08'!$C$8:$C$27,$B10,'08'!$E$8:$E$27)+SUMIF('09'!$C$8:$C$27,$B10,'09'!$E$8:$E$27)+SUMIF('10'!$C$8:$C$27,$B10,'10'!$E$8:$E$27)+SUMIF('11'!$C$8:$C$27,$B10,'11'!$E$8:$E$27)+SUMIF('12'!$C$8:$C$27,$B10,'12'!$E$8:$E$27)+SUMIF('13'!$C$8:$C$27,$B10,'13'!$E$8:$E$27)+SUMIF('14'!$C$8:$C$27,$B10,'14'!$E$8:$E$27)+SUMIF('15'!$C$8:$C$27,$B10,'15'!$E$8:$E$27)+SUMIF('16'!$C$8:$C$27,$B10,'16'!$E$8:$E$27)+SUMIF('17'!$C$8:$C$27,$B10,'17'!$E$8:$E$27)+SUMIF('18'!$C$8:$C$27,$B10,'18'!$E$8:$E$27)+SUMIF('19'!$C$8:$C$27,$B10,'19'!$E$8:$E$27)+SUMIF('20'!$C$8:$C$27,$B10,'20'!$E$8:$E$27)+SUMIF('21'!$C$8:$C$27,$B10,'21'!$E$8:$E$27)+SUMIF('22'!$C$8:$C$27,$B10,'22'!$E$8:$E$27)+SUMIF('23'!$C$8:$C$27,$B10,'23'!$E$8:$E$27)+SUMIF('24'!$C$8:$C$27,$B10,'24'!$E$8:$E$27)+SUMIF('25'!$C$8:$C$27,$B10,'25'!$E$8:$E$27)+SUMIF('26'!$C$8:$C$27,$B10,'26'!$E$8:$E$27)+SUMIF('27'!$C$8:$C$27,$B10,'27'!$E$8:$E$27)+SUMIF('28'!$C$8:$C$27,$B10,'28'!$E$8:$E$27)+SUMIF('29'!$C$8:$C$27,$B10,'29'!$E$8:$E$27)+SUMIF('30'!$C$8:$C$27,$B10,'30'!$E$8:$E$27)+SUMIF('31'!$C$8:$C$27,$B10,'31'!$E$8:$E$27) | E10: =SUMIF('01'!$C$8:$C$27,$B10,'01'!$F$8:$F$27)+SUMIF('02'!$C$8:$C$27,$B10,'02'!$F$8:$F$27)+SUMIF('03'!$C$8:$C$27,$B10,'03'!$F$8:$F$27)+SUMIF('04'!$C$8:$C$27,$B10,'04'!$F$8:$F$27)+SUMIF('05'!$C$8:$C$27,$B10,'05'!$F$8:$F$27)+SUMIF('06'!$C$8:$C$27,$B10,'06'!$F$8:$F$27)+SUMIF('07'!$C$8:$C$27,$B10,'07'!$F$8:$F$27)+SUMIF('08'!$C$8:$C$27,$B10,'08'!$F$8:$F$27)+SUMIF('09'!$C$8:$C$27,$B10,'09'!$F$8:$F$27)+SUMIF('10'!$C$8:$C$27,$B10,'10'!$F$8:$F$27)+SUMIF('11'!$C$8:$C$27,$B10,'11'!$F$8:$F$27)+SUMIF('12'!$C$8:$C$27,$B10,'12'!$F$8:$F$27)+SUMIF('13'!$C$8:$C$27,$B10,'13'!$F$8:$F$27)+SUMIF('14'!$C$8:$C$27,$B10,'14'!$F$8:$F$27)+SUMIF('15'!$C$8:$C$27,$B10,'15'!$F$8:$F$27)+SUMIF('16'!$C$8:$C$27,$B10,'16'!$F$8:$F$27)+SUMIF('17'!$C$8:$C$27,$B10,'17'!$F$8:$F$27)+SUMIF('18'!$C$8:$C$27,$B10,'18'!$F$8:$F$27)+SUMIF('19'!$C$8:$C$27,$B10,'19'!$F$8:$F$27)+SUMIF('20'!$C$8:$C$27,$B10,'20'!$F$8:$F$27)+SUMIF('21'!$C$8:$C$27,$B10,'21'!$F$8:$F$27)+SUMIF('22'!$C$8:$C$27,$B10,'22'!$F$8:$F$27)+SUMIF('23'!$C$8:$C$27,$B10,'23'!$F$8:$F$27)+SUMIF('24'!$C$8:$C$27,$B10,'24'!$F$8:$F$27)+SUMIF('25'!$C$8:$C$27,$B10,'25'!$F$8:$F$27)+SUMIF('26'!$C$8:$C$27,$B10,'26'!$F$8:$F$27)+SUMIF('27'!$C$8:$C$27,$B10,'27'!$F$8:$F$27)+SUMIF('28'!$C$8:$C$27,$B10,'28'!$F$8:$F$27)+SUMIF('29'!$C$8:$C$27,$B10,'29'!$F$8:$F$27)+SUMIF('30'!$C$8:$C$27,$B10,'30'!$F$8:$F$27)+SUMIF('31'!$C$8:$C$27,$B10,'31'!$F$8:$F$27) | F10: =SUMIF('01'!$C$8:$C$27,$B10,'01'!$H$8:$H$27)+SUMIF('02'!$C$8:$C$27,$B10,'02'!$H$8:$H$27)+SUMIF('03'!$C$8:$C$27,$B10,'03'!$H$8:$H$27)+SUMIF('04'!$C$8:$C$27,$B10,'04'!$H$8:$H$27)+SUMIF('05'!$C$8:$C$27,$B10,'05'!$H$8:$H$27)+SUMIF('06'!$C$8:$C$27,$B10,'06'!$H$8:$H$27)+SUMIF('07'!$C$8:$C$27,$B10,'07'!$H$8:$H$27)+SUMIF('08'!$C$8:$C$27,$B10,'08'!$H$8:$H$27)+SUMIF('09'!$C$8:$C$27,$B10,'09'!$H$8:$H$27)+SUMIF('10'!$C$8:$C$27,$B10,'10'!$H$8:$H$27)+SUMIF('11'!$C$8:$C$27,$B10,'11'!$H$8:$H$27)+SUMIF('12'!$C$8:$C$27,$B10,'12'!$H$8:$H$27)+SUMIF('13'!$C$8:$C$27,$B10,'13'!$H$8:$H$27)+SUMIF('14'!$C$8:$C$27,$B10,'14'!$H$8:$H$27)+SUMIF('15'!$C$8:$C$27,$B10,'15'!$H$8:$H$27)+SUMIF('16'!$C$8:$C$27,$B10,'16'!$H$8:$H$27)+SUMIF('17'!$C$8:$C$27,$B10,'17'!$H$8:$H$27)+SUMIF('18'!$C$8:$C$27,$B10,'18'!$H$8:$H$27)+SUMIF('19'!$C$8:$C$27,$B10,'19'!$H$8:$H$27)+SUMIF('20'!$C$8:$C$27,$B10,'20'!$H$8:$H$27)+SUMIF('21'!$C$8:$C$27,$B10,'21'!$H$8:$H$27)+SUMIF('22'!$C$8:$C$27,$B10,'22'!$H$8:$H$27)+SUMIF('23'!$C$8:$C$27,$B10,'23'!$H$8:$H$27)+SUMIF('24'!$C$8:$C$27,$B10,'24'!$H$8:$H$27)+SUMIF('25'!$C$8:$C$27,$B10,'25'!$H$8:$H$27)+SUMIF('26'!$C$8:$C$27,$B10,'26'!$H$8:$H$27)+SUMIF('27'!$C$8:$C$27,$B10,'27'!$H$8:$H$27)+SUMIF('28'!$C$8:$C$27,$B10,'28'!$H$8:$H$27)+SUMIF('29'!$C$8:$C$27,$B10,'29'!$H$8:$H$27)+SUMIF('30'!$C$8:$C$27,$B10,'30'!$H$8:$H$27)+SUMIF('31'!$C$8:$C$27,$B10,'31'!$H$8:$H$27) | G10: =D10+E10+F10 | H10: =C10-G10 | I10: =IF($C$26=0,0,C10/$C$26) | J10: =$C10-ROW()/1000000 | L10: =INDEX($B$6:$B$25,MATCH(LARGE($J$6:$J$25,6),$J$6:$J$25,0)) | M10: =INDEX($C$6:$C$25,MATCH(LARGE($J$6:$J$25,6),$J$6:$J$25,0))
